{
  "type": "Feature",
  "properties": {
    "gn:admin1_code":"C",
    "gn:admin2_code":"89",
    "gn:asciiname":"Maziba",
    "gn:country_code":"UG",
    "gn:dem":1194,
    "gn:feature_class":"P",
    "gn:feature_code":"PPL",
    "gn:name":"Maziba",
    "gn:population":0,
    "gn:timezone":"Africa/Kampala",
    "iso:country":"UG",
    "wof:name":"Maziba",
    "wof:placetype":"locality"
},
  "geometry": {"coordinates":[32.3486,0.21815],"type":"Point"}
}