{
  "type": "Feature",
  "properties": {
    "gn:admin1_code":"W",
    "gn:admin2_code":"I2",
    "gn:admin3_code":"8644161.0",
    "gn:admin4_code":"8657709.0",
    "gn:asciiname":"Lubanyi",
    "gn:country_code":"UG",
    "gn:dem":1081,
    "gn:feature_class":"P",
    "gn:feature_code":"PPL",
    "gn:name":"Lubanyi",
    "gn:population":0,
    "gn:timezone":"Africa/Kampala",
    "iso:country":"UG",
    "wof:name":"Lubanyi",
    "wof:placetype":"locality"
},
  "geometry": {"coordinates":[31.35,1.15],"type":"Point"}
}