{
  "type": "Feature",
  "properties": {
    "gn:admin1_code":"E",
    "gn:admin2_code":"G4",
    "gn:admin3_code":"229762.0",
    "gn:admin4_code":"8657669.0",
    "gn:asciiname":"Buseete",
    "gn:country_code":"UG",
    "gn:dem":1094,
    "gn:feature_class":"P",
    "gn:feature_code":"PPL",
    "gn:name":"Buseete",
    "gn:population":0,
    "gn:timezone":"Africa/Kampala",
    "iso:country":"UG",
    "name:und_x_variant":[
        "Busete",
        "Buseete"
    ],
    "wof:name":"Buseete",
    "wof:placetype":"locality"
},
  "geometry": {"coordinates":[33.29575,0.80795],"type":"Point"}
}