{
  "type": "Feature",
  "properties": {
    "gn:admin1_code":"E",
    "gn:admin2_code":"38",
    "gn:asciiname":"Bugaga",
    "gn:country_code":"UG",
    "gn:dem":1090,
    "gn:feature_class":"P",
    "gn:feature_code":"PPL",
    "gn:name":"Bugaga",
    "gn:population":0,
    "gn:timezone":"Africa/Kampala",
    "iso:country":"UG",
    "wof:name":"Bugaga",
    "wof:placetype":"locality"
},
  "geometry": {"coordinates":[33.25307,0.96222],"type":"Point"}
}