{
  "type": "Feature",
  "properties": {
    "gn:admin1_code":"E",
    "gn:admin2_code":"66",
    "gn:asciiname":"Bugombo",
    "gn:country_code":"UG",
    "gn:dem":1111,
    "gn:feature_class":"P",
    "gn:feature_code":"PPL",
    "gn:name":"Bugombo",
    "gn:population":0,
    "gn:timezone":"Africa/Kampala",
    "iso:country":"UG",
    "wof:name":"Bugombo",
    "wof:placetype":"locality"
},
  "geometry": {"coordinates":[33.66954,0.56413],"type":"Point"}
}