{
  "type": "Feature",
  "properties": {
    "gn:admin1_code":"W",
    "gn:admin2_code":"79",
    "gn:asciiname":"Kihamba",
    "gn:country_code":"UG",
    "gn:dem":1596,
    "gn:feature_class":"P",
    "gn:feature_code":"PPL",
    "gn:name":"Kihamba",
    "gn:population":0,
    "gn:timezone":"Africa/Kampala",
    "iso:country":"UG",
    "name:eng_x_preferred":[
        "Kihamba"
    ],
    "wof:name":"Kihamba",
    "wof:placetype":"locality"
},
  "geometry": {"coordinates":[30.3627,0.73823],"type":"Point"}
}