{
  "type": "Feature",
  "properties": {
    "gn:admin1_code":"C",
    "gn:admin2_code":"96",
    "gn:asciiname":"Kavuna",
    "gn:country_code":"UG",
    "gn:dem":1206,
    "gn:feature_class":"P",
    "gn:feature_code":"PPL",
    "gn:name":"Kavuna",
    "gn:population":0,
    "gn:timezone":"Africa/Kampala",
    "iso:country":"UG",
    "wof:name":"Kavuna",
    "wof:placetype":"locality"
},
  "geometry": {"coordinates":[32.46233,0.40274],"type":"Point"}
}