{
  "type": "Feature",
  "properties": {
    "gn:admin1_code":"N",
    "gn:admin2_code":"G8",
    "gn:admin3_code":"234720.0",
    "gn:admin4_code":"8657946.0",
    "gn:asciiname":"Napak",
    "gn:country_code":"UG",
    "gn:dem":1161,
    "gn:feature_class":"P",
    "gn:feature_code":"PPL",
    "gn:name":"Napak",
    "gn:population":0,
    "gn:timezone":"Africa/Kampala",
    "iso:country":"UG",
    "name:heb_x_preferred":[
        "\u05e0\u05d0\u05e4\u05e7"
    ],
    "name:hun_x_preferred":[
        "Napak"
    ],
    "name:swa_x_preferred":[
        "Napak"
    ],
    "name:urd_x_preferred":[
        "\u0646\u0627\u067e\u0627\u06a9"
    ],
    "wof:name":"Napak",
    "wof:placetype":"locality"
},
  "geometry": {"coordinates":[34.25,2.25],"type":"Point"}
}