{
  "type": "Feature",
  "properties": {
    "gn:admin1_code":"N",
    "gn:admin2_code":"G8",
    "gn:admin3_code":"234720.0",
    "gn:admin4_code":"8657946.0",
    "gn:asciiname":"Napak",
    "gn:country_code":"UG",
    "gn:dem":1161,
    "gn:feature_class":"P",
    "gn:feature_code":"PPL",
    "gn:name":"Napak",
    "gn:population":0,
    "gn:timezone":"Africa/Kampala",
    "iso:country":"UG",
    "wof:name":"Napak",
    "wof:placetype":"locality"
},
  "geometry": {"coordinates":[34.25,2.25],"type":"Point"}
}