{
  "type": "Feature",
  "properties": {
    "gn:admin1_code":"N",
    "gn:admin2_code":"E3",
    "gn:admin3_code":"235459.0",
    "gn:admin4_code":"8658597.0",
    "gn:asciiname":"Kalera",
    "gn:country_code":"UG",
    "gn:dem":1161,
    "gn:feature_class":"P",
    "gn:feature_code":"PPLL",
    "gn:name":"Kalera",
    "gn:population":0,
    "gn:timezone":"Africa/Kampala",
    "iso:country":"UG",
    "wof:name":"Kalera",
    "wof:placetype":"locality"
},
  "geometry": {"coordinates":[33.39652,3.09018],"type":"Point"}
}