{
  "type": "Feature",
  "properties": {
    "gn:admin1_code":"W",
    "gn:admin2_code":"40",
    "gn:admin3_code":"234040.0",
    "gn:admin4_code":"8657765.0",
    "gn:asciiname":"Busambo",
    "gn:country_code":"UG",
    "gn:dem":1466,
    "gn:feature_class":"P",
    "gn:feature_code":"PPL",
    "gn:name":"Busambo",
    "gn:population":0,
    "gn:timezone":"Africa/Kampala",
    "iso:country":"UG",
    "wof:name":"Busambo",
    "wof:placetype":"locality"
},
  "geometry": {"coordinates":[30.01667,0.11667],"type":"Point"}
}