{
  "type": "Feature",
  "properties": {
    "gn:admin1_code":"C",
    "gn:admin2_code":"D8",
    "gn:asciiname":"Nsisi",
    "gn:country_code":"UG",
    "gn:dem":1258,
    "gn:feature_class":"P",
    "gn:feature_code":"PPL",
    "gn:name":"Nsisi",
    "gn:population":0,
    "gn:timezone":"Africa/Kampala",
    "iso:country":"UG",
    "wof:name":"Nsisi",
    "wof:placetype":"locality"
},
  "geometry": {"coordinates":[32.24074,0.32282],"type":"Point"}
}