{
  "type": "Feature",
  "properties": {
    "gn:admin1_code":"E",
    "gn:admin2_code":"78",
    "gn:asciiname":"Nawangwe",
    "gn:country_code":"UG",
    "gn:dem":1156,
    "gn:feature_class":"P",
    "gn:feature_code":"PPL",
    "gn:name":"Nawangwe",
    "gn:population":0,
    "gn:timezone":"Africa/Kampala",
    "iso:country":"UG",
    "wof:name":"Nawangwe",
    "wof:placetype":"locality"
},
  "geometry": {"coordinates":[33.4667,0.58054],"type":"Point"}
}