{
  "type": "Feature",
  "properties": {
    "gn:admin1_code":"C",
    "gn:admin2_code":"83",
    "gn:admin3_code":"227613.0",
    "gn:admin4_code":"8658174.0",
    "gn:asciiname":"Ntenjeru",
    "gn:country_code":"UG",
    "gn:dem":1079,
    "gn:feature_class":"P",
    "gn:feature_code":"PPL",
    "gn:name":"Ntenjeru",
    "gn:population":0,
    "gn:timezone":"Africa/Kampala",
    "iso:country":"UG",
    "name:ceb_x_preferred":[
        "Ntenjeru"
    ],
    "wof:name":"Ntenjeru",
    "wof:placetype":"locality"
},
  "geometry": {"coordinates":[32.885,0.7525],"type":"Point"}
}