{
  "type": "Feature",
  "properties": {
    "gn:admin1_code":"C",
    "gn:admin2_code":"96",
    "gn:admin3_code":"7732385.0",
    "gn:admin4_code":"8658187.0",
    "gn:asciiname":"Kazinga",
    "gn:country_code":"UG",
    "gn:dem":1180,
    "gn:feature_class":"P",
    "gn:feature_code":"PPL",
    "gn:name":"Kazinga",
    "gn:population":0,
    "gn:timezone":"Africa/Kampala",
    "iso:country":"UG",
    "wof:name":"Kazinga",
    "wof:placetype":"locality"
},
  "geometry": {"coordinates":[32.64005,0.38336],"type":"Point"}
}