{
  "type": "Feature",
  "properties": {
    "gn:admin1_code":"C",
    "gn:admin2_code":"42",
    "gn:admin3_code":"8644178.0",
    "gn:admin4_code":"8657687.0",
    "gn:asciiname":"Kabanga",
    "gn:country_code":"UG",
    "gn:dem":1131,
    "gn:feature_class":"P",
    "gn:feature_code":"PPL",
    "gn:name":"Kabanga",
    "gn:population":0,
    "gn:timezone":"Africa/Kampala",
    "iso:country":"UG",
    "name:ceb_x_preferred":[
        "Kabanga"
    ],
    "name:fra_x_preferred":[
        "Kabanga"
    ],
    "name:swe_x_preferred":[
        "Kabanga"
    ],
    "wof:name":"Kabanga",
    "wof:placetype":"locality"
},
  "geometry": {"coordinates":[31.68333,0.98333],"type":"Point"}
}