{
  "type": "Feature",
  "properties": {
    "gn:admin1_code":"W",
    "gn:admin2_code":"59",
    "gn:admin3_code":"7732261.0",
    "gn:admin4_code":"8658180.0",
    "gn:asciiname":"Kabira",
    "gn:country_code":"UG",
    "gn:dem":1703,
    "gn:feature_class":"P",
    "gn:feature_code":"PPL",
    "gn:name":"Kabira",
    "gn:population":0,
    "gn:timezone":"Africa/Kampala",
    "iso:country":"UG",
    "name:ceb_x_preferred":[
        "Kabira"
    ],
    "name:swe_x_preferred":[
        "Kabira"
    ],
    "wof:name":"Kabira",
    "wof:placetype":"locality"
},
  "geometry": {"coordinates":[30.13333,-1.15],"type":"Point"}
}