{
  "type": "Feature",
  "properties": {
    "gn:admin1_code":"C",
    "gn:admin2_code":"96",
    "gn:admin3_code":"7732385.0",
    "gn:admin4_code":"8658261.0",
    "gn:asciiname":"Buwagga",
    "gn:country_code":"UG",
    "gn:dem":1169,
    "gn:feature_class":"P",
    "gn:feature_code":"PPL",
    "gn:name":"Buwagga",
    "gn:population":0,
    "gn:timezone":"Africa/Kampala",
    "iso:country":"UG",
    "wof:name":"Buwagga",
    "wof:placetype":"locality"
},
  "geometry": {"coordinates":[32.5831,0.47187],"type":"Point"}
}