{
  "type": "Feature",
  "properties": {
    "gn:admin1_code":"E",
    "gn:admin2_code":"69",
    "gn:admin3_code":"8644130.0",
    "gn:admin4_code":"8629350.0",
    "gn:asciiname":"Alekilek",
    "gn:country_code":"UG",
    "gn:dem":1128,
    "gn:feature_class":"P",
    "gn:feature_code":"PPL",
    "gn:name":"Alekilek",
    "gn:population":0,
    "gn:timezone":"Africa/Kampala",
    "iso:country":"UG",
    "wof:name":"Alekilek",
    "wof:placetype":"locality"
},
  "geometry": {"coordinates":[34.16667,2.08333],"type":"Point"}
}