{
  "type": "Feature",
  "properties": {
    "gn:admin1_code":"W",
    "gn:admin2_code":"29",
    "gn:admin3_code":"7732267.0",
    "gn:admin4_code":"8657649.0",
    "gn:asciiname":"Kyamugabo",
    "gn:country_code":"UG",
    "gn:dem":1593,
    "gn:feature_class":"P",
    "gn:feature_code":"PPL",
    "gn:name":"Kyamugabo",
    "gn:population":0,
    "gn:timezone":"Africa/Kampala",
    "iso:country":"UG",
    "wof:name":"Kyamugabo",
    "wof:placetype":"locality"
},
  "geometry": {"coordinates":[30.15,-0.63333],"type":"Point"}
}