{
  "type": "Feature",
  "properties": {
    "gn:admin1_code":"E",
    "gn:admin2_code":"E1",
    "gn:asciiname":"Nawangisa",
    "gn:country_code":"UG",
    "gn:dem":1071,
    "gn:feature_class":"P",
    "gn:feature_code":"PPL",
    "gn:name":"Nawangisa",
    "gn:population":0,
    "gn:timezone":"Africa/Kampala",
    "iso:country":"UG",
    "wof:name":"Nawangisa",
    "wof:placetype":"locality"
},
  "geometry": {"coordinates":[33.56497,0.82629],"type":"Point"}
}