{
  "type": "Feature",
  "properties": {
    "gn:admin1_code":"W",
    "gn:admin2_code":"52",
    "gn:admin3_code":"7732072.0",
    "gn:admin4_code":"8657966.0",
    "gn:asciiname":"Katozho",
    "gn:country_code":"UG",
    "gn:dem":1413,
    "gn:feature_class":"P",
    "gn:feature_code":"PPL",
    "gn:name":"Katozho",
    "gn:population":0,
    "gn:timezone":"Africa/Kampala",
    "iso:country":"UG",
    "wof:name":"Katozho",
    "wof:placetype":"locality"
},
  "geometry": {"coordinates":[30.61667000000001,-0.63333],"type":"Point"}
}