{
  "type": "Feature",
  "properties": {
    "gn:admin1_code":"E",
    "gn:admin2_code":"76",
    "gn:asciiname":"Akworot",
    "gn:country_code":"UG",
    "gn:dem":1244,
    "gn:feature_class":"P",
    "gn:feature_code":"PPL",
    "gn:name":"Akworot",
    "gn:population":0,
    "gn:timezone":"Africa/Kampala",
    "iso:country":"UG",
    "name:eng_x_preferred":[
        "Akworot"
    ],
    "wof:name":"Akworot",
    "wof:placetype":"locality"
},
  "geometry": {"coordinates":[34.21084,0.75721],"type":"Point"}
}