{
  "type": "Feature",
  "properties": {
    "gn:admin1_code":"W",
    "gn:admin2_code":"31",
    "gn:admin3_code":"7732256.0",
    "gn:admin4_code":"8581634.0",
    "gn:asciiname":"Biseruka",
    "gn:country_code":"UG",
    "gn:dem":1048,
    "gn:feature_class":"P",
    "gn:feature_code":"PPL",
    "gn:name":"Biseruka",
    "gn:population":0,
    "gn:timezone":"Africa/Kampala",
    "iso:country":"UG",
    "wof:name":"Biseruka",
    "wof:placetype":"locality"
},
  "geometry": {"coordinates":[31.13649,1.54736],"type":"Point"}
}