{
  "type": "Feature",
  "properties": {
    "gn:admin1_code":"C",
    "gn:admin2_code":"E7",
    "gn:admin3_code":"7732075.0",
    "gn:admin4_code":"8658239.0",
    "gn:asciiname":"Nyenga",
    "gn:country_code":"UG",
    "gn:dem":1239,
    "gn:feature_class":"P",
    "gn:feature_code":"PPL",
    "gn:name":"Nyenga",
    "gn:population":0,
    "gn:timezone":"Africa/Kampala",
    "iso:country":"UG",
    "name:ceb_x_preferred":[
        "Nyenga"
    ],
    "name:eng_x_preferred":[
        "Nyenga"
    ],
    "wof:name":"Nyenga",
    "wof:placetype":"locality"
},
  "geometry": {"coordinates":[33.15167,0.38254],"type":"Point"}
}