{
  "type": "Feature",
  "properties": {
    "gn:admin1_code":"E",
    "gn:admin2_code":"D2",
    "gn:asciiname":"Kajanabulwaire",
    "gn:country_code":"UG",
    "gn:dem":1056,
    "gn:feature_class":"P",
    "gn:feature_code":"PPL",
    "gn:name":"Kajanabulwaire",
    "gn:population":0,
    "gn:timezone":"Africa/Kampala",
    "iso:country":"UG",
    "wof:name":"Kajanabulwaire",
    "wof:placetype":"locality"
},
  "geometry": {"coordinates":[33.42015,0.95111],"type":"Point"}
}