{
  "type": "Feature",
  "properties": {
    "gn:admin1_code":"C",
    "gn:admin2_code":"96",
    "gn:asciiname":"Buwonzi",
    "gn:country_code":"UG",
    "gn:dem":1166,
    "gn:feature_class":"P",
    "gn:feature_code":"PPL",
    "gn:name":"Buwonzi",
    "gn:population":0,
    "gn:timezone":"Africa/Kampala",
    "iso:country":"UG",
    "wof:name":"Buwonzi",
    "wof:placetype":"locality"
},
  "geometry": {"coordinates":[32.47976,0.48763],"type":"Point"}
}