{
  "type": "Feature",
  "properties": {
    "gn:admin1_code":"W",
    "gn:admin2_code":"D3",
    "gn:admin3_code":"7870011.0",
    "gn:admin4_code":"8657791.0",
    "gn:asciiname":"Rubunu",
    "gn:country_code":"UG",
    "gn:dem":1263,
    "gn:feature_class":"P",
    "gn:feature_code":"PPL",
    "gn:name":"Rubunu",
    "gn:population":0,
    "gn:timezone":"Africa/Kampala",
    "iso:country":"UG",
    "wof:name":"Rubunu",
    "wof:placetype":"locality"
},
  "geometry": {"coordinates":[31.08333,-0.65],"type":"Point"}
}