{
  "type": "Feature",
  "properties": {
    "gn:admin1_code":"W",
    "gn:admin2_code":"34",
    "gn:admin3_code":"227915.0",
    "gn:admin4_code":"8658084.0",
    "gn:asciiname":"Muyebe",
    "gn:country_code":"UG",
    "gn:dem":1871,
    "gn:feature_class":"P",
    "gn:feature_code":"PPL",
    "gn:name":"Muyebe",
    "gn:population":0,
    "gn:timezone":"Africa/Kampala",
    "iso:country":"UG",
    "wof:name":"Muyebe",
    "wof:placetype":"locality"
},
  "geometry": {"coordinates":[30.01861,-1.32222],"type":"Point"}
}