{
  "type": "Feature",
  "properties": {
    "gn:admin1_code":"N",
    "gn:admin2_code":"65",
    "gn:admin3_code":"8644133.0",
    "gn:admin4_code":"8658096.0",
    "gn:asciiname":"Ovuvu",
    "gn:country_code":"UG",
    "gn:dem":648,
    "gn:feature_class":"P",
    "gn:feature_code":"PPL",
    "gn:name":"Ovuvu",
    "gn:population":0,
    "gn:timezone":"Africa/Kampala",
    "iso:country":"UG",
    "wof:name":"Ovuvu",
    "wof:placetype":"locality"
},
  "geometry": {"coordinates":[31.95645,3.49542],"type":"Point"}
}