{
  "type": "Feature",
  "properties": {
    "gn:admin1_code":"C",
    "gn:admin2_code":"37",
    "gn:admin3_code":"8644170.0",
    "gn:admin4_code":"7732388.0",
    "gn:asciiname":"Wandegeya",
    "gn:country_code":"UG",
    "gn:dem":1240,
    "gn:feature_class":"P",
    "gn:feature_code":"PPL",
    "gn:name":"Wandegeya",
    "gn:population":0,
    "gn:timezone":"Africa/Kampala",
    "iso:country":"UG",
    "wof:name":"Wandegeya",
    "wof:placetype":"locality"
},
  "geometry": {"coordinates":[32.56992,0.33102],"type":"Point"}
}