{
  "type": "Feature",
  "properties": {
    "gn:admin1_code":"N",
    "gn:admin2_code":"D4",
    "gn:admin3_code":"230723.0",
    "gn:admin4_code":"8657686.0",
    "gn:asciiname":"Ludara",
    "gn:country_code":"UG",
    "gn:dem":1210,
    "gn:feature_class":"P",
    "gn:feature_code":"PPL",
    "gn:name":"Ludara",
    "gn:population":0,
    "gn:timezone":"Africa/Kampala",
    "iso:country":"UG",
    "wof:name":"Ludara",
    "wof:placetype":"locality"
},
  "geometry": {"coordinates":[31.00292,3.52025],"type":"Point"}
}