{
  "type": "Feature",
  "properties": {
    "gn:admin1_code":"E",
    "gn:admin2_code":"33",
    "gn:asciiname":"Kaira",
    "gn:country_code":"UG",
    "gn:dem":1107,
    "gn:feature_class":"P",
    "gn:feature_code":"PPL",
    "gn:name":"Kaira",
    "gn:population":0,
    "gn:timezone":"Africa/Kampala",
    "iso:country":"UG",
    "wof:name":"Kaira",
    "wof:placetype":"locality"
},
  "geometry": {"coordinates":[33.14792,0.64148],"type":"Point"}
}