{
  "type": "Feature",
  "properties": {
    "gn:admin1_code":"E",
    "gn:admin2_code":"95",
    "gn:admin3_code":"226232.0",
    "gn:admin4_code":"8658303.0",
    "gn:asciiname":"Aboket",
    "gn:country_code":"UG",
    "gn:dem":1042,
    "gn:feature_class":"P",
    "gn:feature_code":"PPLL",
    "gn:name":"Aboket",
    "gn:population":0,
    "gn:timezone":"Africa/Kampala",
    "iso:country":"UG",
    "wof:name":"Aboket",
    "wof:placetype":"locality"
},
  "geometry": {"coordinates":[33.46572,1.74301],"type":"Point"}
}