{
  "type": "Feature",
  "properties": {
    "gn:admin1_code":"E",
    "gn:admin2_code":"D6",
    "gn:asciiname":"Bunangabo",
    "gn:country_code":"UG",
    "gn:dem":1225,
    "gn:feature_class":"P",
    "gn:feature_code":"PPL",
    "gn:name":"Bunangabo",
    "gn:population":0,
    "gn:timezone":"Africa/Kampala",
    "iso:country":"UG",
    "name:eng_x_preferred":[
        "Bunangabo"
    ],
    "wof:name":"Bunangabo",
    "wof:placetype":"locality"
},
  "geometry": {"coordinates":[34.28256,0.92922],"type":"Point"}
}