{
  "type": "Feature",
  "properties": {
    "gn:admin1_code":"W",
    "gn:admin2_code":"93",
    "gn:admin3_code":"8644148.0",
    "gn:admin4_code":"8658589.0",
    "gn:asciiname":"Rubanga",
    "gn:country_code":"UG",
    "gn:dem":1506,
    "gn:feature_class":"P",
    "gn:feature_code":"PPL",
    "gn:name":"Rubanga",
    "gn:population":0,
    "gn:timezone":"Africa/Kampala",
    "iso:country":"UG",
    "wof:name":"Rubanga",
    "wof:placetype":"locality"
},
  "geometry": {"coordinates":[29.96667,-0.88333],"type":"Point"}
}