{
  "type": "Feature",
  "properties": {
    "gn:admin1_code":"C",
    "gn:admin2_code":"I3",
    "gn:admin3_code":"8644144.0",
    "gn:admin4_code":"8657994.0",
    "gn:asciiname":"Mirambi",
    "gn:country_code":"UG",
    "gn:dem":1181,
    "gn:feature_class":"P",
    "gn:feature_code":"PPL",
    "gn:name":"Mirambi",
    "gn:population":0,
    "gn:timezone":"Africa/Kampala",
    "iso:country":"UG",
    "wof:name":"Mirambi",
    "wof:placetype":"locality"
},
  "geometry": {"coordinates":[31.58333,-0.58333],"type":"Point"}
}