{
  "type": "Feature",
  "properties": {
    "gn:admin1_code":"E",
    "gn:admin2_code":"C2",
    "gn:asciiname":"Bulule",
    "gn:country_code":"UG",
    "gn:dem":1535,
    "gn:feature_class":"P",
    "gn:feature_code":"PPL",
    "gn:name":"Bulule",
    "gn:population":0,
    "gn:timezone":"Africa/Kampala",
    "iso:country":"UG",
    "name:eng_x_preferred":[
        "Bulule"
    ],
    "wof:name":"Bulule",
    "wof:placetype":"locality"
},
  "geometry": {"coordinates":[34.36924,0.98604],"type":"Point"}
}