{
  "type": "Feature",
  "properties": {
    "gn:admin1_code":"C",
    "gn:admin2_code":"96",
    "gn:admin3_code":"234053.0",
    "gn:admin4_code":"8658010.0",
    "gn:asciiname":"Nsagu",
    "gn:country_code":"UG",
    "gn:dem":1186,
    "gn:feature_class":"P",
    "gn:feature_code":"PPL",
    "gn:name":"Nsagu",
    "gn:population":0,
    "gn:timezone":"Africa/Kampala",
    "iso:country":"UG",
    "name:und_x_variant":[
        "Nsaggu"
    ],
    "wof:name":"Nsagu",
    "wof:placetype":"locality"
},
  "geometry": {"coordinates":[32.48123,0.21744],"type":"Point"}
}