{
  "type": "Feature",
  "properties": {
    "gn:admin1_code":"C",
    "gn:admin2_code":"D8",
    "gn:admin3_code":"8644152.0",
    "gn:admin4_code":"8657698.0",
    "gn:asciiname":"Kibibi",
    "gn:country_code":"UG",
    "gn:dem":1226,
    "gn:feature_class":"P",
    "gn:feature_code":"PPL",
    "gn:name":"Kibibi",
    "gn:population":0,
    "gn:timezone":"Africa/Kampala",
    "iso:country":"UG",
    "wof:name":"Kibibi",
    "wof:placetype":"locality"
},
  "geometry": {"coordinates":[32.07769,0.46917],"type":"Point"}
}