{
  "type": "Feature",
  "properties": {
    "gn:admin1_code":"N",
    "gn:admin2_code":"26",
    "gn:asciiname":"Aringoluk",
    "gn:country_code":"UG",
    "gn:dem":1047,
    "gn:feature_class":"P",
    "gn:feature_code":"PPL",
    "gn:name":"Aringoluk",
    "gn:population":0,
    "gn:timezone":"Africa/Kampala",
    "iso:country":"UG",
    "name:eng_x_preferred":[
        "Aringoluk"
    ],
    "wof:name":"Aringoluk",
    "wof:placetype":"locality"
},
  "geometry": {"coordinates":[32.77873,1.90794],"type":"Point"}
}