{
  "type": "Feature",
  "properties": {
    "gn:admin1_code":"W",
    "gn:admin2_code":"79",
    "gn:asciiname":"Bugarama",
    "gn:country_code":"UG",
    "gn:dem":1614,
    "gn:feature_class":"P",
    "gn:feature_code":"PPL",
    "gn:name":"Bugarama",
    "gn:population":0,
    "gn:timezone":"Africa/Kampala",
    "iso:country":"UG",
    "name:eng_x_preferred":[
        "Bugarama"
    ],
    "wof:name":"Bugarama",
    "wof:placetype":"locality"
},
  "geometry": {"coordinates":[30.15758,0.53468],"type":"Point"}
}