{
  "type": "Feature",
  "properties": {
    "gn:admin1_code":"W",
    "gn:admin2_code":"93",
    "gn:admin3_code":"8644148.0",
    "gn:admin4_code":"8657801.0",
    "gn:asciiname":"Nyalushanje",
    "gn:country_code":"UG",
    "gn:dem":1623,
    "gn:feature_class":"P",
    "gn:feature_code":"PPL",
    "gn:name":"Nyalushanje",
    "gn:population":0,
    "gn:timezone":"Africa/Kampala",
    "iso:country":"UG",
    "name:und_x_variant":[
        "Nyalusanje",
        "Nyalushanje"
    ],
    "wof:name":"Nyalushanje",
    "wof:placetype":"locality"
},
  "geometry": {"coordinates":[29.96667,-0.98333],"type":"Point"}
}