{
  "type": "Feature",
  "properties": {
    "gn:admin1_code":"N",
    "gn:admin2_code":"45",
    "gn:admin3_code":"233117.0",
    "gn:admin4_code":"8658321.0",
    "gn:asciiname":"Nakapelimoru",
    "gn:country_code":"UG",
    "gn:dem":1267,
    "gn:feature_class":"P",
    "gn:feature_code":"PPL",
    "gn:name":"Nakapelimoru",
    "gn:population":0,
    "gn:timezone":"Africa/Kampala",
    "iso:country":"UG",
    "wof:name":"Nakapelimoru",
    "wof:placetype":"locality"
},
  "geometry": {"coordinates":[34.19828,3.00719],"type":"Point"}
}