{
  "type": "Feature",
  "properties": {
    "gn:admin1_code":"W",
    "gn:admin2_code":"79",
    "gn:asciiname":"Harugongo",
    "gn:country_code":"UG",
    "gn:dem":1572,
    "gn:feature_class":"P",
    "gn:feature_code":"PPL",
    "gn:name":"Harugongo",
    "gn:population":0,
    "gn:timezone":"Africa/Kampala",
    "iso:country":"UG",
    "name:eng_x_preferred":[
        "Harugongo"
    ],
    "wof:name":"Harugongo",
    "wof:placetype":"locality"
},
  "geometry": {"coordinates":[30.29626,0.71891],"type":"Point"}
}