{
  "type": "Feature",
  "properties": {
    "gn:admin1_code":"E",
    "gn:admin2_code":"86",
    "gn:admin3_code":"8644164.0",
    "gn:admin4_code":"8658417.0",
    "gn:asciiname":"Mairinya",
    "gn:country_code":"UG",
    "gn:dem":1181,
    "gn:feature_class":"P",
    "gn:feature_code":"PPL",
    "gn:name":"Mairinya",
    "gn:population":0,
    "gn:timezone":"Africa/Kampala",
    "iso:country":"UG",
    "name:eng_x_preferred":[
        "Mairinya"
    ],
    "wof:name":"Mairinya",
    "wof:placetype":"locality"
},
  "geometry": {"coordinates":[33.68399,0.39791],"type":"Point"}
}