{
  "type": "Feature",
  "properties": {
    "gn:admin1_code":"E",
    "gn:admin2_code":"E1",
    "gn:asciiname":"Nawandiyo",
    "gn:country_code":"UG",
    "gn:dem":1110,
    "gn:feature_class":"P",
    "gn:feature_code":"PPL",
    "gn:name":"Nawandiyo",
    "gn:population":0,
    "gn:timezone":"Africa/Kampala",
    "iso:country":"UG",
    "wof:name":"Nawandiyo",
    "wof:placetype":"locality"
},
  "geometry": {"coordinates":[33.77177,0.7537],"type":"Point"}
}