{
  "type": "Feature",
  "properties": {
    "gn:admin1_code":"E",
    "gn:admin2_code":"67",
    "gn:admin3_code":"8644151.0",
    "gn:admin4_code":"8658309.0",
    "gn:asciiname":"Buwandira",
    "gn:country_code":"UG",
    "gn:dem":1158,
    "gn:feature_class":"P",
    "gn:feature_code":"PPL",
    "gn:name":"Buwandira",
    "gn:population":0,
    "gn:timezone":"Africa/Kampala",
    "iso:country":"UG",
    "name:eng_x_preferred":[
        "Buwandira"
    ],
    "wof:name":"Buwandira",
    "wof:placetype":"locality"
},
  "geometry": {"coordinates":[33.99179,0.47922],"type":"Point"}
}