{
  "type": "Feature",
  "properties": {
    "gn:admin1_code":"E",
    "gn:admin2_code":"E1",
    "gn:admin3_code":"8644136.0",
    "gn:admin4_code":"8658118.0",
    "gn:asciiname":"Kavule",
    "gn:country_code":"UG",
    "gn:dem":1073,
    "gn:feature_class":"P",
    "gn:feature_code":"PPL",
    "gn:name":"Kavule",
    "gn:population":0,
    "gn:timezone":"Africa/Kampala",
    "iso:country":"UG",
    "wof:name":"Kavule",
    "wof:placetype":"locality"
},
  "geometry": {"coordinates":[33.55897,0.84768],"type":"Point"}
}