{
  "type": "Feature",
  "properties": {
    "gn:admin1_code":"W",
    "gn:admin2_code":"93",
    "gn:admin3_code":"8644148.0",
    "gn:admin4_code":"8658570.0",
    "gn:asciiname":"Nakishenyi",
    "gn:cc2":"UG",
    "gn:country_code":"UG",
    "gn:dem":1959,
    "gn:feature_class":"P",
    "gn:feature_code":"PPL",
    "gn:name":"Nakishenyi",
    "gn:population":0,
    "gn:timezone":"Africa/Kampala",
    "iso:country":"UG",
    "name:und_x_variant":[
        "Nyakishenyi",
        "Nyakishenie",
        "Nakishenyi"
    ],
    "wof:name":"Nakishenyi",
    "wof:placetype":"locality"
},
  "geometry": {"coordinates":[29.91944,-1.03778],"type":"Point"}
}