{
  "type": "Feature",
  "properties": {
    "gn:admin1_code":"E",
    "gn:admin2_code":"D6",
    "gn:admin3_code":"7869955.0",
    "gn:admin4_code":"8657922.0",
    "gn:asciiname":"Bukhaweka",
    "gn:country_code":"UG",
    "gn:dem":1277,
    "gn:feature_class":"P",
    "gn:feature_code":"PPL",
    "gn:name":"Bukhaweka",
    "gn:population":0,
    "gn:timezone":"Africa/Kampala",
    "iso:country":"UG",
    "name:eng_x_preferred":[
        "Bukhaweka"
    ],
    "wof:name":"Bukhaweka",
    "wof:placetype":"locality"
},
  "geometry": {"coordinates":[34.33,0.91889],"type":"Point"}
}