{
  "type": "Feature",
  "properties": {
    "gn:admin1_code":"C",
    "gn:admin2_code":"56",
    "gn:admin3_code":"8644175.0",
    "gn:admin4_code":"8658716.0",
    "gn:asciiname":"Bukuya",
    "gn:country_code":"UG",
    "gn:dem":1164,
    "gn:feature_class":"P",
    "gn:feature_code":"PPL",
    "gn:name":"Bukuya",
    "gn:population":0,
    "gn:timezone":"Africa/Kampala",
    "iso:country":"UG",
    "name:lug_x_preferred":[
        "Bukuya"
    ],
    "wof:name":"Bukuya",
    "wof:placetype":"locality"
},
  "geometry": {"coordinates":[31.81972,0.67861],"type":"Point"}
}