{
  "type": "Feature",
  "properties": {
    "gn:admin1_code":"E",
    "gn:admin2_code":"C6",
    "gn:admin3_code":"234147.0",
    "gn:admin4_code":"8658285.0",
    "gn:asciiname":"Bukabeba",
    "gn:country_code":"UG",
    "gn:dem":1136,
    "gn:feature_class":"P",
    "gn:feature_code":"PPL",
    "gn:name":"Bukabeba",
    "gn:population":0,
    "gn:timezone":"Africa/Kampala",
    "iso:country":"UG",
    "wof:name":"Bukabeba",
    "wof:placetype":"locality"
},
  "geometry": {"coordinates":[33.9099,0.81353],"type":"Point"}
}