{
  "type": "Feature",
  "properties": {
    "gn:admin1_code":"E",
    "gn:admin2_code":"38",
    "gn:admin3_code":"8644140.0",
    "gn:admin4_code":"8658153.0",
    "gn:asciiname":"Nawanago",
    "gn:country_code":"UG",
    "gn:dem":1093,
    "gn:feature_class":"P",
    "gn:feature_code":"PPL",
    "gn:name":"Nawanago",
    "gn:population":0,
    "gn:timezone":"Africa/Kampala",
    "iso:country":"UG",
    "name:und_x_variant":[
        "Nawanyago",
        "Nawanago"
    ],
    "wof:name":"Nawanago",
    "wof:placetype":"locality"
},
  "geometry": {"coordinates":[33.15028,0.73806],"type":"Point"}
}