{
  "type": "Feature",
  "properties": {
    "gn:admin1_code":"W",
    "gn:admin2_code":"81",
    "gn:admin3_code":"7732901.0",
    "gn:admin4_code":"8657792.0",
    "gn:asciiname":"Kantozi",
    "gn:country_code":"UG",
    "gn:dem":1363,
    "gn:feature_class":"P",
    "gn:feature_code":"PPL",
    "gn:name":"Kantozi",
    "gn:population":0,
    "gn:timezone":"Africa/Kampala",
    "iso:country":"UG",
    "wof:name":"Kantozi",
    "wof:placetype":"locality"
},
  "geometry": {"coordinates":[30.38333,-0.06667],"type":"Point"}
}