{
  "type": "Feature",
  "properties": {
    "gn:admin1_code":"W",
    "gn:admin2_code":"C9",
    "gn:admin3_code":"233175.0",
    "gn:admin4_code":"8658677.0",
    "gn:asciiname":"Kisyoro",
    "gn:country_code":"UG",
    "gn:dem":1455,
    "gn:feature_class":"P",
    "gn:feature_code":"PPLL",
    "gn:name":"Kisyoro",
    "gn:population":0,
    "gn:timezone":"Africa/Kampala",
    "iso:country":"UG",
    "wof:name":"Kisyoro",
    "wof:placetype":"locality"
},
  "geometry": {"coordinates":[30.60747000000001,-0.93438],"type":"Point"}
}