{
  "type": "Feature",
  "properties": {
    "gn:admin1_code":"E",
    "gn:admin2_code":"86",
    "gn:admin3_code":"8644164.0",
    "gn:admin4_code":"8658494.0",
    "gn:asciiname":"Ntokolo",
    "gn:country_code":"UG",
    "gn:dem":1157,
    "gn:feature_class":"P",
    "gn:feature_code":"PPL",
    "gn:name":"Ntokolo",
    "gn:population":0,
    "gn:timezone":"Africa/Kampala",
    "iso:country":"UG",
    "name:eng_x_preferred":[
        "Ntokolo"
    ],
    "wof:name":"Ntokolo",
    "wof:placetype":"locality"
},
  "geometry": {"coordinates":[33.35344,0.48832],"type":"Point"}
}