{
  "type": "Feature",
  "properties": {
    "gn:admin1_code":"C",
    "gn:admin2_code":"83",
    "gn:admin3_code":"227613.0",
    "gn:admin4_code":"8658150.0",
    "gn:asciiname":"Kireku",
    "gn:country_code":"UG",
    "gn:dem":1109,
    "gn:feature_class":"P",
    "gn:feature_code":"PPL",
    "gn:name":"Kireku",
    "gn:population":0,
    "gn:timezone":"Africa/Kampala",
    "iso:country":"UG",
    "wof:name":"Kireku",
    "wof:placetype":"locality"
},
  "geometry": {"coordinates":[32.96667,0.61667],"type":"Point"}
}