{
  "type": "Feature",
  "properties": {
    "gn:admin1_code":"C",
    "gn:admin2_code":"73",
    "gn:admin3_code":"234123.0",
    "gn:admin4_code":"8658189.0",
    "gn:asciiname":"Muwolwe",
    "gn:country_code":"UG",
    "gn:dem":1106,
    "gn:feature_class":"P",
    "gn:feature_code":"PPL",
    "gn:name":"Muwolwe",
    "gn:population":0,
    "gn:timezone":"Africa/Kampala",
    "iso:country":"UG",
    "wof:name":"Muwolwe",
    "wof:placetype":"locality"
},
  "geometry": {"coordinates":[32.51667,1.38333],"type":"Point"}
}