{
  "type": "Feature",
  "properties": {
    "gn:admin1_code":"W",
    "gn:admin2_code":"28",
    "gn:asciiname":"Nyakitokoro",
    "gn:country_code":"UG",
    "gn:dem":930,
    "gn:feature_class":"P",
    "gn:feature_code":"PPL",
    "gn:name":"Nyakitokoro",
    "gn:population":0,
    "gn:timezone":"Africa/Kampala",
    "iso:country":"UG",
    "name:eng_x_preferred":[
        "Nyakitokoro"
    ],
    "wof:name":"Nyakitokoro",
    "wof:placetype":"locality"
},
  "geometry": {"coordinates":[30.07733,0.72658],"type":"Point"}
}