{
  "type": "Feature",
  "properties": {
    "gn:admin1_code":"E",
    "gn:admin2_code":"67",
    "gn:admin3_code":"8644151.0",
    "gn:admin4_code":"8657692.0",
    "gn:asciiname":"Sibodohi",
    "gn:country_code":"UG",
    "gn:dem":1178,
    "gn:feature_class":"P",
    "gn:feature_code":"PPL",
    "gn:name":"Sibodohi",
    "gn:population":0,
    "gn:timezone":"Africa/Kampala",
    "iso:country":"UG",
    "name:eng_x_preferred":[
        "Sibodohi"
    ],
    "wof:name":"Sibodohi",
    "wof:placetype":"locality"
},
  "geometry": {"coordinates":[33.91297,0.28367],"type":"Point"}
}