{
  "type": "Feature",
  "properties": {
    "gn:admin1_code":"W",
    "gn:admin2_code":"79",
    "gn:asciiname":"Busita",
    "gn:country_code":"UG",
    "gn:dem":1530,
    "gn:feature_class":"P",
    "gn:feature_code":"PPL",
    "gn:name":"Busita",
    "gn:population":0,
    "gn:timezone":"Africa/Kampala",
    "iso:country":"UG",
    "name:eng_x_preferred":[
        "Busita"
    ],
    "wof:name":"Busita",
    "wof:placetype":"locality"
},
  "geometry": {"coordinates":[30.17817,0.5142],"type":"Point"}
}