{
  "type": "Feature",
  "properties": {
    "gn:admin1_code":"C",
    "gn:admin2_code":"89",
    "gn:asciiname":"Bunamweri",
    "gn:country_code":"UG",
    "gn:dem":1216,
    "gn:feature_class":"P",
    "gn:feature_code":"PPL",
    "gn:name":"Bunamweri",
    "gn:population":0,
    "gn:timezone":"Africa/Kampala",
    "iso:country":"UG",
    "wof:name":"Bunamweri",
    "wof:placetype":"locality"
},
  "geometry": {"coordinates":[32.3388,0.25143],"type":"Point"}
}