{
  "type": "Feature",
  "properties": {
    "gn:admin1_code":"00",
    "gn:asciiname":"Kagera",
    "gn:country_code":"UG",
    "gn:dem":1462,
    "gn:feature_class":"P",
    "gn:feature_code":"PPL",
    "gn:name":"Kagera",
    "gn:population":0,
    "gn:timezone":"Africa/Kampala",
    "iso:country":"UG",
    "wof:name":"Kagera",
    "wof:placetype":"locality"
},
  "geometry": {"coordinates":[30.37978,0.64473],"type":"Point"}
}