{
  "type": "Feature",
  "properties": {
    "gn:admin1_code":"00",
    "gn:asciiname":"Kagera",
    "gn:country_code":"UG",
    "gn:dem":1462,
    "gn:feature_class":"P",
    "gn:feature_code":"PPL",
    "gn:name":"Kagera",
    "gn:population":0,
    "gn:timezone":"Africa/Kampala",
    "iso:country":"UG",
    "name:ceb_x_preferred":[
        "Kagera"
    ],
    "name:deu_x_preferred":[
        "Kagera"
    ],
    "name:glg_x_preferred":[
        "Kagera"
    ],
    "name:ind_x_preferred":[
        "Kagera"
    ],
    "name:ita_x_preferred":[
        "Kagera"
    ],
    "name:nld_x_preferred":[
        "Kagera"
    ],
    "name:slk_x_preferred":[
        "Kagera"
    ],
    "name:swa_x_preferred":[
        "Kagera"
    ],
    "name:swe_x_preferred":[
        "Kagera"
    ],
    "wof:name":"Kagera",
    "wof:placetype":"locality"
},
  "geometry": {"coordinates":[30.37978,0.64473],"type":"Point"}
}