{
  "type": "Feature",
  "properties": {
    "gn:admin1_code":"C",
    "gn:admin2_code":"96",
    "gn:asciiname":"Bugimba",
    "gn:country_code":"UG",
    "gn:dem":1193,
    "gn:feature_class":"P",
    "gn:feature_code":"PPL",
    "gn:name":"Bugimba",
    "gn:population":0,
    "gn:timezone":"Africa/Kampala",
    "iso:country":"UG",
    "wof:name":"Bugimba",
    "wof:placetype":"locality"
},
  "geometry": {"coordinates":[32.26724,0.48876],"type":"Point"}
}