{
  "type": "Feature",
  "properties": {
    "gn:admin1_code":"C",
    "gn:admin2_code":"89",
    "gn:asciiname":"Mayirikiti",
    "gn:country_code":"UG",
    "gn:dem":1171,
    "gn:feature_class":"P",
    "gn:feature_code":"PPL",
    "gn:name":"Mayirikiti",
    "gn:population":0,
    "gn:timezone":"Africa/Kampala",
    "iso:country":"UG",
    "wof:name":"Mayirikiti",
    "wof:placetype":"locality"
},
  "geometry": {"coordinates":[32.17466,0.05502],"type":"Point"}
}