{
  "type": "Feature",
  "properties": {
    "gn:admin1_code":"N",
    "gn:admin2_code":"D7",
    "gn:admin3_code":"229396.0",
    "gn:admin4_code":"8658185.0",
    "gn:asciiname":"Tara",
    "gn:country_code":"UG",
    "gn:dem":1040,
    "gn:feature_class":"P",
    "gn:feature_code":"PPL",
    "gn:name":"Tara",
    "gn:population":0,
    "gn:timezone":"Africa/Kampala",
    "iso:country":"UG",
    "wof:name":"Tara",
    "wof:placetype":"locality"
},
  "geometry": {"coordinates":[31.0334,3.3102],"type":"Point"}
}