{
  "type": "Feature",
  "properties": {
    "gn:admin1_code":"C",
    "gn:admin2_code":"61",
    "gn:admin3_code":"8644135.0",
    "gn:admin4_code":"8658279.0",
    "gn:asciiname":"Kamengo",
    "gn:country_code":"UG",
    "gn:dem":1231,
    "gn:feature_class":"P",
    "gn:feature_code":"PPL",
    "gn:name":"Kamengo",
    "gn:population":0,
    "gn:timezone":"Africa/Kampala",
    "iso:country":"UG",
    "wof:name":"Kamengo",
    "wof:placetype":"locality"
},
  "geometry": {"coordinates":[31.46667,-0.66667],"type":"Point"}
}