{
  "type": "Feature",
  "properties": {
    "gn:admin1_code":"E",
    "gn:admin2_code":"78",
    "gn:admin3_code":"231410.0",
    "gn:admin4_code":"8658572.0",
    "gn:asciiname":"Baligahna",
    "gn:country_code":"UG",
    "gn:dem":1092,
    "gn:feature_class":"P",
    "gn:feature_code":"PPL",
    "gn:name":"Baligahna",
    "gn:population":0,
    "gn:timezone":"Africa/Kampala",
    "iso:country":"UG",
    "name:und_x_variant":[
        "Buliganya"
    ],
    "wof:name":"Baligahna",
    "wof:placetype":"locality"
},
  "geometry": {"coordinates":[33.40424,0.7671],"type":"Point"}
}