{
  "type": "Feature",
  "properties": {
    "gn:admin1_code":"W",
    "gn:admin2_code":"85",
    "gn:admin3_code":"228643.0",
    "gn:admin4_code":"8657592.0",
    "gn:asciiname":"Bugaki",
    "gn:country_code":"UG",
    "gn:dem":1528,
    "gn:feature_class":"P",
    "gn:feature_code":"PPL",
    "gn:name":"Bugaki",
    "gn:population":0,
    "gn:timezone":"Africa/Kampala",
    "iso:country":"UG",
    "wof:name":"Bugaki",
    "wof:placetype":"locality"
},
  "geometry": {"coordinates":[30.48236,0.67103],"type":"Point"}
}