{
  "type": "Feature",
  "properties": {
    "gn:country":"UG",
    "gn:fcode":"PPLA2",
    "gn:population":11503,
    "iso:country":"UG",
    "name:eng_x_preferred":[
        "Mayuge"
    ],
    "name:jpn_x_preferred":[
        "\u30de\u30e6\u30b2"
    ],
    "name:nld_x_preferred":[
        "Mayuge"
    ],
    "name:nob_x_preferred":[
        "Mayuge"
    ],
    "name:ron_x_preferred":[
        "Mayuge"
    ],
    "name:swa_x_preferred":[
        "Mayuge"
    ],
    "name:urd_x_preferred":[
        "\u0645\u0627\u0626\u0648\u06af\u06cc"
    ],
    "qs_pg:aaroncc":"UG",
    "qs_pg:gn_country":"UG",
    "qs_pg:gn_fcode":"PPLA2",
    "qs_pg:gn_pop":11503,
    "qs_pg:name":"Mayuge",
    "qs_pg:photos_9r":0,
    "qs_pg:photos_sr":0,
    "qs_pg:pop_sr":6,
    "qs_pg:qs_pg_placetype":"locality",
    "wof:name":"Mayuge",
    "wof:placetype":"locality",
    "wof:population":11503
},
  "geometry": {"coordinates":[33.48028,0.45972],"type":"Point"}
}