{
  "type": "Feature",
  "properties": {
    "gn:admin1_code":"E",
    "gn:admin2_code":"46",
    "gn:asciiname":"Olupe",
    "gn:country_code":"UG",
    "gn:dem":1118,
    "gn:feature_class":"P",
    "gn:feature_code":"PPLL",
    "gn:name":"Olupe",
    "gn:population":0,
    "gn:timezone":"Africa/Kampala",
    "iso:country":"UG",
    "wof:name":"Olupe",
    "wof:placetype":"locality"
},
  "geometry": {"coordinates":[33.87905,1.54343],"type":"Point"}
}