{
  "type": "Feature",
  "properties": {
    "gn:admin1_code":"E",
    "gn:admin2_code":"76",
    "gn:asciiname":"Amori-Powino",
    "gn:country_code":"UG",
    "gn:dem":1109,
    "gn:feature_class":"P",
    "gn:feature_code":"PPL",
    "gn:name":"Amori-Powino",
    "gn:population":0,
    "gn:timezone":"Africa/Kampala",
    "iso:country":"UG",
    "name:eng_x_preferred":[
        "Amori-Powino"
    ],
    "wof:name":"Amori-Powino",
    "wof:placetype":"locality"
},
  "geometry": {"coordinates":[34.02863,0.65802],"type":"Point"}
}