{
  "type": "Feature",
  "properties": {
    "gn:admin1_code":"C",
    "gn:admin2_code":"G5",
    "gn:admin3_code":"7910221.0",
    "gn:admin4_code":"8658013.0",
    "gn:asciiname":"Mukukute",
    "gn:country_code":"UG",
    "gn:dem":1453,
    "gn:feature_class":"P",
    "gn:feature_code":"PPL",
    "gn:name":"Mukukute",
    "gn:population":0,
    "gn:timezone":"Africa/Kampala",
    "iso:country":"UG",
    "wof:name":"Mukukute",
    "wof:placetype":"locality"
},
  "geometry": {"coordinates":[31.28333,-0.35],"type":"Point"}
}