{
  "type": "Feature",
  "properties": {
    "gn:admin1_code":"C",
    "gn:admin2_code":"D8",
    "gn:asciiname":"Mbuye",
    "gn:country_code":"UG",
    "gn:dem":1215,
    "gn:feature_class":"P",
    "gn:feature_code":"PPL",
    "gn:name":"Mbuye",
    "gn:population":0,
    "gn:timezone":"Africa/Kampala",
    "iso:country":"UG",
    "wof:name":"Mbuye",
    "wof:placetype":"locality"
},
  "geometry": {"coordinates":[32.05955,0.30646],"type":"Point"}
}