{
  "type": "Feature",
  "properties": {
    "gn:admin1_code":"N",
    "gn:admin2_code":"B7",
    "gn:admin3_code":"231170.0",
    "gn:admin4_code":"8658377.0",
    "gn:asciiname":"Adita",
    "gn:country_code":"UG",
    "gn:dem":1063,
    "gn:feature_class":"P",
    "gn:feature_code":"PPLL",
    "gn:name":"Adita",
    "gn:population":0,
    "gn:timezone":"Africa/Kampala",
    "iso:country":"UG",
    "name:eng_x_preferred":[
        "Adita"
    ],
    "wof:name":"Adita",
    "wof:placetype":"locality"
},
  "geometry": {"coordinates":[32.86943,1.68657],"type":"Point"}
}