{
  "type": "Feature",
  "properties": {
    "gn:admin1_code":"E",
    "gn:admin2_code":"38",
    "gn:asciiname":"Buwuda",
    "gn:country_code":"UG",
    "gn:dem":1085,
    "gn:feature_class":"P",
    "gn:feature_code":"PPL",
    "gn:name":"Buwuda",
    "gn:population":0,
    "gn:timezone":"Africa/Kampala",
    "iso:country":"UG",
    "wof:name":"Buwuda",
    "wof:placetype":"locality"
},
  "geometry": {"coordinates":[33.08579,0.93091],"type":"Point"}
}