{
  "type": "Feature",
  "properties": {
    "gn:admin1_code":"E",
    "gn:admin2_code":"33",
    "gn:asciiname":"Lukonko",
    "gn:country_code":"UG",
    "gn:dem":1160,
    "gn:feature_class":"P",
    "gn:feature_code":"PPL",
    "gn:name":"Lukonko",
    "gn:population":0,
    "gn:timezone":"Africa/Kampala",
    "iso:country":"UG",
    "wof:name":"Lukonko",
    "wof:placetype":"locality"
},
  "geometry": {"coordinates":[33.29508,0.5747],"type":"Point"}
}