{
  "type": "Feature",
  "properties": {
    "gn:admin1_code":"N",
    "gn:admin2_code":"77",
    "gn:admin3_code":"8644146.0",
    "gn:admin4_code":"8261591.0",
    "gn:asciiname":"Abarua",
    "gn:country_code":"UG",
    "gn:dem":674,
    "gn:feature_class":"P",
    "gn:feature_code":"PPL",
    "gn:name":"Abarua",
    "gn:population":0,
    "gn:timezone":"Africa/Kampala",
    "iso:country":"UG",
    "name:deu_x_preferred":[
        "Arua"
    ],
    "name:eng_x_preferred":[
        "Arua"
    ],
    "name:fra_x_preferred":[
        "Arua"
    ],
    "wof:name":"Abarua",
    "wof:placetype":"locality"
},
  "geometry": {"coordinates":[31.36674,2.9504],"type":"Point"}
}