{
  "type": "Feature",
  "properties": {
    "gn:admin1_code":"E",
    "gn:admin2_code":"87",
    "gn:asciiname":"Namakye",
    "gn:country_code":"UG",
    "gn:dem":1118,
    "gn:feature_class":"P",
    "gn:feature_code":"PPL",
    "gn:name":"Namakye",
    "gn:population":0,
    "gn:timezone":"Africa/Kampala",
    "iso:country":"UG",
    "name:eng_x_preferred":[
        "Namakye"
    ],
    "wof:name":"Namakye",
    "wof:placetype":"locality"
},
  "geometry": {"coordinates":[34.13552,0.94598],"type":"Point"}
}