{
  "type": "Feature",
  "properties": {
    "gn:admin1_code":"C",
    "gn:admin2_code":"73",
    "gn:admin3_code":"234123.0",
    "gn:admin4_code":"8658578.0",
    "gn:asciiname":"Kidugali",
    "gn:country_code":"UG",
    "gn:dem":1044,
    "gn:feature_class":"P",
    "gn:feature_code":"PPL",
    "gn:name":"Kidugali",
    "gn:population":0,
    "gn:timezone":"Africa/Kampala",
    "iso:country":"UG",
    "wof:name":"Kidugali",
    "wof:placetype":"locality"
},
  "geometry": {"coordinates":[32.10740999999999,1.61492],"type":"Point"}
}