{
  "type": "Feature",
  "properties": {
    "gn:admin1_code":"W",
    "gn:admin2_code":"C5",
    "gn:admin3_code":"7869947.0",
    "gn:admin4_code":"8657899.0",
    "gn:asciiname":"Bugoigo",
    "gn:country_code":"UG",
    "gn:dem":627,
    "gn:feature_class":"P",
    "gn:feature_code":"PPL",
    "gn:name":"Bugoigo",
    "gn:population":0,
    "gn:timezone":"Africa/Kampala",
    "iso:country":"UG",
    "wof:name":"Bugoigo",
    "wof:placetype":"locality"
},
  "geometry": {"coordinates":[31.3997,1.89656],"type":"Point"}
}