{
  "type": "Feature",
  "properties": {
    "gn:admin1_code":"C",
    "gn:admin2_code":"90",
    "gn:admin3_code":"7732383.0",
    "gn:admin4_code":"8657984.0",
    "gn:asciiname":"Kasawo",
    "gn:country_code":"UG",
    "gn:dem":1111,
    "gn:feature_class":"P",
    "gn:feature_code":"PPL",
    "gn:name":"Kasawo",
    "gn:population":0,
    "gn:timezone":"Africa/Kampala",
    "iso:country":"UG",
    "name:lug_x_preferred":[
        "Kasawo"
    ],
    "wof:name":"Kasawo",
    "wof:placetype":"locality"
},
  "geometry": {"coordinates":[32.82528,0.6775],"type":"Point"}
}