{
  "type": "Feature",
  "properties": {
    "gn:admin1_code":"E",
    "gn:admin2_code":"D6",
    "gn:asciiname":"Bumayayo",
    "gn:country_code":"UG",
    "gn:dem":1534,
    "gn:feature_class":"P",
    "gn:feature_code":"PPL",
    "gn:name":"Bumayayo",
    "gn:population":0,
    "gn:timezone":"Africa/Kampala",
    "iso:country":"UG",
    "name:eng_x_preferred":[
        "Bumayayo"
    ],
    "wof:name":"Bumayayo",
    "wof:placetype":"locality"
},
  "geometry": {"coordinates":[34.35948,0.86992],"type":"Point"}
}