{
  "type": "Feature",
  "properties": {
    "gn:admin1_code":"W",
    "gn:admin2_code":"28",
    "gn:asciiname":"Bundinduru",
    "gn:country_code":"UG",
    "gn:dem":809,
    "gn:feature_class":"P",
    "gn:feature_code":"PPL",
    "gn:name":"Bundinduru",
    "gn:population":0,
    "gn:timezone":"Africa/Kampala",
    "iso:country":"UG",
    "name:eng_x_preferred":[
        "Bundinduru"
    ],
    "wof:name":"Bundinduru",
    "wof:placetype":"locality"
},
  "geometry": {"coordinates":[30.03879,0.74002],"type":"Point"}
}