{
  "type": "Feature",
  "properties": {
    "gn:admin1_code":"E",
    "gn:admin2_code":"66",
    "gn:asciiname":"Butyabule",
    "gn:country_code":"UG",
    "gn:dem":1094,
    "gn:feature_class":"P",
    "gn:feature_code":"PPL",
    "gn:name":"Butyabule",
    "gn:population":0,
    "gn:timezone":"Africa/Kampala",
    "iso:country":"UG",
    "wof:name":"Butyabule",
    "wof:placetype":"locality"
},
  "geometry": {"coordinates":[33.75807,0.68947],"type":"Point"}
}