{
  "type": "Feature",
  "properties": {
    "gn:admin1_code":"W",
    "gn:admin2_code":"85",
    "gn:asciiname":"Nyamasoga",
    "gn:country_code":"UG",
    "gn:dem":1519,
    "gn:feature_class":"P",
    "gn:feature_code":"PPL",
    "gn:name":"Nyamasoga",
    "gn:population":0,
    "gn:timezone":"Africa/Kampala",
    "iso:country":"UG",
    "name:eng_x_preferred":[
        "Nyamasoga"
    ],
    "wof:name":"Nyamasoga",
    "wof:placetype":"locality"
},
  "geometry": {"coordinates":[30.45908,0.73069],"type":"Point"}
}