{
  "type": "Feature",
  "properties": {
    "gn:admin1_code":"N",
    "gn:admin2_code":"I5",
    "gn:admin3_code":"227037.0",
    "gn:admin4_code":"8658086.0",
    "gn:asciiname":"Koro",
    "gn:country_code":"UG",
    "gn:dem":1096,
    "gn:feature_class":"P",
    "gn:feature_code":"PPL",
    "gn:name":"Koro",
    "gn:population":0,
    "gn:timezone":"Africa/Kampala",
    "iso:country":"UG",
    "name:ceb_x_preferred":[
        "Koro"
    ],
    "name:ces_x_preferred":[
        "Koro"
    ],
    "name:deu_x_preferred":[
        "Koro"
    ],
    "name:epo_x_preferred":[
        "Koro"
    ],
    "name:eus_x_preferred":[
        "Koro"
    ],
    "name:fin_x_preferred":[
        "Koro"
    ],
    "name:fra_x_preferred":[
        "Koro"
    ],
    "name:hrv_x_preferred":[
        "Koro"
    ],
    "name:ido_x_preferred":[
        "Koro"
    ],
    "name:ita_x_preferred":[
        "Koro"
    ],
    "name:lit_x_preferred":[
        "Koras"
    ],
    "name:lmo_x_preferred":[
        "Koro"
    ],
    "name:nld_x_preferred":[
        "Koro"
    ],
    "name:spa_x_preferred":[
        "Koro"
    ],
    "name:swa_x_preferred":[
        "Koro"
    ],
    "name:swe_x_preferred":[
        "Koro"
    ],
    "name:tur_x_preferred":[
        "Koro"
    ],
    "wof:name":"Koro",
    "wof:placetype":"locality"
},
  "geometry": {"coordinates":[32.30972,2.72306],"type":"Point"}
}