{
  "type": "Feature",
  "properties": {
    "gn:admin1_code":"E",
    "gn:admin2_code":"67",
    "gn:admin3_code":"8644151.0",
    "gn:admin4_code":"8658207.0",
    "gn:asciiname":"Mudoma",
    "gn:country_code":"UG",
    "gn:dem":1195,
    "gn:feature_class":"P",
    "gn:feature_code":"PPL",
    "gn:name":"Mudoma",
    "gn:population":0,
    "gn:timezone":"Africa/Kampala",
    "iso:country":"UG",
    "name:eng_x_preferred":[
        "Mudoma"
    ],
    "wof:name":"Mudoma",
    "wof:placetype":"locality"
},
  "geometry": {"coordinates":[33.97924,0.32063],"type":"Point"}
}