{
  "type": "Feature",
  "properties": {
    "gn:admin1_code":"N",
    "gn:admin2_code":"B7",
    "gn:admin3_code":"231170.0",
    "gn:admin4_code":"8657992.0",
    "gn:asciiname":"Kikondo",
    "gn:country_code":"UG",
    "gn:dem":1045,
    "gn:feature_class":"P",
    "gn:feature_code":"PPLL",
    "gn:name":"Kikondo",
    "gn:population":0,
    "gn:timezone":"Africa/Kampala",
    "iso:country":"UG",
    "name:eng_x_preferred":[
        "Kikondo"
    ],
    "wof:name":"Kikondo",
    "wof:placetype":"locality"
},
  "geometry": {"coordinates":[32.7024,1.51146],"type":"Point"}
}