{
  "type": "Feature",
  "properties": {
    "gn:admin1_code":"W",
    "gn:admin2_code":"79",
    "gn:asciiname":"Bukuba",
    "gn:country_code":"UG",
    "gn:dem":1680,
    "gn:feature_class":"P",
    "gn:feature_code":"PPL",
    "gn:name":"Bukuba",
    "gn:population":0,
    "gn:timezone":"Africa/Kampala",
    "iso:country":"UG",
    "name:eng_x_preferred":[
        "Bukuba"
    ],
    "wof:name":"Bukuba",
    "wof:placetype":"locality"
},
  "geometry": {"coordinates":[30.13944,0.50846],"type":"Point"}
}