{
  "type": "Feature",
  "properties": {
    "gn:admin1_code":"C",
    "gn:admin2_code":"96",
    "gn:admin3_code":"234053.0",
    "gn:admin4_code":"8658010.0",
    "gn:asciiname":"Nakigalala",
    "gn:country_code":"UG",
    "gn:dem":1204,
    "gn:feature_class":"P",
    "gn:feature_code":"PPL",
    "gn:name":"Nakigalala",
    "gn:population":0,
    "gn:timezone":"Africa/Kampala",
    "iso:country":"UG",
    "wof:name":"Nakigalala",
    "wof:placetype":"locality"
},
  "geometry": {"coordinates":[32.51341,0.21636],"type":"Point"}
}