{
  "type": "Feature",
  "properties": {
    "gn:admin1_code":"E",
    "gn:admin2_code":"D6",
    "gn:asciiname":"Buwere",
    "gn:country_code":"UG",
    "gn:dem":1217,
    "gn:feature_class":"P",
    "gn:feature_code":"PPL",
    "gn:name":"Buwere",
    "gn:population":0,
    "gn:timezone":"Africa/Kampala",
    "iso:country":"UG",
    "name:eng_x_preferred":[
        "Buwere"
    ],
    "wof:name":"Buwere",
    "wof:placetype":"locality"
},
  "geometry": {"coordinates":[34.24225,0.92324],"type":"Point"}
}