{
  "type": "Feature",
  "properties": {
    "gn:admin1_code":"E",
    "gn:admin2_code":"76",
    "gn:asciiname":"Ramogi",
    "gn:country_code":"UG",
    "gn:dem":1173,
    "gn:feature_class":"P",
    "gn:feature_code":"PPL",
    "gn:name":"Ramogi",
    "gn:population":0,
    "gn:timezone":"Africa/Kampala",
    "iso:country":"UG",
    "name:eng_x_preferred":[
        "Ramogi"
    ],
    "wof:name":"Ramogi",
    "wof:placetype":"locality"
},
  "geometry": {"coordinates":[34.10733,0.77838],"type":"Point"}
}