{
  "type": "Feature",
  "properties": {
    "gn:admin1_code":"N",
    "gn:admin2_code":"88",
    "gn:admin3_code":"229332.0",
    "gn:admin4_code":"8630016.0",
    "gn:asciiname":"Tapak",
    "gn:country_code":"UG",
    "gn:dem":1747,
    "gn:feature_class":"P",
    "gn:feature_code":"PPL",
    "gn:name":"Tapak",
    "gn:population":0,
    "gn:timezone":"Africa/Kampala",
    "iso:country":"UG",
    "wof:name":"Tapak",
    "wof:placetype":"locality"
},
  "geometry": {"coordinates":[34.8319,2.49795],"type":"Point"}
}