{
  "type": "Feature",
  "properties": {
    "gn:admin1_code":"C",
    "gn:admin2_code":"96",
    "gn:admin3_code":"234053.0",
    "gn:admin4_code":"7732546.0",
    "gn:asciiname":"Sempya",
    "gn:country_code":"UG",
    "gn:dem":1198,
    "gn:feature_class":"P",
    "gn:feature_code":"PPL",
    "gn:name":"Sempya",
    "gn:population":0,
    "gn:timezone":"Africa/Kampala",
    "iso:country":"UG",
    "wof:name":"Sempya",
    "wof:placetype":"locality"
},
  "geometry": {"coordinates":[32.22433,0.491],"type":"Point"}
}