{
  "type": "Feature",
  "properties": {
    "gn:admin1_code":"E",
    "gn:admin2_code":"38",
    "gn:asciiname":"Buwande",
    "gn:country_code":"UG",
    "gn:dem":1082,
    "gn:feature_class":"P",
    "gn:feature_code":"PPL",
    "gn:name":"Buwande",
    "gn:population":0,
    "gn:timezone":"Africa/Kampala",
    "iso:country":"UG",
    "wof:name":"Buwande",
    "wof:placetype":"locality"
},
  "geometry": {"coordinates":[33.28026,0.84268],"type":"Point"}
}