{
  "type": "Feature",
  "properties": {
    "gn:admin1_code":"W",
    "gn:admin2_code":"52",
    "gn:admin3_code":"232055.0",
    "gn:admin4_code":"8658575.0",
    "gn:asciiname":"Kakika",
    "gn:country_code":"UG",
    "gn:dem":1415,
    "gn:feature_class":"P",
    "gn:feature_code":"PPL",
    "gn:name":"Kakika",
    "gn:population":0,
    "gn:timezone":"Africa/Kampala",
    "iso:country":"UG",
    "wof:name":"Kakika",
    "wof:placetype":"locality"
},
  "geometry": {"coordinates":[30.65,-0.58333],"type":"Point"}
}