{
  "type": "Feature",
  "properties": {
    "gn:admin1_code":"W",
    "gn:admin2_code":"29",
    "gn:admin3_code":"7732267.0",
    "gn:admin4_code":"8657856.0",
    "gn:asciiname":"Nyanga",
    "gn:country_code":"UG",
    "gn:dem":1466,
    "gn:feature_class":"P",
    "gn:feature_code":"PPL",
    "gn:name":"Nyanga",
    "gn:population":0,
    "gn:timezone":"Africa/Kampala",
    "iso:country":"UG",
    "wof:name":"Nyanga",
    "wof:placetype":"locality"
},
  "geometry": {"coordinates":[30.16667,-0.45],"type":"Point"}
}