{
  "type": "Feature",
  "properties": {
    "gn:admin1_code":"W",
    "gn:admin2_code":"29",
    "gn:admin3_code":"7732267.0",
    "gn:admin4_code":"8657856.0",
    "gn:asciiname":"Nyanga",
    "gn:country_code":"UG",
    "gn:dem":1466,
    "gn:feature_class":"P",
    "gn:feature_code":"PPL",
    "gn:name":"Nyanga",
    "gn:population":0,
    "gn:timezone":"Africa/Kampala",
    "iso:country":"UG",
    "name:bar_x_preferred":[
        "Nyanga"
    ],
    "name:ceb_x_preferred":[
        "Nyanga"
    ],
    "name:deu_x_preferred":[
        "Nyanga"
    ],
    "name:fin_x_preferred":[
        "Nyanga"
    ],
    "name:fra_x_preferred":[
        "Nyanga"
    ],
    "name:hrv_x_preferred":[
        "Nyanga"
    ],
    "name:ita_x_preferred":[
        "Nyanga"
    ],
    "name:nld_x_preferred":[
        "Nyanga"
    ],
    "name:spa_x_preferred":[
        "Nyanga"
    ],
    "name:srp_x_preferred":[
        "\u040a\u0430\u043d\u0433\u0430"
    ],
    "name:swe_x_preferred":[
        "Nyanga"
    ],
    "name:tur_x_preferred":[
        "Nyanga"
    ],
    "wof:name":"Nyanga",
    "wof:placetype":"locality"
},
  "geometry": {"coordinates":[30.16667,-0.45],"type":"Point"}
}