{
  "type": "Feature",
  "properties": {
    "gn:admin1_code":"N",
    "gn:admin2_code":"88",
    "gn:admin3_code":"7732233.0",
    "gn:admin4_code":"8658523.0",
    "gn:asciiname":"Nadiket",
    "gn:country_code":"UG",
    "gn:dem":1359,
    "gn:feature_class":"P",
    "gn:feature_code":"PPL",
    "gn:name":"Nadiket",
    "gn:population":0,
    "gn:timezone":"Africa/Kampala",
    "iso:country":"UG",
    "name:und_x_variant":[
        "Nandiket"
    ],
    "wof:name":"Nadiket",
    "wof:placetype":"locality"
},
  "geometry": {"coordinates":[34.65702,2.51126],"type":"Point"}
}