{
  "type": "Feature",
  "properties": {
    "gn:admin1_code":"W",
    "gn:admin2_code":"50",
    "gn:admin3_code":"234463.0",
    "gn:admin4_code":"8658090.0",
    "gn:asciiname":"Bikonzi",
    "gn:country_code":"UG",
    "gn:dem":1206,
    "gn:feature_class":"P",
    "gn:feature_code":"PPL",
    "gn:name":"Bikonzi",
    "gn:population":0,
    "gn:timezone":"Africa/Kampala",
    "iso:country":"UG",
    "wof:name":"Bikonzi",
    "wof:placetype":"locality"
},
  "geometry": {"coordinates":[31.6592,1.59524],"type":"Point"}
}