{
  "type": "Feature",
  "properties": {
    "gn:admin1_code":"C",
    "gn:admin2_code":"96",
    "gn:asciiname":"Kakunyu",
    "gn:country_code":"UG",
    "gn:dem":1193,
    "gn:feature_class":"P",
    "gn:feature_code":"PPL",
    "gn:name":"Kakunyu",
    "gn:population":0,
    "gn:timezone":"Africa/Kampala",
    "iso:country":"UG",
    "wof:name":"Kakunyu",
    "wof:placetype":"locality"
},
  "geometry": {"coordinates":[32.46052,0.42773],"type":"Point"}
}