{
  "type": "Feature",
  "properties": {
    "gn:country":"UG",
    "gn:fcode":"PPLA2",
    "gn:pop":10300,
    "iso:country":"UG",
    "name:dut_x_preferred":[
        "Moroto"
    ],
    "name:eng_x_preferred":[
        "Moroto"
    ],
    "name:heb_x_preferred":[
        "\u05de\u05d5\u05e8\u05d5\u05d8\u05d5"
    ],
    "name:hun_x_preferred":[
        "Moroto"
    ],
    "name:jpn_x_preferred":[
        "\u30e2\u30ed\u30c8"
    ],
    "name:nob_x_preferred":[
        "Moroto"
    ],
    "name:rum_x_preferred":[
        "Moroto"
    ],
    "name:swa_x_preferred":[
        "Moroto"
    ],
    "name:unk_x_variant":[
        "Maroto"
    ],
    "name:urd_x_preferred":[
        "\u0645\u0648\u0631\u0648\u062a\u0648 \u0679\u0627\u0624\u0646"
    ],
    "ne:ADM0CAP":0.0,
    "ne:ADM0NAME":"Uganda",
    "ne:ADM0_A3":"UGA",
    "ne:ADM1NAME":"Moroto",
    "ne:ADMIN1_COD":88,
    "ne:CAPALT":0,
    "ne:CHANGED":4,
    "ne:CHECKME":5,
    "ne:COMPARE":0,
    "ne:DIFFASCII":0,
    "ne:DIFFNOTE":"Changed feature to Admin-0 region capital.",
    "ne:ELEVATION":0.0,
    "ne:FEATURECLA":"Admin-1 region capital",
    "ne:FEATURE_CL":"P",
    "ne:FEATURE_CO":"PPLA",
    "ne:GEONAMEID":229112,
    "ne:GEONAMESNO":"GeoNames spatial join with similar names only.",
    "ne:GN_ASCII":"Moroto",
    "ne:GN_POP":0,
    "ne:GTOPO30":1377.0,
    "ne:ISO_A2":"UG",
    "ne:LABELRANK":5,
    "ne:LATITUDE":2.540348,
    "ne:LONGITUDE":34.639994,
    "ne:LS_MATCH":1,
    "ne:LS_NAME":"Moroto",
    "ne:MAX_AREAKM":1.0,
    "ne:MAX_AREAMI":0.0,
    "ne:MAX_BBXMAX":34.641667,
    "ne:MAX_BBXMIN":34.633333,
    "ne:MAX_BBYMAX":2.533333,
    "ne:MAX_BBYMIN":2.525,
    "ne:MAX_NATSCA":20.0,
    "ne:MAX_PERKM":4.0,
    "ne:MAX_PERMI":2.0,
    "ne:MAX_POP10":371,
    "ne:MAX_POP20":371,
    "ne:MAX_POP300":0,
    "ne:MAX_POP310":0,
    "ne:MAX_POP50":0,
    "ne:MEAN_BBXC":34.6375,
    "ne:MEAN_BBYC":2.529167,
    "ne:MEGACITY":0,
    "ne:MIN_AREAKM":1.0,
    "ne:MIN_AREAMI":0.0,
    "ne:MIN_BBXMAX":34.641667,
    "ne:MIN_BBXMIN":34.633333,
    "ne:MIN_BBYMAX":2.533333,
    "ne:MIN_BBYMIN":2.525,
    "ne:MIN_PERKM":4.0,
    "ne:MIN_PERMI":2.0,
    "ne:NAME":"Moroto",
    "ne:NAMEASCII":"Moroto",
    "ne:NAMEDIFF":0,
    "ne:NATSCALE":20,
    "ne:POP1950":0,
    "ne:POP1955":0,
    "ne:POP1960":0,
    "ne:POP1965":0,
    "ne:POP1970":0,
    "ne:POP1975":0,
    "ne:POP1980":0,
    "ne:POP1985":0,
    "ne:POP1990":0,
    "ne:POP1995":0,
    "ne:POP2000":0,
    "ne:POP2005":0,
    "ne:POP2010":0,
    "ne:POP2015":0,
    "ne:POP2020":0,
    "ne:POP2025":0,
    "ne:POP2050":0,
    "ne:POP_MAX":371,
    "ne:POP_MIN":371,
    "ne:POP_OTHER":0,
    "ne:RANK_MAX":2,
    "ne:RANK_MIN":2,
    "ne:SCALERANK":7,
    "ne:SOV0NAME":"Uganda",
    "ne:SOV_A3":"UGA",
    "ne:TIMEZONE":"Africa/Kampala",
    "ne:UN_FID":0,
    "ne:UN_LAT":0.0,
    "ne:UN_LONG":0.0,
    "ne:WORLDCITY":0,
    "qs:name":"Moroto",
    "qs:photos_9r":0,
    "qs:photos_sr":0,
    "qs:pop_sr":"6",
    "wd:wordcount":34,
    "wof:name":"Moroto",
    "wof:placetype":"locality",
    "wof:population":10300
},
  "geometry": {"coordinates":[34.66659,2.53453],"type":"Point"}
}