{
  "type": "Feature",
  "properties": {
    "gn:admin1_code":"C",
    "gn:admin2_code":"90",
    "gn:admin3_code":"7732384.0",
    "gn:admin4_code":"8658501.0",
    "gn:asciiname":"Kamwanyi",
    "gn:country_code":"UG",
    "gn:dem":1154,
    "gn:feature_class":"P",
    "gn:feature_code":"PPL",
    "gn:name":"Kamwanyi",
    "gn:population":0,
    "gn:timezone":"Africa/Kampala",
    "iso:country":"UG",
    "wof:name":"Kamwanyi",
    "wof:placetype":"locality"
},
  "geometry": {"coordinates":[32.70676,0.1053],"type":"Point"}
}