{
  "type": "Feature",
  "properties": {
    "gn:admin1_code":"E",
    "gn:admin2_code":"87",
    "gn:asciiname":"Watsongole",
    "gn:country_code":"UG",
    "gn:dem":1244,
    "gn:feature_class":"P",
    "gn:feature_code":"PPL",
    "gn:name":"Watsongole",
    "gn:population":0,
    "gn:timezone":"Africa/Kampala",
    "iso:country":"UG",
    "name:eng_x_preferred":[
        "Watsongole"
    ],
    "wof:name":"Watsongole",
    "wof:placetype":"locality"
},
  "geometry": {"coordinates":[34.19386,0.95742],"type":"Point"}
}