{
  "type": "Feature",
  "properties": {
    "gn:admin1_code":"E",
    "gn:admin2_code":"46",
    "gn:admin3_code":"7732907.0",
    "gn:admin4_code":"8658082.0",
    "gn:asciiname":"Atutur",
    "gn:country_code":"UG",
    "gn:dem":1138,
    "gn:feature_class":"P",
    "gn:feature_code":"PPL",
    "gn:name":"Atutur",
    "gn:population":0,
    "gn:timezone":"Africa/Kampala",
    "iso:country":"UG",
    "name:und_x_variant":[
        "Aturituri",
        "Atutur"
    ],
    "wof:name":"Atutur",
    "wof:placetype":"locality"
},
  "geometry": {"coordinates":[33.98333,1.45],"type":"Point"}
}