{
  "type": "Feature",
  "properties": {
    "gn:admin1_code":"E",
    "gn:admin2_code":"78",
    "gn:asciiname":"Namusiisi",
    "gn:country_code":"UG",
    "gn:dem":1122,
    "gn:feature_class":"P",
    "gn:feature_code":"PPL",
    "gn:name":"Namusiisi",
    "gn:population":0,
    "gn:timezone":"Africa/Kampala",
    "iso:country":"UG",
    "wof:name":"Namusiisi",
    "wof:placetype":"locality"
},
  "geometry": {"coordinates":[33.43919,0.8538],"type":"Point"}
}