{
  "type": "Feature",
  "properties": {
    "gn:admin1_code":"C",
    "gn:admin2_code":"96",
    "gn:asciiname":"Wakimesi",
    "gn:country_code":"UG",
    "gn:dem":1164,
    "gn:feature_class":"P",
    "gn:feature_code":"PPL",
    "gn:name":"Wakimesi",
    "gn:population":0,
    "gn:timezone":"Africa/Kampala",
    "iso:country":"UG",
    "wof:name":"Wakimesi",
    "wof:placetype":"locality"
},
  "geometry": {"coordinates":[32.49677,0.28706],"type":"Point"}
}