{
  "type": "Feature",
  "properties": {
    "gn:admin1_code":"W",
    "gn:admin2_code":"79",
    "gn:asciiname":"Mukiko",
    "gn:country_code":"UG",
    "gn:dem":1490,
    "gn:feature_class":"P",
    "gn:feature_code":"PPL",
    "gn:name":"Mukiko",
    "gn:population":0,
    "gn:timezone":"Africa/Kampala",
    "iso:country":"UG",
    "name:eng_x_preferred":[
        "Mukiko"
    ],
    "wof:name":"Mukiko",
    "wof:placetype":"locality"
},
  "geometry": {"coordinates":[30.291,0.52818],"type":"Point"}
}