{
  "type": "Feature",
  "properties": {
    "gn:admin1_code":"W",
    "gn:admin2_code":"52",
    "gn:admin3_code":"226512.0",
    "gn:admin4_code":"8658590.0",
    "gn:asciiname":"Nshungezi",
    "gn:country_code":"UG",
    "gn:dem":1422,
    "gn:feature_class":"P",
    "gn:feature_code":"PPL",
    "gn:name":"Nshungezi",
    "gn:population":0,
    "gn:timezone":"Africa/Kampala",
    "iso:country":"UG",
    "wof:name":"Nshungezi",
    "wof:placetype":"locality"
},
  "geometry": {"coordinates":[30.55,-0.65],"type":"Point"}
}