{
  "type": "Feature",
  "properties": {
    "gn:admin1_code":"C",
    "gn:admin2_code":"90",
    "gn:admin3_code":"8644169.0",
    "gn:admin4_code":"8658070.0",
    "gn:asciiname":"Kitale",
    "gn:country_code":"UG",
    "gn:dem":1178,
    "gn:feature_class":"P",
    "gn:feature_code":"PPL",
    "gn:name":"Kitale",
    "gn:population":0,
    "gn:timezone":"Africa/Kampala",
    "iso:country":"UG",
    "name:azb_x_preferred":[
        "\u06a9\u06cc\u062a\u0627\u0644\u0647"
    ],
    "name:cat_x_preferred":[
        "Kitale"
    ],
    "name:deu_x_preferred":[
        "Kitale"
    ],
    "name:epo_x_preferred":[
        "Kitale"
    ],
    "name:est_x_preferred":[
        "Kitale"
    ],
    "name:fas_x_preferred":[
        "\u06a9\u06cc\u062a\u0627\u0644\u0647"
    ],
    "name:fra_x_preferred":[
        "Kitale"
    ],
    "name:hrv_x_preferred":[
        "Kitale"
    ],
    "name:ita_x_preferred":[
        "Kitale"
    ],
    "name:jpn_x_preferred":[
        "\u30ad\u30bf\u30ec"
    ],
    "name:kat_x_preferred":[
        "\u10d9\u10d8\u10e2\u10d0\u10da\u10d4"
    ],
    "name:lit_x_preferred":[
        "Kital\u0117"
    ],
    "name:nld_x_preferred":[
        "Kitale"
    ],
    "name:nor_x_preferred":[
        "Kitale"
    ],
    "name:pol_x_preferred":[
        "Kitale"
    ],
    "name:ron_x_preferred":[
        "Kitale"
    ],
    "name:rus_x_preferred":[
        "\u041a\u0438\u0442\u0430\u043b\u0435"
    ],
    "name:spa_x_preferred":[
        "Kitale"
    ],
    "name:swa_x_preferred":[
        "Kitale"
    ],
    "name:swe_x_preferred":[
        "Kitale"
    ],
    "name:urd_x_preferred":[
        "\u06a9\u06cc\u062a\u0627\u0644\u06d2"
    ],
    "name:zho_x_preferred":[
        "\u57fa\u5854\u840a"
    ],
    "wof:name":"Kitale",
    "wof:placetype":"locality"
},
  "geometry": {"coordinates":[32.72281,0.31815],"type":"Point"}
}