{
  "type": "Feature",
  "properties": {
    "gn:admin1_code":"C",
    "gn:admin2_code":"D8",
    "gn:admin3_code":"8644137.0",
    "gn:admin4_code":"8658318.0",
    "gn:asciiname":"Kande",
    "gn:country_code":"UG",
    "gn:dem":1228,
    "gn:feature_class":"P",
    "gn:feature_code":"PPL",
    "gn:name":"Kande",
    "gn:population":0,
    "gn:timezone":"Africa/Kampala",
    "iso:country":"UG",
    "name:ceb_x_preferred":[
        "Kande"
    ],
    "name:swe_x_preferred":[
        "Kande"
    ],
    "wof:name":"Kande",
    "wof:placetype":"locality"
},
  "geometry": {"coordinates":[32.05513,0.28787],"type":"Point"}
}