{
  "type": "Feature",
  "properties": {
    "gn:admin1_code":"C",
    "gn:admin2_code":"F2",
    "gn:admin3_code":"233919.0",
    "gn:admin4_code":"8658170.0",
    "gn:asciiname":"Bukayo",
    "gn:country_code":"UG",
    "gn:dem":1214,
    "gn:feature_class":"P",
    "gn:feature_code":"PPL",
    "gn:name":"Bukayo",
    "gn:population":0,
    "gn:timezone":"Africa/Kampala",
    "iso:country":"UG",
    "name:eng_x_preferred":[
        "Bukayo"
    ],
    "wof:name":"Bukayo",
    "wof:placetype":"locality"
},
  "geometry": {"coordinates":[33.25409000000001,0.25181],"type":"Point"}
}