{
  "type": "Feature",
  "properties": {
    "gn:admin1_code":"W",
    "gn:admin2_code":"79",
    "gn:asciiname":"Rutoma",
    "gn:country_code":"UG",
    "gn:dem":1488,
    "gn:feature_class":"P",
    "gn:feature_code":"PPL",
    "gn:name":"Rutoma",
    "gn:population":0,
    "gn:timezone":"Africa/Kampala",
    "iso:country":"UG",
    "name:eng_x_preferred":[
        "Rutoma"
    ],
    "wof:name":"Rutoma",
    "wof:placetype":"locality"
},
  "geometry": {"coordinates":[30.30758,0.53547],"type":"Point"}
}