{
  "type": "Feature",
  "properties": {
    "gn:admin1_code":"E",
    "gn:admin2_code":"D6",
    "gn:admin3_code":"7869955.0",
    "gn:admin4_code":"8658049.0",
    "gn:asciiname":"Tomi",
    "gn:country_code":"UG",
    "gn:dem":1210,
    "gn:feature_class":"P",
    "gn:feature_code":"PPL",
    "gn:name":"Tomi",
    "gn:population":0,
    "gn:timezone":"Africa/Kampala",
    "iso:country":"UG",
    "name:ceb_x_preferred":[
        "Tomi"
    ],
    "name:deu_x_preferred":[
        "Tomi"
    ],
    "name:fra_x_preferred":[
        "Tomi"
    ],
    "name:ita_x_preferred":[
        "Tomi"
    ],
    "name:nld_x_preferred":[
        "Tomi"
    ],
    "name:pol_x_preferred":[
        "Tomi"
    ],
    "name:swe_x_preferred":[
        "Tomi"
    ],
    "name:und_x_variant":[
        "Toma"
    ],
    "wof:name":"Tomi",
    "wof:placetype":"locality"
},
  "geometry": {"coordinates":[34.26316,0.93217],"type":"Point"}
}