{
  "type": "Feature",
  "properties": {
    "gn:admin1_code":"C",
    "gn:admin2_code":"96",
    "gn:asciiname":"Nkowe",
    "gn:country_code":"UG",
    "gn:dem":1223,
    "gn:feature_class":"P",
    "gn:feature_code":"PPL",
    "gn:name":"Nkowe",
    "gn:population":0,
    "gn:timezone":"Africa/Kampala",
    "iso:country":"UG",
    "wof:name":"Nkowe",
    "wof:placetype":"locality"
},
  "geometry": {"coordinates":[32.44302,0.41649],"type":"Point"}
}