{
  "type": "Feature",
  "properties": {
    "gn:admin1_code":"W",
    "gn:admin2_code":"31",
    "gn:admin3_code":"8644163.0",
    "gn:admin4_code":"8658625.0",
    "gn:asciiname":"Kiziranfumbi",
    "gn:cc2":"UG",
    "gn:country_code":"UG",
    "gn:dem":1097,
    "gn:feature_class":"P",
    "gn:feature_code":"PPL",
    "gn:name":"Kiziranfumbi",
    "gn:population":0,
    "gn:timezone":"Africa/Kampala",
    "iso:country":"UG",
    "name:und_x_variant":[
        "Kiziranfambi",
        "Kiziranfumbi"
    ],
    "wof:name":"Kiziranfumbi",
    "wof:placetype":"locality"
},
  "geometry": {"coordinates":[31.19972000000001,1.34056],"type":"Point"}
}