{
  "type": "Feature",
  "properties": {
    "gn:admin1_code":"E",
    "gn:admin2_code":"76",
    "gn:asciiname":"Jarau",
    "gn:country_code":"UG",
    "gn:dem":1231,
    "gn:feature_class":"P",
    "gn:feature_code":"PPL",
    "gn:name":"Jarau",
    "gn:population":0,
    "gn:timezone":"Africa/Kampala",
    "iso:country":"UG",
    "name:eng_x_preferred":[
        "Jarau"
    ],
    "wof:name":"Jarau",
    "wof:placetype":"locality"
},
  "geometry": {"coordinates":[34.20134,0.76402],"type":"Point"}
}