{
  "type": "Feature",
  "properties": {
    "gn:admin1_code":"E",
    "gn:admin2_code":"76",
    "gn:admin3_code":"226108.0",
    "gn:admin4_code":"8657726.0",
    "gn:asciiname":"Kwapa",
    "gn:country_code":"UG",
    "gn:dem":1287,
    "gn:feature_class":"P",
    "gn:feature_code":"PPL",
    "gn:name":"Kwapa",
    "gn:population":0,
    "gn:timezone":"Africa/Kampala",
    "iso:country":"UG",
    "name:eng_x_preferred":[
        "Kwapa"
    ],
    "wof:name":"Kwapa",
    "wof:placetype":"locality"
},
  "geometry": {"coordinates":[34.24235,0.74609],"type":"Point"}
}