{
  "type": "Feature",
  "properties": {
    "gn:admin1_code":"E",
    "gn:admin2_code":"78",
    "gn:asciiname":"Bwigula",
    "gn:country_code":"UG",
    "gn:dem":1119,
    "gn:feature_class":"P",
    "gn:feature_code":"PPL",
    "gn:name":"Bwigula",
    "gn:population":0,
    "gn:timezone":"Africa/Kampala",
    "iso:country":"UG",
    "wof:name":"Bwigula",
    "wof:placetype":"locality"
},
  "geometry": {"coordinates":[33.64734,0.62149],"type":"Point"}
}