{
  "type": "Feature",
  "properties": {
    "gn:admin1_code":"W",
    "gn:admin2_code":"C9",
    "gn:admin3_code":"8644166.0",
    "gn:admin4_code":"8658430.0",
    "gn:asciiname":"Rugaga",
    "gn:country_code":"UG",
    "gn:dem":1299,
    "gn:feature_class":"P",
    "gn:feature_code":"PPL",
    "gn:name":"Rugaga",
    "gn:population":0,
    "gn:timezone":"Africa/Kampala",
    "iso:country":"UG",
    "name:und_x_variant":[
        "Lugaga",
        "Rugaga"
    ],
    "wof:name":"Rugaga",
    "wof:placetype":"locality"
},
  "geometry": {"coordinates":[30.99722,-0.81611],"type":"Point"}
}