{
  "type": "Feature",
  "properties": {
    "gn:admin1_code":"W",
    "gn:admin2_code":"G6",
    "gn:admin3_code":"7869954.0",
    "gn:admin4_code":"8657855.0",
    "gn:asciiname":"Kigimbi",
    "gn:country_code":"UG",
    "gn:dem":1699,
    "gn:feature_class":"P",
    "gn:feature_code":"PPL",
    "gn:name":"Kigimbi",
    "gn:population":0,
    "gn:timezone":"Africa/Kampala",
    "iso:country":"UG",
    "wof:name":"Kigimbi",
    "wof:placetype":"locality"
},
  "geometry": {"coordinates":[30.01667,-0.71667],"type":"Point"}
}