{
  "type": "Feature",
  "properties": {
    "gn:admin1_code":"N",
    "gn:admin2_code":"58",
    "gn:admin3_code":"8080237.0",
    "gn:admin4_code":"8657802.0",
    "gn:asciiname":"Jupugeta",
    "gn:country_code":"UG",
    "gn:dem":1441,
    "gn:feature_class":"P",
    "gn:feature_code":"PPL",
    "gn:name":"Jupugeta",
    "gn:population":0,
    "gn:timezone":"Africa/Kampala",
    "iso:country":"UG",
    "wof:name":"Jupugeta",
    "wof:placetype":"locality"
},
  "geometry": {"coordinates":[31.12599,2.32327],"type":"Point"}
}