{
  "type": "Feature",
  "properties": {
    "gn:admin1_code":"N",
    "gn:admin2_code":"I5",
    "gn:admin3_code":"227037.0",
    "gn:admin4_code":"8261619.0",
    "gn:asciiname":"Bobi",
    "gn:country_code":"UG",
    "gn:dem":1080,
    "gn:feature_class":"P",
    "gn:feature_code":"PPL",
    "gn:name":"Bobi",
    "gn:population":0,
    "gn:timezone":"Africa/Kampala",
    "iso:country":"UG",
    "name:ceb_x_preferred":[
        "Bobi"
    ],
    "name:lug_x_preferred":[
        "Bobi"
    ],
    "name:swe_x_preferred":[
        "Bobi"
    ],
    "wof:name":"Bobi",
    "wof:placetype":"locality"
},
  "geometry": {"coordinates":[32.35737,2.55573],"type":"Point"}
}