{
  "type": "Feature",
  "properties": {
    "gn:admin1_code":"C",
    "gn:admin2_code":"E7",
    "gn:admin3_code":"7732075.0",
    "gn:admin4_code":"8658514.0",
    "gn:asciiname":"Bubiro",
    "gn:country_code":"UG",
    "gn:dem":1305,
    "gn:feature_class":"P",
    "gn:feature_code":"PPL",
    "gn:name":"Bubiro",
    "gn:population":0,
    "gn:timezone":"Africa/Kampala",
    "iso:country":"UG",
    "name:eng_x_preferred":[
        "Bubiro"
    ],
    "wof:name":"Bubiro",
    "wof:placetype":"locality"
},
  "geometry": {"coordinates":[33.0491,0.19521],"type":"Point"}
}