{
  "type": "Feature",
  "properties": {
    "gn:admin1_code":"E",
    "gn:admin2_code":"C6",
    "gn:asciiname":"Mugulu-Mabale",
    "gn:country_code":"UG",
    "gn:dem":1129,
    "gn:feature_class":"P",
    "gn:feature_code":"PPL",
    "gn:name":"Mugulu-Mabale",
    "gn:population":0,
    "gn:timezone":"Africa/Kampala",
    "iso:country":"UG",
    "wof:name":"Mugulu-Mabale",
    "wof:placetype":"locality"
},
  "geometry": {"coordinates":[33.89907,0.8236],"type":"Point"}
}