{
  "type": "Feature",
  "properties": {
    "gn:admin1_code":"C",
    "gn:admin2_code":"89",
    "gn:admin3_code":"7910214.0",
    "gn:admin4_code":"7732543.0",
    "gn:asciiname":"Kisammula",
    "gn:country_code":"UG",
    "gn:dem":1197,
    "gn:feature_class":"P",
    "gn:feature_code":"PPL",
    "gn:name":"Kisammula",
    "gn:population":0,
    "gn:timezone":"Africa/Kampala",
    "iso:country":"UG",
    "name:und_x_variant":[
        "Kisamula"
    ],
    "wof:name":"Kisammula",
    "wof:placetype":"locality"
},
  "geometry": {"coordinates":[32.3991,0.34368],"type":"Point"}
}