{
  "type": "Feature",
  "properties": {
    "gn:admin1_code":"E",
    "gn:admin2_code":"G9",
    "gn:admin3_code":"7732908.0",
    "gn:admin4_code":"227840.0",
    "gn:asciiname":"Kopelo",
    "gn:country_code":"UG",
    "gn:dem":1078,
    "gn:feature_class":"P",
    "gn:feature_code":"PPL",
    "gn:name":"Kopelo",
    "gn:population":0,
    "gn:timezone":"Africa/Kampala",
    "iso:country":"UG",
    "wof:name":"Kopelo",
    "wof:placetype":"locality"
},
  "geometry": {"coordinates":[33.75,1.45],"type":"Point"}
}