{
  "type": "Feature",
  "properties": {
    "gn:admin1_code":"E",
    "gn:admin2_code":"H5",
    "gn:admin3_code":"8644174.0",
    "gn:admin4_code":"8658240.0",
    "gn:asciiname":"Arapoo",
    "gn:country_code":"UG",
    "gn:dem":1037,
    "gn:feature_class":"P",
    "gn:feature_code":"PPL",
    "gn:name":"Arapoo",
    "gn:population":0,
    "gn:timezone":"Africa/Kampala",
    "iso:country":"UG",
    "wof:name":"Arapoo",
    "wof:placetype":"locality"
},
  "geometry": {"coordinates":[33.25,1.41667],"type":"Point"}
}