{
  "type": "Feature",
  "properties": {
    "gn:admin1_code":"W",
    "gn:admin2_code":"93",
    "gn:admin3_code":"8644165.0",
    "gn:admin4_code":"7732514.0",
    "gn:asciiname":"Kalangalo",
    "gn:country_code":"UG",
    "gn:dem":1596,
    "gn:feature_class":"P",
    "gn:feature_code":"PPL",
    "gn:name":"Kalangalo",
    "gn:population":0,
    "gn:timezone":"Africa/Kampala",
    "iso:country":"UG",
    "wof:name":"Kalangalo",
    "wof:placetype":"locality"
},
  "geometry": {"coordinates":[29.91667,-0.73333],"type":"Point"}
}