{
  "type": "Feature",
  "properties": {
    "gn:admin1_code":"E",
    "gn:admin2_code":"86",
    "gn:asciiname":"Musita",
    "gn:country_code":"UG",
    "gn:dem":1164,
    "gn:feature_class":"P",
    "gn:feature_code":"PPL",
    "gn:name":"Musita",
    "gn:population":0,
    "gn:timezone":"Africa/Kampala",
    "iso:country":"UG",
    "wof:name":"Musita",
    "wof:placetype":"locality"
},
  "geometry": {"coordinates":[33.38445,0.52766],"type":"Point"}
}