{
  "type": "Feature",
  "properties": {
    "gn:admin1_code":"N",
    "gn:admin2_code":"72",
    "gn:admin3_code":"8644127.0",
    "gn:admin4_code":"8657844.0",
    "gn:asciiname":"Dembele",
    "gn:country_code":"UG",
    "gn:dem":641,
    "gn:feature_class":"P",
    "gn:feature_code":"PPL",
    "gn:name":"Dembele",
    "gn:population":0,
    "gn:timezone":"Africa/Kampala",
    "iso:country":"UG",
    "wof:name":"Dembele",
    "wof:placetype":"locality"
},
  "geometry": {"coordinates":[31.59957,3.3994],"type":"Point"}
}