{
  "type": "Feature",
  "properties": {
    "gn:admin1_code":"N",
    "gn:admin2_code":"97",
    "gn:admin3_code":"235054.0",
    "gn:admin4_code":"8657619.0",
    "gn:asciiname":"Kechuru",
    "gn:country_code":"UG",
    "gn:dem":985,
    "gn:feature_class":"P",
    "gn:feature_code":"PPL",
    "gn:name":"Kechuru",
    "gn:population":0,
    "gn:timezone":"Africa/Kampala",
    "iso:country":"UG",
    "wof:name":"Kechuru",
    "wof:placetype":"locality"
},
  "geometry": {"coordinates":[31.10998,3.46452],"type":"Point"}
}