{
  "type": "Feature",
  "properties": {
    "gn:admin1_code":"E",
    "gn:admin2_code":"E1",
    "gn:asciiname":"Nabote",
    "gn:country_code":"UG",
    "gn:dem":1095,
    "gn:feature_class":"P",
    "gn:feature_code":"PPL",
    "gn:name":"Nabote",
    "gn:population":0,
    "gn:timezone":"Africa/Kampala",
    "iso:country":"UG",
    "wof:name":"Nabote",
    "wof:placetype":"locality"
},
  "geometry": {"coordinates":[33.60661,0.79685],"type":"Point"}
}