{
  "type": "Feature",
  "properties": {
    "gn:admin1_code":"C",
    "gn:admin2_code":"F4",
    "gn:admin3_code":"233383.0",
    "gn:admin4_code":"8657604.0",
    "gn:asciiname":"Bukandula",
    "gn:country_code":"UG",
    "gn:dem":1234,
    "gn:feature_class":"P",
    "gn:feature_code":"PPL",
    "gn:name":"Bukandula",
    "gn:population":0,
    "gn:timezone":"Africa/Kampala",
    "iso:country":"UG",
    "wof:name":"Bukandula",
    "wof:placetype":"locality"
},
  "geometry": {"coordinates":[31.85,0.16667],"type":"Point"}
}