{
  "type": "Feature",
  "properties": {
    "gn:country":"UG",
    "gn:fcode":"PPL",
    "gn:pop":5109,
    "iso:country":"UG",
    "qs:name":"Margherita",
    "qs:photos_9r":0,
    "qs:photos_sr":0,
    "qs:pop_sr":"5",
    "wd:wordcount":241,
    "wof:name":"Margherita",
    "wof:placetype":"locality",
    "wof:population":5109
},
  "geometry": {"coordinates":[29.89111,0.41861],"type":"Point"}
}