{
  "type": "Feature",
  "properties": {
    "gn:admin1_code":"N",
    "gn:admin2_code":"58",
    "gn:admin3_code":"8080237.0",
    "gn:admin4_code":"8080219.0",
    "gn:asciiname":"Olago",
    "gn:country_code":"UG",
    "gn:dem":844,
    "gn:feature_class":"P",
    "gn:feature_code":"PPL",
    "gn:name":"Olago",
    "gn:population":0,
    "gn:timezone":"Africa/Kampala",
    "iso:country":"UG",
    "wof:name":"Olago",
    "wof:placetype":"locality"
},
  "geometry": {"coordinates":[31.26706,2.46969],"type":"Point"}
}