{
  "type": "Feature",
  "properties": {
    "gn:admin1_code":"E",
    "gn:admin2_code":"G7",
    "gn:admin3_code":"8644167.0",
    "gn:admin4_code":"8657618.0",
    "gn:asciiname":"Kapyanga",
    "gn:country_code":"UG",
    "gn:dem":1170,
    "gn:feature_class":"P",
    "gn:feature_code":"PPL",
    "gn:name":"Kapyanga",
    "gn:population":0,
    "gn:timezone":"Africa/Kampala",
    "iso:country":"UG",
    "name:und_x_variant":[
        "Kapianga",
        "Kapyanga"
    ],
    "wof:name":"Kapyanga",
    "wof:placetype":"locality"
},
  "geometry": {"coordinates":[33.76222,0.55139],"type":"Point"}
}