{
  "type": "Feature",
  "properties": {
    "gn:admin1_code":"E",
    "gn:admin2_code":"80",
    "gn:admin3_code":"7732909.0",
    "gn:admin4_code":"8658509.0",
    "gn:asciiname":"Kekale",
    "gn:country_code":"UG",
    "gn:dem":1036,
    "gn:feature_class":"P",
    "gn:feature_code":"PPL",
    "gn:name":"Kekale",
    "gn:population":0,
    "gn:timezone":"Africa/Kampala",
    "iso:country":"UG",
    "wof:name":"Kekale",
    "wof:placetype":"locality"
},
  "geometry": {"coordinates":[33.29915,1.77227],"type":"Point"}
}