{
  "type": "Feature",
  "properties": {
    "gn:admin1_code":"W",
    "gn:admin2_code":"28",
    "gn:asciiname":"Bundingoma",
    "gn:country_code":"UG",
    "gn:dem":839,
    "gn:feature_class":"P",
    "gn:feature_code":"PPL",
    "gn:name":"Bundingoma",
    "gn:population":0,
    "gn:timezone":"Africa/Kampala",
    "iso:country":"UG",
    "name:eng_x_preferred":[
        "Bundingoma"
    ],
    "wof:name":"Bundingoma",
    "wof:placetype":"locality"
},
  "geometry": {"coordinates":[29.97112000000001,0.684],"type":"Point"}
}