{
  "type": "Feature",
  "properties": {
    "gn:admin1_code":"E",
    "gn:admin2_code":"38",
    "gn:asciiname":"Bumyuka",
    "gn:country_code":"UG",
    "gn:dem":1088,
    "gn:feature_class":"P",
    "gn:feature_code":"PPL",
    "gn:name":"Bumyuka",
    "gn:population":0,
    "gn:timezone":"Africa/Kampala",
    "iso:country":"UG",
    "wof:name":"Bumyuka",
    "wof:placetype":"locality"
},
  "geometry": {"coordinates":[33.1364,0.87414],"type":"Point"}
}