{
  "type": "Feature",
  "properties": {
    "gn:admin1_code":"E",
    "gn:admin2_code":"86",
    "gn:admin3_code":"8644164.0",
    "gn:admin4_code":"8658491.0",
    "gn:asciiname":"Namugongo Point",
    "gn:country_code":"UG",
    "gn:dem":1144,
    "gn:feature_class":"P",
    "gn:feature_code":"PPL",
    "gn:name":"Namugongo Point",
    "gn:population":0,
    "gn:timezone":"Africa/Kampala",
    "iso:country":"UG",
    "name:eng_x_preferred":[
        "Namugongo Point"
    ],
    "wof:name":"Namugongo Point",
    "wof:placetype":"locality"
},
  "geometry": {"coordinates":[33.30962,0.36313],"type":"Point"}
}