{
  "type": "Feature",
  "properties": {
    "gn:admin1_code":"C",
    "gn:admin2_code":"D8",
    "gn:asciiname":"Kamuvobe",
    "gn:country_code":"UG",
    "gn:dem":1275,
    "gn:feature_class":"P",
    "gn:feature_code":"PPL",
    "gn:name":"Kamuvobe",
    "gn:population":0,
    "gn:timezone":"Africa/Kampala",
    "iso:country":"UG",
    "wof:name":"Kamuvobe",
    "wof:placetype":"locality"
},
  "geometry": {"coordinates":[32.11308,0.42815],"type":"Point"}
}