{
  "type": "Feature",
  "properties": {
    "gn:admin1_code":"C",
    "gn:admin2_code":"D9",
    "gn:admin3_code":"8644153.0",
    "gn:admin4_code":"8658024.0",
    "gn:asciiname":"Kikubanimba",
    "gn:country_code":"UG",
    "gn:dem":1096,
    "gn:feature_class":"P",
    "gn:feature_code":"PPL",
    "gn:name":"Kikubanimba",
    "gn:population":0,
    "gn:timezone":"Africa/Kampala",
    "iso:country":"UG",
    "wof:name":"Kikubanimba",
    "wof:placetype":"locality"
},
  "geometry": {"coordinates":[32.41667,0.85],"type":"Point"}
}