{
  "type": "Feature",
  "properties": {
    "gn:admin1_code":"C",
    "gn:admin2_code":"96",
    "gn:admin3_code":"7732385.0",
    "gn:admin4_code":"8657924.0",
    "gn:asciiname":"Nakanako",
    "gn:country_code":"UG",
    "gn:dem":1199,
    "gn:feature_class":"P",
    "gn:feature_code":"PPL",
    "gn:name":"Nakanako",
    "gn:population":0,
    "gn:timezone":"Africa/Kampala",
    "iso:country":"UG",
    "wof:name":"Nakanako",
    "wof:placetype":"locality"
},
  "geometry": {"coordinates":[32.57012,0.44773],"type":"Point"}
}