{
  "type": "Feature",
  "properties": {
    "gn:admin1_code":"C",
    "gn:admin2_code":"90",
    "gn:admin3_code":"7732384.0",
    "gn:admin4_code":"8658288.0",
    "gn:asciiname":"Walusibi",
    "gn:country_code":"UG",
    "gn:dem":1109,
    "gn:feature_class":"P",
    "gn:feature_code":"PPL",
    "gn:name":"Walusibi",
    "gn:population":0,
    "gn:timezone":"Africa/Kampala",
    "iso:country":"UG",
    "wof:name":"Walusibi",
    "wof:placetype":"locality"
},
  "geometry": {"coordinates":[32.84447,0.39044],"type":"Point"}
}