{
  "type": "Feature",
  "properties": {
    "gn:admin1_code":"C",
    "gn:admin2_code":"96",
    "gn:asciiname":"Seeta",
    "gn:country_code":"UG",
    "gn:dem":1188,
    "gn:feature_class":"P",
    "gn:feature_code":"PPL",
    "gn:name":"Seeta",
    "gn:population":0,
    "gn:timezone":"Africa/Kampala",
    "iso:country":"UG",
    "wof:name":"Seeta",
    "wof:placetype":"locality"
},
  "geometry": {"coordinates":[32.34439,0.04699],"type":"Point"}
}