{
  "type": "Feature",
  "properties": {
    "gn:admin1_code":"E",
    "gn:admin2_code":"67",
    "gn:asciiname":"Manyanya",
    "gn:country_code":"UG",
    "gn:dem":1153,
    "gn:feature_class":"P",
    "gn:feature_code":"PPL",
    "gn:name":"Manyanya",
    "gn:population":0,
    "gn:timezone":"Africa/Kampala",
    "iso:country":"UG",
    "name:eng_x_preferred":[
        "Manyanya"
    ],
    "wof:name":"Manyanya",
    "wof:placetype":"locality"
},
  "geometry": {"coordinates":[34.06501,0.54031],"type":"Point"}
}