{
  "type": "Feature",
  "properties": {
    "gn:admin1_code":"E",
    "gn:admin2_code":"B8",
    "gn:admin3_code":"8644171.0",
    "gn:admin4_code":"8657915.0",
    "gn:asciiname":"Kapelebyong",
    "gn:country_code":"UG",
    "gn:dem":1080,
    "gn:feature_class":"P",
    "gn:feature_code":"PPL",
    "gn:name":"Kapelebyong",
    "gn:population":0,
    "gn:timezone":"Africa/Kampala",
    "iso:country":"UG",
    "name:und_x_variant":[
        "Kaperabyong",
        "Kapelebyong"
    ],
    "wof:name":"Kapelebyong",
    "wof:placetype":"locality"
},
  "geometry": {"coordinates":[33.83083,2.29333],"type":"Point"}
}