{
  "type": "Feature",
  "properties": {
    "gn:admin1_code":"W",
    "gn:admin2_code":"79",
    "gn:asciiname":"Kitwera",
    "gn:country_code":"UG",
    "gn:dem":1631,
    "gn:feature_class":"P",
    "gn:feature_code":"PPL",
    "gn:name":"Kitwera",
    "gn:population":0,
    "gn:timezone":"Africa/Kampala",
    "iso:country":"UG",
    "name:eng_x_preferred":[
        "Kitwera"
    ],
    "wof:name":"Kitwera",
    "wof:placetype":"locality"
},
  "geometry": {"coordinates":[30.18193,0.65619],"type":"Point"}
}