{
  "type": "Feature",
  "properties": {
    "gn:admin1_code":"E",
    "gn:admin2_code":"69",
    "gn:admin3_code":"8644130.0",
    "gn:admin4_code":"8657832.0",
    "gn:asciiname":"Koritok",
    "gn:country_code":"UG",
    "gn:dem":1095,
    "gn:feature_class":"P",
    "gn:feature_code":"PPL",
    "gn:name":"Koritok",
    "gn:population":0,
    "gn:timezone":"Africa/Kampala",
    "iso:country":"UG",
    "wof:name":"Koritok",
    "wof:placetype":"locality"
},
  "geometry": {"coordinates":[33.98248,2.04135],"type":"Point"}
}