{
  "type": "Feature",
  "properties": {
    "gn:admin1_code":"C",
    "gn:admin2_code":"90",
    "gn:admin3_code":"8644169.0",
    "gn:admin4_code":"8658070.0",
    "gn:asciiname":"Seta",
    "gn:country_code":"UG",
    "gn:dem":1194,
    "gn:feature_class":"P",
    "gn:feature_code":"PPL",
    "gn:name":"Seta",
    "gn:population":0,
    "gn:timezone":"Africa/Kampala",
    "iso:country":"UG",
    "name:deu_x_preferred":[
        "Seta"
    ],
    "name:epo_x_preferred":[
        "\u0124eto"
    ],
    "name:fra_x_preferred":[
        "Seta"
    ],
    "name:hun_x_preferred":[
        "Szeta"
    ],
    "name:ita_x_preferred":[
        "Setae"
    ],
    "name:nld_x_preferred":[
        "Seta"
    ],
    "name:pol_x_preferred":[
        "Szczecinka"
    ],
    "wof:name":"Seta",
    "wof:placetype":"locality"
},
  "geometry": {"coordinates":[32.7139,0.36896],"type":"Point"}
}