{
  "type": "Feature",
  "properties": {
    "gn:admin1_code":"W",
    "gn:admin2_code":"28",
    "gn:asciiname":"Mujuba",
    "gn:country_code":"UG",
    "gn:dem":702,
    "gn:feature_class":"P",
    "gn:feature_code":"PPL",
    "gn:name":"Mujuba",
    "gn:population":0,
    "gn:timezone":"Africa/Kampala",
    "iso:country":"UG",
    "name:eng_x_preferred":[
        "Mujuba"
    ],
    "wof:name":"Mujuba",
    "wof:placetype":"locality"
},
  "geometry": {"coordinates":[30.0699,0.83538],"type":"Point"}
}