{
  "type": "Feature",
  "properties": {
    "gn:admin1_code":"N",
    "gn:admin2_code":"E2",
    "gn:admin3_code":"226883.0",
    "gn:admin4_code":"8657728.0",
    "gn:asciiname":"Acokara",
    "gn:country_code":"UG",
    "gn:dem":1092,
    "gn:feature_class":"P",
    "gn:feature_code":"PPLL",
    "gn:name":"Acokara",
    "gn:population":0,
    "gn:timezone":"Africa/Kampala",
    "iso:country":"UG",
    "wof:name":"Acokara",
    "wof:placetype":"locality"
},
  "geometry": {"coordinates":[32.61952,2.56008],"type":"Point"}
}