{
  "type": "Feature",
  "properties": {
    "gn:admin1_code":"E",
    "gn:admin2_code":"94",
    "gn:admin3_code":"7869959.0",
    "gn:admin4_code":"8657633.0",
    "gn:asciiname":"Bumasifwa",
    "gn:country_code":"UG",
    "gn:dem":1337,
    "gn:feature_class":"P",
    "gn:feature_code":"PPL",
    "gn:name":"Bumasifwa",
    "gn:population":0,
    "gn:timezone":"Africa/Kampala",
    "iso:country":"UG",
    "wof:name":"Bumasifwa",
    "wof:placetype":"locality"
},
  "geometry": {"coordinates":[34.35,1.18333],"type":"Point"}
}