{
  "type": "Feature",
  "properties": {
    "gn:admin1_code":"C",
    "gn:admin2_code":"83",
    "gn:asciiname":"Kiwuba",
    "gn:country_code":"UG",
    "gn:dem":1075,
    "gn:feature_class":"P",
    "gn:feature_code":"PPL",
    "gn:name":"Kiwuba",
    "gn:population":0,
    "gn:timezone":"Africa/Kampala",
    "iso:country":"UG",
    "wof:name":"Kiwuba",
    "wof:placetype":"locality"
},
  "geometry": {"coordinates":[33.04477,0.71966],"type":"Point"}
}