{
  "type": "Feature",
  "properties": {
    "gn:admin1_code":"E",
    "gn:admin2_code":"D2",
    "gn:asciiname":"Kiboyo-Buyodi",
    "gn:country_code":"UG",
    "gn:dem":1082,
    "gn:feature_class":"P",
    "gn:feature_code":"PPL",
    "gn:name":"Kiboyo-Buyodi",
    "gn:population":0,
    "gn:timezone":"Africa/Kampala",
    "iso:country":"UG",
    "wof:name":"Kiboyo-Buyodi",
    "wof:placetype":"locality"
},
  "geometry": {"coordinates":[33.53644,0.93107],"type":"Point"}
}