{
  "type": "Feature",
  "properties": {
    "gn:admin1_code":"C",
    "gn:admin2_code":"E7",
    "gn:admin3_code":"7732075.0",
    "gn:admin4_code":"8658088.0",
    "gn:asciiname":"Seyira",
    "gn:country_code":"UG",
    "gn:dem":1203,
    "gn:feature_class":"P",
    "gn:feature_code":"PPL",
    "gn:name":"Seyira",
    "gn:population":0,
    "gn:timezone":"Africa/Kampala",
    "iso:country":"UG",
    "wof:name":"Seyira",
    "wof:placetype":"locality"
},
  "geometry": {"coordinates":[32.94301,0.14831],"type":"Point"}
}