{
  "type": "Feature",
  "properties": {
    "gn:admin1_code":"C",
    "gn:admin2_code":"I3",
    "gn:admin3_code":"8643028.0",
    "gn:admin4_code":"8658741.0",
    "gn:asciiname":"Mutukula",
    "gn:cc2":"UG",
    "gn:country_code":"UG",
    "gn:dem":1176,
    "gn:feature_class":"P",
    "gn:feature_code":"PPL",
    "gn:name":"Mutukula",
    "gn:population":0,
    "gn:timezone":"Africa/Kampala",
    "iso:country":"UG",
    "name:deu_x_preferred":[
        "Mutukula"
    ],
    "name:und_x_variant":[
        "Mucukula",
        "Mutukula"
    ],
    "name:urd_x_preferred":[
        "\u0645\u0648\u062a\u0648\u06a9\u0648\u0644\u0627"
    ],
    "wof:name":"Mutukula",
    "wof:placetype":"locality"
},
  "geometry": {"coordinates":[31.39389000000001,-0.95806],"type":"Point"}
}