{
  "type": "Feature",
  "properties": {
    "gn:admin1_code":"E",
    "gn:admin2_code":"F6",
    "gn:asciiname":"Buganza",
    "gn:country_code":"UG",
    "gn:dem":1088,
    "gn:feature_class":"P",
    "gn:feature_code":"PPL",
    "gn:name":"Buganza",
    "gn:population":0,
    "gn:timezone":"Africa/Kampala",
    "iso:country":"UG",
    "wof:name":"Buganza",
    "wof:placetype":"locality"
},
  "geometry": {"coordinates":[33.83305,0.99267],"type":"Point"}
}