{
  "type": "Feature",
  "properties": {
    "gn:admin1_code":"C",
    "gn:admin2_code":"42",
    "gn:admin3_code":"8644178.0",
    "gn:admin4_code":"8657526.0",
    "gn:asciiname":"Mumasole",
    "gn:country_code":"UG",
    "gn:dem":1120,
    "gn:feature_class":"P",
    "gn:feature_code":"PPL",
    "gn:name":"Mumasole",
    "gn:population":0,
    "gn:timezone":"Africa/Kampala",
    "iso:country":"UG",
    "wof:name":"Mumasole",
    "wof:placetype":"locality"
},
  "geometry": {"coordinates":[31.55,1.21667],"type":"Point"}
}