{
  "type": "Feature",
  "properties": {
    "gn:admin1_code":"W",
    "gn:admin2_code":"79",
    "gn:asciiname":"Muhumbi",
    "gn:country_code":"UG",
    "gn:dem":1468,
    "gn:feature_class":"P",
    "gn:feature_code":"PPL",
    "gn:name":"Muhumbi",
    "gn:population":0,
    "gn:timezone":"Africa/Kampala",
    "iso:country":"UG",
    "name:eng_x_preferred":[
        "Muhumbi"
    ],
    "wof:name":"Muhumbi",
    "wof:placetype":"locality"
},
  "geometry": {"coordinates":[30.37842,0.63508],"type":"Point"}
}