{
  "type": "Feature",
  "properties": {
    "gn:admin1_code":"E",
    "gn:admin2_code":"87",
    "gn:asciiname":"Bumwalye",
    "gn:country_code":"UG",
    "gn:dem":1158,
    "gn:feature_class":"P",
    "gn:feature_code":"PPL",
    "gn:name":"Bumwalye",
    "gn:population":0,
    "gn:timezone":"Africa/Kampala",
    "iso:country":"UG",
    "name:eng_x_preferred":[
        "Bumwalye"
    ],
    "wof:name":"Bumwalye",
    "wof:placetype":"locality"
},
  "geometry": {"coordinates":[34.13036,0.98449],"type":"Point"}
}