{
  "type": "Feature",
  "properties": {
    "gn:admin1_code":"C",
    "gn:admin2_code":"96",
    "gn:asciiname":"Gimbo",
    "gn:country_code":"UG",
    "gn:dem":1208,
    "gn:feature_class":"P",
    "gn:feature_code":"PPL",
    "gn:name":"Gimbo",
    "gn:population":0,
    "gn:timezone":"Africa/Kampala",
    "iso:country":"UG",
    "wof:name":"Gimbo",
    "wof:placetype":"locality"
},
  "geometry": {"coordinates":[32.45084,0.37213],"type":"Point"}
}