{
  "type": "Feature",
  "properties": {
    "gn:admin1_code":"W",
    "gn:admin2_code":"28",
    "gn:asciiname":"Humiya",
    "gn:country_code":"UG",
    "gn:dem":771,
    "gn:feature_class":"P",
    "gn:feature_code":"PPL",
    "gn:name":"Humiya",
    "gn:population":0,
    "gn:timezone":"Africa/Kampala",
    "iso:country":"UG",
    "name:eng_x_preferred":[
        "Humiya"
    ],
    "wof:name":"Humiya",
    "wof:placetype":"locality"
},
  "geometry": {"coordinates":[30.04804,0.76504],"type":"Point"}
}