{
  "type": "Feature",
  "properties": {
    "gn:admin1_code":"W",
    "gn:admin2_code":"D3",
    "gn:admin3_code":"7870011.0",
    "gn:admin4_code":"8657542.0",
    "gn:asciiname":"Ishagama",
    "gn:country_code":"UG",
    "gn:dem":1340,
    "gn:feature_class":"P",
    "gn:feature_code":"PPL",
    "gn:name":"Ishagama",
    "gn:population":0,
    "gn:timezone":"Africa/Kampala",
    "iso:country":"UG",
    "wof:name":"Ishagama",
    "wof:placetype":"locality"
},
  "geometry": {"coordinates":[30.83333,-0.25],"type":"Point"}
}