{
  "type": "Feature",
  "properties": {
    "gn:admin1_code":"E",
    "gn:admin2_code":"C1",
    "gn:asciiname":"Natalo",
    "gn:country_code":"UG",
    "gn:dem":1083,
    "gn:feature_class":"P",
    "gn:feature_code":"PPL",
    "gn:name":"Natalo",
    "gn:population":0,
    "gn:timezone":"Africa/Kampala",
    "iso:country":"UG",
    "wof:name":"Natalo",
    "wof:placetype":"locality"
},
  "geometry": {"coordinates":[33.88139,0.97913],"type":"Point"}
}