{
  "type": "Feature",
  "properties": {
    "gn:admin1_code":"E",
    "gn:admin2_code":"78",
    "gn:asciiname":"Ntinda",
    "gn:country_code":"UG",
    "gn:dem":1149,
    "gn:feature_class":"P",
    "gn:feature_code":"PPL",
    "gn:name":"Ntinda",
    "gn:population":0,
    "gn:timezone":"Africa/Kampala",
    "iso:country":"UG",
    "wof:name":"Ntinda",
    "wof:placetype":"locality"
},
  "geometry": {"coordinates":[33.45878,0.58578],"type":"Point"}
}