{
  "type": "Feature",
  "properties": {
    "gn:admin1_code":"N",
    "gn:admin2_code":"72",
    "gn:admin3_code":"8644127.0",
    "gn:admin4_code":"8658016.0",
    "gn:asciiname":"Lewa",
    "gn:country_code":"UG",
    "gn:dem":645,
    "gn:feature_class":"P",
    "gn:feature_code":"PPL",
    "gn:name":"Lewa",
    "gn:population":0,
    "gn:timezone":"Africa/Kampala",
    "iso:country":"UG",
    "name:ceb_x_preferred":[
        "Lewa"
    ],
    "name:deu_x_preferred":[
        "Lewa"
    ],
    "name:swe_x_preferred":[
        "Lewa"
    ],
    "name:und_x_variant":[
        "Liwa"
    ],
    "wof:name":"Lewa",
    "wof:placetype":"locality"
},
  "geometry": {"coordinates":[31.50146,3.27405],"type":"Point"}
}