{
  "type": "Feature",
  "properties": {
    "gn:admin1_code":"W",
    "gn:admin2_code":"85",
    "gn:asciiname":"Bulyambuzi",
    "gn:country_code":"UG",
    "gn:dem":1498,
    "gn:feature_class":"P",
    "gn:feature_code":"PPL",
    "gn:name":"Bulyambuzi",
    "gn:population":0,
    "gn:timezone":"Africa/Kampala",
    "iso:country":"UG",
    "name:eng_x_preferred":[
        "Bulyambuzi"
    ],
    "wof:name":"Bulyambuzi",
    "wof:placetype":"locality"
},
  "geometry": {"coordinates":[30.4423,0.69498],"type":"Point"}
}