{
  "type": "Feature",
  "properties": {
    "gn:admin1_code":"E",
    "gn:admin2_code":"69",
    "gn:admin3_code":"8644130.0",
    "gn:admin4_code":"8657776.0",
    "gn:asciiname":"Ajesai",
    "gn:country_code":"UG",
    "gn:dem":1067,
    "gn:feature_class":"P",
    "gn:feature_code":"PPL",
    "gn:name":"Ajesai",
    "gn:population":0,
    "gn:timezone":"Africa/Kampala",
    "iso:country":"UG",
    "wof:name":"Ajesai",
    "wof:placetype":"locality"
},
  "geometry": {"coordinates":[33.9058,1.86545],"type":"Point"}
}