{
  "type": "Feature",
  "properties": {
    "gn:admin1_code":"E",
    "gn:admin2_code":"B8",
    "gn:admin3_code":"8644171.0",
    "gn:admin4_code":"8657915.0",
    "gn:asciiname":"Okoboi",
    "gn:country_code":"UG",
    "gn:dem":1084,
    "gn:feature_class":"P",
    "gn:feature_code":"PPL",
    "gn:name":"Okoboi",
    "gn:population":0,
    "gn:timezone":"Africa/Kampala",
    "iso:country":"UG",
    "wof:name":"Okoboi",
    "wof:placetype":"locality"
},
  "geometry": {"coordinates":[33.85,2.31667],"type":"Point"}
}