{
  "type": "Feature",
  "properties": {
    "gn:admin1_code":"E",
    "gn:admin2_code":"D6",
    "gn:asciiname":"Butinduyi",
    "gn:country_code":"UG",
    "gn:dem":1620,
    "gn:feature_class":"P",
    "gn:feature_code":"PPL",
    "gn:name":"Butinduyi",
    "gn:population":0,
    "gn:timezone":"Africa/Kampala",
    "iso:country":"UG",
    "name:eng_x_preferred":[
        "Butinduyi"
    ],
    "wof:name":"Butinduyi",
    "wof:placetype":"locality"
},
  "geometry": {"coordinates":[34.37739000000001,0.88689],"type":"Point"}
}