{
  "type": "Feature",
  "properties": {
    "gn:admin1_code":"E",
    "gn:admin2_code":"C1",
    "gn:admin3_code":"8644159.0",
    "gn:admin4_code":"8658295.0",
    "gn:asciiname":"Naboa",
    "gn:country_code":"UG",
    "gn:dem":1128,
    "gn:feature_class":"P",
    "gn:feature_code":"PPL",
    "gn:name":"Naboa",
    "gn:population":0,
    "gn:timezone":"Africa/Kampala",
    "iso:country":"UG",
    "name:ceb_x_preferred":[
        "Naboa"
    ],
    "name:swe_x_preferred":[
        "Naboa"
    ],
    "name:vie_x_preferred":[
        "Naboa"
    ],
    "name:war_x_preferred":[
        "Naboa"
    ],
    "wof:name":"Naboa",
    "wof:placetype":"locality"
},
  "geometry": {"coordinates":[34.02056,1.03278],"type":"Point"}
}