{
  "type": "Feature",
  "properties": {
    "gn:admin1_code":"C",
    "gn:admin2_code":"I3",
    "gn:admin3_code":"8643028.0",
    "gn:admin4_code":"8658741.0",
    "gn:asciiname":"Bigada",
    "gn:country_code":"UG",
    "gn:dem":1220,
    "gn:feature_class":"P",
    "gn:feature_code":"PPL",
    "gn:name":"Bigada",
    "gn:population":0,
    "gn:timezone":"Africa/Kampala",
    "iso:country":"UG",
    "wof:name":"Bigada",
    "wof:placetype":"locality"
},
  "geometry": {"coordinates":[31.43333,-0.86667],"type":"Point"}
}