{
  "type": "Feature",
  "properties": {
    "gn:admin1_code":"E",
    "gn:admin2_code":"C6",
    "gn:asciiname":"Busoni",
    "gn:country_code":"UG",
    "gn:dem":1092,
    "gn:feature_class":"P",
    "gn:feature_code":"PPL",
    "gn:name":"Busoni",
    "gn:population":0,
    "gn:timezone":"Africa/Kampala",
    "iso:country":"UG",
    "wof:name":"Busoni",
    "wof:placetype":"locality"
},
  "geometry": {"coordinates":[33.93625,0.83269],"type":"Point"}
}