{
  "type": "Feature",
  "properties": {
    "gn:admin1_code":"E",
    "gn:admin2_code":"76",
    "gn:asciiname":"Kadapanyi",
    "gn:country_code":"UG",
    "gn:dem":1255,
    "gn:feature_class":"P",
    "gn:feature_code":"PPL",
    "gn:name":"Kadapanyi",
    "gn:population":0,
    "gn:timezone":"Africa/Kampala",
    "iso:country":"UG",
    "name:eng_x_preferred":[
        "Kadapanyi"
    ],
    "wof:name":"Kadapanyi",
    "wof:placetype":"locality"
},
  "geometry": {"coordinates":[34.26002,0.70673],"type":"Point"}
}