{
  "type": "Feature",
  "properties": {
    "gn:admin1_code":"C",
    "gn:admin2_code":"89",
    "gn:admin3_code":"7910214.0",
    "gn:admin4_code":"8658615.0",
    "gn:asciiname":"Luwala",
    "gn:country_code":"UG",
    "gn:dem":1159,
    "gn:feature_class":"P",
    "gn:feature_code":"PPL",
    "gn:name":"Luwala",
    "gn:population":0,
    "gn:timezone":"Africa/Kampala",
    "iso:country":"UG",
    "wof:name":"Luwala",
    "wof:placetype":"locality"
},
  "geometry": {"coordinates":[32.2344,0.06903],"type":"Point"}
}