{
  "type": "Feature",
  "properties": {
    "gn:admin1_code":"E",
    "gn:admin2_code":"76",
    "gn:admin3_code":"8644131.0",
    "gn:admin4_code":"8657949.0",
    "gn:asciiname":"Maruki",
    "gn:country_code":"UG",
    "gn:dem":1162,
    "gn:feature_class":"P",
    "gn:feature_code":"PPL",
    "gn:name":"Maruki",
    "gn:population":0,
    "gn:timezone":"Africa/Kampala",
    "iso:country":"UG",
    "name:eng_x_preferred":[
        "Maruki"
    ],
    "wof:name":"Maruki",
    "wof:placetype":"locality"
},
  "geometry": {"coordinates":[34.06676,0.80517],"type":"Point"}
}