{
  "type": "Feature",
  "properties": {
    "gn:admin1_code":"E",
    "gn:admin2_code":"95",
    "gn:asciiname":"Akum",
    "gn:country_code":"UG",
    "gn:dem":1115,
    "gn:feature_class":"P",
    "gn:feature_code":"PPLL",
    "gn:name":"Akum",
    "gn:population":0,
    "gn:timezone":"Africa/Kampala",
    "iso:country":"UG",
    "wof:name":"Akum",
    "wof:placetype":"locality"
},
  "geometry": {"coordinates":[33.62608,1.76184],"type":"Point"}
}