{
  "type": "Feature",
  "properties": {
    "gn:admin1_code":"C",
    "gn:admin2_code":"36",
    "gn:admin3_code":"8644180.0",
    "gn:admin4_code":"8658214.0",
    "gn:asciiname":"Bufumira",
    "gn:country_code":"UG",
    "gn:dem":1157,
    "gn:feature_class":"P",
    "gn:feature_code":"PPL",
    "gn:name":"Bufumira",
    "gn:population":0,
    "gn:timezone":"Africa/Kampala",
    "iso:country":"UG",
    "wof:name":"Bufumira",
    "wof:placetype":"locality"
},
  "geometry": {"coordinates":[32.38333,-0.33333],"type":"Point"}
}