{
  "type": "Feature",
  "properties": {
    "gn:admin1_code":"W",
    "gn:admin2_code":"50",
    "gn:admin3_code":"8644129.0",
    "gn:admin4_code":"8657772.0",
    "gn:asciiname":"Bukooba",
    "gn:country_code":"UG",
    "gn:dem":1072,
    "gn:feature_class":"P",
    "gn:feature_code":"PPL",
    "gn:name":"Bukooba",
    "gn:population":0,
    "gn:timezone":"Africa/Kampala",
    "iso:country":"UG",
    "wof:name":"Bukooba",
    "wof:placetype":"locality"
},
  "geometry": {"coordinates":[31.76878,1.50811],"type":"Point"}
}