{
  "type": "Feature",
  "properties": {
    "gn:admin1_code":"E",
    "gn:admin2_code":"76",
    "gn:asciiname":"Pawanga",
    "gn:country_code":"UG",
    "gn:dem":1095,
    "gn:feature_class":"P",
    "gn:feature_code":"PPL",
    "gn:name":"Pawanga",
    "gn:population":0,
    "gn:timezone":"Africa/Kampala",
    "iso:country":"UG",
    "wof:name":"Pawanga",
    "wof:placetype":"locality"
},
  "geometry": {"coordinates":[33.92032,0.70686],"type":"Point"}
}