{
  "type": "Feature",
  "properties": {
    "gn:admin1_code":"C",
    "gn:admin2_code":"90",
    "gn:admin3_code":"7732383.0",
    "gn:admin4_code":"8658299.0",
    "gn:asciiname":"Nakadindiri",
    "gn:country_code":"UG",
    "gn:dem":1060,
    "gn:feature_class":"P",
    "gn:feature_code":"PPL",
    "gn:name":"Nakadindiri",
    "gn:population":0,
    "gn:timezone":"Africa/Kampala",
    "iso:country":"UG",
    "wof:name":"Nakadindiri",
    "wof:placetype":"locality"
},
  "geometry": {"coordinates":[32.78333,0.83333],"type":"Point"}
}