{
  "type": "Feature",
  "properties": {
    "gn:admin1_code":"C",
    "gn:admin2_code":"56",
    "gn:admin3_code":"233891.0",
    "gn:admin4_code":"8658584.0",
    "gn:asciiname":"Kirawula",
    "gn:country_code":"UG",
    "gn:dem":1292,
    "gn:feature_class":"P",
    "gn:feature_code":"PPL",
    "gn:name":"Kirawula",
    "gn:population":0,
    "gn:timezone":"Africa/Kampala",
    "iso:country":"UG",
    "wof:name":"Kirawula",
    "wof:placetype":"locality"
},
  "geometry": {"coordinates":[31.45,0.63333],"type":"Point"}
}