{
  "type": "Feature",
  "properties": {
    "gn:admin1_code":"W",
    "gn:admin2_code":"40",
    "gn:admin3_code":"234040.0",
    "gn:admin4_code":"8657783.0",
    "gn:asciiname":"Hima",
    "gn:country_code":"UG",
    "gn:dem":1291,
    "gn:feature_class":"P",
    "gn:feature_code":"PPL",
    "gn:name":"Hima",
    "gn:population":0,
    "gn:timezone":"Africa/Kampala",
    "iso:country":"UG",
    "name:jpn_x_preferred":[
        "\u30d2\u30de"
    ],
    "name:lug_x_preferred":[
        "Hima"
    ],
    "name:urd_x_preferred":[
        "\u06c1\u06cc\u0645\u0627"
    ],
    "wof:name":"Hima",
    "wof:placetype":"locality"
},
  "geometry": {"coordinates":[30.16222,0.34889],"type":"Point"}
}