{
  "type": "Feature",
  "properties": {
    "gn:admin1_code":"E",
    "gn:admin2_code":"38",
    "gn:asciiname":"Nsadha",
    "gn:country_code":"UG",
    "gn:dem":1116,
    "gn:feature_class":"P",
    "gn:feature_code":"PPL",
    "gn:name":"Nsadha",
    "gn:population":0,
    "gn:timezone":"Africa/Kampala",
    "iso:country":"UG",
    "wof:name":"Nsadha",
    "wof:placetype":"locality"
},
  "geometry": {"coordinates":[33.27718,0.88507],"type":"Point"}
}