{
  "type": "Feature",
  "properties": {
    "gn:admin1_code":"E",
    "gn:admin2_code":"G7",
    "gn:admin3_code":"8644167.0",
    "gn:admin4_code":"8657689.0",
    "gn:asciiname":"Buwolya",
    "gn:country_code":"UG",
    "gn:dem":1153,
    "gn:feature_class":"P",
    "gn:feature_code":"PPL",
    "gn:name":"Buwolya",
    "gn:population":0,
    "gn:timezone":"Africa/Kampala",
    "iso:country":"UG",
    "name:und_x_variant":[
        "Bwolya",
        "Buwolya"
    ],
    "wof:name":"Buwolya",
    "wof:placetype":"locality"
},
  "geometry": {"coordinates":[33.81667,0.41667],"type":"Point"}
}