{
  "type": "Feature",
  "properties": {
    "gn:admin1_code":"C",
    "gn:admin2_code":"F4",
    "gn:admin3_code":"233383.0",
    "gn:admin4_code":"8657834.0",
    "gn:asciiname":"Bitibyamukasa",
    "gn:country_code":"UG",
    "gn:dem":1219,
    "gn:feature_class":"P",
    "gn:feature_code":"PPL",
    "gn:name":"Bitibyamukasa",
    "gn:population":0,
    "gn:timezone":"Africa/Kampala",
    "iso:country":"UG",
    "name:und_x_variant":[
        "Bitbyamukasa",
        "Bitibyamukasa"
    ],
    "wof:name":"Bitibyamukasa",
    "wof:placetype":"locality"
},
  "geometry": {"coordinates":[31.56667,0.28333],"type":"Point"}
}