{
  "type": "Feature",
  "properties": {
    "gn:admin1_code":"C",
    "gn:admin2_code":"89",
    "gn:admin3_code":"7910214.0",
    "gn:admin4_code":"8658563.0",
    "gn:asciiname":"Buwanda",
    "gn:country_code":"UG",
    "gn:dem":1183,
    "gn:feature_class":"P",
    "gn:feature_code":"PPL",
    "gn:name":"Buwanda",
    "gn:population":0,
    "gn:timezone":"Africa/Kampala",
    "iso:country":"UG",
    "wof:name":"Buwanda",
    "wof:placetype":"locality"
},
  "geometry": {"coordinates":[32.12956,0.04186],"type":"Point"}
}