{
  "type": "Feature",
  "properties": {
    "gn:admin1_code":"N",
    "gn:admin2_code":"26",
    "gn:admin3_code":"229387.0",
    "gn:admin4_code":"8261614.0",
    "gn:asciiname":"Adira",
    "gn:country_code":"UG",
    "gn:dem":1049,
    "gn:feature_class":"P",
    "gn:feature_code":"PPL",
    "gn:name":"Adira",
    "gn:population":0,
    "gn:timezone":"Africa/Kampala",
    "iso:country":"UG",
    "name:swe_x_preferred":[
        "Adira"
    ],
    "wof:name":"Adira",
    "wof:placetype":"locality"
},
  "geometry": {"coordinates":[32.43278,2.06021],"type":"Point"}
}