{
  "type": "Feature",
  "properties": {
    "gn:admin1_code":"W",
    "gn:admin2_code":"I8",
    "gn:admin3_code":"226611.0",
    "gn:admin4_code":"8657659.0",
    "gn:asciiname":"Kashambya",
    "gn:country_code":"UG",
    "gn:dem":1754,
    "gn:feature_class":"P",
    "gn:feature_code":"PPL",
    "gn:name":"Kashambya",
    "gn:population":0,
    "gn:timezone":"Africa/Kampala",
    "iso:country":"UG",
    "wof:name":"Kashambya",
    "wof:placetype":"locality"
},
  "geometry": {"coordinates":[29.98083,-1.04556],"type":"Point"}
}