{
  "type": "Feature",
  "properties": {
    "gn:admin1_code":"C",
    "gn:admin2_code":"42",
    "gn:admin3_code":"8644178.0",
    "gn:admin4_code":"8657540.0",
    "gn:asciiname":"Bugaba",
    "gn:country_code":"UG",
    "gn:dem":1104,
    "gn:feature_class":"P",
    "gn:feature_code":"PPL",
    "gn:name":"Bugaba",
    "gn:population":0,
    "gn:timezone":"Africa/Kampala",
    "iso:country":"UG",
    "name:deu_x_preferred":[
        "Bugaba"
    ],
    "wof:name":"Bugaba",
    "wof:placetype":"locality"
},
  "geometry": {"coordinates":[31.58333,1.16667],"type":"Point"}
}