{
  "type": "Feature",
  "properties": {
    "gn:admin1_code":"C",
    "gn:admin2_code":"D8",
    "gn:admin3_code":"8644152.0",
    "gn:admin4_code":"8658544.0",
    "gn:asciiname":"Kikandwa",
    "gn:country_code":"UG",
    "gn:dem":1180,
    "gn:feature_class":"P",
    "gn:feature_code":"PPL",
    "gn:name":"Kikandwa",
    "gn:population":0,
    "gn:timezone":"Africa/Kampala",
    "iso:country":"UG",
    "wof:name":"Kikandwa",
    "wof:placetype":"locality"
},
  "geometry": {"coordinates":[32.09611,0.63722],"type":"Point"}
}