{
  "type": "Feature",
  "properties": {
    "gn:admin1_code":"E",
    "gn:admin2_code":"G7",
    "gn:admin3_code":"8644167.0",
    "gn:admin4_code":"8658486.0",
    "gn:asciiname":"Bukunya",
    "gn:country_code":"UG",
    "gn:dem":1163,
    "gn:feature_class":"P",
    "gn:feature_code":"PPLL",
    "gn:name":"Bukunya",
    "gn:population":0,
    "gn:timezone":"Africa/Kampala",
    "iso:country":"UG",
    "name:eng_x_preferred":[
        "Bukunya"
    ],
    "wof:name":"Bukunya",
    "wof:placetype":"locality"
},
  "geometry": {"coordinates":[33.916,0.22618],"type":"Point"}
}