{
  "type": "Feature",
  "properties": {
    "gn:admin1_code":"E",
    "gn:admin2_code":"C6",
    "gn:asciiname":"Bugwe",
    "gn:country_code":"UG",
    "gn:dem":1100,
    "gn:feature_class":"P",
    "gn:feature_code":"PPL",
    "gn:name":"Bugwe",
    "gn:population":0,
    "gn:timezone":"Africa/Kampala",
    "iso:country":"UG",
    "name:eng_x_preferred":[
        "Bugwe"
    ],
    "wof:name":"Bugwe",
    "wof:placetype":"locality"
},
  "geometry": {"coordinates":[34.09978,0.94336],"type":"Point"}
}