{
  "type": "Feature",
  "properties": {
    "gn:admin1_code":"E",
    "gn:admin2_code":"66",
    "gn:asciiname":"Makoma",
    "gn:country_code":"UG",
    "gn:dem":1139,
    "gn:feature_class":"P",
    "gn:feature_code":"PPL",
    "gn:name":"Makoma",
    "gn:population":0,
    "gn:timezone":"Africa/Kampala",
    "iso:country":"UG",
    "name:lin_x_preferred":[
        "Makoma"
    ],
    "name:swa_x_preferred":[
        "Makoma"
    ],
    "wof:name":"Makoma",
    "wof:placetype":"locality"
},
  "geometry": {"coordinates":[33.71792,0.52991],"type":"Point"}
}