{
  "type": "Feature",
  "properties": {
    "gn:admin1_code":"C",
    "gn:admin2_code":"D8",
    "gn:admin3_code":"8644152.0",
    "gn:admin4_code":"8657790.0",
    "gn:asciiname":"Ndibulungi",
    "gn:country_code":"UG",
    "gn:dem":1286,
    "gn:feature_class":"P",
    "gn:feature_code":"PPL",
    "gn:name":"Ndibulungi",
    "gn:population":0,
    "gn:timezone":"Africa/Kampala",
    "iso:country":"UG",
    "wof:name":"Ndibulungi",
    "wof:placetype":"locality"
},
  "geometry": {"coordinates":[32.08333,0.38333],"type":"Point"}
}