{
  "type": "Feature",
  "properties": {
    "gn:admin1_code":"E",
    "gn:admin2_code":"D6",
    "gn:asciiname":"Bunamahe",
    "gn:country_code":"UG",
    "gn:dem":1508,
    "gn:feature_class":"P",
    "gn:feature_code":"PPL",
    "gn:name":"Bunamahe",
    "gn:population":0,
    "gn:timezone":"Africa/Kampala",
    "iso:country":"UG",
    "name:eng_x_preferred":[
        "Bunamahe"
    ],
    "wof:name":"Bunamahe",
    "wof:placetype":"locality"
},
  "geometry": {"coordinates":[34.35596,0.9514],"type":"Point"}
}