{
  "type": "Feature",
  "properties": {
    "gn:admin1_code":"E",
    "gn:admin2_code":"G4",
    "gn:admin3_code":"229762.0",
    "gn:admin4_code":"8658403.0",
    "gn:asciiname":"Kiyunga",
    "gn:country_code":"UG",
    "gn:dem":1130,
    "gn:feature_class":"P",
    "gn:feature_code":"PPL",
    "gn:name":"Kiyunga",
    "gn:population":0,
    "gn:timezone":"Africa/Kampala",
    "iso:country":"UG",
    "wof:name":"Kiyunga",
    "wof:placetype":"locality"
},
  "geometry": {"coordinates":[33.32895,0.76891],"type":"Point"}
}