{
  "type": "Feature",
  "properties": {
    "gn:admin1_code":"E",
    "gn:admin2_code":"E1",
    "gn:asciiname":"Mazuba",
    "gn:country_code":"UG",
    "gn:dem":1076,
    "gn:feature_class":"P",
    "gn:feature_code":"PPL",
    "gn:name":"Mazuba",
    "gn:population":0,
    "gn:timezone":"Africa/Kampala",
    "iso:country":"UG",
    "wof:name":"Mazuba",
    "wof:placetype":"locality"
},
  "geometry": {"coordinates":[33.72847,0.93464],"type":"Point"}
}