{
  "type": "Feature",
  "properties": {
    "gn:admin1_code":"W",
    "gn:admin2_code":"43",
    "gn:admin3_code":"7874701.0",
    "gn:admin4_code":"8658184.0",
    "gn:asciiname":"Bushoka",
    "gn:country_code":"UG",
    "gn:dem":2003,
    "gn:feature_class":"P",
    "gn:feature_code":"PPL",
    "gn:name":"Bushoka",
    "gn:population":0,
    "gn:timezone":"Africa/Kampala",
    "iso:country":"UG",
    "wof:name":"Bushoka",
    "wof:placetype":"locality"
},
  "geometry": {"coordinates":[29.71667,-1.31667],"type":"Point"}
}