{
  "type": "Feature",
  "properties": {
    "gn:admin1_code":"E",
    "gn:admin2_code":"D6",
    "gn:asciiname":"Buwangolo",
    "gn:country_code":"UG",
    "gn:dem":1342,
    "gn:feature_class":"P",
    "gn:feature_code":"PPL",
    "gn:name":"Buwangolo",
    "gn:population":0,
    "gn:timezone":"Africa/Kampala",
    "iso:country":"UG",
    "name:eng_x_preferred":[
        "Buwangolo"
    ],
    "wof:name":"Buwangolo",
    "wof:placetype":"locality"
},
  "geometry": {"coordinates":[34.30817,0.80362],"type":"Point"}
}