{
  "type": "Feature",
  "properties": {
    "gn:admin1_code":"N",
    "gn:admin2_code":"D4",
    "gn:admin3_code":"230723.0",
    "gn:admin4_code":"8657696.0",
    "gn:asciiname":"Media",
    "gn:country_code":"UG",
    "gn:dem":1230,
    "gn:feature_class":"P",
    "gn:feature_code":"PPL",
    "gn:name":"Media",
    "gn:population":0,
    "gn:timezone":"Africa/Kampala",
    "iso:country":"UG",
    "name:afr_x_preferred":[
        "Media"
    ],
    "name:ara_x_preferred":[
        "\u0648\u0633\u0627\u0626\u0637"
    ],
    "name:ast_x_preferred":[
        "Media"
    ],
    "name:cat_x_preferred":[
        "M\u00e8dia"
    ],
    "name:ceb_x_preferred":[
        "Media"
    ],
    "name:che_x_preferred":[
        "\u041c\u0435\u0434\u0438\u0430"
    ],
    "name:deu_x_preferred":[
        "Media"
    ],
    "name:fra_x_preferred":[
        "Media"
    ],
    "name:glg_x_preferred":[
        "Media"
    ],
    "name:heb_x_preferred":[
        "\u05de\u05d3\u05d9\u05d4"
    ],
    "name:hin_x_preferred":[
        "\u092e\u0940\u0921\u093f\u092f\u093e"
    ],
    "name:hun_x_preferred":[
        "M\u00e9dia"
    ],
    "name:ind_x_preferred":[
        "Media"
    ],
    "name:ita_x_preferred":[
        "Media"
    ],
    "name:jpn_x_preferred":[
        "\u30e1\u30c7\u30a3\u30a2"
    ],
    "name:mya_x_preferred":[
        "\u1019\u102e\u1012\u102e\u101a\u102c"
    ],
    "name:nld_x_preferred":[
        "Media"
    ],
    "name:pan_x_preferred":[
        "\u0a2e\u0a40\u0a21\u0a40\u0a06"
    ],
    "name:pol_x_preferred":[
        "Media"
    ],
    "name:por_x_preferred":[
        "M\u00e9dia"
    ],
    "name:scn_x_preferred":[
        "Media"
    ],
    "name:sco_x_preferred":[
        "Media"
    ],
    "name:spa_x_preferred":[
        "Media"
    ],
    "name:srd_x_preferred":[
        "M\u00e8dia"
    ],
    "name:srp_x_preferred":[
        "\u041c\u0438\u0434\u0438\u0458\u0430"
    ],
    "name:tgl_x_preferred":[
        "Media"
    ],
    "name:tur_x_preferred":[
        "Medya"
    ],
    "name:ukr_x_preferred":[
        "\u041c\u0435\u0434\u0456\u044f"
    ],
    "name:und_x_variant":[
        "Midia",
        "Media"
    ],
    "name:vol_x_preferred":[
        "Media"
    ],
    "name:yid_x_preferred":[
        "\u05de\u05e2\u05d3\u05d9\u05e2"
    ],
    "wof:name":"Media",
    "wof:placetype":"locality"
},
  "geometry": {"coordinates":[30.98091,3.43269],"type":"Point"}
}