{
  "type": "Feature",
  "properties": {
    "gn:admin1_code":"N",
    "gn:admin2_code":"D4",
    "gn:admin3_code":"230723.0",
    "gn:admin4_code":"8657696.0",
    "gn:asciiname":"Media",
    "gn:country_code":"UG",
    "gn:dem":1230,
    "gn:feature_class":"P",
    "gn:feature_code":"PPL",
    "gn:name":"Media",
    "gn:population":0,
    "gn:timezone":"Africa/Kampala",
    "iso:country":"UG",
    "name:und_x_variant":[
        "Midia",
        "Media"
    ],
    "wof:name":"Media",
    "wof:placetype":"locality"
},
  "geometry": {"coordinates":[30.98091,3.43269],"type":"Point"}
}