{
  "type": "Feature",
  "properties": {
    "gn:gn_country":"UG",
    "gn:gn_fcode":"PPL",
    "gn:gn_pop":22507,
    "gn:population":22507,
    "iso:country":"UG",
    "qs_pg:aaroncc":"UG",
    "qs_pg:gn_country":"UG",
    "qs_pg:gn_fcode":"PPL",
    "qs_pg:gn_pop":22507,
    "qs_pg:name":"Namasuba",
    "qs_pg:photos_9r":0,
    "qs_pg:photos_sr":0,
    "qs_pg:pop_sr":7,
    "qs_pg:qs_pg_placetype":"locality",
    "wof:name":"Namasuba",
    "wof:placetype":"locality",
    "wof:population":22507
},
  "geometry": {"coordinates":[32.42139,0.68944],"type":"Point"}
}