{
  "type": "Feature",
  "properties": {
    "gn:admin1_code":"N",
    "gn:admin2_code":"65",
    "gn:admin3_code":"8644133.0",
    "gn:admin4_code":"8657828.0",
    "gn:asciiname":"Opi",
    "gn:country_code":"UG",
    "gn:dem":793,
    "gn:feature_class":"P",
    "gn:feature_code":"PPL",
    "gn:name":"Opi",
    "gn:population":0,
    "gn:timezone":"Africa/Kampala",
    "iso:country":"UG",
    "wof:name":"Opi",
    "wof:placetype":"locality"
},
  "geometry": {"coordinates":[31.76763,3.30403],"type":"Point"}
}