{
  "type": "Feature",
  "properties": {
    "gn:admin1_code":"E",
    "gn:admin2_code":"66",
    "gn:asciiname":"Nawanjuki",
    "gn:country_code":"UG",
    "gn:dem":1105,
    "gn:feature_class":"P",
    "gn:feature_code":"PPL",
    "gn:name":"Nawanjuki",
    "gn:population":0,
    "gn:timezone":"Africa/Kampala",
    "iso:country":"UG",
    "wof:name":"Nawanjuki",
    "wof:placetype":"locality"
},
  "geometry": {"coordinates":[33.70118,0.5923],"type":"Point"}
}