{
  "type": "Feature",
  "properties": {
    "gn:admin1_code":"E",
    "gn:admin2_code":"66",
    "gn:asciiname":"Bukaye-Bukuda",
    "gn:country_code":"UG",
    "gn:dem":1110,
    "gn:feature_class":"P",
    "gn:feature_code":"PPL",
    "gn:name":"Bukaye-Bukuda",
    "gn:population":0,
    "gn:timezone":"Africa/Kampala",
    "iso:country":"UG",
    "wof:name":"Bukaye-Bukuda",
    "wof:placetype":"locality"
},
  "geometry": {"coordinates":[33.73415,0.59934],"type":"Point"}
}