{
  "type": "Feature",
  "properties": {
    "gn:admin1_code":"W",
    "gn:admin2_code":"G6",
    "gn:admin3_code":"7869954.0",
    "gn:admin4_code":"8657837.0",
    "gn:asciiname":"Mitoma",
    "gn:country_code":"UG",
    "gn:dem":1596,
    "gn:feature_class":"P",
    "gn:feature_code":"PPLA2",
    "gn:name":"Mitoma",
    "gn:population":0,
    "gn:timezone":"Africa/Kampala",
    "iso:country":"UG",
    "wof:name":"Mitoma",
    "wof:placetype":"locality"
},
  "geometry": {"coordinates":[30.07,-0.68417],"type":"Point"}
}