{
  "type": "Feature",
  "properties": {
    "gn:admin1_code":"N",
    "gn:admin2_code":"H2",
    "gn:admin3_code":"8644126.0",
    "gn:admin4_code":"8200494.0",
    "gn:asciiname":"Got-Apwoyo",
    "gn:country_code":"UG",
    "gn:dem":713,
    "gn:feature_class":"P",
    "gn:feature_code":"PPL",
    "gn:name":"Got-Apwoyo",
    "gn:population":0,
    "gn:timezone":"Africa/Kampala",
    "iso:country":"UG",
    "wof:name":"Got-Apwoyo",
    "wof:placetype":"locality"
},
  "geometry": {"coordinates":[31.55654,2.4628],"type":"Point"}
}