{
  "type": "Feature",
  "properties": {
    "gn:admin1_code":"E",
    "gn:admin2_code":"D6",
    "gn:asciiname":"Bumaafu",
    "gn:country_code":"UG",
    "gn:dem":1390,
    "gn:feature_class":"P",
    "gn:feature_code":"PPL",
    "gn:name":"Bumaafu",
    "gn:population":0,
    "gn:timezone":"Africa/Kampala",
    "iso:country":"UG",
    "name:eng_x_preferred":[
        "Bumaafu"
    ],
    "wof:name":"Bumaafu",
    "wof:placetype":"locality"
},
  "geometry": {"coordinates":[34.35106,0.81846],"type":"Point"}
}