{
  "type": "Feature",
  "properties": {
    "gn:admin1_code":"C",
    "gn:admin2_code":"E8",
    "gn:admin3_code":"7910224.0",
    "gn:admin4_code":"8658069.0",
    "gn:asciiname":"Misanvu",
    "gn:country_code":"UG",
    "gn:dem":1264,
    "gn:feature_class":"P",
    "gn:feature_code":"PPL",
    "gn:name":"Misanvu",
    "gn:population":0,
    "gn:timezone":"Africa/Kampala",
    "iso:country":"UG",
    "wof:name":"Misanvu",
    "wof:placetype":"locality"
},
  "geometry": {"coordinates":[31.64667,-0.26556],"type":"Point"}
}