{
  "type": "Feature",
  "properties": {
    "gn:admin1_code":"W",
    "gn:admin2_code":"50",
    "gn:admin3_code":"8644129.0",
    "gn:admin4_code":"8657823.0",
    "gn:asciiname":"Waiga",
    "gn:country_code":"UG",
    "gn:dem":1119,
    "gn:feature_class":"P",
    "gn:feature_code":"PPL",
    "gn:name":"Waiga",
    "gn:population":0,
    "gn:timezone":"Africa/Kampala",
    "iso:country":"UG",
    "wof:name":"Waiga",
    "wof:placetype":"locality"
},
  "geometry": {"coordinates":[31.78297,1.824],"type":"Point"}
}