{
  "type": "Feature",
  "properties": {
    "gn:admin1_code":"C",
    "gn:admin2_code":"37",
    "gn:admin3_code":"8644170.0",
    "gn:admin4_code":"7732388.0",
    "gn:asciiname":"Buye",
    "gn:country_code":"UG",
    "gn:dem":1236,
    "gn:feature_class":"P",
    "gn:feature_code":"PPL",
    "gn:name":"Buye",
    "gn:population":0,
    "gn:timezone":"Africa/Kampala",
    "iso:country":"UG",
    "wof:name":"Buye",
    "wof:placetype":"locality"
},
  "geometry": {"coordinates":[32.61425999999999,0.36301],"type":"Point"}
}