{
  "type": "Feature",
  "properties": {
    "gn:admin1_code":"W",
    "gn:admin2_code":"85",
    "gn:admin3_code":"228643.0",
    "gn:admin4_code":"8657840.0",
    "gn:asciiname":"Muhangi",
    "gn:country_code":"UG",
    "gn:dem":1508,
    "gn:feature_class":"P",
    "gn:feature_code":"PPL",
    "gn:name":"Muhangi",
    "gn:population":0,
    "gn:timezone":"Africa/Kampala",
    "iso:country":"UG",
    "name:eng_x_preferred":[
        "Muhangi"
    ],
    "wof:name":"Muhangi",
    "wof:placetype":"locality"
},
  "geometry": {"coordinates":[30.48169,0.62239],"type":"Point"}
}