{
  "type": "Feature",
  "properties": {
    "gn:admin1_code":"E",
    "gn:admin2_code":"76",
    "gn:asciiname":"Bendo",
    "gn:country_code":"UG",
    "gn:dem":1224,
    "gn:feature_class":"P",
    "gn:feature_code":"PPL",
    "gn:name":"Bendo",
    "gn:population":0,
    "gn:timezone":"Africa/Kampala",
    "iso:country":"UG",
    "name:eng_x_preferred":[
        "Bendo"
    ],
    "wof:name":"Bendo",
    "wof:placetype":"locality"
},
  "geometry": {"coordinates":[34.11022,0.74356],"type":"Point"}
}