{
  "type": "Feature",
  "properties": {
    "iso:country":"UG",
    "name:eng_x_preferred":[
        "Kagadi"
    ],
    "name:lug_x_preferred":[
        "Kagadi"
    ],
    "name:nld_x_preferred":[
        "Kagadi"
    ],
    "name:urd_x_preferred":[
        "\u06a9\u0627\u06af\u0627\u062f\u06cc"
    ],
    "qs:gn_country":"UG",
    "qs:gn_fcode":"PPL",
    "qs:gn_pop":2097,
    "qs:name":"Kagadi",
    "qs:name_adm0":"Uganda",
    "qs:name_adm1":"Kibaale",
    "qs:photos":0,
    "qs:photos_1k":0,
    "qs:photos_9k":1,
    "qs:photos_9r":1,
    "qs:photos_all":1,
    "qs:photos_sr":0,
    "qs:placetype":"Town",
    "qs:pop_sr":"4",
    "qs:woe_adm0":23424974,
    "wd:wordcount":335,
    "wof:name":"Kagadi",
    "wof:placetype":"locality",
    "wof:population":2097
},
  "geometry": {"coordinates":[30.79667,0.96056],"type":"Point"}
}