{
  "type": "Feature",
  "properties": {
    "gn:admin1_code":"E",
    "gn:admin2_code":"87",
    "gn:admin3_code":"7732232.0",
    "gn:admin4_code":"8658325.0",
    "gn:asciiname":"Namakwekwe",
    "gn:country_code":"UG",
    "gn:dem":1122,
    "gn:feature_class":"P",
    "gn:feature_code":"PPL",
    "gn:name":"Namakwekwe",
    "gn:population":0,
    "gn:timezone":"Africa/Kampala",
    "iso:country":"UG",
    "wof:name":"Namakwekwe",
    "wof:placetype":"locality"
},
  "geometry": {"coordinates":[34.17758,1.09196],"type":"Point"}
}