{
  "type": "Feature",
  "properties": {
    "gn:admin1_code":"E",
    "gn:admin2_code":"80",
    "gn:admin3_code":"233018.0",
    "gn:admin4_code":"8658267.0",
    "gn:asciiname":"Kelle",
    "gn:country_code":"UG",
    "gn:dem":1027,
    "gn:feature_class":"P",
    "gn:feature_code":"PPL",
    "gn:name":"Kelle",
    "gn:population":0,
    "gn:timezone":"Africa/Kampala",
    "iso:country":"UG",
    "name:und_x_variant":[
        "Kele",
        "Kelle"
    ],
    "wof:name":"Kelle",
    "wof:placetype":"locality"
},
  "geometry": {"coordinates":[33.17154,1.65747],"type":"Point"}
}