{
  "type": "Feature",
  "properties": {
    "gn:admin1_code":"E",
    "gn:admin2_code":"38",
    "gn:asciiname":"Busubo",
    "gn:country_code":"UG",
    "gn:dem":1097,
    "gn:feature_class":"P",
    "gn:feature_code":"PPL",
    "gn:name":"Busubo",
    "gn:population":0,
    "gn:timezone":"Africa/Kampala",
    "iso:country":"UG",
    "wof:name":"Busubo",
    "wof:placetype":"locality"
},
  "geometry": {"coordinates":[33.20261,0.83088],"type":"Point"}
}