{
  "type": "Feature",
  "properties": {
    "gn:admin1_code":"C",
    "gn:admin2_code":"E7",
    "gn:admin3_code":"7732075.0",
    "gn:admin4_code":"8658239.0",
    "gn:asciiname":"Kitovu",
    "gn:country_code":"UG",
    "gn:dem":1291,
    "gn:feature_class":"P",
    "gn:feature_code":"PPL",
    "gn:name":"Kitovu",
    "gn:population":0,
    "gn:timezone":"Africa/Kampala",
    "iso:country":"UG",
    "name:eng_x_preferred":[
        "Kitovu"
    ],
    "wof:name":"Kitovu",
    "wof:placetype":"locality"
},
  "geometry": {"coordinates":[33.1755,0.37099],"type":"Point"}
}