{
  "type": "Feature",
  "properties": {
    "gn:admin1_code":"E",
    "gn:admin2_code":"D2",
    "gn:asciiname":"Bugero-Nyalinyali",
    "gn:country_code":"UG",
    "gn:dem":1098,
    "gn:feature_class":"P",
    "gn:feature_code":"PPL",
    "gn:name":"Bugero-Nyalinyali",
    "gn:population":0,
    "gn:timezone":"Africa/Kampala",
    "iso:country":"UG",
    "wof:name":"Bugero-Nyalinyali",
    "wof:placetype":"locality"
},
  "geometry": {"coordinates":[33.47701,0.88451],"type":"Point"}
}