{
  "type": "Feature",
  "properties": {
    "gn:admin1_code":"N",
    "gn:admin2_code":"77",
    "gn:admin3_code":"226029.0",
    "gn:admin4_code":"8657975.0",
    "gn:asciiname":"Kuluva",
    "gn:country_code":"UG",
    "gn:dem":1211,
    "gn:feature_class":"P",
    "gn:feature_code":"PPL",
    "gn:name":"Kuluva",
    "gn:population":0,
    "gn:timezone":"Africa/Kampala",
    "iso:country":"UG",
    "name:und_x_variant":[
        "Kuluva Leper Settlement",
        "Kuluva"
    ],
    "wof:name":"Kuluva",
    "wof:placetype":"locality"
},
  "geometry": {"coordinates":[30.93366,2.94706],"type":"Point"}
}