{
  "type": "Feature",
  "properties": {
    "gn:admin1_code":"W",
    "gn:admin2_code":"85",
    "gn:asciiname":"Kiganda",
    "gn:country_code":"UG",
    "gn:dem":1421,
    "gn:feature_class":"P",
    "gn:feature_code":"PPL",
    "gn:name":"Kiganda",
    "gn:population":0,
    "gn:timezone":"Africa/Kampala",
    "iso:country":"UG",
    "name:ceb_x_preferred":[
        "Kiganda"
    ],
    "name:eng_x_preferred":[
        "Kiganda"
    ],
    "name:fra_x_preferred":[
        "Kiganda"
    ],
    "name:swe_x_preferred":[
        "Kiganda"
    ],
    "wof:name":"Kiganda",
    "wof:placetype":"locality"
},
  "geometry": {"coordinates":[30.48885,0.59481],"type":"Point"}
}