{
  "type": "Feature",
  "properties": {
    "gn:admin1_code":"E",
    "gn:admin2_code":"H5",
    "gn:admin3_code":"8644174.0",
    "gn:admin4_code":"8658502.0",
    "gn:asciiname":"Nzalo",
    "gn:country_code":"UG",
    "gn:dem":1034,
    "gn:feature_class":"P",
    "gn:feature_code":"PPL",
    "gn:name":"Nzalo",
    "gn:population":0,
    "gn:timezone":"Africa/Kampala",
    "iso:country":"UG",
    "wof:name":"Nzalo",
    "wof:placetype":"locality"
},
  "geometry": {"coordinates":[33.14669,1.54402],"type":"Point"}
}