{
  "type": "Feature",
  "properties": {
    "gn:admin1_code":"E",
    "gn:admin2_code":"F6",
    "gn:asciiname":"Nandere",
    "gn:country_code":"UG",
    "gn:dem":1090,
    "gn:feature_class":"P",
    "gn:feature_code":"PPL",
    "gn:name":"Nandere",
    "gn:population":0,
    "gn:timezone":"Africa/Kampala",
    "iso:country":"UG",
    "wof:name":"Nandere",
    "wof:placetype":"locality"
},
  "geometry": {"coordinates":[33.87094,0.99702],"type":"Point"}
}