{
  "type": "Feature",
  "properties": {
    "gn:admin1_code":"C",
    "gn:admin2_code":"90",
    "gn:admin3_code":"7732384.0",
    "gn:admin4_code":"8658391.0",
    "gn:asciiname":"Ntumusi",
    "gn:country_code":"UG",
    "gn:dem":1216,
    "gn:feature_class":"P",
    "gn:feature_code":"PPL",
    "gn:name":"Ntumusi",
    "gn:population":0,
    "gn:timezone":"Africa/Kampala",
    "iso:country":"UG",
    "wof:name":"Ntumusi",
    "wof:placetype":"locality"
},
  "geometry": {"coordinates":[32.79982,0.25194],"type":"Point"}
}