{
  "type": "Feature",
  "properties": {
    "gn:admin1_code":"E",
    "gn:admin2_code":"D6",
    "gn:asciiname":"Sikhomosi",
    "gn:country_code":"UG",
    "gn:dem":1237,
    "gn:feature_class":"P",
    "gn:feature_code":"PPL",
    "gn:name":"Sikhomosi",
    "gn:population":0,
    "gn:timezone":"Africa/Kampala",
    "iso:country":"UG",
    "name:eng_x_preferred":[
        "Sikhomosi"
    ],
    "wof:name":"Sikhomosi",
    "wof:placetype":"locality"
},
  "geometry": {"coordinates":[34.31184,0.92661],"type":"Point"}
}