{
  "type": "Feature",
  "properties": {
    "gn:admin1_code":"W",
    "gn:admin2_code":"28",
    "gn:asciiname":"Kijanjaba",
    "gn:country_code":"UG",
    "gn:dem":827,
    "gn:feature_class":"P",
    "gn:feature_code":"PPL",
    "gn:name":"Kijanjaba",
    "gn:population":0,
    "gn:timezone":"Africa/Kampala",
    "iso:country":"UG",
    "name:eng_x_preferred":[
        "Kijanjaba"
    ],
    "wof:name":"Kijanjaba",
    "wof:placetype":"locality"
},
  "geometry": {"coordinates":[30.02472,0.71626],"type":"Point"}
}