{
  "type": "Feature",
  "properties": {
    "gn:admin1_code":"E",
    "gn:admin2_code":"C6",
    "gn:asciiname":"Lwamboga",
    "gn:country_code":"UG",
    "gn:dem":1083,
    "gn:feature_class":"P",
    "gn:feature_code":"PPL",
    "gn:name":"Lwamboga",
    "gn:population":0,
    "gn:timezone":"Africa/Kampala",
    "iso:country":"UG",
    "wof:name":"Lwamboga",
    "wof:placetype":"locality"
},
  "geometry": {"coordinates":[33.88409,0.90142],"type":"Point"}
}