{
  "type": "Feature",
  "properties": {
    "gn:admin1_code":"E",
    "gn:admin2_code":"C4",
    "gn:admin3_code":"7732537.0",
    "gn:admin4_code":"8658216.0",
    "gn:asciiname":"Kabei",
    "gn:country_code":"UG",
    "gn:dem":2648,
    "gn:feature_class":"P",
    "gn:feature_code":"PPL",
    "gn:name":"Kabei",
    "gn:population":0,
    "gn:timezone":"Africa/Kampala",
    "iso:country":"UG",
    "wof:name":"Kabei",
    "wof:placetype":"locality"
},
  "geometry": {"coordinates":[34.64005,1.29339],"type":"Point"}
}