{
  "type": "Feature",
  "properties": {
    "gn:admin1_code":"W",
    "gn:admin2_code":"85",
    "gn:asciiname":"Kyairumba",
    "gn:country_code":"UG",
    "gn:dem":1505,
    "gn:feature_class":"P",
    "gn:feature_code":"PPL",
    "gn:name":"Kyairumba",
    "gn:population":0,
    "gn:timezone":"Africa/Kampala",
    "iso:country":"UG",
    "name:eng_x_preferred":[
        "Kyairumba"
    ],
    "wof:name":"Kyairumba",
    "wof:placetype":"locality"
},
  "geometry": {"coordinates":[30.49678,0.70127],"type":"Point"}
}