{
  "type": "Feature",
  "properties": {
    "gn:admin1_code":"W",
    "gn:admin2_code":"31",
    "gn:admin3_code":"8644142.0",
    "gn:admin4_code":"8658374.0",
    "gn:asciiname":"Buhanika",
    "gn:country_code":"UG",
    "gn:dem":1194,
    "gn:feature_class":"P",
    "gn:feature_code":"PPL",
    "gn:name":"Buhanika",
    "gn:population":0,
    "gn:timezone":"Africa/Kampala",
    "iso:country":"UG",
    "wof:name":"Buhanika",
    "wof:placetype":"locality"
},
  "geometry": {"coordinates":[31.41667,1.41667],"type":"Point"}
}