{
  "type": "Feature",
  "properties": {
    "gn:admin1_code":"C",
    "gn:admin2_code":"96",
    "gn:admin3_code":"7732385.0",
    "gn:admin4_code":"8658439.0",
    "gn:asciiname":"Kirolo",
    "gn:country_code":"UG",
    "gn:dem":1200,
    "gn:feature_class":"P",
    "gn:feature_code":"PPL",
    "gn:name":"Kirolo",
    "gn:population":0,
    "gn:timezone":"Africa/Kampala",
    "iso:country":"UG",
    "wof:name":"Kirolo",
    "wof:placetype":"locality"
},
  "geometry": {"coordinates":[32.52205,0.47811],"type":"Point"}
}