{
  "type": "Feature",
  "properties": {
    "gn:admin1_code":"E",
    "gn:admin2_code":"38",
    "gn:asciiname":"Budiba",
    "gn:country_code":"UG",
    "gn:dem":1122,
    "gn:feature_class":"P",
    "gn:feature_code":"PPL",
    "gn:name":"Budiba",
    "gn:population":0,
    "gn:timezone":"Africa/Kampala",
    "iso:country":"UG",
    "wof:name":"Budiba",
    "wof:placetype":"locality"
},
  "geometry": {"coordinates":[33.19095,0.8733],"type":"Point"}
}