{
  "type": "Feature",
  "properties": {
    "gn:admin1_code":"E",
    "gn:admin2_code":"80",
    "gn:admin3_code":"233018.0",
    "gn:admin4_code":"8658326.0",
    "gn:asciiname":"Swagere",
    "gn:country_code":"UG",
    "gn:dem":1041,
    "gn:feature_class":"P",
    "gn:feature_code":"PPLL",
    "gn:name":"Swagere",
    "gn:population":0,
    "gn:timezone":"Africa/Kampala",
    "iso:country":"UG",
    "name:eng_x_preferred":[
        "Swagere"
    ],
    "wof:name":"Swagere",
    "wof:placetype":"locality"
},
  "geometry": {"coordinates":[33.0029,1.55001],"type":"Point"}
}