{
  "type": "Feature",
  "properties": {
    "gn:admin1_code":"N",
    "gn:admin2_code":"D1",
    "gn:admin3_code":"233569.0",
    "gn:admin4_code":"8658487.0",
    "gn:asciiname":"Lemej",
    "gn:country_code":"UG",
    "gn:dem":1410,
    "gn:feature_class":"P",
    "gn:feature_code":"PPL",
    "gn:name":"Lemej",
    "gn:population":0,
    "gn:timezone":"Africa/Kampala",
    "iso:country":"UG",
    "wof:name":"Lemej",
    "wof:placetype":"locality"
},
  "geometry": {"coordinates":[33.81141,3.74453],"type":"Point"}
}