{
  "type": "Feature",
  "properties": {
    "gn:admin1_code":"C",
    "gn:admin2_code":"E7",
    "gn:admin3_code":"7732075.0",
    "gn:admin4_code":"8658088.0",
    "gn:asciiname":"Lunajja",
    "gn:country_code":"UG",
    "gn:dem":1236,
    "gn:feature_class":"P",
    "gn:feature_code":"PPL",
    "gn:name":"Lunajja",
    "gn:population":0,
    "gn:timezone":"Africa/Kampala",
    "iso:country":"UG",
    "name:eng_x_preferred":[
        "Lunajja"
    ],
    "wof:name":"Lunajja",
    "wof:placetype":"locality"
},
  "geometry": {"coordinates":[33.00252,0.13309],"type":"Point"}
}