{
  "type": "Feature",
  "properties": {
    "gn:admin1_code":"W",
    "gn:admin2_code":"28",
    "gn:asciiname":"Kadindere",
    "gn:country_code":"UG",
    "gn:dem":878,
    "gn:feature_class":"P",
    "gn:feature_code":"PPL",
    "gn:name":"Kadindere",
    "gn:population":0,
    "gn:timezone":"Africa/Kampala",
    "iso:country":"UG",
    "name:eng_x_preferred":[
        "Kadindere"
    ],
    "wof:name":"Kadindere",
    "wof:placetype":"locality"
},
  "geometry": {"coordinates":[30.0392,0.71173],"type":"Point"}
}