{
  "type": "Feature",
  "properties": {
    "gn:admin1_code":"N",
    "gn:admin2_code":"58",
    "gn:admin3_code":"8080237.0",
    "gn:admin4_code":"8261564.0",
    "gn:asciiname":"Kosh",
    "gn:country_code":"UG",
    "gn:dem":905,
    "gn:feature_class":"P",
    "gn:feature_code":"PPL",
    "gn:name":"Kosh",
    "gn:population":0,
    "gn:timezone":"Africa/Kampala",
    "iso:country":"UG",
    "name:aze_x_preferred":[
        "Qo\u015f"
    ],
    "name:ceb_x_preferred":[
        "Kosh"
    ],
    "name:est_x_preferred":[
        "Kosh"
    ],
    "name:hye_x_preferred":[
        "\u053f\u0578\u0577"
    ],
    "name:swe_x_preferred":[
        "Kosh"
    ],
    "wof:name":"Kosh",
    "wof:placetype":"locality"
},
  "geometry": {"coordinates":[31.14553,2.54632],"type":"Point"}
}