{
  "type": "Feature",
  "properties": {
    "gn:admin1_code":"C",
    "gn:admin2_code":"F1",
    "gn:asciiname":"Seeta",
    "gn:country_code":"UG",
    "gn:dem":1245,
    "gn:feature_class":"P",
    "gn:feature_code":"PPL",
    "gn:name":"Seeta",
    "gn:population":0,
    "gn:timezone":"Africa/Kampala",
    "iso:country":"UG",
    "wof:name":"Seeta",
    "wof:placetype":"locality"
},
  "geometry": {"coordinates":[32.04487,0.11359],"type":"Point"}
}