{
  "type": "Feature",
  "properties": {
    "gn:admin1_code":"C",
    "gn:admin2_code":"F4",
    "gn:admin3_code":"233383.0",
    "gn:admin4_code":"8657737.0",
    "gn:asciiname":"Taba",
    "gn:country_code":"UG",
    "gn:dem":1244,
    "gn:feature_class":"P",
    "gn:feature_code":"PPL",
    "gn:name":"Taba",
    "gn:population":0,
    "gn:timezone":"Africa/Kampala",
    "iso:country":"UG",
    "wof:name":"Taba",
    "wof:placetype":"locality"
},
  "geometry": {"coordinates":[32.02423,0.20808],"type":"Point"}
}