{
  "type": "Feature",
  "properties": {
    "gn:admin1_code":"E",
    "gn:admin2_code":"76",
    "gn:asciiname":"Per-Per",
    "gn:country_code":"UG",
    "gn:dem":1144,
    "gn:feature_class":"P",
    "gn:feature_code":"PPL",
    "gn:name":"Per-Per",
    "gn:population":0,
    "gn:timezone":"Africa/Kampala",
    "iso:country":"UG",
    "name:eng_x_preferred":[
        "Per-Per"
    ],
    "wof:name":"Per-Per",
    "wof:placetype":"locality"
},
  "geometry": {"coordinates":[34.04555,0.81241],"type":"Point"}
}