{
  "type": "Feature",
  "properties": {
    "gn:admin1_code":"W",
    "gn:admin2_code":"H8",
    "gn:admin3_code":"234153.0",
    "gn:admin4_code":"8658414.0",
    "gn:asciiname":"Kyeitembe",
    "gn:country_code":"UG",
    "gn:dem":1530,
    "gn:feature_class":"P",
    "gn:feature_code":"PPL",
    "gn:name":"Kyeitembe",
    "gn:population":0,
    "gn:timezone":"Africa/Kampala",
    "iso:country":"UG",
    "wof:name":"Kyeitembe",
    "wof:placetype":"locality"
},
  "geometry": {"coordinates":[30.1779,0.54667],"type":"Point"}
}