{
  "type": "Feature",
  "properties": {
    "gn:admin1_code":"E",
    "gn:admin2_code":"E1",
    "gn:admin3_code":"8644136.0",
    "gn:admin4_code":"8658179.0",
    "gn:asciiname":"Bunyagwe",
    "gn:country_code":"UG",
    "gn:dem":1071,
    "gn:feature_class":"P",
    "gn:feature_code":"PPL",
    "gn:name":"Bunyagwe",
    "gn:population":0,
    "gn:timezone":"Africa/Kampala",
    "iso:country":"UG",
    "wof:name":"Bunyagwe",
    "wof:placetype":"locality"
},
  "geometry": {"coordinates":[33.57796,0.82451],"type":"Point"}
}