{
  "type": "Feature",
  "properties": {
    "gn:admin1_code":"N",
    "gn:admin2_code":"65",
    "gn:admin3_code":"8644133.0",
    "gn:admin4_code":"8658573.0",
    "gn:asciiname":"Pamonye",
    "gn:country_code":"UG",
    "gn:dem":641,
    "gn:feature_class":"P",
    "gn:feature_code":"PPL",
    "gn:name":"Pamonye",
    "gn:population":0,
    "gn:timezone":"Africa/Kampala",
    "iso:country":"UG",
    "wof:name":"Pamonye",
    "wof:placetype":"locality"
},
  "geometry": {"coordinates":[31.88211,3.4898],"type":"Point"}
}