{
  "type": "Feature",
  "properties": {
    "gn:admin1_code":"N",
    "gn:admin2_code":"58",
    "gn:admin3_code":"8080237.0",
    "gn:admin4_code":"8261562.0",
    "gn:asciiname":"Apola",
    "gn:country_code":"UG",
    "gn:dem":1034,
    "gn:feature_class":"P",
    "gn:feature_code":"PPL",
    "gn:name":"Apola",
    "gn:population":0,
    "gn:timezone":"Africa/Kampala",
    "iso:country":"UG",
    "wof:name":"Apola",
    "wof:placetype":"locality"
},
  "geometry": {"coordinates":[31.17519,2.3792],"type":"Point"}
}