{
  "type": "Feature",
  "properties": {
    "gn:admin1_code":"N",
    "gn:admin2_code":"77",
    "gn:admin3_code":"8644146.0",
    "gn:admin4_code":"8658077.0",
    "gn:asciiname":"Parabik",
    "gn:country_code":"UG",
    "gn:dem":664,
    "gn:feature_class":"P",
    "gn:feature_code":"PPL",
    "gn:name":"Parabik",
    "gn:population":0,
    "gn:timezone":"Africa/Kampala",
    "iso:country":"UG",
    "wof:name":"Parabik",
    "wof:placetype":"locality"
},
  "geometry": {"coordinates":[31.3289,2.78655],"type":"Point"}
}