{
  "type": "Feature",
  "properties": {
    "gn:admin1_code":"C",
    "gn:admin2_code":"96",
    "gn:asciiname":"Masanda",
    "gn:country_code":"UG",
    "gn:dem":1173,
    "gn:feature_class":"P",
    "gn:feature_code":"PPL",
    "gn:name":"Masanda",
    "gn:population":0,
    "gn:timezone":"Africa/Kampala",
    "iso:country":"UG",
    "wof:name":"Masanda",
    "wof:placetype":"locality"
},
  "geometry": {"coordinates":[32.49862,0.30307],"type":"Point"}
}