{
  "type": "Feature",
  "properties": {
    "gn:admin1_code":"C",
    "gn:admin2_code":"D5",
    "gn:admin3_code":"232958.0",
    "gn:admin4_code":"8658140.0",
    "gn:asciiname":"Nske",
    "gn:country_code":"UG",
    "gn:dem":1337,
    "gn:feature_class":"P",
    "gn:feature_code":"PPL",
    "gn:name":"Nske",
    "gn:population":0,
    "gn:timezone":"Africa/Kampala",
    "iso:country":"UG",
    "wof:name":"Nske",
    "wof:placetype":"locality"
},
  "geometry": {"coordinates":[31.19111,-0.24889],"type":"Point"}
}