{
  "type": "Feature",
  "properties": {
    "gn:admin1_code":"C",
    "gn:admin2_code":"D8",
    "gn:asciiname":"Namukomago",
    "gn:country_code":"UG",
    "gn:dem":1301,
    "gn:feature_class":"P",
    "gn:feature_code":"PPL",
    "gn:name":"Namukomago",
    "gn:population":0,
    "gn:timezone":"Africa/Kampala",
    "iso:country":"UG",
    "wof:name":"Namukomago",
    "wof:placetype":"locality"
},
  "geometry": {"coordinates":[32.10674,0.44518],"type":"Point"}
}