{
  "type": "Feature",
  "properties": {
    "gn:admin1_code":"C",
    "gn:admin2_code":"D9",
    "gn:admin3_code":"8644153.0",
    "gn:admin4_code":"8658601.0",
    "gn:asciiname":"Budzi",
    "gn:country_code":"UG",
    "gn:dem":1069,
    "gn:feature_class":"P",
    "gn:feature_code":"PPL",
    "gn:name":"Budzi",
    "gn:population":0,
    "gn:timezone":"Africa/Kampala",
    "iso:country":"UG",
    "wof:name":"Budzi",
    "wof:placetype":"locality"
},
  "geometry": {"coordinates":[31.96845,1.25764],"type":"Point"}
}