{
  "type": "Feature",
  "properties": {
    "gn:admin1_code":"E",
    "gn:admin2_code":"H5",
    "gn:admin3_code":"8644174.0",
    "gn:admin4_code":"8658380.0",
    "gn:asciiname":"Omolotok",
    "gn:country_code":"UG",
    "gn:dem":1070,
    "gn:feature_class":"P",
    "gn:feature_code":"PPL",
    "gn:name":"Omolotok",
    "gn:population":0,
    "gn:timezone":"Africa/Kampala",
    "iso:country":"UG",
    "name:und_x_variant":[
        "Molotok",
        "Omolotok"
    ],
    "wof:name":"Omolotok",
    "wof:placetype":"locality"
},
  "geometry": {"coordinates":[33.38333,1.48333],"type":"Point"}
}