{
  "type": "Feature",
  "properties": {
    "gn:admin1_code":"E",
    "gn:admin2_code":"D6",
    "gn:asciiname":"Busilali",
    "gn:country_code":"UG",
    "gn:dem":1295,
    "gn:feature_class":"P",
    "gn:feature_code":"PPL",
    "gn:name":"Busilali",
    "gn:population":0,
    "gn:timezone":"Africa/Kampala",
    "iso:country":"UG",
    "name:eng_x_preferred":[
        "Busilali"
    ],
    "wof:name":"Busilali",
    "wof:placetype":"locality"
},
  "geometry": {"coordinates":[34.28974,0.81712],"type":"Point"}
}