{
  "type": "Feature",
  "properties": {
    "gn:admin1_code":"C",
    "gn:admin2_code":"90",
    "gn:admin3_code":"7732384.0",
    "gn:admin4_code":"8658156.0",
    "gn:asciiname":"Mwanyangiri",
    "gn:country_code":"UG",
    "gn:dem":1163,
    "gn:feature_class":"P",
    "gn:feature_code":"PPL",
    "gn:name":"Mwanyangiri",
    "gn:population":0,
    "gn:timezone":"Africa/Kampala",
    "iso:country":"UG",
    "wof:name":"Mwanyangiri",
    "wof:placetype":"locality"
},
  "geometry": {"coordinates":[32.8279,0.33631],"type":"Point"}
}