{
  "type": "Feature",
  "properties": {
    "gn:admin1_code":"W",
    "gn:admin2_code":"50",
    "gn:admin3_code":"234463.0",
    "gn:admin4_code":"8657903.0",
    "gn:asciiname":"Buganda",
    "gn:country_code":"UG",
    "gn:dem":1101,
    "gn:feature_class":"P",
    "gn:feature_code":"PPL",
    "gn:name":"Buganda",
    "gn:population":0,
    "gn:timezone":"Africa/Kampala",
    "iso:country":"UG",
    "wof:name":"Buganda",
    "wof:placetype":"locality"
},
  "geometry": {"coordinates":[31.41287,1.63037],"type":"Point"}
}