{
  "type": "Feature",
  "properties": {
    "gn:admin1_code":"E",
    "gn:admin2_code":"76",
    "gn:asciiname":"Suruti",
    "gn:country_code":"UG",
    "gn:dem":1133,
    "gn:feature_class":"P",
    "gn:feature_code":"PPL",
    "gn:name":"Suruti",
    "gn:population":0,
    "gn:timezone":"Africa/Kampala",
    "iso:country":"UG",
    "name:eng_x_preferred":[
        "Suruti"
    ],
    "wof:name":"Suruti",
    "wof:placetype":"locality"
},
  "geometry": {"coordinates":[34.14966,0.83881],"type":"Point"}
}