{
  "type": "Feature",
  "properties": {
    "gn:admin1_code":"C",
    "gn:admin2_code":"71",
    "gn:admin3_code":"7732231.0",
    "gn:admin4_code":"8657583.0",
    "gn:asciiname":"Kyanja",
    "gn:country_code":"UG",
    "gn:dem":1218,
    "gn:feature_class":"P",
    "gn:feature_code":"PPL",
    "gn:name":"Kyanja",
    "gn:population":0,
    "gn:timezone":"Africa/Kampala",
    "iso:country":"UG",
    "wof:name":"Kyanja",
    "wof:placetype":"locality"
},
  "geometry": {"coordinates":[31.71028,-0.33194],"type":"Point"}
}