{
  "type": "Feature",
  "properties": {
    "gn:admin1_code":"C",
    "gn:admin2_code":"89",
    "gn:admin3_code":"7910214.0",
    "gn:admin4_code":"8658615.0",
    "gn:asciiname":"Kajjaga",
    "gn:country_code":"UG",
    "gn:dem":1208,
    "gn:feature_class":"P",
    "gn:feature_code":"PPL",
    "gn:name":"Kajjaga",
    "gn:population":0,
    "gn:timezone":"Africa/Kampala",
    "iso:country":"UG",
    "name:und_x_variant":[
        "Kajaga"
    ],
    "wof:name":"Kajjaga",
    "wof:placetype":"locality"
},
  "geometry": {"coordinates":[32.26481,0.20008],"type":"Point"}
}