{
  "type": "Feature",
  "properties": {
    "gn:admin1_code":"E",
    "gn:admin2_code":"86",
    "gn:admin3_code":"8644164.0",
    "gn:admin4_code":"8658692.0",
    "gn:asciiname":"Mukonda",
    "gn:country_code":"UG",
    "gn:dem":1175,
    "gn:feature_class":"P",
    "gn:feature_code":"PPL",
    "gn:name":"Mukonda",
    "gn:population":0,
    "gn:timezone":"Africa/Kampala",
    "iso:country":"UG",
    "name:eng_x_preferred":[
        "Mukonda"
    ],
    "wof:name":"Mukonda",
    "wof:placetype":"locality"
},
  "geometry": {"coordinates":[33.51912,0.43064],"type":"Point"}
}