{
  "type": "Feature",
  "properties": {
    "gn:admin1_code":"W",
    "gn:admin2_code":"C5",
    "gn:admin3_code":"7869947.0",
    "gn:admin4_code":"8657960.0",
    "gn:asciiname":"Itutwe",
    "gn:country_code":"UG",
    "gn:dem":951,
    "gn:feature_class":"P",
    "gn:feature_code":"PPL",
    "gn:name":"Itutwe",
    "gn:population":0,
    "gn:timezone":"Africa/Kampala",
    "iso:country":"UG",
    "wof:name":"Itutwe",
    "wof:placetype":"locality"
},
  "geometry": {"coordinates":[31.39725,1.74936],"type":"Point"}
}