{
  "type": "Feature",
  "properties": {
    "gn:admin1_code":"C",
    "gn:admin2_code":"74",
    "gn:admin3_code":"229304.0",
    "gn:admin4_code":"8657816.0",
    "gn:asciiname":"Nakaseta",
    "gn:country_code":"UG",
    "gn:dem":1250,
    "gn:feature_class":"P",
    "gn:feature_code":"PPL",
    "gn:name":"Nakaseta",
    "gn:population":0,
    "gn:timezone":"Africa/Kampala",
    "iso:country":"UG",
    "wof:name":"Nakaseta",
    "wof:placetype":"locality"
},
  "geometry": {"coordinates":[31.53056,-0.21917],"type":"Point"}
}