{
  "type": "Feature",
  "properties": {
    "gn:admin1_code":"W",
    "gn:admin2_code":"79",
    "gn:asciiname":"Kyanjura",
    "gn:country_code":"UG",
    "gn:dem":1709,
    "gn:feature_class":"P",
    "gn:feature_code":"PPL",
    "gn:name":"Kyanjura",
    "gn:population":0,
    "gn:timezone":"Africa/Kampala",
    "iso:country":"UG",
    "name:eng_x_preferred":[
        "Kyanjura"
    ],
    "wof:name":"Kyanjura",
    "wof:placetype":"locality"
},
  "geometry": {"coordinates":[30.13586,0.56223],"type":"Point"}
}