{
  "type": "Feature",
  "properties": {
    "gn:admin1_code":"C",
    "gn:admin2_code":"73",
    "gn:admin3_code":"234123.0",
    "gn:admin4_code":"8657970.0",
    "gn:asciiname":"Wabukala",
    "gn:country_code":"UG",
    "gn:dem":1060,
    "gn:feature_class":"P",
    "gn:feature_code":"PPL",
    "gn:name":"Wabukala",
    "gn:population":0,
    "gn:timezone":"Africa/Kampala",
    "iso:country":"UG",
    "wof:name":"Wabukala",
    "wof:placetype":"locality"
},
  "geometry": {"coordinates":[32.22846,1.52087],"type":"Point"}
}