{
  "type": "Feature",
  "properties": {
    "gn:admin1_code":"N",
    "gn:admin2_code":"26",
    "gn:admin3_code":"230563.0",
    "gn:admin4_code":"8658296.0",
    "gn:asciiname":"Inomo",
    "gn:country_code":"UG",
    "gn:dem":1072,
    "gn:feature_class":"P",
    "gn:feature_code":"PPL",
    "gn:name":"Inomo",
    "gn:population":0,
    "gn:timezone":"Africa/Kampala",
    "iso:country":"UG",
    "name:und_x_variant":[
        "Kinomo",
        "Inomo"
    ],
    "wof:name":"Inomo",
    "wof:placetype":"locality"
},
  "geometry": {"coordinates":[32.68333,2.06667],"type":"Point"}
}