{
  "type": "Feature",
  "properties": {
    "gn:admin1_code":"E",
    "gn:admin2_code":"33",
    "gn:admin3_code":"8644138.0",
    "gn:admin4_code":"8658668.0",
    "gn:asciiname":"Budumbuli",
    "gn:country_code":"UG",
    "gn:dem":1160,
    "gn:feature_class":"P",
    "gn:feature_code":"PPL",
    "gn:name":"Budumbuli",
    "gn:population":0,
    "gn:timezone":"Africa/Kampala",
    "iso:country":"UG",
    "name:eng_x_preferred":[
        "Budumbuli"
    ],
    "wof:name":"Budumbuli",
    "wof:placetype":"locality"
},
  "geometry": {"coordinates":[33.23755999999999,0.46257],"type":"Point"}
}