{
  "type": "Feature",
  "properties": {
    "gn:admin1_code":"E",
    "gn:admin2_code":"76",
    "gn:asciiname":"Wiyola",
    "gn:country_code":"UG",
    "gn:dem":1140,
    "gn:feature_class":"P",
    "gn:feature_code":"PPL",
    "gn:name":"Wiyola",
    "gn:population":0,
    "gn:timezone":"Africa/Kampala",
    "iso:country":"UG",
    "wof:name":"Wiyola",
    "wof:placetype":"locality"
},
  "geometry": {"coordinates":[33.99448,0.76804],"type":"Point"}
}