{
  "type": "Feature",
  "properties": {
    "gn:admin1_code":"E",
    "gn:admin2_code":"80",
    "gn:admin3_code":"7732909.0",
    "gn:admin4_code":"8658623.0",
    "gn:asciiname":"Katiti",
    "gn:country_code":"UG",
    "gn:dem":1047,
    "gn:feature_class":"P",
    "gn:feature_code":"PPL",
    "gn:name":"Katiti",
    "gn:population":0,
    "gn:timezone":"Africa/Kampala",
    "iso:country":"UG",
    "wof:name":"Katiti",
    "wof:placetype":"locality"
},
  "geometry": {"coordinates":[33.41005,1.78274],"type":"Point"}
}