{
  "type": "Feature",
  "properties": {
    "gn:admin1_code":"C",
    "gn:admin2_code":"E7",
    "gn:admin3_code":"7732075.0",
    "gn:admin4_code":"8658675.0",
    "gn:asciiname":"Kito",
    "gn:country_code":"UG",
    "gn:dem":1225,
    "gn:feature_class":"P",
    "gn:feature_code":"PPL",
    "gn:name":"Kito",
    "gn:population":0,
    "gn:timezone":"Africa/Kampala",
    "iso:country":"UG",
    "name:ceb_x_preferred":[
        "Kito"
    ],
    "name:deu_x_preferred":[
        "Kito"
    ],
    "name:eng_x_preferred":[
        "Kito"
    ],
    "name:eus_x_preferred":[
        "Kito"
    ],
    "name:ita_x_preferred":[
        "Kito"
    ],
    "name:swa_x_preferred":[
        "Kito"
    ],
    "name:swe_x_preferred":[
        "Kito"
    ],
    "wof:name":"Kito",
    "wof:placetype":"locality"
},
  "geometry": {"coordinates":[33.05245,0.34119],"type":"Point"}
}