{
  "type": "Feature",
  "properties": {
    "gn:admin1_code":"W",
    "gn:admin2_code":"79",
    "gn:admin3_code":"7732226.0",
    "gn:admin4_code":"8658114.0",
    "gn:asciiname":"Virika",
    "gn:country_code":"UG",
    "gn:dem":1556,
    "gn:feature_class":"P",
    "gn:feature_code":"PPL",
    "gn:name":"Virika",
    "gn:population":0,
    "gn:timezone":"Africa/Kampala",
    "iso:country":"UG",
    "name:eng_x_preferred":[
        "Virika"
    ],
    "wof:name":"Virika",
    "wof:placetype":"locality"
},
  "geometry": {"coordinates":[30.26984,0.63547],"type":"Point"}
}