{
  "type": "Feature",
  "properties": {
    "gn:admin1_code":"W",
    "gn:admin2_code":"29",
    "gn:admin3_code":"7732267.0",
    "gn:admin4_code":"8658195.0",
    "gn:asciiname":"Nyarutoma",
    "gn:country_code":"UG",
    "gn:dem":1550,
    "gn:feature_class":"P",
    "gn:feature_code":"PPL",
    "gn:name":"Nyarutoma",
    "gn:population":0,
    "gn:timezone":"Africa/Kampala",
    "iso:country":"UG",
    "wof:name":"Nyarutoma",
    "wof:placetype":"locality"
},
  "geometry": {"coordinates":[30.08333,-0.51667],"type":"Point"}
}