{
  "type": "Feature",
  "properties": {
    "gn:admin1_code":"E",
    "gn:admin2_code":"76",
    "gn:asciiname":"Amorigee",
    "gn:country_code":"UG",
    "gn:dem":1119,
    "gn:feature_class":"P",
    "gn:feature_code":"PPL",
    "gn:name":"Amorigee",
    "gn:population":0,
    "gn:timezone":"Africa/Kampala",
    "iso:country":"UG",
    "name:eng_x_preferred":[
        "Amorigee"
    ],
    "wof:name":"Amorigee",
    "wof:placetype":"locality"
},
  "geometry": {"coordinates":[34.04366,0.65952],"type":"Point"}
}