{
  "type": "Feature",
  "properties": {
    "gn:admin1_code":"N",
    "gn:admin2_code":"77",
    "gn:admin3_code":"226029.0",
    "gn:admin4_code":"8658545.0",
    "gn:asciiname":"Alivu",
    "gn:country_code":"UG",
    "gn:dem":948,
    "gn:feature_class":"P",
    "gn:feature_code":"PPL",
    "gn:name":"Alivu",
    "gn:population":0,
    "gn:timezone":"Africa/Kampala",
    "iso:country":"UG",
    "wof:name":"Alivu",
    "wof:placetype":"locality"
},
  "geometry": {"coordinates":[31.00147,2.99541],"type":"Point"}
}