{
  "type": "Feature",
  "properties": {
    "gn:admin1_code":"E",
    "gn:admin2_code":"76",
    "gn:asciiname":"Kachinga",
    "gn:country_code":"UG",
    "gn:dem":1143,
    "gn:feature_class":"P",
    "gn:feature_code":"PPL",
    "gn:name":"Kachinga",
    "gn:population":0,
    "gn:timezone":"Africa/Kampala",
    "iso:country":"UG",
    "name:eng_x_preferred":[
        "Kachinga"
    ],
    "wof:name":"Kachinga",
    "wof:placetype":"locality"
},
  "geometry": {"coordinates":[34.12325999999999,0.82729],"type":"Point"}
}