{
  "type": "Feature",
  "properties": {
    "gn:admin1_code":"E",
    "gn:admin2_code":"G7",
    "gn:admin3_code":"8644167.0",
    "gn:admin4_code":"8657677.0",
    "gn:asciiname":"Nansaga",
    "gn:country_code":"UG",
    "gn:dem":1205,
    "gn:feature_class":"P",
    "gn:feature_code":"PPL",
    "gn:name":"Nansaga",
    "gn:population":0,
    "gn:timezone":"Africa/Kampala",
    "iso:country":"UG",
    "name:eng_x_preferred":[
        "Nansaga"
    ],
    "wof:name":"Nansaga",
    "wof:placetype":"locality"
},
  "geometry": {"coordinates":[33.72168,0.43427],"type":"Point"}
}