{
  "type": "Feature",
  "properties": {
    "gn:country":"UG",
    "gn:fcode":"PPLA2",
    "gn:pop":28700,
    "iso:country":"UG",
    "name:ara_x_preferred":[
        "\u0623\u062f\u062c\u0648\u0645\u0627\u0646\u0649"
    ],
    "name:dut_x_preferred":[
        "Adjumani"
    ],
    "name:eng_x_preferred":[
        "Adjumani"
    ],
    "name:fre_x_preferred":[
        "Adjumani"
    ],
    "name:ita_x_preferred":[
        "Adjumani"
    ],
    "name:jpn_x_preferred":[
        "\u30a2\u30b8\u30e5\u30de\u30cb"
    ],
    "name:lug_x_preferred":[
        "Adjumani"
    ],
    "name:nob_x_preferred":[
        "Adjumani"
    ],
    "name:per_x_preferred":[
        "\u0627\u062c\u0648\u0645\u0627\u0646\u06cc"
    ],
    "name:pol_x_preferred":[
        "Adjumani"
    ],
    "name:por_x_preferred":[
        "Adjumani"
    ],
    "name:rum_x_preferred":[
        "Adjumani"
    ],
    "name:spa_x_preferred":[
        "Adjumani"
    ],
    "name:swa_x_preferred":[
        "Adjumani"
    ],
    "name:unk_x_variant":[
        "Ajumani"
    ],
    "name:urd_x_preferred":[
        "\u0627\u062f\u062c\u0648\u0645\u0627\u0646\u06cc"
    ],
    "ne:ADM0CAP":0.0,
    "ne:ADM0NAME":"Uganda",
    "ne:ADM0_A3":"UGA",
    "ne:ADM1NAME":"Adjumani",
    "ne:ADMIN1_COD":65,
    "ne:CAPALT":0,
    "ne:CHANGED":4,
    "ne:CHECKME":0,
    "ne:COMPARE":0,
    "ne:DIFFASCII":0,
    "ne:DIFFNOTE":"Added missing admin-1 capital round B. Population from GeoNames.",
    "ne:ELEVATION":0.0,
    "ne:FEATURECLA":"Admin-1 capital",
    "ne:FEATURE_CL":"P",
    "ne:FEATURE_CO":"PPLA",
    "ne:GEONAMEID":235489,
    "ne:GEONAMESNO":"GeoNames match general.",
    "ne:GN_ASCII":"Adjumani",
    "ne:GN_POP":0,
    "ne:GTOPO30":762.0,
    "ne:ISO_A2":"UG",
    "ne:LABELRANK":5,
    "ne:LATITUDE":3.361389,
    "ne:LONGITUDE":31.809722,
    "ne:LS_MATCH":0,
    "ne:MAX_AREAKM":0.0,
    "ne:MAX_AREAMI":0.0,
    "ne:MAX_BBXMAX":0.0,
    "ne:MAX_BBXMIN":0.0,
    "ne:MAX_BBYMAX":0.0,
    "ne:MAX_BBYMIN":0.0,
    "ne:MAX_NATSCA":0.0,
    "ne:MAX_PERKM":0.0,
    "ne:MAX_PERMI":0.0,
    "ne:MAX_POP10":0,
    "ne:MAX_POP20":0,
    "ne:MAX_POP300":0,
    "ne:MAX_POP310":0,
    "ne:MAX_POP50":0,
    "ne:MEAN_BBXC":0.0,
    "ne:MEAN_BBYC":0.0,
    "ne:MEGACITY":0,
    "ne:MIN_AREAKM":0.0,
    "ne:MIN_AREAMI":0.0,
    "ne:MIN_BBXMAX":0.0,
    "ne:MIN_BBXMIN":0.0,
    "ne:MIN_BBYMAX":0.0,
    "ne:MIN_BBYMIN":0.0,
    "ne:MIN_PERKM":0.0,
    "ne:MIN_PERMI":0.0,
    "ne:NAME":"Adjumani",
    "ne:NAMEASCII":"Adjumani",
    "ne:NAMEDIFF":0,
    "ne:NATSCALE":1,
    "ne:POP1950":0,
    "ne:POP1955":0,
    "ne:POP1960":0,
    "ne:POP1965":0,
    "ne:POP1970":0,
    "ne:POP1975":0,
    "ne:POP1980":0,
    "ne:POP1985":0,
    "ne:POP1990":0,
    "ne:POP1995":0,
    "ne:POP2000":0,
    "ne:POP2005":0,
    "ne:POP2010":0,
    "ne:POP2015":0,
    "ne:POP2020":0,
    "ne:POP2025":0,
    "ne:POP2050":0,
    "ne:POP_MAX":34700,
    "ne:POP_MIN":34700,
    "ne:POP_OTHER":0,
    "ne:RANK_MAX":7,
    "ne:RANK_MIN":7,
    "ne:SCALERANK":10,
    "ne:SOV0NAME":"Uganda",
    "ne:SOV_A3":"UGA",
    "ne:TIMEZONE":"Africa/Kampala",
    "ne:UN_FID":0,
    "ne:UN_LAT":0.0,
    "ne:UN_LONG":0.0,
    "ne:WORLDCITY":0,
    "qs:name":"Adjumani",
    "qs:photos_9r":0,
    "qs:photos_sr":0,
    "qs:pop_sr":"7",
    "wd:wordcount":314,
    "wof:name":"Adjumani",
    "wof:placetype":"locality",
    "wof:population":28700
},
  "geometry": {"coordinates":[31.7909,3.37786],"type":"Point"}
}