{
  "type": "Feature",
  "properties": {
    "gn:admin1_code":"N",
    "gn:admin2_code":"D7",
    "gn:admin3_code":"229396.0",
    "gn:admin4_code":"8658274.0",
    "gn:asciiname":"Obuje",
    "gn:country_code":"UG",
    "gn:dem":1093,
    "gn:feature_class":"P",
    "gn:feature_code":"PPL",
    "gn:name":"Obuje",
    "gn:population":0,
    "gn:timezone":"Africa/Kampala",
    "iso:country":"UG",
    "name:und_x_variant":[
        "Offude",
        "Ofude",
        "Obuje"
    ],
    "wof:name":"Obuje",
    "wof:placetype":"locality"
},
  "geometry": {"coordinates":[30.97058,3.19433],"type":"Point"}
}