{
  "type": "Feature",
  "properties": {
    "gn:admin1_code":"C",
    "gn:admin2_code":"F4",
    "gn:asciiname":"Kilwanya",
    "gn:country_code":"UG",
    "gn:dem":1237,
    "gn:feature_class":"P",
    "gn:feature_code":"PPL",
    "gn:name":"Kilwanya",
    "gn:population":0,
    "gn:timezone":"Africa/Kampala",
    "iso:country":"UG",
    "wof:name":"Kilwanya",
    "wof:placetype":"locality"
},
  "geometry": {"coordinates":[32.14641,0.25532],"type":"Point"}
}