{
  "type": "Feature",
  "properties": {
    "gn:admin1_code":"E",
    "gn:admin2_code":"D6",
    "gn:asciiname":"Buwanyama",
    "gn:country_code":"UG",
    "gn:dem":1247,
    "gn:feature_class":"P",
    "gn:feature_code":"PPL",
    "gn:name":"Buwanyama",
    "gn:population":0,
    "gn:timezone":"Africa/Kampala",
    "iso:country":"UG",
    "name:eng_x_preferred":[
        "Buwanyama"
    ],
    "wof:name":"Buwanyama",
    "wof:placetype":"locality"
},
  "geometry": {"coordinates":[34.27669,0.85305],"type":"Point"}
}