{
  "type": "Feature",
  "properties": {
    "gn:admin1_code":"C",
    "gn:admin2_code":"73",
    "gn:admin3_code":"234123.0",
    "gn:admin4_code":"8657735.0",
    "gn:asciiname":"Kaleire",
    "gn:country_code":"UG",
    "gn:dem":1086,
    "gn:feature_class":"P",
    "gn:feature_code":"PPL",
    "gn:name":"Kaleire",
    "gn:population":0,
    "gn:timezone":"Africa/Kampala",
    "iso:country":"UG",
    "wof:name":"Kaleire",
    "wof:placetype":"locality"
},
  "geometry": {"coordinates":[32.46667,1.16667],"type":"Point"}
}