{
  "type": "Feature",
  "properties": {
    "gn:admin1_code":"C",
    "gn:admin2_code":"96",
    "gn:asciiname":"Nakyerongosa",
    "gn:country_code":"UG",
    "gn:dem":1180,
    "gn:feature_class":"P",
    "gn:feature_code":"PPL",
    "gn:name":"Nakyerongosa",
    "gn:population":0,
    "gn:timezone":"Africa/Kampala",
    "iso:country":"UG",
    "wof:name":"Nakyerongosa",
    "wof:placetype":"locality"
},
  "geometry": {"coordinates":[32.36631,0.43935],"type":"Point"}
}