{
  "type": "Feature",
  "properties": {
    "gn:admin1_code":"W",
    "gn:admin2_code":"79",
    "gn:asciiname":"Kagera",
    "gn:country_code":"UG",
    "gn:dem":1497,
    "gn:feature_class":"P",
    "gn:feature_code":"PPL",
    "gn:name":"Kagera",
    "gn:population":0,
    "gn:timezone":"Africa/Kampala",
    "iso:country":"UG",
    "name:ceb_x_preferred":[
        "Kagera"
    ],
    "name:deu_x_preferred":[
        "Kagera"
    ],
    "name:ell_x_preferred":[
        "\u039a\u03b1\u03b3\u03ba\u03ad\u03c1\u03b1"
    ],
    "name:eng_x_preferred":[
        "Kagera"
    ],
    "name:glg_x_preferred":[
        "Kagera"
    ],
    "name:heb_x_preferred":[
        "\u05e7\u05d0\u05d2\u05e8\u05d4"
    ],
    "name:hun_x_preferred":[
        "Kagera"
    ],
    "name:ind_x_preferred":[
        "Kagera"
    ],
    "name:ita_x_preferred":[
        "Kagera"
    ],
    "name:kor_x_preferred":[
        "\uce74\uac8c\ub77c"
    ],
    "name:nld_x_preferred":[
        "Kagera"
    ],
    "name:slk_x_preferred":[
        "Kagera"
    ],
    "name:swa_x_preferred":[
        "Kagera"
    ],
    "name:swe_x_preferred":[
        "Kagera"
    ],
    "name:urd_x_preferred":[
        "\u06a9\u0627\u06af\u06cc\u0631\u0627"
    ],
    "wof:name":"Kagera",
    "wof:placetype":"locality"
},
  "geometry": {"coordinates":[30.34194,0.56432],"type":"Point"}
}