{
  "type": "Feature",
  "properties": {
    "gn:admin1_code":"C",
    "gn:admin2_code":"I3",
    "gn:admin3_code":"8643028.0",
    "gn:admin4_code":"8657995.0",
    "gn:asciiname":"Machodi",
    "gn:country_code":"UG",
    "gn:dem":1259,
    "gn:feature_class":"P",
    "gn:feature_code":"PPL",
    "gn:name":"Machodi",
    "gn:population":0,
    "gn:timezone":"Africa/Kampala",
    "iso:country":"UG",
    "name:und_x_variant":[
        "Machobi",
        "Machodi"
    ],
    "wof:name":"Machodi",
    "wof:placetype":"locality"
},
  "geometry": {"coordinates":[31.35,-0.85],"type":"Point"}
}