{
  "type": "Feature",
  "properties": {
    "gn:admin1_code":"N",
    "gn:admin2_code":"77",
    "gn:admin3_code":"8644146.0",
    "gn:admin4_code":"8261591.0",
    "gn:asciiname":"Agulubu",
    "gn:country_code":"UG",
    "gn:dem":661,
    "gn:feature_class":"P",
    "gn:feature_code":"PPL",
    "gn:name":"Agulubu",
    "gn:population":0,
    "gn:timezone":"Africa/Kampala",
    "iso:country":"UG",
    "wof:name":"Agulubu",
    "wof:placetype":"locality"
},
  "geometry": {"coordinates":[31.31506,2.97966],"type":"Point"}
}