{
  "type": "Feature",
  "properties": {
    "gn:admin1_code":"C",
    "gn:admin2_code":"96",
    "gn:asciiname":"Kiteredde",
    "gn:country_code":"UG",
    "gn:dem":1183,
    "gn:feature_class":"P",
    "gn:feature_code":"PPL",
    "gn:name":"Kiteredde",
    "gn:population":0,
    "gn:timezone":"Africa/Kampala",
    "iso:country":"UG",
    "wof:name":"Kiteredde",
    "wof:placetype":"locality"
},
  "geometry": {"coordinates":[32.38868,0.4369],"type":"Point"}
}