{
  "type": "Feature",
  "properties": {
    "gn:admin1_code":"C",
    "gn:admin2_code":"E7",
    "gn:admin3_code":"7732075.0",
    "gn:admin4_code":"8658239.0",
    "gn:asciiname":"Bugoba",
    "gn:country_code":"UG",
    "gn:dem":1157,
    "gn:feature_class":"P",
    "gn:feature_code":"PPL",
    "gn:name":"Bugoba",
    "gn:population":0,
    "gn:timezone":"Africa/Kampala",
    "iso:country":"UG",
    "name:eng_x_preferred":[
        "Bugoba"
    ],
    "wof:name":"Bugoba",
    "wof:placetype":"locality"
},
  "geometry": {"coordinates":[33.16975,0.32239],"type":"Point"}
}