{
  "type": "Feature",
  "properties": {
    "gn:admin1_code":"C",
    "gn:admin2_code":"70",
    "gn:admin3_code":"8644176.0",
    "gn:admin4_code":"8657621.0",
    "gn:asciiname":"Kalongo",
    "gn:country_code":"UG",
    "gn:dem":1056,
    "gn:feature_class":"P",
    "gn:feature_code":"PPL",
    "gn:name":"Kalongo",
    "gn:population":0,
    "gn:timezone":"Africa/Kampala",
    "iso:country":"UG",
    "name:ceb_x_preferred":[
        "Kalongo"
    ],
    "name:fra_x_preferred":[
        "Kalongo"
    ],
    "name:lug_x_preferred":[
        "Kalongo"
    ],
    "name:urd_x_preferred":[
        "\u06a9\u0627\u0644\u0648\u0646\u06af\u0648"
    ],
    "wof:name":"Kalongo",
    "wof:placetype":"locality"
},
  "geometry": {"coordinates":[32.43333,1.05],"type":"Point"}
}