{
  "type": "Feature",
  "properties": {
    "gn:admin1_code":"E",
    "gn:admin2_code":"76",
    "gn:asciiname":"Lukikoyo",
    "gn:country_code":"UG",
    "gn:dem":1171,
    "gn:feature_class":"P",
    "gn:feature_code":"PPL",
    "gn:name":"Lukikoyo",
    "gn:population":0,
    "gn:timezone":"Africa/Kampala",
    "iso:country":"UG",
    "name:eng_x_preferred":[
        "Lukikoyo"
    ],
    "wof:name":"Lukikoyo",
    "wof:placetype":"locality"
},
  "geometry": {"coordinates":[34.1383,0.66493],"type":"Point"}
}