{
  "type": "Feature",
  "properties": {
    "gn:admin1_code":"E",
    "gn:admin2_code":"D2",
    "gn:asciiname":"Bugonza",
    "gn:country_code":"UG",
    "gn:dem":1090,
    "gn:feature_class":"P",
    "gn:feature_code":"PPL",
    "gn:name":"Bugonza",
    "gn:population":0,
    "gn:timezone":"Africa/Kampala",
    "iso:country":"UG",
    "wof:name":"Bugonza",
    "wof:placetype":"locality"
},
  "geometry": {"coordinates":[33.48423,0.91128],"type":"Point"}
}