{
  "type": "Feature",
  "properties": {
    "gn:admin1_code":"C",
    "gn:admin2_code":"89",
    "gn:admin3_code":"7910214.0",
    "gn:admin4_code":"7732543.0",
    "gn:asciiname":"Bulamu",
    "gn:country_code":"UG",
    "gn:dem":1188,
    "gn:feature_class":"P",
    "gn:feature_code":"PPL",
    "gn:name":"Bulamu",
    "gn:population":0,
    "gn:timezone":"Africa/Kampala",
    "iso:country":"UG",
    "wof:name":"Bulamu",
    "wof:placetype":"locality"
},
  "geometry": {"coordinates":[32.28838,0.35937],"type":"Point"}
}