{
  "type": "Feature",
  "properties": {
    "gn:admin1_code":"N",
    "gn:admin2_code":"65",
    "gn:admin3_code":"8644133.0",
    "gn:admin4_code":"8657957.0",
    "gn:asciiname":"East Ogboro",
    "gn:country_code":"UG",
    "gn:dem":759,
    "gn:feature_class":"P",
    "gn:feature_code":"PPL",
    "gn:name":"East Ogboro",
    "gn:population":0,
    "gn:timezone":"Africa/Kampala",
    "iso:country":"UG",
    "wof:name":"East Ogboro",
    "wof:placetype":"locality"
},
  "geometry": {"coordinates":[31.69582,3.36067],"type":"Point"}
}