{
  "type": "Feature",
  "properties": {
    "gn:admin1_code":"W",
    "gn:admin2_code":"79",
    "gn:asciiname":"Bukama",
    "gn:country_code":"UG",
    "gn:dem":1497,
    "gn:feature_class":"P",
    "gn:feature_code":"PPL",
    "gn:name":"Bukama",
    "gn:population":0,
    "gn:timezone":"Africa/Kampala",
    "iso:country":"UG",
    "name:ceb_x_preferred":[
        "Bukama"
    ],
    "name:eng_x_preferred":[
        "Bukama"
    ],
    "name:fra_x_preferred":[
        "Bukama"
    ],
    "name:heb_x_preferred":[
        "\u05d1\u05d5\u05e7\u05de\u05d4"
    ],
    "name:ita_x_preferred":[
        "Bukama"
    ],
    "name:pol_x_preferred":[
        "Bukama"
    ],
    "name:ron_x_preferred":[
        "Bukama"
    ],
    "name:swe_x_preferred":[
        "Bukama"
    ],
    "name:tgl_x_preferred":[
        "Bukama"
    ],
    "name:zho_x_preferred":[
        "\u5e03\u5361\u99ac"
    ],
    "wof:name":"Bukama",
    "wof:placetype":"locality"
},
  "geometry": {"coordinates":[30.2987,0.56766],"type":"Point"}
}