{
  "type": "Feature",
  "properties": {
    "gn:admin1_code":"E",
    "gn:admin2_code":"76",
    "gn:asciiname":"Nyakesi",
    "gn:country_code":"UG",
    "gn:dem":1202,
    "gn:feature_class":"P",
    "gn:feature_code":"PPL",
    "gn:name":"Nyakesi",
    "gn:population":0,
    "gn:timezone":"Africa/Kampala",
    "iso:country":"UG",
    "name:eng_x_preferred":[
        "Nyakesi"
    ],
    "wof:name":"Nyakesi",
    "wof:placetype":"locality"
},
  "geometry": {"coordinates":[34.14664,0.7405],"type":"Point"}
}