{
  "type": "Feature",
  "properties": {
    "gn:admin1_code":"N",
    "gn:admin2_code":"E4",
    "gn:admin3_code":"229109.0",
    "gn:admin4_code":"8658405.0",
    "gn:asciiname":"Abala",
    "gn:country_code":"UG",
    "gn:dem":1071,
    "gn:feature_class":"P",
    "gn:feature_code":"PPL",
    "gn:name":"Abala",
    "gn:population":0,
    "gn:timezone":"Africa/Kampala",
    "iso:country":"UG",
    "name:ceb_x_preferred":[
        "Abala"
    ],
    "name:deu_x_preferred":[
        "Abala"
    ],
    "name:fra_x_preferred":[
        "Abala"
    ],
    "name:ita_x_preferred":[
        "Abala"
    ],
    "name:srp_x_preferred":[
        "\u0410\u0431\u0430\u043b\u0430"
    ],
    "name:swe_x_preferred":[
        "Abala"
    ],
    "name:und_x_variant":[
        "Apala",
        "Abala"
    ],
    "wof:name":"Abala",
    "wof:placetype":"locality"
},
  "geometry": {"coordinates":[33.045,2.38278],"type":"Point"}
}