{
  "type": "Feature",
  "properties": {
    "gn:admin1_code":"E",
    "gn:admin2_code":"80",
    "gn:admin3_code":"233018.0",
    "gn:admin4_code":"8658326.0",
    "gn:asciiname":"Bweyale",
    "gn:country_code":"UG",
    "gn:dem":1032,
    "gn:feature_class":"P",
    "gn:feature_code":"PPL",
    "gn:name":"Bweyale",
    "gn:population":0,
    "gn:timezone":"Africa/Kampala",
    "iso:country":"UG",
    "wof:name":"Bweyale",
    "wof:placetype":"locality"
},
  "geometry": {"coordinates":[33.05315,1.6069],"type":"Point"}
}