{
  "type": "Feature",
  "properties": {
    "gn:admin1_code":"C",
    "gn:admin2_code":"83",
    "gn:admin3_code":"8644158.0",
    "gn:admin4_code":"8658127.0",
    "gn:asciiname":"Kitatya",
    "gn:country_code":"UG",
    "gn:dem":1079,
    "gn:feature_class":"P",
    "gn:feature_code":"PPL",
    "gn:name":"Kitatya",
    "gn:population":0,
    "gn:timezone":"Africa/Kampala",
    "iso:country":"UG",
    "wof:name":"Kitatya",
    "wof:placetype":"locality"
},
  "geometry": {"coordinates":[32.91667,0.81667],"type":"Point"}
}