{
  "type": "Feature",
  "properties": {
    "gn:admin1_code":"C",
    "gn:admin2_code":"83",
    "gn:admin3_code":"8644158.0",
    "gn:admin4_code":"7732529.0",
    "gn:asciiname":"Kisuga",
    "gn:country_code":"UG",
    "gn:dem":1043,
    "gn:feature_class":"P",
    "gn:feature_code":"PPL",
    "gn:name":"Kisuga",
    "gn:population":0,
    "gn:timezone":"Africa/Kampala",
    "iso:country":"UG",
    "wof:name":"Kisuga",
    "wof:placetype":"locality"
},
  "geometry": {"coordinates":[32.81667,1.38333],"type":"Point"}
}