{
  "type": "Feature",
  "properties": {
    "gn:admin1_code":"E",
    "gn:admin2_code":"86",
    "gn:admin3_code":"8644164.0",
    "gn:admin4_code":"8658694.0",
    "gn:asciiname":"Ivugunyu",
    "gn:country_code":"UG",
    "gn:dem":1170,
    "gn:feature_class":"P",
    "gn:feature_code":"PPL",
    "gn:name":"Ivugunyu",
    "gn:population":0,
    "gn:timezone":"Africa/Kampala",
    "iso:country":"UG",
    "name:eng_x_preferred":[
        "Ivugunyu"
    ],
    "wof:name":"Ivugunyu",
    "wof:placetype":"locality"
},
  "geometry": {"coordinates":[33.47942,0.48762],"type":"Point"}
}