{
  "type": "Feature",
  "properties": {
    "gn:admin1_code":"E",
    "gn:admin2_code":"C3",
    "gn:admin3_code":"7732906.0",
    "gn:admin4_code":"8658081.0",
    "gn:asciiname":"Miroi",
    "gn:country_code":"UG",
    "gn:dem":1132,
    "gn:feature_class":"P",
    "gn:feature_code":"PPL",
    "gn:name":"Miroi",
    "gn:population":0,
    "gn:timezone":"Africa/Kampala",
    "iso:country":"UG",
    "wof:name":"Miroi",
    "wof:placetype":"locality"
},
  "geometry": {"coordinates":[34.15,1.26667],"type":"Point"}
}