{
  "type": "Feature",
  "properties": {
    "gn:admin1_code":"E",
    "gn:admin2_code":"G4",
    "gn:asciiname":"Buutu",
    "gn:country_code":"UG",
    "gn:dem":1076,
    "gn:feature_class":"P",
    "gn:feature_code":"PPL",
    "gn:name":"Buutu",
    "gn:population":0,
    "gn:timezone":"Africa/Kampala",
    "iso:country":"UG",
    "wof:name":"Buutu",
    "wof:placetype":"locality"
},
  "geometry": {"coordinates":[33.33577,0.95061],"type":"Point"}
}