{
  "type": "Feature",
  "properties": {
    "gn:admin1_code":"E",
    "gn:admin2_code":"G7",
    "gn:admin3_code":"8644167.0",
    "gn:admin4_code":"8658486.0",
    "gn:asciiname":"Lugala",
    "gn:country_code":"UG",
    "gn:dem":1144,
    "gn:feature_class":"P",
    "gn:feature_code":"PPL",
    "gn:name":"Lugala",
    "gn:population":0,
    "gn:timezone":"Africa/Kampala",
    "iso:country":"UG",
    "name:eng_x_preferred":[
        "Lugala"
    ],
    "wof:name":"Lugala",
    "wof:placetype":"locality"
},
  "geometry": {"coordinates":[33.89655,0.20191],"type":"Point"}
}