{
  "type": "Feature",
  "properties": {
    "gn:admin1_code":"E",
    "gn:admin2_code":"C2",
    "gn:admin3_code":"7869957.0",
    "gn:admin4_code":"8658372.0",
    "gn:asciiname":"Buwagiyu",
    "gn:country_code":"UG",
    "gn:dem":1389,
    "gn:feature_class":"P",
    "gn:feature_code":"PPLL",
    "gn:name":"Buwagiyu",
    "gn:population":0,
    "gn:timezone":"Africa/Kampala",
    "iso:country":"UG",
    "wof:name":"Buwagiyu",
    "wof:placetype":"locality"
},
  "geometry": {"coordinates":[34.36471,0.99279],"type":"Point"}
}