{
  "type": "Feature",
  "properties": {
    "gn:admin1_code":"E",
    "gn:admin2_code":"C6",
    "gn:admin3_code":"234147.0",
    "gn:admin4_code":"8657552.0",
    "gn:asciiname":"Buhiralire",
    "gn:country_code":"UG",
    "gn:dem":1090,
    "gn:feature_class":"P",
    "gn:feature_code":"PPL",
    "gn:name":"Buhiralire",
    "gn:population":0,
    "gn:timezone":"Africa/Kampala",
    "iso:country":"UG",
    "name:und_x_variant":[
        "Bukiralire"
    ],
    "wof:name":"Buhiralire",
    "wof:placetype":"locality"
},
  "geometry": {"coordinates":[33.95846,0.9046],"type":"Point"}
}