{
  "type": "Feature",
  "properties": {
    "gn:admin1_code":"E",
    "gn:admin2_code":"B8",
    "gn:admin3_code":"235185.0",
    "gn:admin4_code":"8658728.0",
    "gn:asciiname":"Apeduru",
    "gn:country_code":"UG",
    "gn:dem":1143,
    "gn:feature_class":"P",
    "gn:feature_code":"PPL",
    "gn:name":"Apeduru",
    "gn:population":0,
    "gn:timezone":"Africa/Kampala",
    "iso:country":"UG",
    "name:und_x_variant":[
        "Peduru",
        "Apeduru"
    ],
    "wof:name":"Apeduru",
    "wof:placetype":"locality"
},
  "geometry": {"coordinates":[33.68333,2.05],"type":"Point"}
}