{
  "type": "Feature",
  "properties": {
    "gn:admin1_code":"W",
    "gn:admin2_code":"81",
    "gn:admin3_code":"7732901.0",
    "gn:admin4_code":"8657822.0",
    "gn:asciiname":"Ntara",
    "gn:country_code":"UG",
    "gn:dem":1316,
    "gn:feature_class":"P",
    "gn:feature_code":"PPLL",
    "gn:name":"Ntara",
    "gn:population":0,
    "gn:timezone":"Africa/Kampala",
    "iso:country":"UG",
    "wof:name":"Ntara",
    "wof:placetype":"locality"
},
  "geometry": {"coordinates":[30.34714,0.00987],"type":"Point"}
}