{
  "type": "Feature",
  "properties": {
    "gn:admin1_code":"E",
    "gn:admin2_code":"G7",
    "gn:admin3_code":"8644167.0",
    "gn:admin4_code":"8658486.0",
    "gn:asciiname":"Seka",
    "gn:country_code":"UG",
    "gn:dem":1155,
    "gn:feature_class":"P",
    "gn:feature_code":"PPLL",
    "gn:name":"Seka",
    "gn:population":0,
    "gn:timezone":"Africa/Kampala",
    "iso:country":"UG",
    "name:ara_x_preferred":[
        "\u0633\u064a\u0643\u0627"
    ],
    "name:arz_x_preferred":[
        "\u0633\u064a\u0643\u0627"
    ],
    "name:aze_x_preferred":[
        "Seka"
    ],
    "name:deu_x_preferred":[
        "Seka"
    ],
    "name:eng_x_preferred":[
        "Seka"
    ],
    "name:fas_x_preferred":[
        "\u0633\u06a9\u0627"
    ],
    "name:fin_x_preferred":[
        "Seka"
    ],
    "name:fra_x_preferred":[
        "Seka"
    ],
    "name:hun_x_preferred":[
        "Seka"
    ],
    "name:ita_x_preferred":[
        "Seka"
    ],
    "name:mar_x_preferred":[
        "\u0938\u0947\u0915\u093e"
    ],
    "name:por_x_preferred":[
        "Seka"
    ],
    "name:rus_x_preferred":[
        "\u0421\u0435\u043a\u0430"
    ],
    "name:spa_x_preferred":[
        "Seka"
    ],
    "name:swe_x_preferred":[
        "Seka"
    ],
    "name:urd_x_preferred":[
        "\u0633\u06cc\u06a9\u0627"
    ],
    "wof:name":"Seka",
    "wof:placetype":"locality"
},
  "geometry": {"coordinates":[33.84465,0.21709],"type":"Point"}
}