{
  "type": "Feature",
  "properties": {
    "gn:admin1_code":"E",
    "gn:admin2_code":"G7",
    "gn:admin3_code":"8644167.0",
    "gn:admin4_code":"8658486.0",
    "gn:asciiname":"Seka",
    "gn:country_code":"UG",
    "gn:dem":1155,
    "gn:feature_class":"P",
    "gn:feature_code":"PPLL",
    "gn:name":"Seka",
    "gn:population":0,
    "gn:timezone":"Africa/Kampala",
    "iso:country":"UG",
    "name:eng_x_preferred":[
        "Seka"
    ],
    "wof:name":"Seka",
    "wof:placetype":"locality"
},
  "geometry": {"coordinates":[33.84465,0.21709],"type":"Point"}
}