{
  "type": "Feature",
  "properties": {
    "gn:admin1_code":"C",
    "gn:admin2_code":"37",
    "gn:admin3_code":"8644170.0",
    "gn:admin4_code":"7732387.0",
    "gn:asciiname":"Kiwatule",
    "gn:country_code":"UG",
    "gn:dem":1210,
    "gn:feature_class":"P",
    "gn:feature_code":"PPL",
    "gn:name":"Kiwatule",
    "gn:population":0,
    "gn:timezone":"Africa/Kampala",
    "iso:country":"UG",
    "wof:name":"Kiwatule",
    "wof:placetype":"locality"
},
  "geometry": {"coordinates":[32.62461,0.36718],"type":"Point"}
}