{
  "type": "Feature",
  "properties": {
    "gn:admin1_code":"C",
    "gn:admin2_code":"F1",
    "gn:asciiname":"Bukandaganyi",
    "gn:country_code":"UG",
    "gn:dem":1236,
    "gn:feature_class":"P",
    "gn:feature_code":"PPL",
    "gn:name":"Bukandaganyi",
    "gn:population":0,
    "gn:timezone":"Africa/Kampala",
    "iso:country":"UG",
    "wof:name":"Bukandaganyi",
    "wof:placetype":"locality"
},
  "geometry": {"coordinates":[32.2956,0.28553],"type":"Point"}
}