{
  "type": "Feature",
  "properties": {
    "gn:admin1_code":"E",
    "gn:admin2_code":"67",
    "gn:admin3_code":"8644151.0",
    "gn:admin4_code":"8657692.0",
    "gn:asciiname":"Lumuli",
    "gn:country_code":"UG",
    "gn:dem":1163,
    "gn:feature_class":"P",
    "gn:feature_code":"PPL",
    "gn:name":"Lumuli",
    "gn:population":0,
    "gn:timezone":"Africa/Kampala",
    "iso:country":"UG",
    "name:eng_x_preferred":[
        "Lumuli"
    ],
    "name:swa_x_preferred":[
        "Lumuli"
    ],
    "wof:name":"Lumuli",
    "wof:placetype":"locality"
},
  "geometry": {"coordinates":[33.95682,0.28019],"type":"Point"}
}