{
  "type": "Feature",
  "properties": {
    "gn:admin1_code":"C",
    "gn:admin2_code":"83",
    "gn:asciiname":"Kamira",
    "gn:country_code":"UG",
    "gn:dem":1111,
    "gn:feature_class":"P",
    "gn:feature_code":"PPL",
    "gn:name":"Kamira",
    "gn:population":0,
    "gn:timezone":"Africa/Kampala",
    "iso:country":"UG",
    "name:lit_x_preferred":[
        "Kamira"
    ],
    "wof:name":"Kamira",
    "wof:placetype":"locality"
},
  "geometry": {"coordinates":[33.03081,0.59576],"type":"Point"}
}