{
  "type": "Feature",
  "properties": {
    "gn:admin1_code":"W",
    "gn:admin2_code":"79",
    "gn:asciiname":"Rwengabi",
    "gn:country_code":"UG",
    "gn:dem":1401,
    "gn:feature_class":"P",
    "gn:feature_code":"PPL",
    "gn:name":"Rwengabi",
    "gn:population":0,
    "gn:timezone":"Africa/Kampala",
    "iso:country":"UG",
    "name:eng_x_preferred":[
        "Rwengabi"
    ],
    "wof:name":"Rwengabi",
    "wof:placetype":"locality"
},
  "geometry": {"coordinates":[30.23879,0.50061],"type":"Point"}
}