{
  "type": "Feature",
  "properties": {
    "gn:admin1_code":"E",
    "gn:admin2_code":"C2",
    "gn:asciiname":"Bunango",
    "gn:country_code":"UG",
    "gn:dem":1452,
    "gn:feature_class":"P",
    "gn:feature_code":"PPL",
    "gn:name":"Bunango",
    "gn:population":0,
    "gn:timezone":"Africa/Kampala",
    "iso:country":"UG",
    "name:eng_x_preferred":[
        "Bunango"
    ],
    "wof:name":"Bunango",
    "wof:placetype":"locality"
},
  "geometry": {"coordinates":[34.37285,0.99025],"type":"Point"}
}