{
  "type": "Feature",
  "properties": {
    "gn:admin1_code":"E",
    "gn:admin2_code":"D6",
    "gn:asciiname":"Butemulani",
    "gn:country_code":"UG",
    "gn:dem":1441,
    "gn:feature_class":"P",
    "gn:feature_code":"PPL",
    "gn:name":"Butemulani",
    "gn:population":0,
    "gn:timezone":"Africa/Kampala",
    "iso:country":"UG",
    "name:eng_x_preferred":[
        "Butemulani"
    ],
    "wof:name":"Butemulani",
    "wof:placetype":"locality"
},
  "geometry": {"coordinates":[34.36871,0.82475],"type":"Point"}
}