{
  "type": "Feature",
  "properties": {
    "gn:admin1_code":"E",
    "gn:admin2_code":"38",
    "gn:admin3_code":"8644140.0",
    "gn:admin4_code":"8658007.0",
    "gn:asciiname":"Kisozi",
    "gn:country_code":"UG",
    "gn:dem":1093,
    "gn:feature_class":"P",
    "gn:feature_code":"PPL",
    "gn:name":"Kisozi",
    "gn:population":0,
    "gn:timezone":"Africa/Kampala",
    "iso:country":"UG",
    "name:lug_x_preferred":[
        "Kisozi"
    ],
    "wof:name":"Kisozi",
    "wof:placetype":"locality"
},
  "geometry": {"coordinates":[33.08161,0.74362],"type":"Point"}
}