{
  "type": "Feature",
  "properties": {
    "gn:admin1_code":"W",
    "gn:admin2_code":"40",
    "gn:admin3_code":"7869968.0",
    "gn:admin4_code":"8657746.0",
    "gn:asciiname":"Nyakiyumbu",
    "gn:country_code":"UG",
    "gn:dem":1242,
    "gn:feature_class":"P",
    "gn:feature_code":"PPL",
    "gn:name":"Nyakiyumbu",
    "gn:population":0,
    "gn:timezone":"Africa/Kampala",
    "iso:country":"UG",
    "wof:name":"Nyakiyumbu",
    "wof:placetype":"locality"
},
  "geometry": {"coordinates":[29.78856,0.02583],"type":"Point"}
}