{
  "type": "Feature",
  "properties": {
    "gn:admin1_code":"E",
    "gn:admin2_code":"C4",
    "gn:admin3_code":"7732537.0",
    "gn:admin4_code":"8657956.0",
    "gn:asciiname":"Suam",
    "gn:country_code":"UG",
    "gn:dem":2158,
    "gn:feature_class":"P",
    "gn:feature_code":"PPL",
    "gn:name":"Suam",
    "gn:population":0,
    "gn:timezone":"Africa/Kampala",
    "iso:country":"UG",
    "name:ceb_x_preferred":[
        "Suam"
    ],
    "name:lug_x_preferred":[
        "Suam"
    ],
    "name:swe_x_preferred":[
        "Suam"
    ],
    "wof:name":"Suam",
    "wof:placetype":"locality"
},
  "geometry": {"coordinates":[34.71667,1.21667],"type":"Point"}
}