{
  "type": "Feature",
  "properties": {
    "gn:admin1_code":"W",
    "gn:admin2_code":"79",
    "gn:asciiname":"Kyakanyuma",
    "gn:country_code":"UG",
    "gn:dem":1492,
    "gn:feature_class":"P",
    "gn:feature_code":"PPL",
    "gn:name":"Kyakanyuma",
    "gn:population":0,
    "gn:timezone":"Africa/Kampala",
    "iso:country":"UG",
    "name:eng_x_preferred":[
        "Kyakanyuma"
    ],
    "wof:name":"Kyakanyuma",
    "wof:placetype":"locality"
},
  "geometry": {"coordinates":[30.32244,0.61143],"type":"Point"}
}