{
  "type": "Feature",
  "properties": {
    "gn:admin1_code":"C",
    "gn:admin2_code":"G5",
    "gn:admin3_code":"7910221.0",
    "gn:admin4_code":"8657539.0",
    "gn:asciiname":"Zimwe",
    "gn:country_code":"UG",
    "gn:dem":1202,
    "gn:feature_class":"P",
    "gn:feature_code":"PPL",
    "gn:name":"Zimwe",
    "gn:population":0,
    "gn:timezone":"Africa/Kampala",
    "iso:country":"UG",
    "wof:name":"Zimwe",
    "wof:placetype":"locality"
},
  "geometry": {"coordinates":[31.75,-0.51667],"type":"Point"}
}