{
  "type": "Feature",
  "properties": {
    "gn:admin1_code":"C",
    "gn:admin2_code":"70",
    "gn:admin3_code":"8644176.0",
    "gn:admin4_code":"8657989.0",
    "gn:asciiname":"Sambwe",
    "gn:country_code":"UG",
    "gn:dem":1198,
    "gn:feature_class":"P",
    "gn:feature_code":"PPL",
    "gn:name":"Sambwe",
    "gn:population":0,
    "gn:timezone":"Africa/Kampala",
    "iso:country":"UG",
    "wof:name":"Sambwe",
    "wof:placetype":"locality"
},
  "geometry": {"coordinates":[32.48333,0.56667],"type":"Point"}
}