{
  "type": "Feature",
  "properties": {
    "gn:admin1_code":"E",
    "gn:admin2_code":"D6",
    "gn:asciiname":"Nantseko",
    "gn:country_code":"UG",
    "gn:dem":1637,
    "gn:feature_class":"P",
    "gn:feature_code":"PPL",
    "gn:name":"Nantseko",
    "gn:population":0,
    "gn:timezone":"Africa/Kampala",
    "iso:country":"UG",
    "name:eng_x_preferred":[
        "Nantseko"
    ],
    "wof:name":"Nantseko",
    "wof:placetype":"locality"
},
  "geometry": {"coordinates":[34.36078,0.95869],"type":"Point"}
}