{
  "type": "Feature",
  "properties": {
    "gn:admin1_code":"E",
    "gn:admin2_code":"76",
    "gn:asciiname":"Ngota",
    "gn:country_code":"UG",
    "gn:dem":1118,
    "gn:feature_class":"P",
    "gn:feature_code":"PPL",
    "gn:name":"Ngota",
    "gn:population":0,
    "gn:timezone":"Africa/Kampala",
    "iso:country":"UG",
    "wof:name":"Ngota",
    "wof:placetype":"locality"
},
  "geometry": {"coordinates":[33.95038,0.67644],"type":"Point"}
}