{
  "type": "Feature",
  "properties": {
    "gn:admin1_code":"E",
    "gn:admin2_code":"76",
    "gn:admin3_code":"226108.0",
    "gn:admin4_code":"8658493.0",
    "gn:asciiname":"Tuba",
    "gn:country_code":"UG",
    "gn:dem":1171,
    "gn:feature_class":"P",
    "gn:feature_code":"PPL",
    "gn:name":"Tuba",
    "gn:population":0,
    "gn:timezone":"Africa/Kampala",
    "iso:country":"UG",
    "name:eng_x_preferred":[
        "Tuba"
    ],
    "wof:name":"Tuba",
    "wof:placetype":"locality"
},
  "geometry": {"coordinates":[34.17213,0.79826],"type":"Point"}
}