{
  "type": "Feature",
  "properties": {
    "gn:admin1_code":"E",
    "gn:admin2_code":"38",
    "gn:asciiname":"Butaama",
    "gn:country_code":"UG",
    "gn:dem":1090,
    "gn:feature_class":"P",
    "gn:feature_code":"PPL",
    "gn:name":"Butaama",
    "gn:population":0,
    "gn:timezone":"Africa/Kampala",
    "iso:country":"UG",
    "wof:name":"Butaama",
    "wof:placetype":"locality"
},
  "geometry": {"coordinates":[33.10842,0.9113],"type":"Point"}
}