{
  "type": "Feature",
  "properties": {
    "gn:admin1_code":"N",
    "gn:admin2_code":"65",
    "gn:admin3_code":"8644133.0",
    "gn:admin4_code":"8657957.0",
    "gn:asciiname":"Ciforo",
    "gn:country_code":"UG",
    "gn:dem":782,
    "gn:feature_class":"P",
    "gn:feature_code":"PPL",
    "gn:name":"Ciforo",
    "gn:population":0,
    "gn:timezone":"Africa/Kampala",
    "iso:country":"UG",
    "wof:name":"Ciforo",
    "wof:placetype":"locality"
},
  "geometry": {"coordinates":[31.71083,3.35682],"type":"Point"}
}