{
  "type": "Feature",
  "properties": {
    "gn:admin1_code":"C",
    "gn:admin2_code":"96",
    "gn:asciiname":"Kayunga",
    "gn:country_code":"UG",
    "gn:dem":1185,
    "gn:feature_class":"P",
    "gn:feature_code":"PPL",
    "gn:name":"Kayunga",
    "gn:population":0,
    "gn:timezone":"Africa/Kampala",
    "iso:country":"UG",
    "name:ben_x_preferred":[
        "\u0995\u09cd\u09af\u09be\u0989\u0982\u0997\u09be"
    ],
    "name:ceb_x_preferred":[
        "Kayunga"
    ],
    "name:deu_x_preferred":[
        "Kayunga"
    ],
    "name:ell_x_preferred":[
        "\u039a\u03b1\u03b3\u03b9\u03bf\u03cd\u03bd\u03b3\u03ba\u03b1"
    ],
    "name:fas_x_preferred":[
        "\u06a9\u0627\u06cc\u0648\u0646\u06af\u0627"
    ],
    "name:fra_x_preferred":[
        "Kayunga"
    ],
    "name:heb_x_preferred":[
        "\u05e7\u05d9\u05d9\u05d5\u05e0\u05d2\u05d4"
    ],
    "name:hin_x_preferred":[
        "\u0915\u0947\u092f\u0941\u0902\u0917\u093e"
    ],
    "name:hun_x_preferred":[
        "Kayunga"
    ],
    "name:ind_x_preferred":[
        "Kayunga"
    ],
    "name:ita_x_preferred":[
        "Kayunga"
    ],
    "name:kor_x_preferred":[
        "\uce74\uc724\uac00"
    ],
    "name:lug_x_preferred":[
        "Kayunga"
    ],
    "name:nld_x_preferred":[
        "Kayunga"
    ],
    "name:nor_x_preferred":[
        "Kayunga"
    ],
    "name:ron_x_preferred":[
        "Kayunga"
    ],
    "name:rus_x_preferred":[
        "\u041a\u0430\u044e\u043d\u0433\u0430"
    ],
    "name:spa_x_preferred":[
        "Kayunga"
    ],
    "name:swa_x_preferred":[
        "Kayunga"
    ],
    "name:swe_x_preferred":[
        "Kayunga"
    ],
    "name:tur_x_preferred":[
        "Kayunga"
    ],
    "name:ukr_x_preferred":[
        "\u041a\u0430\u044e\u043d\u0433\u0430"
    ],
    "name:urd_x_preferred":[
        "\u06a9\u0627\u0626\u0648\u0646\u06af\u0627"
    ],
    "name:vie_x_preferred":[
        "Kayunga"
    ],
    "name:zho_cn_x_preferred":[
        "\u5361\u6c38\u52a0"
    ],
    "name:zho_tw_x_preferred":[
        "\u5361\u6c38\u52a0"
    ],
    "wof:name":"Kayunga",
    "wof:placetype":"locality"
},
  "geometry": {"coordinates":[32.49629,0.39613],"type":"Point"}
}