{
  "type": "Feature",
  "properties": {
    "gn:admin1_code":"C",
    "gn:admin2_code":"96",
    "gn:asciiname":"Kayunga",
    "gn:country_code":"UG",
    "gn:dem":1185,
    "gn:feature_class":"P",
    "gn:feature_code":"PPL",
    "gn:name":"Kayunga",
    "gn:population":0,
    "gn:timezone":"Africa/Kampala",
    "iso:country":"UG",
    "name:ceb_x_preferred":[
        "Kayunga"
    ],
    "name:deu_x_preferred":[
        "Kayunga"
    ],
    "name:fra_x_preferred":[
        "Kayunga"
    ],
    "name:ita_x_preferred":[
        "Kayunga"
    ],
    "name:lug_x_preferred":[
        "Kayunga"
    ],
    "name:nld_x_preferred":[
        "Kayunga"
    ],
    "name:nor_x_preferred":[
        "Kayunga"
    ],
    "name:ron_x_preferred":[
        "Kayunga"
    ],
    "name:swa_x_preferred":[
        "Kayunga"
    ],
    "name:urd_x_preferred":[
        "\u06a9\u0627\u0626\u0648\u0646\u06af\u0627"
    ],
    "wof:name":"Kayunga",
    "wof:placetype":"locality"
},
  "geometry": {"coordinates":[32.49629,0.39613],"type":"Point"}
}