{
  "type": "Feature",
  "properties": {
    "gn:admin1_code":"E",
    "gn:admin2_code":"86",
    "gn:admin3_code":"8644164.0",
    "gn:admin4_code":"8657878.0",
    "gn:asciiname":"Nkombe",
    "gn:country_code":"UG",
    "gn:dem":1161,
    "gn:feature_class":"P",
    "gn:feature_code":"PPL",
    "gn:name":"Nkombe",
    "gn:population":0,
    "gn:timezone":"Africa/Kampala",
    "iso:country":"UG",
    "name:eng_x_preferred":[
        "Nkombe"
    ],
    "wof:name":"Nkombe",
    "wof:placetype":"locality"
},
  "geometry": {"coordinates":[33.40913,0.45886],"type":"Point"}
}