{
  "type": "Feature",
  "properties": {
    "gn:admin1_code":"E",
    "gn:admin2_code":"G7",
    "gn:admin3_code":"8644167.0",
    "gn:admin4_code":"8658483.0",
    "gn:asciiname":"Buyombo",
    "gn:country_code":"UG",
    "gn:dem":1173,
    "gn:feature_class":"P",
    "gn:feature_code":"PPL",
    "gn:name":"Buyombo",
    "gn:population":0,
    "gn:timezone":"Africa/Kampala",
    "iso:country":"UG",
    "name:eng_x_preferred":[
        "Buyombo"
    ],
    "wof:name":"Buyombo",
    "wof:placetype":"locality"
},
  "geometry": {"coordinates":[33.84701,0.25836],"type":"Point"}
}