{
  "type": "Feature",
  "properties": {
    "gn:admin1_code":"E",
    "gn:admin2_code":"38",
    "gn:admin3_code":"234617.0",
    "gn:admin4_code":"8658484.0",
    "gn:asciiname":"Bulopa",
    "gn:country_code":"UG",
    "gn:dem":1112,
    "gn:feature_class":"P",
    "gn:feature_code":"PPL",
    "gn:name":"Bulopa",
    "gn:population":0,
    "gn:timezone":"Africa/Kampala",
    "iso:country":"UG",
    "wof:name":"Bulopa",
    "wof:placetype":"locality"
},
  "geometry": {"coordinates":[33.25098,0.84775],"type":"Point"}
}