{
  "type": "Feature",
  "properties": {
    "gn:admin1_code":"E",
    "gn:admin2_code":"67",
    "gn:admin3_code":"8644151.0",
    "gn:admin4_code":"8657977.0",
    "gn:asciiname":"Budandu",
    "gn:country_code":"UG",
    "gn:dem":1173,
    "gn:feature_class":"P",
    "gn:feature_code":"PPL",
    "gn:name":"Budandu",
    "gn:population":0,
    "gn:timezone":"Africa/Kampala",
    "iso:country":"UG",
    "name:eng_x_preferred":[
        "Budandu"
    ],
    "wof:name":"Budandu",
    "wof:placetype":"locality"
},
  "geometry": {"coordinates":[33.98767,0.42427],"type":"Point"}
}