{
  "type": "Feature",
  "properties": {
    "gn:admin1_code":"N",
    "gn:admin2_code":"F8",
    "gn:admin3_code":"8644134.0",
    "gn:admin4_code":"8657829.0",
    "gn:asciiname":"Bala",
    "gn:country_code":"UG",
    "gn:dem":1077,
    "gn:feature_class":"P",
    "gn:feature_code":"PPL",
    "gn:name":"Bala",
    "gn:population":0,
    "gn:timezone":"Africa/Kampala",
    "iso:country":"UG",
    "name:bul_x_preferred":[
        "\u0411\u0430\u043b\u0430"
    ],
    "name:ceb_x_preferred":[
        "Bala"
    ],
    "name:ces_x_preferred":[
        "Bala"
    ],
    "name:cym_x_preferred":[
        "Bala"
    ],
    "name:deu_x_preferred":[
        "Bala"
    ],
    "name:epo_x_preferred":[
        "Bala"
    ],
    "name:fra_x_preferred":[
        "Bala"
    ],
    "name:glg_x_preferred":[
        "Bala"
    ],
    "name:hye_x_preferred":[
        "\u0532\u0561\u056c\u0561"
    ],
    "name:ita_x_preferred":[
        "Bala"
    ],
    "name:nld_x_preferred":[
        "Bala"
    ],
    "name:nor_x_preferred":[
        "Bala"
    ],
    "name:pol_x_preferred":[
        "Bala"
    ],
    "name:por_x_preferred":[
        "Bala"
    ],
    "name:ron_x_preferred":[
        "Bala"
    ],
    "name:rus_x_preferred":[
        "\u0411\u0430\u043b\u0430"
    ],
    "name:slv_x_preferred":[
        "Bala"
    ],
    "name:spa_x_preferred":[
        "Bala"
    ],
    "name:srp_x_preferred":[
        "\u0411\u0430\u043b\u0430"
    ],
    "name:swe_x_preferred":[
        "Bala"
    ],
    "name:tur_x_preferred":[
        "Bala"
    ],
    "name:ukr_x_preferred":[
        "\u0411\u0430\u043b\u0430"
    ],
    "wof:name":"Bala",
    "wof:placetype":"locality"
},
  "geometry": {"coordinates":[32.755,2.16611],"type":"Point"}
}