{
  "type": "Feature",
  "properties": {
    "gn:admin1_code":"N",
    "gn:admin2_code":"F8",
    "gn:admin3_code":"8644134.0",
    "gn:admin4_code":"8657829.0",
    "gn:asciiname":"Bala",
    "gn:country_code":"UG",
    "gn:dem":1077,
    "gn:feature_class":"P",
    "gn:feature_code":"PPL",
    "gn:name":"Bala",
    "gn:population":0,
    "gn:timezone":"Africa/Kampala",
    "iso:country":"UG",
    "wof:name":"Bala",
    "wof:placetype":"locality"
},
  "geometry": {"coordinates":[32.755,2.16611],"type":"Point"}
}