{
  "type": "Feature",
  "properties": {
    "gn:admin1_code":"E",
    "gn:admin2_code":"80",
    "gn:admin3_code":"7732909.0",
    "gn:admin4_code":"8658383.0",
    "gn:asciiname":"Amidakan",
    "gn:country_code":"UG",
    "gn:dem":1100,
    "gn:feature_class":"P",
    "gn:feature_code":"PPL",
    "gn:name":"Amidakan",
    "gn:population":0,
    "gn:timezone":"Africa/Kampala",
    "iso:country":"UG",
    "wof:name":"Amidakan",
    "wof:placetype":"locality"
},
  "geometry": {"coordinates":[33.34862,1.9409],"type":"Point"}
}