{
  "type": "Feature",
  "properties": {
    "gn:admin1_code":"E",
    "gn:admin2_code":"C6",
    "gn:asciiname":"Buwumu-Busoko",
    "gn:country_code":"UG",
    "gn:dem":1110,
    "gn:feature_class":"P",
    "gn:feature_code":"PPL",
    "gn:name":"Buwumu-Busoko",
    "gn:population":0,
    "gn:timezone":"Africa/Kampala",
    "iso:country":"UG",
    "wof:name":"Buwumu-Busoko",
    "wof:placetype":"locality"
},
  "geometry": {"coordinates":[33.87773,0.82979],"type":"Point"}
}