{
  "type": "Feature",
  "properties": {
    "gn:admin1_code":"W",
    "gn:admin2_code":"52",
    "gn:admin3_code":"7732072.0",
    "gn:admin4_code":"8657803.0",
    "gn:asciiname":"Nyamityobora",
    "gn:country_code":"UG",
    "gn:dem":1414,
    "gn:feature_class":"P",
    "gn:feature_code":"PPLL",
    "gn:name":"Nyamityobora",
    "gn:population":0,
    "gn:timezone":"Africa/Kampala",
    "iso:country":"UG",
    "wof:name":"Nyamityobora",
    "wof:placetype":"locality"
},
  "geometry": {"coordinates":[30.66933,-0.5923],"type":"Point"}
}