{
  "type": "Feature",
  "properties": {
    "gn:admin1_code":"E",
    "gn:admin2_code":"76",
    "gn:admin3_code":"8644131.0",
    "gn:admin4_code":"8658001.0",
    "gn:asciiname":"Magola",
    "gn:country_code":"UG",
    "gn:dem":1127,
    "gn:feature_class":"P",
    "gn:feature_code":"PPL",
    "gn:name":"Magola",
    "gn:population":0,
    "gn:timezone":"Africa/Kampala",
    "iso:country":"UG",
    "name:eng_x_preferred":[
        "Magola"
    ],
    "wof:name":"Magola",
    "wof:placetype":"locality"
},
  "geometry": {"coordinates":[34.06712,0.63648],"type":"Point"}
}