{
  "type": "Feature",
  "properties": {
    "gn:admin1_code":"E",
    "gn:admin2_code":"80",
    "gn:admin3_code":"233018.0",
    "gn:admin4_code":"8658028.0",
    "gn:asciiname":"Okapel",
    "gn:country_code":"UG",
    "gn:dem":1038,
    "gn:feature_class":"P",
    "gn:feature_code":"PPL",
    "gn:name":"Okapel",
    "gn:population":0,
    "gn:timezone":"Africa/Kampala",
    "iso:country":"UG",
    "name:und_x_variant":[
        "Kaperu",
        "Okapel"
    ],
    "wof:name":"Okapel",
    "wof:placetype":"locality"
},
  "geometry": {"coordinates":[33.22186,1.74364],"type":"Point"}
}