{
  "type": "Feature",
  "properties": {
    "gn:admin1_code":"C",
    "gn:admin2_code":"G5",
    "gn:admin3_code":"7910221.0",
    "gn:admin4_code":"8657534.0",
    "gn:asciiname":"Magiri",
    "gn:country_code":"UG",
    "gn:dem":1197,
    "gn:feature_class":"P",
    "gn:feature_code":"PPL",
    "gn:name":"Magiri",
    "gn:population":0,
    "gn:timezone":"Africa/Kampala",
    "iso:country":"UG",
    "wof:name":"Magiri",
    "wof:placetype":"locality"
},
  "geometry": {"coordinates":[31.71667,-0.55],"type":"Point"}
}