{
  "type": "Feature",
  "properties": {
    "gn:admin1_code":"E",
    "gn:admin2_code":"33",
    "gn:asciiname":"Nabusagwa",
    "gn:country_code":"UG",
    "gn:dem":1128,
    "gn:feature_class":"P",
    "gn:feature_code":"PPL",
    "gn:name":"Nabusagwa",
    "gn:population":0,
    "gn:timezone":"Africa/Kampala",
    "iso:country":"UG",
    "wof:name":"Nabusagwa",
    "wof:placetype":"locality"
},
  "geometry": {"coordinates":[33.25151,0.65808],"type":"Point"}
}