{
  "type": "Feature",
  "properties": {
    "gn:admin1_code":"E",
    "gn:admin2_code":"87",
    "gn:asciiname":"Namunyu",
    "gn:country_code":"UG",
    "gn:dem":1140,
    "gn:feature_class":"P",
    "gn:feature_code":"PPL",
    "gn:name":"Namunyu",
    "gn:population":0,
    "gn:timezone":"Africa/Kampala",
    "iso:country":"UG",
    "name:eng_x_preferred":[
        "Namunyu"
    ],
    "wof:name":"Namunyu",
    "wof:placetype":"locality"
},
  "geometry": {"coordinates":[34.14255,0.91015],"type":"Point"}
}