{
  "type": "Feature",
  "properties": {
    "gn:admin1_code":"C",
    "gn:admin2_code":"37",
    "gn:admin3_code":"8644170.0",
    "gn:admin4_code":"8260676.0",
    "gn:asciiname":"Luwafu",
    "gn:country_code":"UG",
    "gn:dem":1198,
    "gn:feature_class":"P",
    "gn:feature_code":"PPL",
    "gn:name":"Luwafu",
    "gn:population":0,
    "gn:timezone":"Africa/Kampala",
    "iso:country":"UG",
    "wof:name":"Luwafu",
    "wof:placetype":"locality"
},
  "geometry": {"coordinates":[32.59864,0.26986],"type":"Point"}
}