{
  "type": "Feature",
  "properties": {
    "gn:admin1_code":"N",
    "gn:admin2_code":"30",
    "gn:admin3_code":"235009.0",
    "gn:admin4_code":"8657703.0",
    "gn:asciiname":"Patiko",
    "gn:country_code":"UG",
    "gn:dem":1084,
    "gn:feature_class":"P",
    "gn:feature_code":"PPL",
    "gn:name":"Patiko",
    "gn:population":0,
    "gn:timezone":"Africa/Kampala",
    "iso:country":"UG",
    "wof:name":"Patiko",
    "wof:placetype":"locality"
},
  "geometry": {"coordinates":[32.32337,3.01379],"type":"Point"}
}