{
  "type": "Feature",
  "properties": {
    "gn:admin1_code":"C",
    "gn:admin2_code":"F2",
    "gn:admin3_code":"233919.0",
    "gn:admin4_code":"8658170.0",
    "gn:asciiname":"Mawanga",
    "gn:country_code":"UG",
    "gn:dem":1155,
    "gn:feature_class":"P",
    "gn:feature_code":"PPL",
    "gn:name":"Mawanga",
    "gn:population":0,
    "gn:timezone":"Africa/Kampala",
    "iso:country":"UG",
    "name:eng_x_preferred":[
        "Mawanga"
    ],
    "wof:name":"Mawanga",
    "wof:placetype":"locality"
},
  "geometry": {"coordinates":[33.30098,0.26355],"type":"Point"}
}