{
  "type": "Feature",
  "properties": {
    "gn:admin1_code":"E",
    "gn:admin2_code":"H5",
    "gn:admin3_code":"226329.0",
    "gn:admin4_code":"7732527.0",
    "gn:asciiname":"Kamusala",
    "gn:country_code":"UG",
    "gn:dem":1054,
    "gn:feature_class":"P",
    "gn:feature_code":"PPL",
    "gn:name":"Kamusala",
    "gn:population":0,
    "gn:timezone":"Africa/Kampala",
    "iso:country":"UG",
    "wof:name":"Kamusala",
    "wof:placetype":"locality"
},
  "geometry": {"coordinates":[33.58333,1.43333],"type":"Point"}
}