{
  "type": "Feature",
  "properties": {
    "gn:admin1_code":"N",
    "gn:admin2_code":"H2",
    "gn:admin3_code":"8644126.0",
    "gn:admin4_code":"8200494.0",
    "gn:asciiname":"Wianaka",
    "gn:country_code":"UG",
    "gn:dem":970,
    "gn:feature_class":"P",
    "gn:feature_code":"PPL",
    "gn:name":"Wianaka",
    "gn:population":0,
    "gn:timezone":"Africa/Kampala",
    "iso:country":"UG",
    "wof:name":"Wianaka",
    "wof:placetype":"locality"
},
  "geometry": {"coordinates":[31.78246,2.57533],"type":"Point"}
}