{
  "type": "Feature",
  "properties": {
    "gn:admin1_code":"N",
    "gn:admin2_code":"77",
    "gn:admin3_code":"226158.0",
    "gn:admin4_code":"8657683.0",
    "gn:asciiname":"Ejomi",
    "gn:country_code":"UG",
    "gn:dem":889,
    "gn:feature_class":"P",
    "gn:feature_code":"PPL",
    "gn:name":"Ejomi",
    "gn:population":0,
    "gn:timezone":"Africa/Kampala",
    "iso:country":"UG",
    "wof:name":"Ejomi",
    "wof:placetype":"locality"
},
  "geometry": {"coordinates":[31.08457000000001,3.15252],"type":"Point"}
}