{
  "type": "Feature",
  "properties": {
    "gn:admin1_code":"C",
    "gn:admin2_code":"F4",
    "gn:asciiname":"Kabuye",
    "gn:country_code":"UG",
    "gn:dem":1256,
    "gn:feature_class":"P",
    "gn:feature_code":"PPL",
    "gn:name":"Kabuye",
    "gn:population":0,
    "gn:timezone":"Africa/Kampala",
    "iso:country":"UG",
    "wof:name":"Kabuye",
    "wof:placetype":"locality"
},
  "geometry": {"coordinates":[32.12855,0.24684],"type":"Point"}
}