{
  "type": "Feature",
  "properties": {
    "gn:admin1_code":"E",
    "gn:admin2_code":"69",
    "gn:asciiname":"Akoboi",
    "gn:country_code":"UG",
    "gn:dem":1071,
    "gn:feature_class":"P",
    "gn:feature_code":"PPLL",
    "gn:name":"Akoboi",
    "gn:population":0,
    "gn:timezone":"Africa/Kampala",
    "iso:country":"UG",
    "wof:name":"Akoboi",
    "wof:placetype":"locality"
},
  "geometry": {"coordinates":[33.93852,1.75577],"type":"Point"}
}