{
  "type": "Feature",
  "properties": {
    "gn:admin1_code":"E",
    "gn:admin2_code":"95",
    "gn:admin3_code":"226232.0",
    "gn:admin4_code":"8657815.0",
    "gn:asciiname":"Omulala",
    "gn:country_code":"UG",
    "gn:dem":1065,
    "gn:feature_class":"P",
    "gn:feature_code":"PPL",
    "gn:name":"Omulala",
    "gn:population":0,
    "gn:timezone":"Africa/Kampala",
    "iso:country":"UG",
    "wof:name":"Omulala",
    "wof:placetype":"locality"
},
  "geometry": {"coordinates":[33.64902,1.63866],"type":"Point"}
}