{
  "type": "Feature",
  "properties": {
    "gn:admin1_code":"N",
    "gn:admin2_code":"77",
    "gn:admin3_code":"234911.0",
    "gn:admin4_code":"8658074.0",
    "gn:asciiname":"Bunyu",
    "gn:country_code":"UG",
    "gn:dem":1187,
    "gn:feature_class":"P",
    "gn:feature_code":"PPL",
    "gn:name":"Bunyu",
    "gn:population":0,
    "gn:timezone":"Africa/Kampala",
    "iso:country":"UG",
    "wof:name":"Bunyu",
    "wof:placetype":"locality"
},
  "geometry": {"coordinates":[30.93357,2.99998],"type":"Point"}
}