{
  "type": "Feature",
  "properties": {
    "gn:admin1_code":"C",
    "gn:admin2_code":"E7",
    "gn:admin3_code":"7732075.0",
    "gn:admin4_code":"8658079.0",
    "gn:asciiname":"Mukwanya",
    "gn:country_code":"UG",
    "gn:dem":1249,
    "gn:feature_class":"P",
    "gn:feature_code":"PPL",
    "gn:name":"Mukwanya",
    "gn:population":0,
    "gn:timezone":"Africa/Kampala",
    "iso:country":"UG",
    "name:eng_x_preferred":[
        "Mukwanya"
    ],
    "wof:name":"Mukwanya",
    "wof:placetype":"locality"
},
  "geometry": {"coordinates":[33.14763,0.45026],"type":"Point"}
}