{
  "type": "Feature",
  "properties": {
    "gn:admin1_code":"N",
    "gn:admin2_code":"65",
    "gn:admin3_code":"8644133.0",
    "gn:admin4_code":"8657987.0",
    "gn:asciiname":"Marindi",
    "gn:country_code":"UG",
    "gn:dem":717,
    "gn:feature_class":"P",
    "gn:feature_code":"PPL",
    "gn:name":"Marindi",
    "gn:population":0,
    "gn:timezone":"Africa/Kampala",
    "iso:country":"UG",
    "wof:name":"Marindi",
    "wof:placetype":"locality"
},
  "geometry": {"coordinates":[31.74381,3.44821],"type":"Point"}
}