{
  "type": "Feature",
  "properties": {
    "gn:admin1_code":"E",
    "gn:admin2_code":"C6",
    "gn:asciiname":"Masanghe",
    "gn:country_code":"UG",
    "gn:dem":1082,
    "gn:feature_class":"P",
    "gn:feature_code":"PPL",
    "gn:name":"Masanghe",
    "gn:population":0,
    "gn:timezone":"Africa/Kampala",
    "iso:country":"UG",
    "wof:name":"Masanghe",
    "wof:placetype":"locality"
},
  "geometry": {"coordinates":[33.81282,0.82855],"type":"Point"}
}