{
  "type": "Feature",
  "properties": {
    "gn:admin1_code":"E",
    "gn:admin2_code":"H5",
    "gn:admin3_code":"8644174.0",
    "gn:admin4_code":"8658240.0",
    "gn:asciiname":"Kalamai",
    "gn:country_code":"UG",
    "gn:dem":1046,
    "gn:feature_class":"P",
    "gn:feature_code":"PPL",
    "gn:name":"Kalamai",
    "gn:population":0,
    "gn:timezone":"Africa/Kampala",
    "iso:country":"UG",
    "name:fra_x_preferred":[
        "Kalamai"
    ],
    "name:und_x_variant":[
        "Karamayi",
        "Kalamai"
    ],
    "wof:name":"Kalamai",
    "wof:placetype":"locality"
},
  "geometry": {"coordinates":[33.28333,1.46667],"type":"Point"}
}