{
  "type": "Feature",
  "properties": {
    "gn:admin1_code":"C",
    "gn:admin2_code":"83",
    "gn:admin3_code":"227613.0",
    "gn:admin4_code":"8658452.0",
    "gn:asciiname":"Seeta",
    "gn:country_code":"UG",
    "gn:dem":1137,
    "gn:feature_class":"P",
    "gn:feature_code":"PPL",
    "gn:name":"Seeta",
    "gn:population":0,
    "gn:timezone":"Africa/Kampala",
    "iso:country":"UG",
    "name:und_x_variant":[
        "Seta"
    ],
    "wof:name":"Seeta",
    "wof:placetype":"locality"
},
  "geometry": {"coordinates":[33.03846,0.55082],"type":"Point"}
}