{
  "type": "Feature",
  "properties": {
    "gn:admin1_code":"C",
    "gn:admin2_code":"90",
    "gn:admin3_code":"7732384.0",
    "gn:admin4_code":"8658391.0",
    "gn:asciiname":"Kibale",
    "gn:country_code":"UG",
    "gn:dem":1218,
    "gn:feature_class":"P",
    "gn:feature_code":"PPL",
    "gn:name":"Kibale",
    "gn:population":0,
    "gn:timezone":"Africa/Kampala",
    "iso:country":"UG",
    "wof:name":"Kibale",
    "wof:placetype":"locality"
},
  "geometry": {"coordinates":[32.7962,0.22905],"type":"Point"}
}