{
  "type": "Feature",
  "properties": {
    "gn:admin1_code":"C",
    "gn:admin2_code":"89",
    "gn:asciiname":"Kiswa",
    "gn:country_code":"UG",
    "gn:dem":1190,
    "gn:feature_class":"P",
    "gn:feature_code":"PPL",
    "gn:name":"Kiswa",
    "gn:population":0,
    "gn:timezone":"Africa/Kampala",
    "iso:country":"UG",
    "wof:name":"Kiswa",
    "wof:placetype":"locality"
},
  "geometry": {"coordinates":[32.23782,0.14733],"type":"Point"}
}