{
  "type": "Feature",
  "properties": {
    "gn:admin1_code":"W",
    "gn:admin2_code":"C8",
    "gn:admin3_code":"7732900.0",
    "gn:admin4_code":"8658667.0",
    "gn:asciiname":"Bigyera",
    "gn:country_code":"UG",
    "gn:dem":1307,
    "gn:feature_class":"P",
    "gn:feature_code":"PPL",
    "gn:name":"Bigyera",
    "gn:population":0,
    "gn:timezone":"Africa/Kampala",
    "iso:country":"UG",
    "wof:name":"Bigyera",
    "wof:placetype":"locality"
},
  "geometry": {"coordinates":[30.45167,-0.05944],"type":"Point"}
}