{
  "type": "Feature",
  "properties": {
    "gn:admin1_code":"E",
    "gn:admin2_code":"38",
    "gn:asciiname":"Bulyoko",
    "gn:country_code":"UG",
    "gn:dem":1114,
    "gn:feature_class":"P",
    "gn:feature_code":"PPL",
    "gn:name":"Bulyoko",
    "gn:population":0,
    "gn:timezone":"Africa/Kampala",
    "iso:country":"UG",
    "wof:name":"Bulyoko",
    "wof:placetype":"locality"
},
  "geometry": {"coordinates":[33.1419,0.92123],"type":"Point"}
}