{
  "type": "Feature",
  "properties": {
    "gn:admin1_code":"N",
    "gn:admin2_code":"B7",
    "gn:admin3_code":"231170.0",
    "gn:admin4_code":"8657892.0",
    "gn:asciiname":"Agonyolako",
    "gn:country_code":"UG",
    "gn:dem":1063,
    "gn:feature_class":"P",
    "gn:feature_code":"PPLL",
    "gn:name":"Agonyolako",
    "gn:population":0,
    "gn:timezone":"Africa/Kampala",
    "iso:country":"UG",
    "name:eng_x_preferred":[
        "Agonyolako"
    ],
    "wof:name":"Agonyolako",
    "wof:placetype":"locality"
},
  "geometry": {"coordinates":[32.77885,1.64388],"type":"Point"}
}