{
  "type": "Feature",
  "properties": {
    "gn:admin1_code":"E",
    "gn:admin2_code":"D6",
    "gn:asciiname":"Butsema",
    "gn:country_code":"UG",
    "gn:dem":1207,
    "gn:feature_class":"P",
    "gn:feature_code":"PPL",
    "gn:name":"Butsema",
    "gn:population":0,
    "gn:timezone":"Africa/Kampala",
    "iso:country":"UG",
    "name:eng_x_preferred":[
        "Butsema"
    ],
    "wof:name":"Butsema",
    "wof:placetype":"locality"
},
  "geometry": {"coordinates":[34.22677,0.82534],"type":"Point"}
}