{
  "type": "Feature",
  "properties": {
    "gn:admin1_code":"E",
    "gn:admin2_code":"86",
    "gn:admin3_code":"8644164.0",
    "gn:admin4_code":"8658417.0",
    "gn:asciiname":"Matovu",
    "gn:country_code":"UG",
    "gn:dem":1208,
    "gn:feature_class":"P",
    "gn:feature_code":"PPL",
    "gn:name":"Matovu",
    "gn:population":0,
    "gn:timezone":"Africa/Kampala",
    "iso:country":"UG",
    "name:eng_x_preferred":[
        "Matovu"
    ],
    "wof:name":"Matovu",
    "wof:placetype":"locality"
},
  "geometry": {"coordinates":[33.61091,0.36412],"type":"Point"}
}