{
  "type": "Feature",
  "properties": {
    "gn:admin1_code":"C",
    "gn:admin2_code":"83",
    "gn:admin3_code":"227613.0",
    "gn:admin4_code":"8658452.0",
    "gn:asciiname":"Soona",
    "gn:country_code":"UG",
    "gn:dem":1109,
    "gn:feature_class":"P",
    "gn:feature_code":"PPL",
    "gn:name":"Soona",
    "gn:population":0,
    "gn:timezone":"Africa/Kampala",
    "iso:country":"UG",
    "name:und_x_variant":[
        "Sonda",
        "Sona",
        "Soona"
    ],
    "wof:name":"Soona",
    "wof:placetype":"locality"
},
  "geometry": {"coordinates":[33.00964,0.56041],"type":"Point"}
}