{
  "type": "Feature",
  "properties": {
    "gn:admin1_code":"C",
    "gn:admin2_code":"89",
    "gn:asciiname":"Nyondo",
    "gn:country_code":"UG",
    "gn:dem":1187,
    "gn:feature_class":"P",
    "gn:feature_code":"PPL",
    "gn:name":"Nyondo",
    "gn:population":0,
    "gn:timezone":"Africa/Kampala",
    "iso:country":"UG",
    "wof:name":"Nyondo",
    "wof:placetype":"locality"
},
  "geometry": {"coordinates":[32.14728,0.10358],"type":"Point"}
}