{
  "type": "Feature",
  "properties": {
    "gn:admin1_code":"E",
    "gn:admin2_code":"69",
    "gn:asciiname":"Alogochi",
    "gn:country_code":"UG",
    "gn:dem":1068,
    "gn:feature_class":"P",
    "gn:feature_code":"PPLL",
    "gn:name":"Alogochi",
    "gn:population":0,
    "gn:timezone":"Africa/Kampala",
    "iso:country":"UG",
    "wof:name":"Alogochi",
    "wof:placetype":"locality"
},
  "geometry": {"coordinates":[33.92769000000001,1.97694],"type":"Point"}
}