{
  "type": "Feature",
  "properties": {
    "gn:admin1_code":"W",
    "gn:admin2_code":"79",
    "gn:asciiname":"Nyansohera",
    "gn:country_code":"UG",
    "gn:dem":1563,
    "gn:feature_class":"P",
    "gn:feature_code":"PPL",
    "gn:name":"Nyansohera",
    "gn:population":0,
    "gn:timezone":"Africa/Kampala",
    "iso:country":"UG",
    "name:eng_x_preferred":[
        "Nyansohera"
    ],
    "wof:name":"Nyansohera",
    "wof:placetype":"locality"
},
  "geometry": {"coordinates":[30.26865,0.61641],"type":"Point"}
}