{
  "type": "Feature",
  "properties": {
    "gn:admin1_code":"W",
    "gn:admin2_code":"79",
    "gn:admin3_code":"7732254.0",
    "gn:admin4_code":"8657930.0",
    "gn:asciiname":"Kyangabukama",
    "gn:country_code":"UG",
    "gn:dem":1490,
    "gn:feature_class":"P",
    "gn:feature_code":"PPL",
    "gn:name":"Kyangabukama",
    "gn:population":0,
    "gn:timezone":"Africa/Kampala",
    "iso:country":"UG",
    "name:eng_x_preferred":[
        "Kyangabukama"
    ],
    "wof:name":"Kyangabukama",
    "wof:placetype":"locality"
},
  "geometry": {"coordinates":[30.44346,0.86085],"type":"Point"}
}