{
  "type": "Feature",
  "properties": {
    "gn:admin1_code":"E",
    "gn:admin2_code":"B8",
    "gn:admin3_code":"235185.0",
    "gn:admin4_code":"8657827.0",
    "gn:asciiname":"Kuju",
    "gn:country_code":"UG",
    "gn:dem":1137,
    "gn:feature_class":"P",
    "gn:feature_code":"PPL",
    "gn:name":"Kuju",
    "gn:population":0,
    "gn:timezone":"Africa/Kampala",
    "iso:country":"UG",
    "name:ceb_x_preferred":[
        "Kuju"
    ],
    "name:swe_x_preferred":[
        "Kuju"
    ],
    "wof:name":"Kuju",
    "wof:placetype":"locality"
},
  "geometry": {"coordinates":[33.60417,2.02694],"type":"Point"}
}