{
  "type": "Feature",
  "properties": {
    "gn:admin1_code":"N",
    "gn:admin2_code":"65",
    "gn:admin3_code":"8644133.0",
    "gn:admin4_code":"8657897.0",
    "gn:asciiname":"Limule",
    "gn:country_code":"UG",
    "gn:dem":790,
    "gn:feature_class":"P",
    "gn:feature_code":"PPL",
    "gn:name":"Limule",
    "gn:population":0,
    "gn:timezone":"Africa/Kampala",
    "iso:country":"UG",
    "name:und_x_variant":[
        "Nimule"
    ],
    "wof:name":"Limule",
    "wof:placetype":"locality"
},
  "geometry": {"coordinates":[31.81349,3.36491],"type":"Point"}
}