{
  "type": "Feature",
  "properties": {
    "gn:admin1_code":"N",
    "gn:admin2_code":"G3",
    "gn:admin3_code":"230209.0",
    "gn:admin4_code":"8647187.0",
    "gn:asciiname":"Madi Opei",
    "gn:country_code":"UG",
    "gn:dem":1029,
    "gn:feature_class":"P",
    "gn:feature_code":"PPL",
    "gn:name":"Madi Opei",
    "gn:population":0,
    "gn:timezone":"Africa/Kampala",
    "iso:country":"UG",
    "wof:name":"Madi Opei",
    "wof:placetype":"locality"
},
  "geometry": {"coordinates":[33.08729,3.60545],"type":"Point"}
}