{
  "type": "Feature",
  "properties": {
    "gn:admin1_code":"E",
    "gn:admin2_code":"G4",
    "gn:admin3_code":"229762.0",
    "gn:admin4_code":"8658139.0",
    "gn:asciiname":"Nabyoto",
    "gn:country_code":"UG",
    "gn:dem":1059,
    "gn:feature_class":"P",
    "gn:feature_code":"PPL",
    "gn:name":"Nabyoto",
    "gn:population":0,
    "gn:timezone":"Africa/Kampala",
    "iso:country":"UG",
    "wof:name":"Nabyoto",
    "wof:placetype":"locality"
},
  "geometry": {"coordinates":[33.38378,0.90697],"type":"Point"}
}