{
  "type": "Feature",
  "properties": {
    "gn:admin1_code":"E",
    "gn:admin2_code":"E1",
    "gn:asciiname":"Bubuusa",
    "gn:country_code":"UG",
    "gn:dem":1132,
    "gn:feature_class":"P",
    "gn:feature_code":"PPL",
    "gn:name":"Bubuusa",
    "gn:population":0,
    "gn:timezone":"Africa/Kampala",
    "iso:country":"UG",
    "wof:name":"Bubuusa",
    "wof:placetype":"locality"
},
  "geometry": {"coordinates":[33.75354,0.73371],"type":"Point"}
}