{
  "type": "Feature",
  "properties": {
    "gn:admin1_code":"C",
    "gn:admin2_code":"73",
    "gn:admin3_code":"234123.0",
    "gn:admin4_code":"8658578.0",
    "gn:asciiname":"Lwamboga",
    "gn:country_code":"UG",
    "gn:dem":1067,
    "gn:feature_class":"P",
    "gn:feature_code":"PPL",
    "gn:name":"Lwamboga",
    "gn:population":0,
    "gn:timezone":"Africa/Kampala",
    "iso:country":"UG",
    "name:und_x_variant":[
        "Lwambogo",
        "Lwamboga"
    ],
    "wof:name":"Lwamboga",
    "wof:placetype":"locality"
},
  "geometry": {"coordinates":[32.15,1.45],"type":"Point"}
}