{
  "type": "Feature",
  "properties": {
    "gn:admin1_code":"C",
    "gn:admin2_code":"96",
    "gn:asciiname":"Butega",
    "gn:country_code":"UG",
    "gn:dem":1192,
    "gn:feature_class":"P",
    "gn:feature_code":"PPL",
    "gn:name":"Butega",
    "gn:population":0,
    "gn:timezone":"Africa/Kampala",
    "iso:country":"UG",
    "name:run_x_preferred":[
        "Butega"
    ],
    "wof:name":"Butega",
    "wof:placetype":"locality"
},
  "geometry": {"coordinates":[32.47636,0.22357],"type":"Point"}
}