{
  "type": "Feature",
  "properties": {
    "gn:admin1_code":"E",
    "gn:admin2_code":"E1",
    "gn:asciiname":"Buwaga",
    "gn:country_code":"UG",
    "gn:dem":1126,
    "gn:feature_class":"P",
    "gn:feature_code":"PPL",
    "gn:name":"Buwaga",
    "gn:population":0,
    "gn:timezone":"Africa/Kampala",
    "iso:country":"UG",
    "wof:name":"Buwaga",
    "wof:placetype":"locality"
},
  "geometry": {"coordinates":[33.75568,0.72894],"type":"Point"}
}