{
  "type": "Feature",
  "properties": {
    "gn:admin1_code":"N",
    "gn:admin2_code":"72",
    "gn:admin3_code":"8644127.0",
    "gn:admin4_code":"8658016.0",
    "gn:asciiname":"Tokaru",
    "gn:country_code":"UG",
    "gn:dem":659,
    "gn:feature_class":"P",
    "gn:feature_code":"PPL",
    "gn:name":"Tokaru",
    "gn:population":0,
    "gn:timezone":"Africa/Kampala",
    "iso:country":"UG",
    "wof:name":"Tokaru",
    "wof:placetype":"locality"
},
  "geometry": {"coordinates":[31.46212,3.36667],"type":"Point"}
}