{
  "type": "Feature",
  "properties": {
    "gn:admin1_code":"N",
    "gn:admin2_code":"58",
    "gn:admin3_code":"8080237.0",
    "gn:admin4_code":"8658147.0",
    "gn:asciiname":"Alego",
    "gn:country_code":"UG",
    "gn:dem":1107,
    "gn:feature_class":"P",
    "gn:feature_code":"PPL",
    "gn:name":"Alego",
    "gn:population":0,
    "gn:timezone":"Africa/Kampala",
    "iso:country":"UG",
    "name:bre_x_preferred":[
        "Alego"
    ],
    "name:ceb_x_preferred":[
        "Alego"
    ],
    "name:swe_x_preferred":[
        "Alego"
    ],
    "wof:name":"Alego",
    "wof:placetype":"locality"
},
  "geometry": {"coordinates":[31.0735,2.47454],"type":"Point"}
}