{
  "type": "Feature",
  "properties": {
    "gn:admin1_code":"N",
    "gn:admin2_code":"I5",
    "gn:admin3_code":"227037.0",
    "gn:admin4_code":"8658086.0",
    "gn:asciiname":"Laminabili",
    "gn:country_code":"UG",
    "gn:dem":1096,
    "gn:feature_class":"P",
    "gn:feature_code":"PPL",
    "gn:name":"Laminabili",
    "gn:population":0,
    "gn:timezone":"Africa/Kampala",
    "iso:country":"UG",
    "name:und_x_variant":[
        "Barabili",
        "Laminabil",
        "Laminabili"
    ],
    "wof:name":"Laminabili",
    "wof:placetype":"locality"
},
  "geometry": {"coordinates":[32.31505,2.69831],"type":"Point"}
}