{
  "type": "Feature",
  "properties": {
    "gn:admin1_code":"C",
    "gn:admin2_code":"89",
    "gn:asciiname":"Buwunga",
    "gn:country_code":"UG",
    "gn:dem":1161,
    "gn:feature_class":"P",
    "gn:feature_code":"PPL",
    "gn:name":"Buwunga",
    "gn:population":0,
    "gn:timezone":"Africa/Kampala",
    "iso:country":"UG",
    "wof:name":"Buwunga",
    "wof:placetype":"locality"
},
  "geometry": {"coordinates":[32.13211,0.06344],"type":"Point"}
}