{
  "type": "Feature",
  "properties": {
    "gn:admin1_code":"C",
    "gn:admin2_code":"E8",
    "gn:admin3_code":"7910224.0",
    "gn:admin4_code":"8657560.0",
    "gn:asciiname":"Kasaka",
    "gn:country_code":"UG",
    "gn:dem":1235,
    "gn:feature_class":"P",
    "gn:feature_code":"PPL",
    "gn:name":"Kasaka",
    "gn:population":0,
    "gn:timezone":"Africa/Kampala",
    "iso:country":"UG",
    "name:und_x_variant":[
        "Kisaka",
        "Kasaka"
    ],
    "wof:name":"Kasaka",
    "wof:placetype":"locality"
},
  "geometry": {"coordinates":[31.56667,-0.16667],"type":"Point"}
}