{
  "type": "Feature",
  "properties": {
    "gn:admin1_code":"C",
    "gn:admin2_code":"F1",
    "gn:admin3_code":"234000.0",
    "gn:admin4_code":"8658604.0",
    "gn:asciiname":"Bwala",
    "gn:country_code":"UG",
    "gn:dem":1172,
    "gn:feature_class":"P",
    "gn:feature_code":"PPL",
    "gn:name":"Bwala",
    "gn:population":0,
    "gn:timezone":"Africa/Kampala",
    "iso:country":"UG",
    "wof:name":"Bwala",
    "wof:placetype":"locality"
},
  "geometry": {"coordinates":[31.98333,0.08333],"type":"Point"}
}