{
  "type": "Feature",
  "properties": {
    "iso:country":"UG",
    "name:dut_x_preferred":[
        "Masindi Port"
    ],
    "name:eng_x_preferred":[
        "Masindi Port"
    ],
    "name:urd_x_preferred":[
        "\u0645\u0627\u0633\u06cc\u0646\u062f\u06cc \u067e\u0648\u0631\u0679"
    ],
    "ne:ADM0CAP":0.0,
    "ne:ADM0NAME":"Uganda",
    "ne:ADM0_A3":"UGA",
    "ne:ADM1NAME":"Masindi",
    "ne:ADMIN1_COD":50,
    "ne:CAPALT":0,
    "ne:CHANGED":4,
    "ne:CHECKME":2,
    "ne:COMPARE":0,
    "ne:DIFFASCII":0,
    "ne:DIFFNOTE":"Changed feature class. Changed scale rank.",
    "ne:ELEVATION":0.0,
    "ne:FEATURECLA":"Admin-1 capital",
    "ne:FEATURE_CL":"P",
    "ne:FEATURE_CO":"PPL",
    "ne:GEONAMEID":229361,
    "ne:GEONAMESNO":"GeoNames spatial join with similar names only.",
    "ne:GN_ASCII":"Masindi Port",
    "ne:GN_POP":7828,
    "ne:GTOPO30":1041.0,
    "ne:ISO_A2":"UG",
    "ne:LABELRANK":5,
    "ne:LATITUDE":1.700399,
    "ne:LONGITUDE":32.069918,
    "ne:LS_MATCH":1,
    "ne:LS_NAME":"Masindi-Port",
    "ne:MAX_AREAKM":3.0,
    "ne:MAX_AREAMI":1.0,
    "ne:MAX_BBXMAX":32.075,
    "ne:MAX_BBXMIN":32.058333,
    "ne:MAX_BBYMAX":1.716667,
    "ne:MAX_BBYMIN":1.691667,
    "ne:MAX_NATSCA":10.0,
    "ne:MAX_PERKM":9.0,
    "ne:MAX_PERMI":6.0,
    "ne:MAX_POP10":8319,
    "ne:MAX_POP20":0,
    "ne:MAX_POP300":0,
    "ne:MAX_POP310":0,
    "ne:MAX_POP50":0,
    "ne:MEAN_BBXC":32.066667,
    "ne:MEAN_BBYC":1.704167,
    "ne:MEGACITY":0,
    "ne:MIN_AREAKM":3.0,
    "ne:MIN_AREAMI":1.0,
    "ne:MIN_BBXMAX":32.075,
    "ne:MIN_BBXMIN":32.058333,
    "ne:MIN_BBYMAX":1.716667,
    "ne:MIN_BBYMIN":1.691667,
    "ne:MIN_PERKM":9.0,
    "ne:MIN_PERMI":6.0,
    "ne:NAME":"Masindi-Port",
    "ne:NAMEASCII":"Masindi-Port",
    "ne:NAMEDIFF":0,
    "ne:NATSCALE":20,
    "ne:POP1950":0,
    "ne:POP1955":0,
    "ne:POP1960":0,
    "ne:POP1965":0,
    "ne:POP1970":0,
    "ne:POP1975":0,
    "ne:POP1980":0,
    "ne:POP1985":0,
    "ne:POP1990":0,
    "ne:POP1995":0,
    "ne:POP2000":0,
    "ne:POP2005":0,
    "ne:POP2010":0,
    "ne:POP2015":0,
    "ne:POP2020":0,
    "ne:POP2025":0,
    "ne:POP2050":0,
    "ne:POP_MAX":8319,
    "ne:POP_MIN":7828,
    "ne:POP_OTHER":8319,
    "ne:RANK_MAX":5,
    "ne:RANK_MIN":5,
    "ne:SCALERANK":7,
    "ne:SOV0NAME":"Uganda",
    "ne:SOV_A3":"UGA",
    "ne:TIMEZONE":"Africa/Kampala",
    "ne:UN_FID":0,
    "ne:UN_LAT":0.0,
    "ne:UN_LONG":0.0,
    "ne:WORLDCITY":0,
    "ne:min_zoom":6.1,
    "wof:name":"Masindi-Port",
    "wof:placetype":"locality"
},
  "geometry": {"coordinates":[32.06991817091426,1.70039878224975],"type":"Point"}
}