{
  "type": "Feature",
  "properties": {
    "gn:admin1_code":"E",
    "gn:admin2_code":"95",
    "gn:admin3_code":"226232.0",
    "gn:admin4_code":"8658303.0",
    "gn:asciiname":"Olio",
    "gn:country_code":"UG",
    "gn:dem":1060,
    "gn:feature_class":"P",
    "gn:feature_code":"PPL",
    "gn:name":"Olio",
    "gn:population":0,
    "gn:timezone":"Africa/Kampala",
    "iso:country":"UG",
    "name:und_x_variant":[
        "Kolyo",
        "Olio"
    ],
    "wof:name":"Olio",
    "wof:placetype":"locality"
},
  "geometry": {"coordinates":[33.51307,1.76833],"type":"Point"}
}