{
  "type": "Feature",
  "properties": {
    "gn:admin1_code":"E",
    "gn:admin2_code":"38",
    "gn:asciiname":"Busula",
    "gn:country_code":"UG",
    "gn:dem":1075,
    "gn:feature_class":"P",
    "gn:feature_code":"PPL",
    "gn:name":"Busula",
    "gn:population":0,
    "gn:timezone":"Africa/Kampala",
    "iso:country":"UG",
    "wof:name":"Busula",
    "wof:placetype":"locality"
},
  "geometry": {"coordinates":[33.02715999999999,0.86983],"type":"Point"}
}