{
  "type": "Feature",
  "properties": {
    "gn:admin1_code":"E",
    "gn:admin2_code":"66",
    "gn:asciiname":"Namatanga",
    "gn:country_code":"UG",
    "gn:dem":1144,
    "gn:feature_class":"P",
    "gn:feature_code":"PPL",
    "gn:name":"Namatanga",
    "gn:population":0,
    "gn:timezone":"Africa/Kampala",
    "iso:country":"UG",
    "wof:name":"Namatanga",
    "wof:placetype":"locality"
},
  "geometry": {"coordinates":[33.68519000000001,0.54472],"type":"Point"}
}