{
  "type": "Feature",
  "properties": {
    "gn:admin1_code":"W",
    "gn:admin2_code":"41",
    "gn:admin3_code":"8644139.0",
    "gn:admin4_code":"8658062.0",
    "gn:asciiname":"Busesa",
    "gn:country_code":"UG",
    "gn:dem":1265,
    "gn:feature_class":"P",
    "gn:feature_code":"PPL",
    "gn:name":"Busesa",
    "gn:population":0,
    "gn:timezone":"Africa/Kampala",
    "iso:country":"UG",
    "wof:name":"Busesa",
    "wof:placetype":"locality"
},
  "geometry": {"coordinates":[31.15,0.76667],"type":"Point"}
}