{
  "type": "Feature",
  "properties": {
    "gn:admin1_code":"W",
    "gn:admin2_code":"I7",
    "gn:admin3_code":"226689.0",
    "gn:admin4_code":"8657849.0",
    "gn:asciiname":"Luhizha",
    "gn:country_code":"UG",
    "gn:dem":2053,
    "gn:feature_class":"P",
    "gn:feature_code":"PPL",
    "gn:name":"Luhizha",
    "gn:population":0,
    "gn:timezone":"Africa/Kampala",
    "iso:country":"UG",
    "name:und_x_variant":[
        "Luhiza",
        "Luhizha"
    ],
    "wof:name":"Luhizha",
    "wof:placetype":"locality"
},
  "geometry": {"coordinates":[29.78333,-1.03333],"type":"Point"}
}