{
  "type": "Feature",
  "properties": {
    "gn:admin1_code":"E",
    "gn:admin2_code":"78",
    "gn:asciiname":"Kabugweri",
    "gn:country_code":"UG",
    "gn:dem":1136,
    "gn:feature_class":"P",
    "gn:feature_code":"PPL",
    "gn:name":"Kabugweri",
    "gn:population":0,
    "gn:timezone":"Africa/Kampala",
    "iso:country":"UG",
    "wof:name":"Kabugweri",
    "wof:placetype":"locality"
},
  "geometry": {"coordinates":[33.60194,0.56075],"type":"Point"}
}