{
  "type": "Feature",
  "properties": {
    "gn:admin1_code":"E",
    "gn:admin2_code":"D6",
    "gn:asciiname":"Bushibingo",
    "gn:country_code":"UG",
    "gn:dem":1343,
    "gn:feature_class":"P",
    "gn:feature_code":"PPL",
    "gn:name":"Bushibingo",
    "gn:population":0,
    "gn:timezone":"Africa/Kampala",
    "iso:country":"UG",
    "name:eng_x_preferred":[
        "Bushibingo"
    ],
    "wof:name":"Bushibingo",
    "wof:placetype":"locality"
},
  "geometry": {"coordinates":[34.34774,0.96164],"type":"Point"}
}