{
  "type": "Feature",
  "properties": {
    "gn:admin1_code":"C",
    "gn:admin2_code":"E7",
    "gn:admin3_code":"7732075.0",
    "gn:admin4_code":"8658239.0",
    "gn:asciiname":"Kigudu",
    "gn:country_code":"UG",
    "gn:dem":1223,
    "gn:feature_class":"P",
    "gn:feature_code":"PPL",
    "gn:name":"Kigudu",
    "gn:population":0,
    "gn:timezone":"Africa/Kampala",
    "iso:country":"UG",
    "name:eng_x_preferred":[
        "Kigudu"
    ],
    "wof:name":"Kigudu",
    "wof:placetype":"locality"
},
  "geometry": {"coordinates":[33.13504,0.37845],"type":"Point"}
}