{
  "type": "Feature",
  "properties": {
    "gn:admin1_code":"W",
    "gn:admin2_code":"79",
    "gn:asciiname":"Kinyamasika",
    "gn:country_code":"UG",
    "gn:dem":1540,
    "gn:feature_class":"P",
    "gn:feature_code":"PPL",
    "gn:name":"Kinyamasika",
    "gn:population":0,
    "gn:timezone":"Africa/Kampala",
    "iso:country":"UG",
    "name:eng_x_preferred":[
        "Kinyamasika"
    ],
    "wof:name":"Kinyamasika",
    "wof:placetype":"locality"
},
  "geometry": {"coordinates":[30.27437,0.62903],"type":"Point"}
}