{
  "type": "Feature",
  "properties": {
    "gn:admin1_code":"E",
    "gn:admin2_code":"87",
    "gn:asciiname":"Wotsongole",
    "gn:country_code":"UG",
    "gn:dem":1192,
    "gn:feature_class":"P",
    "gn:feature_code":"PPL",
    "gn:name":"Wotsongole",
    "gn:population":0,
    "gn:timezone":"Africa/Kampala",
    "iso:country":"UG",
    "name:eng_x_preferred":[
        "Wotsongole"
    ],
    "wof:name":"Wotsongole",
    "wof:placetype":"locality"
},
  "geometry": {"coordinates":[34.16028,0.97926],"type":"Point"}
}