{
  "type": "Feature",
  "properties": {
    "gn:admin1_code":"E",
    "gn:admin2_code":"86",
    "gn:admin3_code":"8644164.0",
    "gn:admin4_code":"8658692.0",
    "gn:asciiname":"Bugoye",
    "gn:country_code":"UG",
    "gn:dem":1203,
    "gn:feature_class":"P",
    "gn:feature_code":"PPL",
    "gn:name":"Bugoye",
    "gn:population":0,
    "gn:timezone":"Africa/Kampala",
    "iso:country":"UG",
    "name:ceb_x_preferred":[
        "Bugoye"
    ],
    "name:eng_x_preferred":[
        "Bugoye"
    ],
    "name:lug_x_preferred":[
        "Bugoye"
    ],
    "wof:name":"Bugoye",
    "wof:placetype":"locality"
},
  "geometry": {"coordinates":[33.54328,0.41468],"type":"Point"}
}