{
  "type": "Feature",
  "properties": {
    "gn:admin1_code":"E",
    "gn:admin2_code":"D6",
    "gn:asciiname":"Buwandyami",
    "gn:country_code":"UG",
    "gn:dem":1397,
    "gn:feature_class":"P",
    "gn:feature_code":"PPL",
    "gn:name":"Buwandyami",
    "gn:population":0,
    "gn:timezone":"Africa/Kampala",
    "iso:country":"UG",
    "name:eng_x_preferred":[
        "Buwandyami"
    ],
    "wof:name":"Buwandyami",
    "wof:placetype":"locality"
},
  "geometry": {"coordinates":[34.3376,0.80231],"type":"Point"}
}