{
  "type": "Feature",
  "properties": {
    "gn:admin1_code":"W",
    "gn:admin2_code":"G6",
    "gn:admin3_code":"7869954.0",
    "gn:admin4_code":"8658552.0",
    "gn:asciiname":"Rutoma",
    "gn:country_code":"UG",
    "gn:dem":1529,
    "gn:feature_class":"P",
    "gn:feature_code":"PPL",
    "gn:name":"Rutoma",
    "gn:population":0,
    "gn:timezone":"Africa/Kampala",
    "iso:country":"UG",
    "wof:name":"Rutoma",
    "wof:placetype":"locality"
},
  "geometry": {"coordinates":[29.96667,-0.65],"type":"Point"}
}