{
  "type": "Feature",
  "properties": {
    "gn:admin1_code":"C",
    "gn:admin2_code":"D8",
    "gn:admin3_code":"8644137.0",
    "gn:admin4_code":"8658717.0",
    "gn:asciiname":"Gayaza",
    "gn:country_code":"UG",
    "gn:dem":1209,
    "gn:feature_class":"P",
    "gn:feature_code":"PPL",
    "gn:name":"Gayaza",
    "gn:population":0,
    "gn:timezone":"Africa/Kampala",
    "iso:country":"UG",
    "wof:name":"Gayaza",
    "wof:placetype":"locality"
},
  "geometry": {"coordinates":[31.88333,0.23333],"type":"Point"}
}