{
  "type": "Feature",
  "properties": {
    "gn:admin1_code":"E",
    "gn:admin2_code":"38",
    "gn:asciiname":"Nabiyama",
    "gn:country_code":"UG",
    "gn:dem":1085,
    "gn:feature_class":"P",
    "gn:feature_code":"PPL",
    "gn:name":"Nabiyama",
    "gn:population":0,
    "gn:timezone":"Africa/Kampala",
    "iso:country":"UG",
    "wof:name":"Nabiyama",
    "wof:placetype":"locality"
},
  "geometry": {"coordinates":[33.07789,0.73232],"type":"Point"}
}