{
  "type": "Feature",
  "properties": {
    "gn:admin1_code":"W",
    "gn:admin2_code":"79",
    "gn:asciiname":"Kihonolia",
    "gn:country_code":"UG",
    "gn:dem":1529,
    "gn:feature_class":"P",
    "gn:feature_code":"PPL",
    "gn:name":"Kihonolia",
    "gn:population":0,
    "gn:timezone":"Africa/Kampala",
    "iso:country":"UG",
    "name:eng_x_preferred":[
        "Kihonolia"
    ],
    "wof:name":"Kihonolia",
    "wof:placetype":"locality"
},
  "geometry": {"coordinates":[30.41734000000001,0.56646],"type":"Point"}
}