{
  "type": "Feature",
  "properties": {
    "gn:admin1_code":"N",
    "gn:admin2_code":"I6",
    "gn:admin3_code":"233111.0",
    "gn:admin4_code":"8261566.0",
    "gn:asciiname":"Marama",
    "gn:country_code":"UG",
    "gn:dem":715,
    "gn:feature_class":"P",
    "gn:feature_code":"PPL",
    "gn:name":"Marama",
    "gn:population":0,
    "gn:timezone":"Africa/Kampala",
    "iso:country":"UG",
    "name:ceb_x_preferred":[
        "Marama"
    ],
    "name:mri_x_preferred":[
        "Marama"
    ],
    "name:spa_x_preferred":[
        "Marama"
    ],
    "name:swe_x_preferred":[
        "Marama"
    ],
    "wof:name":"Marama",
    "wof:placetype":"locality"
},
  "geometry": {"coordinates":[31.3646,2.38137],"type":"Point"}
}