{
  "type": "Feature",
  "properties": {
    "gn:admin1_code":"E",
    "gn:admin2_code":"67",
    "gn:admin3_code":"8644151.0",
    "gn:admin4_code":"8658208.0",
    "gn:asciiname":"Buhwama",
    "gn:country_code":"UG",
    "gn:dem":1159,
    "gn:feature_class":"P",
    "gn:feature_code":"PPL",
    "gn:name":"Buhwama",
    "gn:population":0,
    "gn:timezone":"Africa/Kampala",
    "iso:country":"UG",
    "name:eng_x_preferred":[
        "Buhwama"
    ],
    "wof:name":"Buhwama",
    "wof:placetype":"locality"
},
  "geometry": {"coordinates":[33.94609000000001,0.33075],"type":"Point"}
}