{
  "type": "Feature",
  "properties": {
    "gn:admin1_code":"N",
    "gn:admin2_code":"B9",
    "gn:admin3_code":"231253.0",
    "gn:admin4_code":"8630008.0",
    "gn:asciiname":"Bibia",
    "gn:country_code":"UG",
    "gn:dem":693,
    "gn:feature_class":"P",
    "gn:feature_code":"PPL",
    "gn:name":"Bibia",
    "gn:population":0,
    "gn:timezone":"Africa/Kampala",
    "iso:country":"UG",
    "wof:name":"Bibia",
    "wof:placetype":"locality"
},
  "geometry": {"coordinates":[32.06732,3.47435],"type":"Point"}
}