{
  "type": "Feature",
  "properties": {
    "gn:admin1_code":"C",
    "gn:admin2_code":"56",
    "gn:admin3_code":"8644175.0",
    "gn:admin4_code":"8658548.0",
    "gn:asciiname":"Kawungera",
    "gn:country_code":"UG",
    "gn:dem":1236,
    "gn:feature_class":"P",
    "gn:feature_code":"PPL",
    "gn:name":"Kawungera",
    "gn:population":0,
    "gn:timezone":"Africa/Kampala",
    "iso:country":"UG",
    "wof:name":"Kawungera",
    "wof:placetype":"locality"
},
  "geometry": {"coordinates":[31.66306,0.45667],"type":"Point"}
}