{
  "type": "Feature",
  "properties": {
    "gn:admin1_code":"N",
    "gn:admin2_code":"B9",
    "gn:admin3_code":"231253.0",
    "gn:admin4_code":"8630017.0",
    "gn:asciiname":"Parabongo",
    "gn:country_code":"UG",
    "gn:dem":1069,
    "gn:feature_class":"P",
    "gn:feature_code":"PPL",
    "gn:name":"Parabongo",
    "gn:population":0,
    "gn:timezone":"Africa/Kampala",
    "iso:country":"UG",
    "name:und_x_variant":[
        "Parabong",
        "Parabongo"
    ],
    "wof:name":"Parabongo",
    "wof:placetype":"locality"
},
  "geometry": {"coordinates":[32.15668,2.895],"type":"Point"}
}