{
  "type": "Feature",
  "properties": {
    "gn:admin1_code":"E",
    "gn:admin2_code":"33",
    "gn:asciiname":"Bukyeyune",
    "gn:country_code":"UG",
    "gn:dem":1199,
    "gn:feature_class":"P",
    "gn:feature_code":"PPL",
    "gn:name":"Bukyeyune",
    "gn:population":0,
    "gn:timezone":"Africa/Kampala",
    "iso:country":"UG",
    "wof:name":"Bukyeyune",
    "wof:placetype":"locality"
},
  "geometry": {"coordinates":[33.28115,0.63725],"type":"Point"}
}