{
  "type": "Feature",
  "properties": {
    "gn:admin1_code":"E",
    "gn:admin2_code":"86",
    "gn:admin3_code":"8644164.0",
    "gn:admin4_code":"8658516.0",
    "gn:asciiname":"Bugobe",
    "gn:country_code":"UG",
    "gn:dem":1183,
    "gn:feature_class":"P",
    "gn:feature_code":"PPL",
    "gn:name":"Bugobe",
    "gn:population":0,
    "gn:timezone":"Africa/Kampala",
    "iso:country":"UG",
    "name:eng_x_preferred":[
        "Bugobe"
    ],
    "wof:name":"Bugobe",
    "wof:placetype":"locality"
},
  "geometry": {"coordinates":[33.58886,0.26891],"type":"Point"}
}