{
  "type": "Feature",
  "properties": {
    "gn:admin1_code":"C",
    "gn:admin2_code":"96",
    "gn:admin3_code":"234053.0",
    "gn:admin4_code":"8657893.0",
    "gn:asciiname":"Kyebando",
    "gn:country_code":"UG",
    "gn:dem":1235,
    "gn:feature_class":"P",
    "gn:feature_code":"PPL",
    "gn:name":"Kyebando",
    "gn:population":0,
    "gn:timezone":"Africa/Kampala",
    "iso:country":"UG",
    "wof:name":"Kyebando",
    "wof:placetype":"locality"
},
  "geometry": {"coordinates":[32.51274,0.36361],"type":"Point"}
}