{
  "type": "Feature",
  "properties": {
    "gn:admin1_code":"N",
    "gn:admin2_code":"26",
    "gn:admin3_code":"229387.0",
    "gn:admin4_code":"8657675.0",
    "gn:asciiname":"Awila",
    "gn:country_code":"UG",
    "gn:dem":1066,
    "gn:feature_class":"P",
    "gn:feature_code":"PPL",
    "gn:name":"Awila",
    "gn:population":0,
    "gn:timezone":"Africa/Kampala",
    "iso:country":"UG",
    "wof:name":"Awila",
    "wof:placetype":"locality"
},
  "geometry": {"coordinates":[32.37579,1.77906],"type":"Point"}
}