{
  "type": "Feature",
  "properties": {
    "gn:admin1_code":"E",
    "gn:admin2_code":"G4",
    "gn:admin3_code":"229762.0",
    "gn:admin4_code":"8658260.0",
    "gn:asciiname":"Irongo",
    "gn:country_code":"UG",
    "gn:dem":1111,
    "gn:feature_class":"P",
    "gn:feature_code":"PPLL",
    "gn:name":"Irongo",
    "gn:population":0,
    "gn:timezone":"Africa/Kampala",
    "iso:country":"UG",
    "wof:name":"Irongo",
    "wof:placetype":"locality"
},
  "geometry": {"coordinates":[33.24309,0.73158],"type":"Point"}
}