{
  "type": "Feature",
  "properties": {
    "gn:admin1_code":"E",
    "gn:admin2_code":"E9",
    "gn:admin3_code":"7869956.0",
    "gn:admin4_code":"8658468.0",
    "gn:asciiname":"Bunagami",
    "gn:country_code":"UG",
    "gn:dem":2152,
    "gn:feature_class":"P",
    "gn:feature_code":"PPL",
    "gn:name":"Bunagami",
    "gn:population":0,
    "gn:timezone":"Africa/Kampala",
    "iso:country":"UG",
    "wof:name":"Bunagami",
    "wof:placetype":"locality"
},
  "geometry": {"coordinates":[34.3891,1.19895],"type":"Point"}
}