{
  "type": "Feature",
  "properties": {
    "gn:admin1_code":"W",
    "gn:admin2_code":"D3",
    "gn:admin3_code":"8644177.0",
    "gn:admin4_code":"8657624.0",
    "gn:asciiname":"Kanoni",
    "gn:country_code":"UG",
    "gn:dem":1289,
    "gn:feature_class":"P",
    "gn:feature_code":"PPL",
    "gn:name":"Kanoni",
    "gn:population":0,
    "gn:timezone":"Africa/Kampala",
    "iso:country":"UG",
    "name:ceb_x_preferred":[
        "Kanoni"
    ],
    "name:lug_x_preferred":[
        "Kanoni"
    ],
    "name:urd_x_preferred":[
        "\u06a9\u0627\u0646\u0648\u0646\u06cc"
    ],
    "wof:name":"Kanoni",
    "wof:placetype":"locality"
},
  "geometry": {"coordinates":[30.65806,-0.12028],"type":"Point"}
}