{
  "type": "Feature",
  "properties": {
    "gn:admin1_code":"N",
    "gn:admin2_code":"D1",
    "gn:admin3_code":"233569.0",
    "gn:admin4_code":"8658540.0",
    "gn:asciiname":"Koputh",
    "gn:country_code":"UG",
    "gn:dem":1415,
    "gn:feature_class":"P",
    "gn:feature_code":"PPL",
    "gn:name":"Koputh",
    "gn:population":0,
    "gn:timezone":"Africa/Kampala",
    "iso:country":"UG",
    "wof:name":"Koputh",
    "wof:placetype":"locality"
},
  "geometry": {"coordinates":[34.13417,3.33944],"type":"Point"}
}