{
  "type": "Feature",
  "properties": {
    "gn:admin1_code":"N",
    "gn:admin2_code":"72",
    "gn:admin3_code":"8644132.0",
    "gn:admin4_code":"7732530.0",
    "gn:asciiname":"Old Dufile",
    "gn:country_code":"UG",
    "gn:dem":615,
    "gn:feature_class":"P",
    "gn:feature_code":"PPL",
    "gn:name":"Old Dufile",
    "gn:population":0,
    "gn:timezone":"Africa/Kampala",
    "iso:country":"UG",
    "name:und_x_variant":[
        "Dufile Old Fort",
        "Old Dufile"
    ],
    "wof:name":"Old Dufile",
    "wof:placetype":"locality"
},
  "geometry": {"coordinates":[31.96667,3.56667],"type":"Point"}
}