{
  "type": "Feature",
  "properties": {
    "gn:admin1_code":"W",
    "gn:admin2_code":"79",
    "gn:asciiname":"Nyamaya",
    "gn:country_code":"UG",
    "gn:dem":1578,
    "gn:feature_class":"P",
    "gn:feature_code":"PPL",
    "gn:name":"Nyamaya",
    "gn:population":0,
    "gn:timezone":"Africa/Kampala",
    "iso:country":"UG",
    "name:eng_x_preferred":[
        "Nyamaya"
    ],
    "wof:name":"Nyamaya",
    "wof:placetype":"locality"
},
  "geometry": {"coordinates":[30.27332,0.71042],"type":"Point"}
}