{
  "type": "Feature",
  "properties": {
    "gn:admin1_code":"E",
    "gn:admin2_code":"78",
    "gn:admin3_code":"234502.0",
    "gn:admin4_code":"8658458.0",
    "gn:asciiname":"Lubira",
    "gn:country_code":"UG",
    "gn:dem":1081,
    "gn:feature_class":"P",
    "gn:feature_code":"PPL",
    "gn:name":"Lubira",
    "gn:population":0,
    "gn:timezone":"Africa/Kampala",
    "iso:country":"UG",
    "wof:name":"Lubira",
    "wof:placetype":"locality"
},
  "geometry": {"coordinates":[33.63191,0.70276],"type":"Point"}
}