{
  "type": "Feature",
  "properties": {
    "gn:admin1_code":"C",
    "gn:admin2_code":"70",
    "gn:admin3_code":"8644157.0",
    "gn:admin4_code":"8657739.0",
    "gn:asciiname":"Koko",
    "gn:country_code":"UG",
    "gn:dem":1120,
    "gn:feature_class":"P",
    "gn:feature_code":"PPL",
    "gn:name":"Koko",
    "gn:population":0,
    "gn:timezone":"Africa/Kampala",
    "iso:country":"UG",
    "wof:name":"Koko",
    "wof:placetype":"locality"
},
  "geometry": {"coordinates":[32.63333,0.61667],"type":"Point"}
}