{
  "type": "Feature",
  "properties": {
    "gn:admin1_code":"E",
    "gn:admin2_code":"E1",
    "gn:asciiname":"Nawansega",
    "gn:country_code":"UG",
    "gn:dem":1085,
    "gn:feature_class":"P",
    "gn:feature_code":"PPL",
    "gn:name":"Nawansega",
    "gn:population":0,
    "gn:timezone":"Africa/Kampala",
    "iso:country":"UG",
    "wof:name":"Nawansega",
    "wof:placetype":"locality"
},
  "geometry": {"coordinates":[33.5665,0.83192],"type":"Point"}
}