{
  "type": "Feature",
  "properties": {
    "gn:admin1_code":"E",
    "gn:admin2_code":"87",
    "gn:admin3_code":"7732903.0",
    "gn:admin4_code":"8658177.0",
    "gn:asciiname":"Busano",
    "gn:country_code":"UG",
    "gn:dem":1579,
    "gn:feature_class":"P",
    "gn:feature_code":"PPL",
    "gn:name":"Busano",
    "gn:population":0,
    "gn:timezone":"Africa/Kampala",
    "iso:country":"UG",
    "name:azb_x_preferred":[
        "\u0628\u0648\u0633\u0627\u0646\u0648"
    ],
    "name:bel_x_preferred":[
        "\u0411\u0443\u0437\u0430\u043d\u0430"
    ],
    "name:bul_x_preferred":[
        "\u0411\u0443\u0437\u0430\u043d\u043e"
    ],
    "name:ceb_x_preferred":[
        "Busano"
    ],
    "name:deu_x_preferred":[
        "Busano"
    ],
    "name:epo_x_preferred":[
        "Busano"
    ],
    "name:eus_x_preferred":[
        "Busano"
    ],
    "name:fas_x_preferred":[
        "\u0628\u0648\u0633\u0627\u0646\u0648"
    ],
    "name:fra_x_preferred":[
        "Busano"
    ],
    "name:hun_x_preferred":[
        "Busano"
    ],
    "name:hye_x_preferred":[
        "\u0532\u0578\u0582\u0566\u0561\u0576\u0578"
    ],
    "name:ind_x_preferred":[
        "Busano"
    ],
    "name:ita_x_preferred":[
        "Busano"
    ],
    "name:jpn_x_preferred":[
        "\u30d6\u30b6\u30fc\u30ce"
    ],
    "name:kaz_x_preferred":[
        "\u0411\u0443\u0437\u0430\u043d\u043e"
    ],
    "name:lat_x_preferred":[
        "Buxanum"
    ],
    "name:lmo_x_preferred":[
        "Busano"
    ],
    "name:msa_x_preferred":[
        "Busano"
    ],
    "name:nap_x_preferred":[
        "Busano"
    ],
    "name:nld_x_preferred":[
        "Busano"
    ],
    "name:pms_x_preferred":[
        "Busan"
    ],
    "name:pol_x_preferred":[
        "Busano"
    ],
    "name:por_x_preferred":[
        "Busano"
    ],
    "name:ron_x_preferred":[
        "Busano"
    ],
    "name:rus_x_preferred":[
        "\u0411\u0443\u0437\u0430\u043d\u043e"
    ],
    "name:scn_x_preferred":[
        "Busano"
    ],
    "name:spa_x_preferred":[
        "Busano"
    ],
    "name:srp_x_preferred":[
        "\u0411\u0443\u0437\u0430\u043d\u043e"
    ],
    "name:swe_x_preferred":[
        "Busano"
    ],
    "name:tgl_x_preferred":[
        "Busano"
    ],
    "name:ukr_x_preferred":[
        "\u0411\u0443\u0437\u0430\u043d\u043e"
    ],
    "name:uzb_x_preferred":[
        "Busano"
    ],
    "name:vie_x_preferred":[
        "Busano"
    ],
    "name:vol_x_preferred":[
        "Busano"
    ],
    "name:war_x_preferred":[
        "Busano"
    ],
    "name:zho_x_preferred":[
        "\u5e03\u8428\u8bfa"
    ],
    "wof:name":"Busano",
    "wof:placetype":"locality"
},
  "geometry": {"coordinates":[34.26667,1.01667],"type":"Point"}
}