{
  "type": "Feature",
  "properties": {
    "gn:admin1_code":"E",
    "gn:admin2_code":"87",
    "gn:admin3_code":"7732903.0",
    "gn:admin4_code":"8658177.0",
    "gn:asciiname":"Busano",
    "gn:country_code":"UG",
    "gn:dem":1579,
    "gn:feature_class":"P",
    "gn:feature_code":"PPL",
    "gn:name":"Busano",
    "gn:population":0,
    "gn:timezone":"Africa/Kampala",
    "iso:country":"UG",
    "wof:name":"Busano",
    "wof:placetype":"locality"
},
  "geometry": {"coordinates":[34.26667,1.01667],"type":"Point"}
}