{
  "type": "Feature",
  "properties": {
    "gn:admin1_code":"C",
    "gn:admin2_code":"F1",
    "gn:asciiname":"Sseta",
    "gn:country_code":"UG",
    "gn:dem":1246,
    "gn:feature_class":"P",
    "gn:feature_code":"PPL",
    "gn:name":"Sseta",
    "gn:population":0,
    "gn:timezone":"Africa/Kampala",
    "iso:country":"UG",
    "wof:name":"Sseta",
    "wof:placetype":"locality"
},
  "geometry": {"coordinates":[32.2531,0.26061],"type":"Point"}
}