{
  "type": "Feature",
  "properties": {
    "gn:admin1_code":"E",
    "gn:admin2_code":"76",
    "gn:asciiname":"Kamenya",
    "gn:country_code":"UG",
    "gn:dem":1308,
    "gn:feature_class":"P",
    "gn:feature_code":"PPL",
    "gn:name":"Kamenya",
    "gn:population":0,
    "gn:timezone":"Africa/Kampala",
    "iso:country":"UG",
    "name:eng_x_preferred":[
        "Kamenya"
    ],
    "wof:name":"Kamenya",
    "wof:placetype":"locality"
},
  "geometry": {"coordinates":[34.2784,0.72876],"type":"Point"}
}