{
  "type": "Feature",
  "properties": {
    "gn:admin1_code":"C",
    "gn:admin2_code":"83",
    "gn:asciiname":"Wantayi",
    "gn:country_code":"UG",
    "gn:dem":1127,
    "gn:feature_class":"P",
    "gn:feature_code":"PPL",
    "gn:name":"Wantayi",
    "gn:population":0,
    "gn:timezone":"Africa/Kampala",
    "iso:country":"UG",
    "wof:name":"Wantayi",
    "wof:placetype":"locality"
},
  "geometry": {"coordinates":[33.03097,0.53381],"type":"Point"}
}