{
  "type": "Feature",
  "properties": {
    "gn:admin1_code":"W",
    "gn:admin2_code":"82",
    "gn:admin3_code":"7732525.0",
    "gn:admin4_code":"8657584.0",
    "gn:asciiname":"Kirima",
    "gn:country_code":"UG",
    "gn:dem":1864,
    "gn:feature_class":"P",
    "gn:feature_code":"PPL",
    "gn:name":"Kirima",
    "gn:population":0,
    "gn:timezone":"Africa/Kampala",
    "iso:country":"UG",
    "wof:name":"Kirima",
    "wof:placetype":"locality"
},
  "geometry": {"coordinates":[29.78694,-0.9425],"type":"Point"}
}