{
  "type": "Feature",
  "properties": {
    "gn:admin1_code":"C",
    "gn:admin2_code":"96",
    "gn:admin3_code":"234053.0",
    "gn:admin4_code":"8658284.0",
    "gn:asciiname":"Bendegere",
    "gn:country_code":"UG",
    "gn:dem":1183,
    "gn:feature_class":"P",
    "gn:feature_code":"PPL",
    "gn:name":"Bendegere",
    "gn:population":0,
    "gn:timezone":"Africa/Kampala",
    "iso:country":"UG",
    "wof:name":"Bendegere",
    "wof:placetype":"locality"
},
  "geometry": {"coordinates":[32.52063,0.06191],"type":"Point"}
}