{
  "type": "Feature",
  "properties": {
    "gn:admin1_code":"E",
    "gn:admin2_code":"E1",
    "gn:admin3_code":"8644136.0",
    "gn:admin4_code":"8657858.0",
    "gn:asciiname":"Namalemba",
    "gn:country_code":"UG",
    "gn:dem":1100,
    "gn:feature_class":"P",
    "gn:feature_code":"PPL",
    "gn:name":"Namalemba",
    "gn:population":0,
    "gn:timezone":"Africa/Kampala",
    "iso:country":"UG",
    "wof:name":"Namalemba",
    "wof:placetype":"locality"
},
  "geometry": {"coordinates":[33.68704,0.92209],"type":"Point"}
}