{
  "type": "Feature",
  "properties": {
    "gn:admin1_code":"E",
    "gn:admin2_code":"76",
    "gn:admin3_code":"8644131.0",
    "gn:admin4_code":"8657528.0",
    "gn:asciiname":"Nyemera",
    "gn:country_code":"UG",
    "gn:dem":1109,
    "gn:feature_class":"P",
    "gn:feature_code":"PPL",
    "gn:name":"Nyemera",
    "gn:population":0,
    "gn:timezone":"Africa/Kampala",
    "iso:country":"UG",
    "wof:name":"Nyemera",
    "wof:placetype":"locality"
},
  "geometry": {"coordinates":[33.9605,0.61196],"type":"Point"}
}