{
  "type": "Feature",
  "properties": {
    "gn:admin1_code":"W",
    "gn:admin2_code":"40",
    "gn:admin3_code":"234040.0",
    "gn:admin4_code":"8657871.0",
    "gn:asciiname":"Chanjojo",
    "gn:country_code":"UG",
    "gn:dem":1257,
    "gn:feature_class":"P",
    "gn:feature_code":"PPL",
    "gn:name":"Chanjojo",
    "gn:population":0,
    "gn:timezone":"Africa/Kampala",
    "iso:country":"UG",
    "wof:name":"Chanjojo",
    "wof:placetype":"locality"
},
  "geometry": {"coordinates":[30.01667,0.18333],"type":"Point"}
}