{
  "type": "Feature",
  "properties": {
    "gn:admin1_code":"E",
    "gn:admin2_code":"C6",
    "gn:admin3_code":"234147.0",
    "gn:admin4_code":"8657812.0",
    "gn:asciiname":"Mutumba",
    "gn:country_code":"UG",
    "gn:dem":1154,
    "gn:feature_class":"P",
    "gn:feature_code":"PPL",
    "gn:name":"Mutumba",
    "gn:population":0,
    "gn:timezone":"Africa/Kampala",
    "iso:country":"UG",
    "name:eng_x_preferred":[
        "Mutumba"
    ],
    "wof:name":"Mutumba",
    "wof:placetype":"locality"
},
  "geometry": {"coordinates":[34.11465,0.97943],"type":"Point"}
}