{
  "type": "Feature",
  "properties": {
    "gn:admin1_code":"W",
    "gn:admin2_code":"41",
    "gn:admin3_code":"8644139.0",
    "gn:admin4_code":"8658061.0",
    "gn:asciiname":"Lutumba",
    "gn:country_code":"UG",
    "gn:dem":1210,
    "gn:feature_class":"P",
    "gn:feature_code":"PPL",
    "gn:name":"Lutumba",
    "gn:population":0,
    "gn:timezone":"Africa/Kampala",
    "iso:country":"UG",
    "wof:name":"Lutumba",
    "wof:placetype":"locality"
},
  "geometry": {"coordinates":[30.98333,0.85],"type":"Point"}
}