{
  "type": "Feature",
  "properties": {
    "gn:admin1_code":"E",
    "gn:admin2_code":"C6",
    "gn:asciiname":"Habiga",
    "gn:country_code":"UG",
    "gn:dem":1103,
    "gn:feature_class":"P",
    "gn:feature_code":"PPL",
    "gn:name":"Habiga",
    "gn:population":0,
    "gn:timezone":"Africa/Kampala",
    "iso:country":"UG",
    "wof:name":"Habiga",
    "wof:placetype":"locality"
},
  "geometry": {"coordinates":[33.86927,0.77737],"type":"Point"}
}