{
  "type": "Feature",
  "properties": {
    "gn:admin1_code":"C",
    "gn:admin2_code":"E7",
    "gn:asciiname":"Namaziba- Bukike",
    "gn:country_code":"UG",
    "gn:dem":1249,
    "gn:feature_class":"P",
    "gn:feature_code":"PPL",
    "gn:name":"Namaziba- Bukike",
    "gn:population":0,
    "gn:timezone":"Africa/Kampala",
    "iso:country":"UG",
    "name:eng_x_preferred":[
        "Namaziba- Bukike"
    ],
    "wof:name":"Namaziba- Bukike",
    "wof:placetype":"locality"
},
  "geometry": {"coordinates":[33.19418,0.37853],"type":"Point"}
}