{
  "type": "Feature",
  "properties": {
    "gn:admin1_code":"C",
    "gn:admin2_code":"F1",
    "gn:admin3_code":"234000.0",
    "gn:admin4_code":"8658117.0",
    "gn:asciiname":"Gwatiro",
    "gn:country_code":"UG",
    "gn:dem":1219,
    "gn:feature_class":"P",
    "gn:feature_code":"PPL",
    "gn:name":"Gwatiro",
    "gn:population":0,
    "gn:timezone":"Africa/Kampala",
    "iso:country":"UG",
    "wof:name":"Gwatiro",
    "wof:placetype":"locality"
},
  "geometry": {"coordinates":[32.1886,0.17916],"type":"Point"}
}