{
  "type": "Feature",
  "properties": {
    "gn:admin1_code":"E",
    "gn:admin2_code":"E1",
    "gn:asciiname":"Bulyowa",
    "gn:country_code":"UG",
    "gn:dem":1068,
    "gn:feature_class":"P",
    "gn:feature_code":"PPL",
    "gn:name":"Bulyowa",
    "gn:population":0,
    "gn:timezone":"Africa/Kampala",
    "iso:country":"UG",
    "wof:name":"Bulyowa",
    "wof:placetype":"locality"
},
  "geometry": {"coordinates":[33.58776,0.92987],"type":"Point"}
}