{
  "type": "Feature",
  "properties": {
    "gn:admin1_code":"C",
    "gn:admin2_code":"96",
    "gn:asciiname":"Koba",
    "gn:country_code":"UG",
    "gn:dem":1199,
    "gn:feature_class":"P",
    "gn:feature_code":"PPL",
    "gn:name":"Koba",
    "gn:population":0,
    "gn:timezone":"Africa/Kampala",
    "iso:country":"UG",
    "name:ceb_x_preferred":[
        "Koba"
    ],
    "name:deu_x_preferred":[
        "Koba"
    ],
    "name:fra_x_preferred":[
        "Koba"
    ],
    "name:ita_x_preferred":[
        "Koba"
    ],
    "name:nld_x_preferred":[
        "Koba"
    ],
    "name:rus_x_preferred":[
        "\u041a\u043e\u0431\u0430"
    ],
    "name:srp_x_preferred":[
        "\u041a\u043e\u0431\u0430"
    ],
    "name:swe_x_preferred":[
        "Koba"
    ],
    "wof:name":"Koba",
    "wof:placetype":"locality"
},
  "geometry": {"coordinates":[32.40362,0.16725],"type":"Point"}
}