{
  "type": "Feature",
  "properties": {
    "gn:admin1_code":"E",
    "gn:admin2_code":"76",
    "gn:asciiname":"Panyangasi",
    "gn:country_code":"UG",
    "gn:dem":1179,
    "gn:feature_class":"P",
    "gn:feature_code":"PPL",
    "gn:name":"Panyangasi",
    "gn:population":0,
    "gn:timezone":"Africa/Kampala",
    "iso:country":"UG",
    "name:eng_x_preferred":[
        "Panyangasi"
    ],
    "wof:name":"Panyangasi",
    "wof:placetype":"locality"
},
  "geometry": {"coordinates":[34.11124,0.70026],"type":"Point"}
}