{
  "type": "Feature",
  "properties": {
    "gn:admin1_code":"E",
    "gn:admin2_code":"G4",
    "gn:asciiname":"Bugabula",
    "gn:country_code":"UG",
    "gn:dem":1111,
    "gn:feature_class":"P",
    "gn:feature_code":"PPL",
    "gn:name":"Bugabula",
    "gn:population":0,
    "gn:timezone":"Africa/Kampala",
    "iso:country":"UG",
    "wof:name":"Bugabula",
    "wof:placetype":"locality"
},
  "geometry": {"coordinates":[33.36393,0.76194],"type":"Point"}
}