{
  "type": "Feature",
  "properties": {
    "gn:admin1_code":"E",
    "gn:admin2_code":"33",
    "gn:asciiname":"Bulugo",
    "gn:country_code":"UG",
    "gn:dem":1101,
    "gn:feature_class":"P",
    "gn:feature_code":"PPL",
    "gn:name":"Bulugo",
    "gn:population":0,
    "gn:timezone":"Africa/Kampala",
    "iso:country":"UG",
    "wof:name":"Bulugo",
    "wof:placetype":"locality"
},
  "geometry": {"coordinates":[33.2374,0.65016],"type":"Point"}
}