{
  "type": "Feature",
  "properties": {
    "gn:admin1_code":"E",
    "gn:admin2_code":"67",
    "gn:asciiname":"Hamasanja",
    "gn:country_code":"UG",
    "gn:dem":1114,
    "gn:feature_class":"P",
    "gn:feature_code":"PPL",
    "gn:name":"Hamasanja",
    "gn:population":0,
    "gn:timezone":"Africa/Kampala",
    "iso:country":"UG",
    "wof:name":"Hamasanja",
    "wof:placetype":"locality"
},
  "geometry": {"coordinates":[33.9711,0.54367],"type":"Point"}
}