{
  "type": "Feature",
  "properties": {
    "gn:admin1_code":"E",
    "gn:admin2_code":"80",
    "gn:admin3_code":"233018.0",
    "gn:admin4_code":"8658028.0",
    "gn:asciiname":"Olerai",
    "gn:country_code":"UG",
    "gn:dem":1061,
    "gn:feature_class":"P",
    "gn:feature_code":"PPLL",
    "gn:name":"Olerai",
    "gn:population":0,
    "gn:timezone":"Africa/Kampala",
    "iso:country":"UG",
    "wof:name":"Olerai",
    "wof:placetype":"locality"
},
  "geometry": {"coordinates":[33.26631,1.74855],"type":"Point"}
}