{
  "type": "Feature",
  "properties": {
    "gn:admin1_code":"E",
    "gn:admin2_code":"86",
    "gn:admin3_code":"8644164.0",
    "gn:admin4_code":"8658516.0",
    "gn:asciiname":"Matuba",
    "gn:country_code":"UG",
    "gn:dem":1177,
    "gn:feature_class":"P",
    "gn:feature_code":"PPL",
    "gn:name":"Matuba",
    "gn:population":0,
    "gn:timezone":"Africa/Kampala",
    "iso:country":"UG",
    "name:eng_x_preferred":[
        "Matuba"
    ],
    "wof:name":"Matuba",
    "wof:placetype":"locality"
},
  "geometry": {"coordinates":[33.56502,0.27311],"type":"Point"}
}