{
  "type": "Feature",
  "properties": {
    "gn:admin1_code":"N",
    "gn:admin2_code":"H7",
    "gn:admin3_code":"227147.0",
    "gn:admin4_code":"8261565.0",
    "gn:asciiname":"Okeyu",
    "gn:country_code":"UG",
    "gn:dem":1524,
    "gn:feature_class":"P",
    "gn:feature_code":"PPL",
    "gn:name":"Okeyu",
    "gn:population":0,
    "gn:timezone":"Africa/Kampala",
    "iso:country":"UG",
    "name:und_x_variant":[
        "Okeyo",
        "Okeyu"
    ],
    "wof:name":"Okeyu",
    "wof:placetype":"locality"
},
  "geometry": {"coordinates":[30.95411,2.41961],"type":"Point"}
}