{
  "type": "Feature",
  "properties": {
    "gn:admin1_code":"E",
    "gn:admin2_code":"67",
    "gn:admin3_code":"8644151.0",
    "gn:admin4_code":"8657980.0",
    "gn:asciiname":"Magale",
    "gn:country_code":"UG",
    "gn:dem":1110,
    "gn:feature_class":"P",
    "gn:feature_code":"PPL",
    "gn:name":"Magale",
    "gn:population":0,
    "gn:timezone":"Africa/Kampala",
    "iso:country":"UG",
    "name:eng_x_preferred":[
        "Magale"
    ],
    "wof:name":"Magale",
    "wof:placetype":"locality"
},
  "geometry": {"coordinates":[33.9191,0.46062],"type":"Point"}
}