{
  "type": "Feature",
  "properties": {
    "gn:admin1_code":"W",
    "gn:admin2_code":"31",
    "gn:admin3_code":"7732256.0",
    "gn:admin4_code":"8657597.0",
    "gn:asciiname":"Kyabisenywa",
    "gn:country_code":"UG",
    "gn:dem":1141,
    "gn:feature_class":"P",
    "gn:feature_code":"PPL",
    "gn:name":"Kyabisenywa",
    "gn:population":0,
    "gn:timezone":"Africa/Kampala",
    "iso:country":"UG",
    "wof:name":"Kyabisenywa",
    "wof:placetype":"locality"
},
  "geometry": {"coordinates":[31.44154,1.573],"type":"Point"}
}