{
  "type": "Feature",
  "properties": {
    "gn:admin1_code":"E",
    "gn:admin2_code":"76",
    "gn:asciiname":"Kandi",
    "gn:country_code":"UG",
    "gn:dem":1128,
    "gn:feature_class":"P",
    "gn:feature_code":"PPL",
    "gn:name":"Kandi",
    "gn:population":0,
    "gn:timezone":"Africa/Kampala",
    "iso:country":"UG",
    "name:ceb_x_preferred":[
        "Kandi"
    ],
    "name:deu_x_preferred":[
        "Kandi"
    ],
    "name:eng_x_preferred":[
        "Kandi"
    ],
    "name:fin_x_preferred":[
        "Kandi"
    ],
    "name:fra_x_preferred":[
        "Kandi"
    ],
    "name:hun_x_preferred":[
        "Kandi"
    ],
    "name:swe_x_preferred":[
        "Kandi"
    ],
    "wof:name":"Kandi",
    "wof:placetype":"locality"
},
  "geometry": {"coordinates":[34.02345,0.71168],"type":"Point"}
}