{
  "type": "Feature",
  "properties": {
    "gn:admin1_code":"E",
    "gn:admin2_code":"67",
    "gn:asciiname":"Buhoya",
    "gn:country_code":"UG",
    "gn:dem":1163,
    "gn:feature_class":"P",
    "gn:feature_code":"PPL",
    "gn:name":"Buhoya",
    "gn:population":0,
    "gn:timezone":"Africa/Kampala",
    "iso:country":"UG",
    "name:eng_x_preferred":[
        "Buhoya"
    ],
    "wof:name":"Buhoya",
    "wof:placetype":"locality"
},
  "geometry": {"coordinates":[34.03367,0.49837],"type":"Point"}
}