{
  "type": "Feature",
  "properties": {
    "gn:admin1_code":"E",
    "gn:admin2_code":"E1",
    "gn:asciiname":"Buyanga",
    "gn:country_code":"UG",
    "gn:dem":1131,
    "gn:feature_class":"P",
    "gn:feature_code":"PPL",
    "gn:name":"Buyanga",
    "gn:population":0,
    "gn:timezone":"Africa/Kampala",
    "iso:country":"UG",
    "wof:name":"Buyanga",
    "wof:placetype":"locality"
},
  "geometry": {"coordinates":[33.67173,0.81226],"type":"Point"}
}