{
  "type": "Feature",
  "properties": {
    "gn:admin1_code":"W",
    "gn:admin2_code":"82",
    "gn:admin3_code":"7732525.0",
    "gn:admin4_code":"8657786.0",
    "gn:asciiname":"Mafuga",
    "gn:country_code":"UG",
    "gn:dem":2403,
    "gn:feature_class":"P",
    "gn:feature_code":"PPL",
    "gn:name":"Mafuga",
    "gn:population":0,
    "gn:timezone":"Africa/Kampala",
    "iso:country":"UG",
    "wof:name":"Mafuga",
    "wof:placetype":"locality"
},
  "geometry": {"coordinates":[29.85,-1.01667],"type":"Point"}
}