{
  "type": "Feature",
  "properties": {
    "gn:admin1_code":"W",
    "gn:admin2_code":"28",
    "gn:asciiname":"Njanja",
    "gn:country_code":"UG",
    "gn:dem":907,
    "gn:feature_class":"P",
    "gn:feature_code":"PPL",
    "gn:name":"Njanja",
    "gn:population":0,
    "gn:timezone":"Africa/Kampala",
    "iso:country":"UG",
    "name:eng_x_preferred":[
        "Njanja"
    ],
    "wof:name":"Njanja",
    "wof:placetype":"locality"
},
  "geometry": {"coordinates":[29.99922,0.65902],"type":"Point"}
}