{
  "type": "Feature",
  "properties": {
    "gn:admin1_code":"E",
    "gn:admin2_code":"D6",
    "gn:asciiname":"Bunatoola",
    "gn:country_code":"UG",
    "gn:dem":1294,
    "gn:feature_class":"P",
    "gn:feature_code":"PPL",
    "gn:name":"Bunatoola",
    "gn:population":0,
    "gn:timezone":"Africa/Kampala",
    "iso:country":"UG",
    "name:eng_x_preferred":[
        "Bunatoola"
    ],
    "wof:name":"Bunatoola",
    "wof:placetype":"locality"
},
  "geometry": {"coordinates":[34.27867,0.91681],"type":"Point"}
}