{
  "type": "Feature",
  "properties": {
    "gn:admin1_code":"W",
    "gn:admin2_code":"I2",
    "gn:admin3_code":"8644161.0",
    "gn:admin4_code":"8658064.0",
    "gn:asciiname":"Kijaguza",
    "gn:country_code":"UG",
    "gn:dem":1194,
    "gn:feature_class":"P",
    "gn:feature_code":"PPL",
    "gn:name":"Kijaguza",
    "gn:population":0,
    "gn:timezone":"Africa/Kampala",
    "iso:country":"UG",
    "wof:name":"Kijaguza",
    "wof:placetype":"locality"
},
  "geometry": {"coordinates":[31.16667,0.93333],"type":"Point"}
}