{
  "type": "Feature",
  "properties": {
    "gn:admin1_code":"W",
    "gn:admin2_code":"G6",
    "gn:admin3_code":"7869954.0",
    "gn:admin4_code":"8657722.0",
    "gn:asciiname":"Nyakashojwa",
    "gn:country_code":"UG",
    "gn:dem":1567,
    "gn:feature_class":"P",
    "gn:feature_code":"PPL",
    "gn:name":"Nyakashojwa",
    "gn:population":0,
    "gn:timezone":"Africa/Kampala",
    "iso:country":"UG",
    "wof:name":"Nyakashojwa",
    "wof:placetype":"locality"
},
  "geometry": {"coordinates":[30.02542,-0.50657],"type":"Point"}
}