{
  "type": "Feature",
  "properties": {
    "gn:admin1_code":"C",
    "gn:admin2_code":"E7",
    "gn:asciiname":"Byabuku",
    "gn:country_code":"UG",
    "gn:dem":1168,
    "gn:feature_class":"P",
    "gn:feature_code":"PPL",
    "gn:name":"Byabuku",
    "gn:population":0,
    "gn:timezone":"Africa/Kampala",
    "iso:country":"UG",
    "wof:name":"Byabuku",
    "wof:placetype":"locality"
},
  "geometry": {"coordinates":[33.03544,0.50297],"type":"Point"}
}