{
  "type": "Feature",
  "properties": {
    "gn:admin1_code":"N",
    "gn:admin2_code":"58",
    "gn:admin3_code":"8080237.0",
    "gn:admin4_code":"8657629.0",
    "gn:asciiname":"Ayombra",
    "gn:country_code":"UG",
    "gn:dem":1219,
    "gn:feature_class":"P",
    "gn:feature_code":"PPL",
    "gn:name":"Ayombra",
    "gn:population":0,
    "gn:timezone":"Africa/Kampala",
    "iso:country":"UG",
    "wof:name":"Ayombra",
    "wof:placetype":"locality"
},
  "geometry": {"coordinates":[31.16233,2.40153],"type":"Point"}
}