{
  "type": "Feature",
  "properties": {
    "gn:admin1_code":"E",
    "gn:admin2_code":"67",
    "gn:asciiname":"Lulonda",
    "gn:country_code":"UG",
    "gn:dem":1169,
    "gn:feature_class":"P",
    "gn:feature_code":"PPL",
    "gn:name":"Lulonda",
    "gn:population":0,
    "gn:timezone":"Africa/Kampala",
    "iso:country":"UG",
    "wof:name":"Lulonda",
    "wof:placetype":"locality"
},
  "geometry": {"coordinates":[33.93133,0.50615],"type":"Point"}
}