{
  "type": "Feature",
  "properties": {
    "gn:admin1_code":"N",
    "gn:admin2_code":"84",
    "gn:admin3_code":"233642.0",
    "gn:admin4_code":"8658649.0",
    "gn:asciiname":"Loini",
    "gn:country_code":"UG",
    "gn:dem":1044,
    "gn:feature_class":"P",
    "gn:feature_code":"PPL",
    "gn:name":"Loini",
    "gn:population":0,
    "gn:timezone":"Africa/Kampala",
    "iso:country":"UG",
    "wof:name":"Loini",
    "wof:placetype":"locality"
},
  "geometry": {"coordinates":[33.52859,3.62343],"type":"Point"}
}