{
  "type": "Feature",
  "properties": {
    "gn:admin1_code":"E",
    "gn:admin2_code":"G7",
    "gn:admin3_code":"8644167.0",
    "gn:admin4_code":"8657679.0",
    "gn:asciiname":"Nsimbirano",
    "gn:country_code":"UG",
    "gn:dem":1170,
    "gn:feature_class":"P",
    "gn:feature_code":"PPL",
    "gn:name":"Nsimbirano",
    "gn:population":0,
    "gn:timezone":"Africa/Kampala",
    "iso:country":"UG",
    "name:eng_x_preferred":[
        "Nsimbirano"
    ],
    "wof:name":"Nsimbirano",
    "wof:placetype":"locality"
},
  "geometry": {"coordinates":[33.79204,0.41962],"type":"Point"}
}