{
  "type": "Feature",
  "properties": {
    "gn:admin1_code":"W",
    "gn:admin2_code":"C8",
    "gn:admin3_code":"7732900.0",
    "gn:admin4_code":"7732408.0",
    "gn:asciiname":"Kigunga",
    "gn:country_code":"UG",
    "gn:dem":1481,
    "gn:feature_class":"P",
    "gn:feature_code":"PPL",
    "gn:name":"Kigunga",
    "gn:population":0,
    "gn:timezone":"Africa/Kampala",
    "iso:country":"UG",
    "wof:name":"Kigunga",
    "wof:placetype":"locality"
},
  "geometry": {"coordinates":[30.46667,-0.23333],"type":"Point"}
}