{
  "type": "Feature",
  "properties": {
    "gn:admin1_code":"E",
    "gn:admin2_code":"66",
    "gn:asciiname":"Luwoko",
    "gn:country_code":"UG",
    "gn:dem":1129,
    "gn:feature_class":"P",
    "gn:feature_code":"PPL",
    "gn:name":"Luwoko",
    "gn:population":0,
    "gn:timezone":"Africa/Kampala",
    "iso:country":"UG",
    "wof:name":"Luwoko",
    "wof:placetype":"locality"
},
  "geometry": {"coordinates":[33.66075,0.52201],"type":"Point"}
}