{
  "type": "Feature",
  "properties": {
    "gn:admin1_code":"N",
    "gn:admin2_code":"30",
    "gn:admin3_code":"235009.0",
    "gn:admin4_code":"8657917.0",
    "gn:asciiname":"Pongdwongo",
    "gn:country_code":"UG",
    "gn:dem":1092,
    "gn:feature_class":"P",
    "gn:feature_code":"PPL",
    "gn:name":"Pongdwongo",
    "gn:population":0,
    "gn:timezone":"Africa/Kampala",
    "iso:country":"UG",
    "wof:name":"Pongdwongo",
    "wof:placetype":"locality"
},
  "geometry": {"coordinates":[32.32463,2.81354],"type":"Point"}
}