{
  "type": "Feature",
  "properties": {
    "gn:admin1_code":"C",
    "gn:admin2_code":"I3",
    "gn:admin3_code":"8644144.0",
    "gn:admin4_code":"8658202.0",
    "gn:asciiname":"Lwagulwe",
    "gn:country_code":"UG",
    "gn:dem":1208,
    "gn:feature_class":"P",
    "gn:feature_code":"PPL",
    "gn:name":"Lwagulwe",
    "gn:population":0,
    "gn:timezone":"Africa/Kampala",
    "iso:country":"UG",
    "wof:name":"Lwagulwe",
    "wof:placetype":"locality"
},
  "geometry": {"coordinates":[31.68333,-0.58333],"type":"Point"}
}