{
  "type": "Feature",
  "properties": {
    "gn:admin1_code":"E",
    "gn:admin2_code":"78",
    "gn:asciiname":"Wairagala",
    "gn:country_code":"UG",
    "gn:dem":1112,
    "gn:feature_class":"P",
    "gn:feature_code":"PPL",
    "gn:name":"Wairagala",
    "gn:population":0,
    "gn:timezone":"Africa/Kampala",
    "iso:country":"UG",
    "wof:name":"Wairagala",
    "wof:placetype":"locality"
},
  "geometry": {"coordinates":[33.57261,0.64057],"type":"Point"}
}