{
  "type": "Feature",
  "properties": {
    "gn:admin1_code":"C",
    "gn:admin2_code":"I3",
    "gn:admin3_code":"8644144.0",
    "gn:admin4_code":"8658249.0",
    "gn:asciiname":"Makondo",
    "gn:cc2":"UG",
    "gn:country_code":"UG",
    "gn:dem":1202,
    "gn:feature_class":"P",
    "gn:feature_code":"PPL",
    "gn:name":"Makondo",
    "gn:population":0,
    "gn:timezone":"Africa/Kampala",
    "iso:country":"UG",
    "name:und_x_variant":[
        "Makando",
        "Makondo"
    ],
    "wof:name":"Makondo",
    "wof:placetype":"locality"
},
  "geometry": {"coordinates":[31.59361,-0.43917],"type":"Point"}
}