{
  "type": "Feature",
  "properties": {
    "gn:admin1_code":"N",
    "gn:admin2_code":"B9",
    "gn:admin3_code":"231253.0",
    "gn:admin4_code":"8629919.0",
    "gn:asciiname":"Patiko",
    "gn:country_code":"UG",
    "gn:dem":1033,
    "gn:feature_class":"P",
    "gn:feature_code":"PPL",
    "gn:name":"Patiko",
    "gn:population":0,
    "gn:timezone":"Africa/Kampala",
    "iso:country":"UG",
    "wof:name":"Patiko",
    "wof:placetype":"locality"
},
  "geometry": {"coordinates":[32.1382,2.94797],"type":"Point"}
}