{
  "type": "Feature",
  "properties": {
    "gn:admin1_code":"N",
    "gn:admin2_code":"47",
    "gn:admin3_code":"7732230.0",
    "gn:admin4_code":"8657998.0",
    "gn:asciiname":"Central",
    "gn:country_code":"UG",
    "gn:dem":1112,
    "gn:feature_class":"P",
    "gn:feature_code":"PPL",
    "gn:name":"Central",
    "gn:population":0,
    "gn:timezone":"Africa/Kampala",
    "iso:country":"UG",
    "name:ceb_x_preferred":[
        "Central"
    ],
    "name:deu_x_preferred":[
        "Central"
    ],
    "name:est_x_preferred":[
        "Central"
    ],
    "name:fas_x_preferred":[
        "\u0645\u0631\u06a9\u0632\u06cc"
    ],
    "name:fra_x_preferred":[
        "Central"
    ],
    "name:ita_x_preferred":[
        "Central"
    ],
    "name:jpn_x_preferred":[
        "\u30bb\u30f3\u30c8\u30e9\u30eb"
    ],
    "name:kor_x_preferred":[
        "\uc13c\ud2b8\ub7f4"
    ],
    "name:nld_x_preferred":[
        "Central"
    ],
    "name:pol_x_preferred":[
        "Central"
    ],
    "name:por_x_preferred":[
        "Central"
    ],
    "name:rus_x_preferred":[
        "\u0426\u0435\u043d\u0442\u0440\u0430\u043b\u044c"
    ],
    "name:slk_x_preferred":[
        "Centr\u00e1l"
    ],
    "name:spa_x_preferred":[
        "Central"
    ],
    "name:swe_x_preferred":[
        "Central"
    ],
    "name:tam_x_preferred":[
        "\u0b9a\u0bc6\u0ba9\u0bcd\u0b9f\u0bcd\u0bb0\u0bb2\u0bcd"
    ],
    "name:tha_x_preferred":[
        "\u0e01\u0e25\u0e32\u0e07"
    ],
    "name:ukr_x_preferred":[
        "\u0421\u0435\u043d\u0442\u0440\u0430\u043b"
    ],
    "name:vol_x_preferred":[
        "Central"
    ],
    "name:zho_x_preferred":[
        "\u4e2d"
    ],
    "wof:name":"Central",
    "wof:placetype":"locality"
},
  "geometry": {"coordinates":[32.89646,2.23722],"type":"Point"}
}