{
  "type": "Feature",
  "properties": {
    "gn:admin1_code":"N",
    "gn:admin2_code":"47",
    "gn:admin3_code":"7732230.0",
    "gn:admin4_code":"8657998.0",
    "gn:asciiname":"Central",
    "gn:country_code":"UG",
    "gn:dem":1112,
    "gn:feature_class":"P",
    "gn:feature_code":"PPL",
    "gn:name":"Central",
    "gn:population":0,
    "gn:timezone":"Africa/Kampala",
    "iso:country":"UG",
    "wof:name":"Central",
    "wof:placetype":"locality"
},
  "geometry": {"coordinates":[32.89646,2.23722],"type":"Point"}
}