{
  "type": "Feature",
  "properties": {
    "gn:admin1_code":"W",
    "gn:admin2_code":"79",
    "gn:asciiname":"Kiseru",
    "gn:country_code":"UG",
    "gn:dem":1576,
    "gn:feature_class":"P",
    "gn:feature_code":"PPL",
    "gn:name":"Kiseru",
    "gn:population":0,
    "gn:timezone":"Africa/Kampala",
    "iso:country":"UG",
    "name:eng_x_preferred":[
        "Kiseru"
    ],
    "wof:name":"Kiseru",
    "wof:placetype":"locality"
},
  "geometry": {"coordinates":[30.20648,0.63047],"type":"Point"}
}