{
  "type": "Feature",
  "properties": {
    "gn:admin1_code":"C",
    "gn:admin2_code":"96",
    "gn:admin3_code":"7732385.0",
    "gn:admin4_code":"8658187.0",
    "gn:asciiname":"Nabwojo",
    "gn:country_code":"UG",
    "gn:dem":1198,
    "gn:feature_class":"P",
    "gn:feature_code":"PPL",
    "gn:name":"Nabwojo",
    "gn:population":0,
    "gn:timezone":"Africa/Kampala",
    "iso:country":"UG",
    "wof:name":"Nabwojo",
    "wof:placetype":"locality"
},
  "geometry": {"coordinates":[32.6579,0.39023],"type":"Point"}
}