{
  "type": "Feature",
  "properties": {
    "gn:admin1_code":"C",
    "gn:admin2_code":"D5",
    "gn:admin3_code":"232958.0",
    "gn:admin4_code":"8658724.0",
    "gn:asciiname":"Mpumude",
    "gn:country_code":"UG",
    "gn:dem":1305,
    "gn:feature_class":"P",
    "gn:feature_code":"PPL",
    "gn:name":"Mpumude",
    "gn:population":0,
    "gn:timezone":"Africa/Kampala",
    "iso:country":"UG",
    "wof:name":"Mpumude",
    "wof:placetype":"locality"
},
  "geometry": {"coordinates":[31.15,-0.36667],"type":"Point"}
}