{
  "type": "Feature",
  "properties": {
    "gn:admin1_code":"E",
    "gn:admin2_code":"D6",
    "gn:asciiname":"Bumulika",
    "gn:country_code":"UG",
    "gn:dem":1365,
    "gn:feature_class":"P",
    "gn:feature_code":"PPL",
    "gn:name":"Bumulika",
    "gn:population":0,
    "gn:timezone":"Africa/Kampala",
    "iso:country":"UG",
    "name:eng_x_preferred":[
        "Bumulika"
    ],
    "wof:name":"Bumulika",
    "wof:placetype":"locality"
},
  "geometry": {"coordinates":[34.30211,0.78219],"type":"Point"}
}