{
  "type": "Feature",
  "properties": {
    "gn:admin1_code":"E",
    "gn:admin2_code":"D6",
    "gn:asciiname":"Bukisasaati",
    "gn:country_code":"UG",
    "gn:dem":1483,
    "gn:feature_class":"P",
    "gn:feature_code":"PPL",
    "gn:name":"Bukisasaati",
    "gn:population":0,
    "gn:timezone":"Africa/Kampala",
    "iso:country":"UG",
    "name:eng_x_preferred":[
        "Bukisasaati"
    ],
    "wof:name":"Bukisasaati",
    "wof:placetype":"locality"
},
  "geometry": {"coordinates":[34.38154,0.85264],"type":"Point"}
}