{
  "type": "Feature",
  "properties": {
    "gn:admin1_code":"C",
    "gn:admin2_code":"56",
    "gn:admin3_code":"8644175.0",
    "gn:admin4_code":"8658719.0",
    "gn:asciiname":"Gogonya",
    "gn:country_code":"UG",
    "gn:dem":1179,
    "gn:feature_class":"P",
    "gn:feature_code":"PPL",
    "gn:name":"Gogonya",
    "gn:population":0,
    "gn:timezone":"Africa/Kampala",
    "iso:country":"UG",
    "wof:name":"Gogonya",
    "wof:placetype":"locality"
},
  "geometry": {"coordinates":[31.95,0.45],"type":"Point"}
}