{
  "type": "Feature",
  "properties": {
    "gn:admin1_code":"E",
    "gn:admin2_code":"66",
    "gn:asciiname":"Bufunda",
    "gn:country_code":"UG",
    "gn:dem":1087,
    "gn:feature_class":"P",
    "gn:feature_code":"PPL",
    "gn:name":"Bufunda",
    "gn:population":0,
    "gn:timezone":"Africa/Kampala",
    "iso:country":"UG",
    "wof:name":"Bufunda",
    "wof:placetype":"locality"
},
  "geometry": {"coordinates":[33.87018,0.59705],"type":"Point"}
}