{
  "type": "Feature",
  "properties": {
    "gn:admin1_code":"E",
    "gn:admin2_code":"76",
    "gn:asciiname":"Kateki",
    "gn:country_code":"UG",
    "gn:dem":1218,
    "gn:feature_class":"P",
    "gn:feature_code":"PPL",
    "gn:name":"Kateki",
    "gn:population":0,
    "gn:timezone":"Africa/Kampala",
    "iso:country":"UG",
    "name:eng_x_preferred":[
        "Kateki"
    ],
    "wof:name":"Kateki",
    "wof:placetype":"locality"
},
  "geometry": {"coordinates":[34.21039,0.7807],"type":"Point"}
}