{
  "type": "Feature",
  "properties": {
    "gn:admin1_code":"W",
    "gn:admin2_code":"50",
    "gn:admin3_code":"8644129.0",
    "gn:admin4_code":"8657798.0",
    "gn:asciiname":"Kidoma",
    "gn:country_code":"UG",
    "gn:dem":1100,
    "gn:feature_class":"P",
    "gn:feature_code":"PPL",
    "gn:name":"Kidoma",
    "gn:population":0,
    "gn:timezone":"Africa/Kampala",
    "iso:country":"UG",
    "wof:name":"Kidoma",
    "wof:placetype":"locality"
},
  "geometry": {"coordinates":[31.81404,1.71397],"type":"Point"}
}