{
  "type": "Feature",
  "properties": {
    "gn:admin1_code":"W",
    "gn:admin2_code":"28",
    "gn:asciiname":"Mamirimi",
    "gn:country_code":"UG",
    "gn:dem":659,
    "gn:feature_class":"P",
    "gn:feature_code":"PPL",
    "gn:name":"Mamirimi",
    "gn:population":0,
    "gn:timezone":"Africa/Kampala",
    "iso:country":"UG",
    "name:eng_x_preferred":[
        "Mamirimi"
    ],
    "wof:name":"Mamirimi",
    "wof:placetype":"locality"
},
  "geometry": {"coordinates":[30.08045,0.87809],"type":"Point"}
}