{
  "type": "Feature",
  "properties": {
    "gn:admin1_code":"W",
    "gn:admin2_code":"43",
    "gn:admin3_code":"7874701.0",
    "gn:admin4_code":"8657636.0",
    "gn:asciiname":"Nyalutembe",
    "gn:country_code":"UG",
    "gn:dem":1622,
    "gn:feature_class":"P",
    "gn:feature_code":"PPL",
    "gn:name":"Nyalutembe",
    "gn:population":0,
    "gn:timezone":"Africa/Kampala",
    "iso:country":"UG",
    "wof:name":"Nyalutembe",
    "wof:placetype":"locality"
},
  "geometry": {"coordinates":[29.58333,-1.13333],"type":"Point"}
}