{
  "type": "Feature",
  "properties": {
    "gn:admin1_code":"N",
    "gn:admin2_code":"H7",
    "gn:admin3_code":"227147.0",
    "gn:admin4_code":"8657635.0",
    "gn:asciiname":"Pei",
    "gn:country_code":"UG",
    "gn:dem":1568,
    "gn:feature_class":"P",
    "gn:feature_code":"PPL",
    "gn:name":"Pei",
    "gn:population":0,
    "gn:timezone":"Africa/Kampala",
    "iso:country":"UG",
    "wof:name":"Pei",
    "wof:placetype":"locality"
},
  "geometry": {"coordinates":[30.95629000000001,2.4587],"type":"Point"}
}