{
  "type": "Feature",
  "properties": {
    "gn:admin1_code":"W",
    "gn:admin2_code":"34",
    "gn:admin3_code":"227915.0",
    "gn:admin4_code":"8657934.0",
    "gn:asciiname":"Bugarama",
    "gn:country_code":"UG",
    "gn:dem":1803,
    "gn:feature_class":"P",
    "gn:feature_code":"PPL",
    "gn:name":"Bugarama",
    "gn:population":0,
    "gn:timezone":"Africa/Kampala",
    "iso:country":"UG",
    "wof:name":"Bugarama",
    "wof:placetype":"locality"
},
  "geometry": {"coordinates":[30.08333,-1.25],"type":"Point"}
}