{
  "type": "Feature",
  "properties": {
    "gn:admin1_code":"C",
    "gn:admin2_code":"73",
    "gn:admin3_code":"234123.0",
    "gn:admin4_code":"8657970.0",
    "gn:asciiname":"Mwalamba",
    "gn:country_code":"UG",
    "gn:dem":1069,
    "gn:feature_class":"P",
    "gn:feature_code":"PPL",
    "gn:name":"Mwalamba",
    "gn:population":0,
    "gn:timezone":"Africa/Kampala",
    "iso:country":"UG",
    "wof:name":"Mwalamba",
    "wof:placetype":"locality"
},
  "geometry": {"coordinates":[32.29575,1.49259],"type":"Point"}
}