{
  "type": "Feature",
  "properties": {
    "gn:admin1_code":"C",
    "gn:admin2_code":"89",
    "gn:asciiname":"Ndugu",
    "gn:country_code":"UG",
    "gn:dem":1218,
    "gn:feature_class":"P",
    "gn:feature_code":"PPL",
    "gn:name":"Ndugu",
    "gn:population":0,
    "gn:timezone":"Africa/Kampala",
    "iso:country":"UG",
    "wof:name":"Ndugu",
    "wof:placetype":"locality"
},
  "geometry": {"coordinates":[32.28167,0.2074],"type":"Point"}
}