{
  "type": "Feature",
  "properties": {
    "gn:admin1_code":"C",
    "gn:admin2_code":"F2",
    "gn:admin3_code":"233919.0",
    "gn:admin4_code":"8658076.0",
    "gn:asciiname":"Lwaji",
    "gn:country_code":"UG",
    "gn:dem":1184,
    "gn:feature_class":"P",
    "gn:feature_code":"PPL",
    "gn:name":"Lwaji",
    "gn:population":0,
    "gn:timezone":"Africa/Kampala",
    "iso:country":"UG",
    "wof:name":"Lwaji",
    "wof:placetype":"locality"
},
  "geometry": {"coordinates":[32.90912,0.00841],"type":"Point"}
}