{
  "type": "Feature",
  "properties": {
    "gn:admin1_code":"W",
    "gn:admin2_code":"H8",
    "gn:admin3_code":"234153.0",
    "gn:admin4_code":"8658611.0",
    "gn:asciiname":"Kasenda",
    "gn:country_code":"UG",
    "gn:dem":1379,
    "gn:feature_class":"P",
    "gn:feature_code":"PPL",
    "gn:name":"Kasenda",
    "gn:population":0,
    "gn:timezone":"Africa/Kampala",
    "iso:country":"UG",
    "wof:name":"Kasenda",
    "wof:placetype":"locality"
},
  "geometry": {"coordinates":[30.27222,0.48056],"type":"Point"}
}