{
  "type": "Feature",
  "properties": {
    "gn:admin1_code":"C",
    "gn:admin2_code":"D5",
    "gn:admin3_code":"232958.0",
    "gn:admin4_code":"8658140.0",
    "gn:asciiname":"Lwentondo",
    "gn:country_code":"UG",
    "gn:dem":1309,
    "gn:feature_class":"P",
    "gn:feature_code":"PPL",
    "gn:name":"Lwentondo",
    "gn:population":0,
    "gn:timezone":"Africa/Kampala",
    "iso:country":"UG",
    "wof:name":"Lwentondo",
    "wof:placetype":"locality"
},
  "geometry": {"coordinates":[31.18333,-0.25],"type":"Point"}
}