{
  "type": "Feature",
  "properties": {
    "gn:admin1_code":"C",
    "gn:admin2_code":"89",
    "gn:asciiname":"Masaka",
    "gn:country_code":"UG",
    "gn:dem":1184,
    "gn:feature_class":"P",
    "gn:feature_code":"PPL",
    "gn:name":"Masaka",
    "gn:population":0,
    "gn:timezone":"Africa/Kampala",
    "iso:country":"UG",
    "name:ceb_x_preferred":[
        "Masaka"
    ],
    "name:dan_x_preferred":[
        "Masaka"
    ],
    "name:deu_x_preferred":[
        "Masaka"
    ],
    "name:fra_x_preferred":[
        "Masaka"
    ],
    "name:hrv_x_preferred":[
        "Masaka"
    ],
    "name:hun_x_preferred":[
        "Masaka"
    ],
    "name:ita_x_preferred":[
        "Masaka"
    ],
    "name:jpn_x_preferred":[
        "\u30de\u30b5\u30ab"
    ],
    "name:lit_x_preferred":[
        "Masaka"
    ],
    "name:lug_x_preferred":[
        "Masaka"
    ],
    "name:nld_x_preferred":[
        "Masaka"
    ],
    "name:pol_x_preferred":[
        "Masaka"
    ],
    "name:ron_x_preferred":[
        "Masaka"
    ],
    "name:rus_x_preferred":[
        "\u041c\u0430\u0441\u0430\u043a\u0430"
    ],
    "name:spa_x_preferred":[
        "Masaka"
    ],
    "name:swa_x_preferred":[
        "Masaka"
    ],
    "name:swe_x_preferred":[
        "Masaka"
    ],
    "wof:name":"Masaka",
    "wof:placetype":"locality"
},
  "geometry": {"coordinates":[32.24279,0.08185],"type":"Point"}
}