{
  "type": "Feature",
  "properties": {
    "gn:admin1_code":"C",
    "gn:admin2_code":"89",
    "gn:asciiname":"Masaka",
    "gn:country_code":"UG",
    "gn:dem":1184,
    "gn:feature_class":"P",
    "gn:feature_code":"PPL",
    "gn:name":"Masaka",
    "gn:population":0,
    "gn:timezone":"Africa/Kampala",
    "iso:country":"UG",
    "wof:name":"Masaka",
    "wof:placetype":"locality"
},
  "geometry": {"coordinates":[32.24279,0.08185],"type":"Point"}
}