{
  "type": "Feature",
  "properties": {
    "gn:admin1_code":"E",
    "gn:admin2_code":"B8",
    "gn:admin3_code":"235185.0",
    "gn:admin4_code":"8657999.0",
    "gn:asciiname":"Ochal",
    "gn:country_code":"UG",
    "gn:dem":1072,
    "gn:feature_class":"P",
    "gn:feature_code":"PPL",
    "gn:name":"Ochal",
    "gn:population":0,
    "gn:timezone":"Africa/Kampala",
    "iso:country":"UG",
    "wof:name":"Ochal",
    "wof:placetype":"locality"
},
  "geometry": {"coordinates":[33.867,1.93099],"type":"Point"}
}