{
  "type": "Feature",
  "properties": {
    "gn:admin1_code":"E",
    "gn:admin2_code":"78",
    "gn:admin3_code":"234502.0",
    "gn:admin4_code":"8643426.0",
    "gn:asciiname":"Bukowe",
    "gn:country_code":"UG",
    "gn:dem":1228,
    "gn:feature_class":"P",
    "gn:feature_code":"PPL",
    "gn:name":"Bukowe",
    "gn:population":0,
    "gn:timezone":"Africa/Kampala",
    "iso:country":"UG",
    "name:azb_x_preferred":[
        "\u0628\u0648\u06a9\u0648\u0648\u0647"
    ],
    "name:eng_x_preferred":[
        "Bukowe"
    ],
    "name:fas_x_preferred":[
        "\u0628\u0648\u06a9\u0648\u0648\u0647"
    ],
    "name:fra_x_preferred":[
        "Bukowe"
    ],
    "name:pol_x_preferred":[
        "Bukowe"
    ],
    "name:ukr_x_preferred":[
        "\u0411\u0443\u043a\u043e\u0432\u0435"
    ],
    "wof:name":"Bukowe",
    "wof:placetype":"locality"
},
  "geometry": {"coordinates":[33.5935,0.47496],"type":"Point"}
}