{
  "type": "Feature",
  "properties": {
    "gn:admin1_code":"N",
    "gn:admin2_code":"77",
    "gn:admin3_code":"8644146.0",
    "gn:admin4_code":"8657958.0",
    "gn:asciiname":"Osiya",
    "gn:country_code":"UG",
    "gn:dem":920,
    "gn:feature_class":"P",
    "gn:feature_code":"PPL",
    "gn:name":"Osiya",
    "gn:population":0,
    "gn:timezone":"Africa/Kampala",
    "iso:country":"UG",
    "wof:name":"Osiya",
    "wof:placetype":"locality"
},
  "geometry": {"coordinates":[31.11661,2.60537],"type":"Point"}
}