{
  "type": "Feature",
  "properties": {
    "gn:admin1_code":"N",
    "gn:admin2_code":"H7",
    "gn:admin3_code":"227147.0",
    "gn:admin4_code":"8658461.0",
    "gn:asciiname":"Ezoo",
    "gn:country_code":"UG",
    "gn:dem":1522,
    "gn:feature_class":"P",
    "gn:feature_code":"PPL",
    "gn:name":"Ezoo",
    "gn:population":0,
    "gn:timezone":"Africa/Kampala",
    "iso:country":"UG",
    "wof:name":"Ezoo",
    "wof:placetype":"locality"
},
  "geometry": {"coordinates":[30.81592,2.64728],"type":"Point"}
}