{
  "type": "Feature",
  "properties": {
    "gn:admin1_code":"E",
    "gn:admin2_code":"76",
    "gn:asciiname":"Akadot",
    "gn:country_code":"UG",
    "gn:dem":1181,
    "gn:feature_class":"P",
    "gn:feature_code":"PPL",
    "gn:name":"Akadot",
    "gn:population":0,
    "gn:timezone":"Africa/Kampala",
    "iso:country":"UG",
    "name:eng_x_preferred":[
        "Akadot"
    ],
    "wof:name":"Akadot",
    "wof:placetype":"locality"
},
  "geometry": {"coordinates":[34.14113,0.76933],"type":"Point"}
}