{
  "type": "Feature",
  "properties": {
    "gn:admin1_code":"E",
    "gn:admin2_code":"B8",
    "gn:admin3_code":"235185.0",
    "gn:admin4_code":"8657827.0",
    "gn:asciiname":"Angorom",
    "gn:country_code":"UG",
    "gn:dem":1156,
    "gn:feature_class":"P",
    "gn:feature_code":"PPL",
    "gn:name":"Angorom",
    "gn:population":0,
    "gn:timezone":"Africa/Kampala",
    "iso:country":"UG",
    "wof:name":"Angorom",
    "wof:placetype":"locality"
},
  "geometry": {"coordinates":[33.56667,2.05],"type":"Point"}
}