{
  "type": "Feature",
  "properties": {
    "gn:admin1_code":"E",
    "gn:admin2_code":"39",
    "gn:admin3_code":"7870033.0",
    "gn:admin4_code":"8658642.0",
    "gn:asciiname":"Kiguli",
    "gn:country_code":"UG",
    "gn:dem":1496,
    "gn:feature_class":"P",
    "gn:feature_code":"PPL",
    "gn:name":"Kiguli",
    "gn:population":0,
    "gn:timezone":"Africa/Kampala",
    "iso:country":"UG",
    "wof:name":"Kiguli",
    "wof:placetype":"locality"
},
  "geometry": {"coordinates":[34.35,1.33333],"type":"Point"}
}