{
  "type": "Feature",
  "properties": {
    "gn:admin1_code":"E",
    "gn:admin2_code":"D6",
    "gn:admin3_code":"7869955.0",
    "gn:admin4_code":"7732539.0",
    "gn:asciiname":"Bunakomola",
    "gn:country_code":"UG",
    "gn:dem":1240,
    "gn:feature_class":"P",
    "gn:feature_code":"PPL",
    "gn:name":"Bunakomola",
    "gn:population":0,
    "gn:timezone":"Africa/Kampala",
    "iso:country":"UG",
    "name:eng_x_preferred":[
        "Bunakomola"
    ],
    "wof:name":"Bunakomola",
    "wof:placetype":"locality"
},
  "geometry": {"coordinates":[34.31667,0.98333],"type":"Point"}
}