{
  "type": "Feature",
  "properties": {
    "gn:admin1_code":"E",
    "gn:admin2_code":"86",
    "gn:asciiname":"Namusenwa",
    "gn:country_code":"UG",
    "gn:dem":1153,
    "gn:feature_class":"P",
    "gn:feature_code":"PPL",
    "gn:name":"Namusenwa",
    "gn:population":0,
    "gn:timezone":"Africa/Kampala",
    "iso:country":"UG",
    "wof:name":"Namusenwa",
    "wof:placetype":"locality"
},
  "geometry": {"coordinates":[33.37771,0.55699],"type":"Point"}
}