{
  "type": "Feature",
  "properties": {
    "gn:admin1_code":"C",
    "gn:admin2_code":"89",
    "gn:asciiname":"Bongole",
    "gn:country_code":"UG",
    "gn:dem":1191,
    "gn:feature_class":"P",
    "gn:feature_code":"PPL",
    "gn:name":"Bongole",
    "gn:population":0,
    "gn:timezone":"Africa/Kampala",
    "iso:country":"UG",
    "wof:name":"Bongole",
    "wof:placetype":"locality"
},
  "geometry": {"coordinates":[32.13805,0.09183],"type":"Point"}
}