{
  "type": "Feature",
  "properties": {
    "gn:admin1_code":"C",
    "gn:admin2_code":"90",
    "gn:admin3_code":"7732384.0",
    "gn:admin4_code":"8658027.0",
    "gn:asciiname":"Musombwa",
    "gn:country_code":"UG",
    "gn:dem":1148,
    "gn:feature_class":"P",
    "gn:feature_code":"PPL",
    "gn:name":"Musombwa",
    "gn:population":0,
    "gn:timezone":"Africa/Kampala",
    "iso:country":"UG",
    "wof:name":"Musombwa",
    "wof:placetype":"locality"
},
  "geometry": {"coordinates":[32.71100999999999,0.45815],"type":"Point"}
}