{
  "type": "Feature",
  "properties": {
    "gn:admin1_code":"C",
    "gn:admin2_code":"83",
    "gn:admin3_code":"227613.0",
    "gn:admin4_code":"8658452.0",
    "gn:asciiname":"Kangulumira",
    "gn:country_code":"UG",
    "gn:dem":1130,
    "gn:feature_class":"P",
    "gn:feature_code":"PPL",
    "gn:name":"Kangulumira",
    "gn:population":0,
    "gn:timezone":"Africa/Kampala",
    "iso:country":"UG",
    "wof:name":"Kangulumira",
    "wof:placetype":"locality"
},
  "geometry": {"coordinates":[33.02669,0.58176],"type":"Point"}
}