{
  "type": "Feature",
  "properties": {
    "gn:admin1_code":"W",
    "gn:admin2_code":"79",
    "gn:admin3_code":"7732254.0",
    "gn:admin4_code":"8657967.0",
    "gn:asciiname":"Kibale",
    "gn:country_code":"UG",
    "gn:dem":1528,
    "gn:feature_class":"P",
    "gn:feature_code":"PPL",
    "gn:name":"Kibale",
    "gn:population":0,
    "gn:timezone":"Africa/Kampala",
    "iso:country":"UG",
    "name:eng_x_preferred":[
        "Kibale"
    ],
    "wof:name":"Kibale",
    "wof:placetype":"locality"
},
  "geometry": {"coordinates":[30.26522000000001,0.6054],"type":"Point"}
}