{
  "type": "Feature",
  "properties": {
    "gn:admin1_code":"N",
    "gn:admin2_code":"58",
    "gn:admin3_code":"8080237.0",
    "gn:admin4_code":"8261561.0",
    "gn:asciiname":"Ossi",
    "gn:country_code":"UG",
    "gn:dem":932,
    "gn:feature_class":"P",
    "gn:feature_code":"PPL",
    "gn:name":"Ossi",
    "gn:population":0,
    "gn:timezone":"Africa/Kampala",
    "iso:country":"UG",
    "name:ceb_x_preferred":[
        "Ossi"
    ],
    "name:deu_x_preferred":[
        "Ossi"
    ],
    "name:fin_x_preferred":[
        "Ossi"
    ],
    "name:hrv_x_preferred":[
        "Ossi"
    ],
    "name:ita_x_preferred":[
        "Ossi"
    ],
    "name:pol_x_preferred":[
        "Ossi"
    ],
    "name:rus_x_preferred":[
        "\u041e\u0441\u0441\u0438"
    ],
    "name:swe_x_preferred":[
        "Ossi"
    ],
    "name:ukr_x_preferred":[
        "\u041e\u0441\u0441\u0456"
    ],
    "wof:name":"Ossi",
    "wof:placetype":"locality"
},
  "geometry": {"coordinates":[31.226,2.36285],"type":"Point"}
}