{
  "type": "Feature",
  "properties": {
    "gn:admin1_code":"C",
    "gn:admin2_code":"F1",
    "gn:asciiname":"Kaguline",
    "gn:country_code":"UG",
    "gn:dem":1258,
    "gn:feature_class":"P",
    "gn:feature_code":"PPL",
    "gn:name":"Kaguline",
    "gn:population":0,
    "gn:timezone":"Africa/Kampala",
    "iso:country":"UG",
    "wof:name":"Kaguline",
    "wof:placetype":"locality"
},
  "geometry": {"coordinates":[32.22113,0.26828],"type":"Point"}
}