{
  "type": "Feature",
  "properties": {
    "gn:admin1_code":"E",
    "gn:admin2_code":"E1",
    "gn:admin3_code":"8644136.0",
    "gn:admin4_code":"8657858.0",
    "gn:asciiname":"Magada",
    "gn:country_code":"UG",
    "gn:dem":1087,
    "gn:feature_class":"P",
    "gn:feature_code":"PPL",
    "gn:name":"Magada",
    "gn:population":0,
    "gn:timezone":"Africa/Kampala",
    "iso:country":"UG",
    "wof:name":"Magada",
    "wof:placetype":"locality"
},
  "geometry": {"coordinates":[33.7261,0.89352],"type":"Point"}
}