{
  "type": "Feature",
  "properties": {
    "gn:admin1_code":"C",
    "gn:admin2_code":"89",
    "gn:asciiname":"Kiwale",
    "gn:country_code":"UG",
    "gn:dem":1242,
    "gn:feature_class":"P",
    "gn:feature_code":"PPL",
    "gn:name":"Kiwale",
    "gn:population":0,
    "gn:timezone":"Africa/Kampala",
    "iso:country":"UG",
    "wof:name":"Kiwale",
    "wof:placetype":"locality"
},
  "geometry": {"coordinates":[32.34335,0.30297],"type":"Point"}
}