{
  "type": "Feature",
  "properties": {
    "gn:admin1_code":"W",
    "gn:admin2_code":"82",
    "gn:admin3_code":"7732525.0",
    "gn:admin4_code":"8657963.0",
    "gn:asciiname":"Kyampoza",
    "gn:country_code":"UG",
    "gn:dem":1500,
    "gn:feature_class":"P",
    "gn:feature_code":"PPL",
    "gn:name":"Kyampoza",
    "gn:population":0,
    "gn:timezone":"Africa/Kampala",
    "iso:country":"UG",
    "wof:name":"Kyampoza",
    "wof:placetype":"locality"
},
  "geometry": {"coordinates":[29.83333,-0.83333],"type":"Point"}
}