{
  "type": "Feature",
  "properties": {
    "gn:admin1_code":"C",
    "gn:admin2_code":"G5",
    "gn:admin3_code":"7910221.0",
    "gn:admin4_code":"8657658.0",
    "gn:asciiname":"Birinuma",
    "gn:country_code":"UG",
    "gn:dem":1280,
    "gn:feature_class":"P",
    "gn:feature_code":"PPL",
    "gn:name":"Birinuma",
    "gn:population":0,
    "gn:timezone":"Africa/Kampala",
    "iso:country":"UG",
    "name:und_x_variant":[
        "Biruruma",
        "Birinuma"
    ],
    "wof:name":"Birinuma",
    "wof:placetype":"locality"
},
  "geometry": {"coordinates":[31.35,-0.43333],"type":"Point"}
}