{
  "type": "Feature",
  "properties": {
    "gn:admin1_code":"N",
    "gn:admin2_code":"H7",
    "gn:admin3_code":"227147.0",
    "gn:admin4_code":"8261565.0",
    "gn:asciiname":"Otheko",
    "gn:country_code":"UG",
    "gn:dem":1048,
    "gn:feature_class":"P",
    "gn:feature_code":"PPL",
    "gn:name":"Otheko",
    "gn:population":0,
    "gn:timezone":"Africa/Kampala",
    "iso:country":"UG",
    "wof:name":"Otheko",
    "wof:placetype":"locality"
},
  "geometry": {"coordinates":[31.01776,2.51095],"type":"Point"}
}