{
  "type": "Feature",
  "properties": {
    "gn:admin1_code":"W",
    "gn:admin2_code":"I8",
    "gn:admin3_code":"226611.0",
    "gn:admin4_code":"8657659.0",
    "gn:asciiname":"Kantale",
    "gn:country_code":"UG",
    "gn:dem":1744,
    "gn:feature_class":"P",
    "gn:feature_code":"PPL",
    "gn:name":"Kantale",
    "gn:population":0,
    "gn:timezone":"Africa/Kampala",
    "iso:country":"UG",
    "name:rus_x_preferred":[
        "\u041a\u0430\u043d\u0442\u0430\u043b\u0430\u0439"
    ],
    "name:sin_x_preferred":[
        "\u0d9a\u0db1\u0dca\u0dad\u0dbd\u0dda"
    ],
    "wof:name":"Kantale",
    "wof:placetype":"locality"
},
  "geometry": {"coordinates":[29.98639,-1.07556],"type":"Point"}
}