{
  "type": "Feature",
  "properties": {
    "gn:admin1_code":"E",
    "gn:admin2_code":"78",
    "gn:asciiname":"Budulu",
    "gn:country_code":"UG",
    "gn:dem":1088,
    "gn:feature_class":"P",
    "gn:feature_code":"PPL",
    "gn:name":"Budulu",
    "gn:population":0,
    "gn:timezone":"Africa/Kampala",
    "iso:country":"UG",
    "wof:name":"Budulu",
    "wof:placetype":"locality"
},
  "geometry": {"coordinates":[33.67202,0.67707],"type":"Point"}
}