{
  "type": "Feature",
  "properties": {
    "gn:admin1_code":"W",
    "gn:admin2_code":"I2",
    "gn:admin3_code":"8644161.0",
    "gn:admin4_code":"8657709.0",
    "gn:asciiname":"Kitawemba",
    "gn:country_code":"UG",
    "gn:dem":1113,
    "gn:feature_class":"P",
    "gn:feature_code":"PPL",
    "gn:name":"Kitawemba",
    "gn:population":0,
    "gn:timezone":"Africa/Kampala",
    "iso:country":"UG",
    "wof:name":"Kitawemba",
    "wof:placetype":"locality"
},
  "geometry": {"coordinates":[31.33333,1.16667],"type":"Point"}
}