{
  "type": "Feature",
  "properties": {
    "gn:admin1_code":"E",
    "gn:admin2_code":"33",
    "gn:admin3_code":"7732228.0",
    "gn:admin4_code":"8657707.0",
    "gn:asciiname":"Nalufenya",
    "gn:country_code":"UG",
    "gn:dem":1178,
    "gn:feature_class":"P",
    "gn:feature_code":"PPL",
    "gn:name":"Nalufenya",
    "gn:population":0,
    "gn:timezone":"Africa/Kampala",
    "iso:country":"UG",
    "name:eng_x_preferred":[
        "Nalufenya"
    ],
    "wof:name":"Nalufenya",
    "wof:placetype":"locality"
},
  "geometry": {"coordinates":[33.19844000000001,0.43624],"type":"Point"}
}