{
  "type": "Feature",
  "properties": {
    "gn:admin1_code":"W",
    "gn:admin2_code":"79",
    "gn:asciiname":"Kabagiro",
    "gn:country_code":"UG",
    "gn:dem":1591,
    "gn:feature_class":"P",
    "gn:feature_code":"PPL",
    "gn:name":"Kabagiro",
    "gn:population":0,
    "gn:timezone":"Africa/Kampala",
    "iso:country":"UG",
    "name:eng_x_preferred":[
        "Kabagiro"
    ],
    "wof:name":"Kabagiro",
    "wof:placetype":"locality"
},
  "geometry": {"coordinates":[30.2602,0.73357],"type":"Point"}
}