{
  "type": "Feature",
  "properties": {
    "gn:admin1_code":"W",
    "gn:admin2_code":"79",
    "gn:asciiname":"Miranga",
    "gn:country_code":"UG",
    "gn:dem":1500,
    "gn:feature_class":"P",
    "gn:feature_code":"PPL",
    "gn:name":"Miranga",
    "gn:population":0,
    "gn:timezone":"Africa/Kampala",
    "iso:country":"UG",
    "name:eng_x_preferred":[
        "Miranga"
    ],
    "wof:name":"Miranga",
    "wof:placetype":"locality"
},
  "geometry": {"coordinates":[30.33207,0.56354],"type":"Point"}
}