{
  "type": "Feature",
  "properties": {
    "gn:admin1_code":"N",
    "gn:admin2_code":"97",
    "gn:admin3_code":"235054.0",
    "gn:admin4_code":"8657619.0",
    "gn:asciiname":"Aoba",
    "gn:country_code":"UG",
    "gn:dem":1022,
    "gn:feature_class":"P",
    "gn:feature_code":"PPL",
    "gn:name":"Aoba",
    "gn:population":0,
    "gn:timezone":"Africa/Kampala",
    "iso:country":"UG",
    "name:deu_x_preferred":[
        "Aoba"
    ],
    "name:fra_x_preferred":[
        "Aoba"
    ],
    "name:jpn_x_preferred":[
        "\u3042\u304a\u3070"
    ],
    "name:nld_x_preferred":[
        "Aoba"
    ],
    "name:pol_x_preferred":[
        "Aoba"
    ],
    "name:rus_x_preferred":[
        "\u0410\u043e\u0431\u0430"
    ],
    "name:spa_x_preferred":[
        "Aoba"
    ],
    "name:ukr_x_preferred":[
        "\u0410\u043e\u0431\u0430"
    ],
    "wof:name":"Aoba",
    "wof:placetype":"locality"
},
  "geometry": {"coordinates":[31.13147,3.53592],"type":"Point"}
}