{
  "type": "Feature",
  "properties": {
    "gn:admin1_code":"C",
    "gn:admin2_code":"89",
    "gn:asciiname":"Kikomanzi",
    "gn:country_code":"UG",
    "gn:dem":1178,
    "gn:feature_class":"P",
    "gn:feature_code":"PPL",
    "gn:name":"Kikomanzi",
    "gn:population":0,
    "gn:timezone":"Africa/Kampala",
    "iso:country":"UG",
    "wof:name":"Kikomanzi",
    "wof:placetype":"locality"
},
  "geometry": {"coordinates":[32.04758,0.00623],"type":"Point"}
}