{
  "type": "Feature",
  "properties": {
    "gn:admin1_code":"E",
    "gn:admin2_code":"H5",
    "gn:asciiname":"Atoneri",
    "gn:country_code":"UG",
    "gn:dem":1059,
    "gn:feature_class":"P",
    "gn:feature_code":"PPLL",
    "gn:name":"Atoneri",
    "gn:population":0,
    "gn:timezone":"Africa/Kampala",
    "iso:country":"UG",
    "wof:name":"Atoneri",
    "wof:placetype":"locality"
},
  "geometry": {"coordinates":[33.52103,1.58014],"type":"Point"}
}