{
  "type": "Feature",
  "properties": {
    "gn:admin1_code":"C",
    "gn:admin2_code":"37",
    "gn:admin3_code":"8644170.0",
    "gn:admin4_code":"7732390.0",
    "gn:asciiname":"Nakulabye",
    "gn:country_code":"UG",
    "gn:dem":1223,
    "gn:feature_class":"P",
    "gn:feature_code":"PPL",
    "gn:name":"Nakulabye",
    "gn:population":0,
    "gn:timezone":"Africa/Kampala",
    "iso:country":"UG",
    "wof:name":"Nakulabye",
    "wof:placetype":"locality"
},
  "geometry": {"coordinates":[32.55997,0.32301],"type":"Point"}
}