{
  "type": "Feature",
  "properties": {
    "gn:admin1_code":"E",
    "gn:admin2_code":"F6",
    "gn:asciiname":"Kugi",
    "gn:country_code":"UG",
    "gn:dem":1076,
    "gn:feature_class":"P",
    "gn:feature_code":"PPL",
    "gn:name":"Kugi",
    "gn:population":0,
    "gn:timezone":"Africa/Kampala",
    "iso:country":"UG",
    "wof:name":"Kugi",
    "wof:placetype":"locality"
},
  "geometry": {"coordinates":[33.77503,0.99314],"type":"Point"}
}