{
  "type": "Feature",
  "properties": {
    "gn:admin1_code":"E",
    "gn:admin2_code":"66",
    "gn:asciiname":"Busimba",
    "gn:country_code":"UG",
    "gn:dem":1090,
    "gn:feature_class":"P",
    "gn:feature_code":"PPL",
    "gn:name":"Busimba",
    "gn:population":0,
    "gn:timezone":"Africa/Kampala",
    "iso:country":"UG",
    "wof:name":"Busimba",
    "wof:placetype":"locality"
},
  "geometry": {"coordinates":[33.82337,0.57927],"type":"Point"}
}