{
  "type": "Feature",
  "properties": {
    "gn:admin1_code":"E",
    "gn:admin2_code":"E1",
    "gn:admin3_code":"8644136.0",
    "gn:admin4_code":"8658412.0",
    "gn:asciiname":"Kirongo",
    "gn:country_code":"UG",
    "gn:dem":1076,
    "gn:feature_class":"P",
    "gn:feature_code":"PPL",
    "gn:name":"Kirongo",
    "gn:population":0,
    "gn:timezone":"Africa/Kampala",
    "iso:country":"UG",
    "wof:name":"Kirongo",
    "wof:placetype":"locality"
},
  "geometry": {"coordinates":[33.67806,0.97174],"type":"Point"}
}