{
  "type": "Feature",
  "properties": {
    "gn:admin1_code":"W",
    "gn:admin2_code":"28",
    "gn:asciiname":"Makimuga",
    "gn:country_code":"UG",
    "gn:dem":905,
    "gn:feature_class":"P",
    "gn:feature_code":"PPL",
    "gn:name":"Makimuga",
    "gn:population":0,
    "gn:timezone":"Africa/Kampala",
    "iso:country":"UG",
    "name:eng_x_preferred":[
        "Makimuga"
    ],
    "wof:name":"Makimuga",
    "wof:placetype":"locality"
},
  "geometry": {"coordinates":[30.10645,0.76737],"type":"Point"}
}