{
  "type": "Feature",
  "properties": {
    "gn:admin1_code":"C",
    "gn:admin2_code":"D8",
    "gn:asciiname":"Bumbu",
    "gn:country_code":"UG",
    "gn:dem":1238,
    "gn:feature_class":"P",
    "gn:feature_code":"PPL",
    "gn:name":"Bumbu",
    "gn:population":0,
    "gn:timezone":"Africa/Kampala",
    "iso:country":"UG",
    "name:ceb_x_preferred":[
        "Bumbu"
    ],
    "name:eus_x_preferred":[
        "Bumbu"
    ],
    "name:fra_x_preferred":[
        "Bumbu"
    ],
    "name:lin_x_preferred":[
        "B\u00fambu"
    ],
    "name:swe_x_preferred":[
        "Bumbu"
    ],
    "wof:name":"Bumbu",
    "wof:placetype":"locality"
},
  "geometry": {"coordinates":[32.16556,0.26557],"type":"Point"}
}