{
  "type": "Feature",
  "properties": {
    "gn:admin1_code":"E",
    "gn:admin2_code":"G7",
    "gn:admin3_code":"8644167.0",
    "gn:admin4_code":"8658689.0",
    "gn:asciiname":"Namaji",
    "gn:country_code":"UG",
    "gn:dem":1141,
    "gn:feature_class":"P",
    "gn:feature_code":"PPL",
    "gn:name":"Namaji",
    "gn:population":0,
    "gn:timezone":"Africa/Kampala",
    "iso:country":"UG",
    "name:eng_x_preferred":[
        "Namaji"
    ],
    "wof:name":"Namaji",
    "wof:placetype":"locality"
},
  "geometry": {"coordinates":[33.87984,0.44308],"type":"Point"}
}