{
  "type": "Feature",
  "properties": {
    "gn:admin1_code":"E",
    "gn:admin2_code":"H5",
    "gn:asciiname":"Owedo",
    "gn:country_code":"UG",
    "gn:dem":1095,
    "gn:feature_class":"P",
    "gn:feature_code":"PPLL",
    "gn:name":"Owedo",
    "gn:population":0,
    "gn:timezone":"Africa/Kampala",
    "iso:country":"UG",
    "wof:name":"Owedo",
    "wof:placetype":"locality"
},
  "geometry": {"coordinates":[33.54427,1.53829],"type":"Point"}
}