{
  "type": "Feature",
  "properties": {
    "gn:admin1_code":"N",
    "gn:admin2_code":"B7",
    "gn:asciiname":"Acengryeny",
    "gn:country_code":"UG",
    "gn:dem":1053,
    "gn:feature_class":"P",
    "gn:feature_code":"PPL",
    "gn:name":"Acengryeny",
    "gn:population":0,
    "gn:timezone":"Africa/Kampala",
    "iso:country":"UG",
    "name:eng_x_preferred":[
        "Acengryeny"
    ],
    "wof:name":"Acengryeny",
    "wof:placetype":"locality"
},
  "geometry": {"coordinates":[32.91839,1.73626],"type":"Point"}
}