{
  "type": "Feature",
  "properties": {
    "gn:admin1_code":"W",
    "gn:admin2_code":"E6",
    "gn:admin3_code":"234484.0",
    "gn:admin4_code":"8658658.0",
    "gn:asciiname":"Nsika",
    "gn:country_code":"UG",
    "gn:dem":1625,
    "gn:feature_class":"P",
    "gn:feature_code":"PPLA2",
    "gn:name":"Nsika",
    "gn:population":0,
    "gn:timezone":"Africa/Kampala",
    "iso:country":"UG",
    "name:und_x_variant":[
        "Nsiika",
        "Nsiki",
        "Nsika"
    ],
    "name:urd_x_preferred":[
        "\u0628\u0648\u06c1\u0648\u06cc\u062c\u0648"
    ],
    "wof:name":"Nsika",
    "wof:placetype":"locality"
},
  "geometry": {"coordinates":[30.43136,-0.358],"type":"Point"}
}