{
  "type": "Feature",
  "properties": {
    "gn:admin1_code":"E",
    "gn:admin2_code":"80",
    "gn:admin3_code":"7732909.0",
    "gn:admin4_code":"8658265.0",
    "gn:asciiname":"Kabalang",
    "gn:country_code":"UG",
    "gn:dem":1135,
    "gn:feature_class":"P",
    "gn:feature_code":"PPL",
    "gn:name":"Kabalang",
    "gn:population":0,
    "gn:timezone":"Africa/Kampala",
    "iso:country":"UG",
    "name:und_x_variant":[
        "Kabalangi",
        "Kabalang"
    ],
    "wof:name":"Kabalang",
    "wof:placetype":"locality"
},
  "geometry": {"coordinates":[33.29490999999999,1.9911],"type":"Point"}
}