{
  "type": "Feature",
  "properties": {
    "gn:admin1_code":"W",
    "gn:admin2_code":"F7",
    "gn:admin3_code":"231597.0",
    "gn:admin4_code":"8657902.0",
    "gn:asciiname":"Kitwara",
    "gn:country_code":"UG",
    "gn:dem":1061,
    "gn:feature_class":"P",
    "gn:feature_code":"PPL",
    "gn:name":"Kitwara",
    "gn:population":0,
    "gn:timezone":"Africa/Kampala",
    "iso:country":"UG",
    "wof:name":"Kitwara",
    "wof:placetype":"locality"
},
  "geometry": {"coordinates":[32.10468,1.78725],"type":"Point"}
}