{
  "type": "Feature",
  "properties": {
    "gn:admin1_code":"W",
    "gn:admin2_code":"50",
    "gn:admin3_code":"234463.0",
    "gn:admin4_code":"8657903.0",
    "gn:asciiname":"Kasenene",
    "gn:country_code":"UG",
    "gn:dem":1081,
    "gn:feature_class":"P",
    "gn:feature_code":"PPL",
    "gn:name":"Kasenene",
    "gn:population":0,
    "gn:timezone":"Africa/Kampala",
    "iso:country":"UG",
    "wof:name":"Kasenene",
    "wof:placetype":"locality"
},
  "geometry": {"coordinates":[31.41362,1.62472],"type":"Point"}
}