{
  "type": "Feature",
  "properties": {
    "gn:admin1_code":"E",
    "gn:admin2_code":"B8",
    "gn:admin3_code":"8644171.0",
    "gn:admin4_code":"8658643.0",
    "gn:asciiname":"Ayola",
    "gn:country_code":"UG",
    "gn:dem":1149,
    "gn:feature_class":"P",
    "gn:feature_code":"PPL",
    "gn:name":"Ayola",
    "gn:population":0,
    "gn:timezone":"Africa/Kampala",
    "iso:country":"UG",
    "wof:name":"Ayola",
    "wof:placetype":"locality"
},
  "geometry": {"coordinates":[33.75,2.05],"type":"Point"}
}