{
  "type": "Feature",
  "properties": {
    "gn:admin1_code":"E",
    "gn:admin2_code":"95",
    "gn:admin3_code":"226232.0",
    "gn:admin4_code":"8657809.0",
    "gn:asciiname":"Ojom",
    "gn:country_code":"UG",
    "gn:dem":1094,
    "gn:feature_class":"P",
    "gn:feature_code":"PPL",
    "gn:name":"Ojom",
    "gn:population":0,
    "gn:timezone":"Africa/Kampala",
    "iso:country":"UG",
    "name:und_x_variant":[
        "Ojomi",
        "Ojom"
    ],
    "wof:name":"Ojom",
    "wof:placetype":"locality"
},
  "geometry": {"coordinates":[33.58342,1.7974],"type":"Point"}
}