{
  "type": "Feature",
  "properties": {
    "gn:admin1_code":"E",
    "gn:admin2_code":"G7",
    "gn:admin3_code":"8644167.0",
    "gn:admin4_code":"8657530.0",
    "gn:asciiname":"Busoga",
    "gn:country_code":"UG",
    "gn:dem":1166,
    "gn:feature_class":"P",
    "gn:feature_code":"PPL",
    "gn:name":"Busoga",
    "gn:population":0,
    "gn:timezone":"Africa/Kampala",
    "iso:country":"UG",
    "name:eng_x_preferred":[
        "Busoga"
    ],
    "wof:name":"Busoga",
    "wof:placetype":"locality"
},
  "geometry": {"coordinates":[33.64801,0.48935],"type":"Point"}
}