{
  "type": "Feature",
  "properties": {
    "gn:admin1_code":"E",
    "gn:admin2_code":"G7",
    "gn:admin3_code":"8644167.0",
    "gn:admin4_code":"8657530.0",
    "gn:asciiname":"Busoga",
    "gn:country_code":"UG",
    "gn:dem":1166,
    "gn:feature_class":"P",
    "gn:feature_code":"PPL",
    "gn:name":"Busoga",
    "gn:population":0,
    "gn:timezone":"Africa/Kampala",
    "iso:country":"UG",
    "name:cat_x_preferred":[
        "Busoga"
    ],
    "name:ces_x_preferred":[
        "Busoga"
    ],
    "name:eng_x_preferred":[
        "Busoga"
    ],
    "name:eus_x_preferred":[
        "Busoga"
    ],
    "name:fra_x_preferred":[
        "Busoga"
    ],
    "name:ita_x_preferred":[
        "Busoga"
    ],
    "name:jpn_x_preferred":[
        "\u30d6\u30bd\u30ac"
    ],
    "name:lit_x_preferred":[
        "Busogos karalyst\u0117"
    ],
    "name:nld_x_preferred":[
        "Busoga"
    ],
    "name:pol_x_preferred":[
        "Busoga"
    ],
    "name:rus_x_preferred":[
        "\u0411\u0443\u0441\u043e\u0433\u0430"
    ],
    "name:spa_x_preferred":[
        "Busoga"
    ],
    "name:urd_x_preferred":[
        "\u0628\u0648\u0633\u0627\u06af\u0627"
    ],
    "wof:name":"Busoga",
    "wof:placetype":"locality"
},
  "geometry": {"coordinates":[33.64801,0.48935],"type":"Point"}
}