{
  "type": "Feature",
  "properties": {
    "gn:admin1_code":"C",
    "gn:admin2_code":"96",
    "gn:admin3_code":"7732385.0",
    "gn:admin4_code":"8658439.0",
    "gn:asciiname":"Nnama",
    "gn:country_code":"UG",
    "gn:dem":1209,
    "gn:feature_class":"P",
    "gn:feature_code":"PPL",
    "gn:name":"Nnama",
    "gn:population":0,
    "gn:timezone":"Africa/Kampala",
    "iso:country":"UG",
    "wof:name":"Nnama",
    "wof:placetype":"locality"
},
  "geometry": {"coordinates":[32.5421,0.46475],"type":"Point"}
}