{
  "type": "Feature",
  "properties": {
    "gn:admin1_code":"C",
    "gn:admin2_code":"E7",
    "gn:admin3_code":"7732075.0",
    "gn:admin4_code":"8658514.0",
    "gn:asciiname":"Kibale",
    "gn:country_code":"UG",
    "gn:dem":1215,
    "gn:feature_class":"P",
    "gn:feature_code":"PPL",
    "gn:name":"Kibale",
    "gn:population":0,
    "gn:timezone":"Africa/Kampala",
    "iso:country":"UG",
    "wof:name":"Kibale",
    "wof:placetype":"locality"
},
  "geometry": {"coordinates":[32.98707,0.24793],"type":"Point"}
}