{
  "type": "Feature",
  "properties": {
    "gn:admin1_code":"C",
    "gn:admin2_code":"E7",
    "gn:admin3_code":"7732075.0",
    "gn:admin4_code":"8658514.0",
    "gn:asciiname":"Kibale",
    "gn:country_code":"UG",
    "gn:dem":1215,
    "gn:feature_class":"P",
    "gn:feature_code":"PPL",
    "gn:name":"Kibale",
    "gn:population":0,
    "gn:timezone":"Africa/Kampala",
    "iso:country":"UG",
    "name:ara_x_preferred":[
        "\u0643\u064a\u0628\u0627\u0644\u064a"
    ],
    "name:ben_x_preferred":[
        "\u0995\u09bf\u09ac\u09be\u09b2\u09c7"
    ],
    "name:ell_x_preferred":[
        "\u039a\u03b9\u03bc\u03c0\u03ac\u03bb\u03b5"
    ],
    "name:fas_x_preferred":[
        "\u06a9\u06cc\u0628\u0627\u0644"
    ],
    "name:heb_x_preferred":[
        "\u05e7\u05d9\u05d1\u05d9\u05d9\u05dc"
    ],
    "name:hin_x_preferred":[
        "\u0915\u093f\u092c\u0947\u0932"
    ],
    "name:hun_x_preferred":[
        "Kibale"
    ],
    "name:ind_x_preferred":[
        "Kibale"
    ],
    "name:kor_x_preferred":[
        "\ud0a4\ubc1c\ub808"
    ],
    "name:pol_x_preferred":[
        "Kibale"
    ],
    "name:por_x_preferred":[
        "Kibale"
    ],
    "name:spa_x_preferred":[
        "Kibale"
    ],
    "name:swe_x_preferred":[
        "Kibale"
    ],
    "name:tur_x_preferred":[
        "Kibale"
    ],
    "name:ukr_x_preferred":[
        "\u041a\u0456\u0431\u0430\u043b\u0435"
    ],
    "name:vie_x_preferred":[
        "Kibale"
    ],
    "name:zho_cn_x_preferred":[
        "\u57fa\u5df4\u83b1"
    ],
    "name:zho_tw_x_preferred":[
        "\u57fa\u5df4\u840a"
    ],
    "wof:name":"Kibale",
    "wof:placetype":"locality"
},
  "geometry": {"coordinates":[32.98707,0.24793],"type":"Point"}
}