{
  "type": "Feature",
  "properties": {
    "iso:country":"UG",
    "name:unk_x_variant":[
        "Sunga"
    ],
    "qs:gn_country":"UG",
    "qs:gn_fcode":"PPL",
    "qs:gn_pop":0,
    "qs:name":"Sanga",
    "qs:name_adm0":"Uganda",
    "qs:name_adm1":"Kiruhuura",
    "qs:photos":14,
    "qs:photos_1k":3,
    "qs:photos_9k":1,
    "qs:photos_9r":1,
    "qs:photos_all":14,
    "qs:photos_sr":1,
    "qs:placetype":"Town",
    "qs:pop_sr":"0",
    "qs:woe_adm0":23424974,
    "wd:wordcount":192,
    "wof:name":"Sanga",
    "wof:placetype":"locality"
},
  "geometry": {"coordinates":[30.61889,-0.54694],"type":"Point"}
}