{
  "type": "Feature",
  "properties": {
    "gn:admin1_code":"C",
    "gn:admin2_code":"D9",
    "gn:admin3_code":"8644153.0",
    "gn:admin4_code":"8658703.0",
    "gn:asciiname":"Bugeye",
    "gn:country_code":"UG",
    "gn:dem":1085,
    "gn:feature_class":"P",
    "gn:feature_code":"PPL",
    "gn:name":"Bugeye",
    "gn:population":0,
    "gn:timezone":"Africa/Kampala",
    "iso:country":"UG",
    "name:und_x_variant":[
        "Bugoye",
        "Bugeye"
    ],
    "wof:name":"Bugeye",
    "wof:placetype":"locality"
},
  "geometry": {"coordinates":[32.26667,1.11667],"type":"Point"}
}