{
  "type": "Feature",
  "properties": {
    "gn:admin1_code":"E",
    "gn:admin2_code":"86",
    "gn:admin3_code":"8644164.0",
    "gn:admin4_code":"8658348.0",
    "gn:asciiname":"Mpumu",
    "gn:country_code":"UG",
    "gn:dem":1186,
    "gn:feature_class":"P",
    "gn:feature_code":"PPL",
    "gn:name":"Mpumu",
    "gn:population":0,
    "gn:timezone":"Africa/Kampala",
    "iso:country":"UG",
    "name:eng_x_preferred":[
        "Mpumu"
    ],
    "wof:name":"Mpumu",
    "wof:placetype":"locality"
},
  "geometry": {"coordinates":[33.54928,0.45513],"type":"Point"}
}