{
  "type": "Feature",
  "properties": {
    "gn:admin1_code":"C",
    "gn:admin2_code":"96",
    "gn:admin3_code":"7732385.0",
    "gn:admin4_code":"8658059.0",
    "gn:asciiname":"Kibwa",
    "gn:country_code":"UG",
    "gn:dem":1207,
    "gn:feature_class":"P",
    "gn:feature_code":"PPL",
    "gn:name":"Kibwa",
    "gn:population":0,
    "gn:timezone":"Africa/Kampala",
    "iso:country":"UG",
    "wof:name":"Kibwa",
    "wof:placetype":"locality"
},
  "geometry": {"coordinates":[32.53861,0.36815],"type":"Point"}
}