{
  "type": "Feature",
  "properties": {
    "gn:admin1_code":"W",
    "gn:admin2_code":"I7",
    "gn:admin3_code":"226689.0",
    "gn:admin4_code":"8642870.0",
    "gn:asciiname":"Bunyonyi",
    "gn:country_code":"UG",
    "gn:dem":2076,
    "gn:feature_class":"P",
    "gn:feature_code":"PPL",
    "gn:name":"Bunyonyi",
    "gn:population":0,
    "gn:timezone":"Africa/Kampala",
    "iso:country":"UG",
    "wof:name":"Bunyonyi",
    "wof:placetype":"locality"
},
  "geometry": {"coordinates":[29.92641,-1.2693],"type":"Point"}
}