{
  "type": "Feature",
  "properties": {
    "gn:admin1_code":"C",
    "gn:admin2_code":"96",
    "gn:admin3_code":"234053.0",
    "gn:admin4_code":"8657875.0",
    "gn:asciiname":"Jungo",
    "gn:country_code":"UG",
    "gn:dem":1218,
    "gn:feature_class":"P",
    "gn:feature_code":"PPL",
    "gn:name":"Jungo",
    "gn:population":0,
    "gn:timezone":"Africa/Kampala",
    "iso:country":"UG",
    "wof:name":"Jungo",
    "wof:placetype":"locality"
},
  "geometry": {"coordinates":[32.43943,0.17522],"type":"Point"}
}