{
  "type": "Feature",
  "properties": {
    "gn:admin1_code":"E",
    "gn:admin2_code":"95",
    "gn:admin3_code":"226232.0",
    "gn:admin4_code":"8658360.0",
    "gn:asciiname":"Ogorai",
    "gn:country_code":"UG",
    "gn:dem":1049,
    "gn:feature_class":"P",
    "gn:feature_code":"PPL",
    "gn:name":"Ogorai",
    "gn:population":0,
    "gn:timezone":"Africa/Kampala",
    "iso:country":"UG",
    "wof:name":"Ogorai",
    "wof:placetype":"locality"
},
  "geometry": {"coordinates":[33.46863,1.93117],"type":"Point"}
}