{
  "type": "Feature",
  "properties": {
    "gn:admin1_code":"E",
    "gn:admin2_code":"G7",
    "gn:admin3_code":"8644167.0",
    "gn:admin4_code":"8657680.0",
    "gn:asciiname":"Nawambwa",
    "gn:country_code":"UG",
    "gn:dem":1147,
    "gn:feature_class":"P",
    "gn:feature_code":"PPL",
    "gn:name":"Nawambwa",
    "gn:population":0,
    "gn:timezone":"Africa/Kampala",
    "iso:country":"UG",
    "wof:name":"Nawambwa",
    "wof:placetype":"locality"
},
  "geometry": {"coordinates":[33.66667,0.45],"type":"Point"}
}