{
  "type": "Feature",
  "properties": {
    "gn:admin1_code":"C",
    "gn:admin2_code":"89",
    "gn:asciiname":"Magejjo",
    "gn:country_code":"UG",
    "gn:dem":1224,
    "gn:feature_class":"P",
    "gn:feature_code":"PPL",
    "gn:name":"Magejjo",
    "gn:population":0,
    "gn:timezone":"Africa/Kampala",
    "iso:country":"UG",
    "wof:name":"Magejjo",
    "wof:placetype":"locality"
},
  "geometry": {"coordinates":[32.23362,0.17561],"type":"Point"}
}