{
  "type": "Feature",
  "properties": {
    "gn:admin1_code":"W",
    "gn:admin2_code":"I8",
    "gn:admin3_code":"226611.0",
    "gn:admin4_code":"8657659.0",
    "gn:asciiname":"Kyehinde",
    "gn:country_code":"UG",
    "gn:dem":1973,
    "gn:feature_class":"P",
    "gn:feature_code":"PPL",
    "gn:name":"Kyehinde",
    "gn:population":0,
    "gn:timezone":"Africa/Kampala",
    "iso:country":"UG",
    "wof:name":"Kyehinde",
    "wof:placetype":"locality"
},
  "geometry": {"coordinates":[29.95,-1.08333],"type":"Point"}
}