{
  "type": "Feature",
  "properties": {
    "gn:admin1_code":"E",
    "gn:admin2_code":"33",
    "gn:asciiname":"Yuka",
    "gn:country_code":"UG",
    "gn:dem":1111,
    "gn:feature_class":"P",
    "gn:feature_code":"PPL",
    "gn:name":"Yuka",
    "gn:population":0,
    "gn:timezone":"Africa/Kampala",
    "iso:country":"UG",
    "wof:name":"Yuka",
    "wof:placetype":"locality"
},
  "geometry": {"coordinates":[33.15117,0.65911],"type":"Point"}
}