{
  "type": "Feature",
  "properties": {
    "gn:admin1_code":"W",
    "gn:admin2_code":"79",
    "gn:asciiname":"Isule",
    "gn:country_code":"UG",
    "gn:dem":1503,
    "gn:feature_class":"P",
    "gn:feature_code":"PPL",
    "gn:name":"Isule",
    "gn:population":0,
    "gn:timezone":"Africa/Kampala",
    "iso:country":"UG",
    "name:eng_x_preferred":[
        "Isule"
    ],
    "wof:name":"Isule",
    "wof:placetype":"locality"
},
  "geometry": {"coordinates":[30.35305,0.60169],"type":"Point"}
}