{
  "type": "Feature",
  "properties": {
    "gn:admin1_code":"E",
    "gn:admin2_code":"38",
    "gn:asciiname":"Bobogo",
    "gn:country_code":"UG",
    "gn:dem":1076,
    "gn:feature_class":"P",
    "gn:feature_code":"PPL",
    "gn:name":"Bobogo",
    "gn:population":0,
    "gn:timezone":"Africa/Kampala",
    "iso:country":"UG",
    "wof:name":"Bobogo",
    "wof:placetype":"locality"
},
  "geometry": {"coordinates":[33.11475,0.85596],"type":"Point"}
}