{
  "type": "Feature",
  "properties": {
    "gn:admin1_code":"E",
    "gn:admin2_code":"G7",
    "gn:admin3_code":"8644167.0",
    "gn:admin4_code":"8658688.0",
    "gn:asciiname":"Bunyika",
    "gn:country_code":"UG",
    "gn:dem":1179,
    "gn:feature_class":"P",
    "gn:feature_code":"PPL",
    "gn:name":"Bunyika",
    "gn:population":0,
    "gn:timezone":"Africa/Kampala",
    "iso:country":"UG",
    "name:eng_x_preferred":[
        "Bunyika"
    ],
    "wof:name":"Bunyika",
    "wof:placetype":"locality"
},
  "geometry": {"coordinates":[33.85505999999999,0.30506],"type":"Point"}
}