{
  "type": "Feature",
  "properties": {
    "gn:admin1_code":"E",
    "gn:admin2_code":"67",
    "gn:asciiname":"Syanyonjo",
    "gn:country_code":"UG",
    "gn:dem":1124,
    "gn:feature_class":"P",
    "gn:feature_code":"PPL",
    "gn:name":"Syanyonjo",
    "gn:population":0,
    "gn:timezone":"Africa/Kampala",
    "iso:country":"UG",
    "name:eng_x_preferred":[
        "Syanyonjo"
    ],
    "wof:name":"Syanyonjo",
    "wof:placetype":"locality"
},
  "geometry": {"coordinates":[34.04299,0.55542],"type":"Point"}
}