{
  "type": "Feature",
  "properties": {
    "gn:admin1_code":"C",
    "gn:admin2_code":"56",
    "gn:admin3_code":"233891.0",
    "gn:admin4_code":"8658595.0",
    "gn:asciiname":"Kiboyo",
    "gn:country_code":"UG",
    "gn:dem":1222,
    "gn:feature_class":"P",
    "gn:feature_code":"PPL",
    "gn:name":"Kiboyo",
    "gn:population":0,
    "gn:timezone":"Africa/Kampala",
    "iso:country":"UG",
    "wof:name":"Kiboyo",
    "wof:placetype":"locality"
},
  "geometry": {"coordinates":[31.33333,0.71667],"type":"Point"}
}