{
  "type": "Feature",
  "properties": {
    "gn:admin1_code":"W",
    "gn:admin2_code":"40",
    "gn:admin3_code":"7869968.0",
    "gn:admin4_code":"8657746.0",
    "gn:asciiname":"Kabahango",
    "gn:country_code":"UG",
    "gn:dem":924,
    "gn:feature_class":"P",
    "gn:feature_code":"PPL",
    "gn:name":"Kabahango",
    "gn:population":0,
    "gn:timezone":"Africa/Kampala",
    "iso:country":"UG",
    "name:und_x_variant":[
        "Kayanja",
        "Kabahango"
    ],
    "wof:name":"Kabahango",
    "wof:placetype":"locality"
},
  "geometry": {"coordinates":[29.76667,-0.08333],"type":"Point"}
}