{
  "type": "Feature",
  "properties": {
    "gn:admin1_code":"N",
    "gn:admin2_code":"72",
    "gn:admin3_code":"8644127.0",
    "gn:admin4_code":"8657844.0",
    "gn:asciiname":"Dikiri",
    "gn:country_code":"UG",
    "gn:dem":676,
    "gn:feature_class":"P",
    "gn:feature_code":"PPL",
    "gn:name":"Dikiri",
    "gn:population":0,
    "gn:timezone":"Africa/Kampala",
    "iso:country":"UG",
    "wof:name":"Dikiri",
    "wof:placetype":"locality"
},
  "geometry": {"coordinates":[31.59548,3.41189],"type":"Point"}
}