{
  "type": "Feature",
  "properties": {
    "gn:admin1_code":"C",
    "gn:admin2_code":"G5",
    "gn:admin3_code":"7910221.0",
    "gn:admin4_code":"8657743.0",
    "gn:asciiname":"Degeya",
    "gn:country_code":"UG",
    "gn:dem":1238,
    "gn:feature_class":"P",
    "gn:feature_code":"PPL",
    "gn:name":"Degeya",
    "gn:population":0,
    "gn:timezone":"Africa/Kampala",
    "iso:country":"UG",
    "wof:name":"Degeya",
    "wof:placetype":"locality"
},
  "geometry": {"coordinates":[31.51667,-0.38333],"type":"Point"}
}