{
  "type": "Feature",
  "properties": {
    "gn:admin1_code":"E",
    "gn:admin2_code":"D6",
    "gn:asciiname":"Bunamuwenge",
    "gn:country_code":"UG",
    "gn:dem":1565,
    "gn:feature_class":"P",
    "gn:feature_code":"PPL",
    "gn:name":"Bunamuwenge",
    "gn:population":0,
    "gn:timezone":"Africa/Kampala",
    "iso:country":"UG",
    "name:eng_x_preferred":[
        "Bunamuwenge"
    ],
    "wof:name":"Bunamuwenge",
    "wof:placetype":"locality"
},
  "geometry": {"coordinates":[34.35225,0.97172],"type":"Point"}
}