{
  "type": "Feature",
  "properties": {
    "gn:admin1_code":"C",
    "gn:admin2_code":"G5",
    "gn:admin3_code":"7910221.0",
    "gn:admin4_code":"8658165.0",
    "gn:asciiname":"Namulaba",
    "gn:country_code":"UG",
    "gn:dem":1259,
    "gn:feature_class":"P",
    "gn:feature_code":"PPL",
    "gn:name":"Namulaba",
    "gn:population":0,
    "gn:timezone":"Africa/Kampala",
    "iso:country":"UG",
    "wof:name":"Namulaba",
    "wof:placetype":"locality"
},
  "geometry": {"coordinates":[31.45,-0.36667],"type":"Point"}
}