{
  "type": "Feature",
  "properties": {
    "gn:admin1_code":"C",
    "gn:admin2_code":"83",
    "gn:admin3_code":"227613.0",
    "gn:admin4_code":"8658174.0",
    "gn:asciiname":"Bukoloto",
    "gn:country_code":"UG",
    "gn:dem":1067,
    "gn:feature_class":"P",
    "gn:feature_code":"PPL",
    "gn:name":"Bukoloto",
    "gn:population":0,
    "gn:timezone":"Africa/Kampala",
    "iso:country":"UG",
    "wof:name":"Bukoloto",
    "wof:placetype":"locality"
},
  "geometry": {"coordinates":[32.91667,0.68333],"type":"Point"}
}