{
  "type": "Feature",
  "properties": {
    "gn:admin1_code":"W",
    "gn:admin2_code":"52",
    "gn:admin3_code":"226512.0",
    "gn:admin4_code":"7732395.0",
    "gn:asciiname":"Kihonzi",
    "gn:country_code":"UG",
    "gn:dem":1429,
    "gn:feature_class":"P",
    "gn:feature_code":"PPL",
    "gn:name":"Kihonzi",
    "gn:population":0,
    "gn:timezone":"Africa/Kampala",
    "iso:country":"UG",
    "wof:name":"Kihonzi",
    "wof:placetype":"locality"
},
  "geometry": {"coordinates":[30.46667,-0.66667],"type":"Point"}
}