{
  "type": "Feature",
  "properties": {
    "gn:admin1_code":"N",
    "gn:admin2_code":"26",
    "gn:admin3_code":"230563.0",
    "gn:admin4_code":"8657821.0",
    "gn:asciiname":"Agil",
    "gn:country_code":"UG",
    "gn:dem":1067,
    "gn:feature_class":"P",
    "gn:feature_code":"PPL",
    "gn:name":"Agil",
    "gn:population":0,
    "gn:timezone":"Africa/Kampala",
    "iso:country":"UG",
    "wof:name":"Agil",
    "wof:placetype":"locality"
},
  "geometry": {"coordinates":[32.75,2.05],"type":"Point"}
}