{
  "type": "Feature",
  "properties": {
    "gn:admin1_code":"E",
    "gn:admin2_code":"D2",
    "gn:admin3_code":"234305.0",
    "gn:admin4_code":"8658350.0",
    "gn:asciiname":"Bukumankola",
    "gn:country_code":"UG",
    "gn:dem":1101,
    "gn:feature_class":"P",
    "gn:feature_code":"PPL",
    "gn:name":"Bukumankola",
    "gn:population":0,
    "gn:timezone":"Africa/Kampala",
    "iso:country":"UG",
    "wof:name":"Bukumankola",
    "wof:placetype":"locality"
},
  "geometry": {"coordinates":[33.48333,0.91667],"type":"Point"}
}