{
  "type": "Feature",
  "properties": {
    "gn:admin1_code":"E",
    "gn:admin2_code":"D6",
    "gn:asciiname":"Bukhasusa",
    "gn:country_code":"UG",
    "gn:dem":1311,
    "gn:feature_class":"P",
    "gn:feature_code":"PPL",
    "gn:name":"Bukhasusa",
    "gn:population":0,
    "gn:timezone":"Africa/Kampala",
    "iso:country":"UG",
    "name:eng_x_preferred":[
        "Bukhasusa"
    ],
    "wof:name":"Bukhasusa",
    "wof:placetype":"locality"
},
  "geometry": {"coordinates":[34.29,0.87784],"type":"Point"}
}