{
  "type": "Feature",
  "properties": {
    "gn:admin1_code":"C",
    "gn:admin2_code":"E8",
    "gn:admin3_code":"7910224.0",
    "gn:admin4_code":"8658427.0",
    "gn:asciiname":"Serinya",
    "gn:country_code":"UG",
    "gn:dem":1202,
    "gn:feature_class":"P",
    "gn:feature_code":"PPL",
    "gn:name":"Serinya",
    "gn:population":0,
    "gn:timezone":"Africa/Kampala",
    "iso:country":"UG",
    "wof:name":"Serinya",
    "wof:placetype":"locality"
},
  "geometry": {"coordinates":[31.68333,-0.23333],"type":"Point"}
}