{
  "type": "Feature",
  "properties": {
    "gn:admin1_code":"C",
    "gn:admin2_code":"D8",
    "gn:admin3_code":"8644152.0",
    "gn:admin4_code":"8657694.0",
    "gn:asciiname":"Kisagala",
    "gn:country_code":"UG",
    "gn:dem":1226,
    "gn:feature_class":"P",
    "gn:feature_code":"PPL",
    "gn:name":"Kisagala",
    "gn:population":0,
    "gn:timezone":"Africa/Kampala",
    "iso:country":"UG",
    "name:und_x_variant":[
        "Kisigala",
        "Kisagala"
    ],
    "wof:name":"Kisagala",
    "wof:placetype":"locality"
},
  "geometry": {"coordinates":[31.95,0.51667],"type":"Point"}
}