{
  "type": "Feature",
  "properties": {
    "gn:admin1_code":"N",
    "gn:admin2_code":"E3",
    "gn:admin3_code":"235459.0",
    "gn:admin4_code":"8658597.0",
    "gn:asciiname":"Paimol-Mutu",
    "gn:country_code":"UG",
    "gn:dem":1231,
    "gn:feature_class":"P",
    "gn:feature_code":"PPL",
    "gn:name":"Paimol-Mutu",
    "gn:population":0,
    "gn:timezone":"Africa/Kampala",
    "iso:country":"UG",
    "wof:name":"Paimol-Mutu",
    "wof:placetype":"locality"
},
  "geometry": {"coordinates":[33.43417,3.12684],"type":"Point"}
}