{
  "type": "Feature",
  "properties": {
    "gn:admin1_code":"E",
    "gn:admin2_code":"80",
    "gn:admin3_code":"233018.0",
    "gn:admin4_code":"8658326.0",
    "gn:asciiname":"Amorkot",
    "gn:country_code":"UG",
    "gn:dem":1061,
    "gn:feature_class":"P",
    "gn:feature_code":"PPLL",
    "gn:name":"Amorkot",
    "gn:population":0,
    "gn:timezone":"Africa/Kampala",
    "iso:country":"UG",
    "name:eng_x_preferred":[
        "Amorkot"
    ],
    "wof:name":"Amorkot",
    "wof:placetype":"locality"
},
  "geometry": {"coordinates":[32.99195,1.65093],"type":"Point"}
}