{
  "type": "Feature",
  "properties": {
    "gn:admin1_code":"N",
    "gn:admin2_code":"C7",
    "gn:admin3_code":"233559.0",
    "gn:admin4_code":"8657873.0",
    "gn:asciiname":"Ekwera",
    "gn:country_code":"UG",
    "gn:dem":1049,
    "gn:feature_class":"P",
    "gn:feature_code":"PPLL",
    "gn:name":"Ekwera",
    "gn:population":0,
    "gn:timezone":"Africa/Kampala",
    "iso:country":"UG",
    "name:und_x_variant":[
        "Kwera"
    ],
    "wof:name":"Ekwera",
    "wof:placetype":"locality"
},
  "geometry": {"coordinates":[32.99271,1.82981],"type":"Point"}
}