{
  "type": "Feature",
  "properties": {
    "gn:admin1_code":"C",
    "gn:admin2_code":"42",
    "gn:admin3_code":"8644178.0",
    "gn:admin4_code":"8657979.0",
    "gn:asciiname":"Katuku",
    "gn:country_code":"UG",
    "gn:dem":1131,
    "gn:feature_class":"P",
    "gn:feature_code":"PPL",
    "gn:name":"Katuku",
    "gn:population":0,
    "gn:timezone":"Africa/Kampala",
    "iso:country":"UG",
    "wof:name":"Katuku",
    "wof:placetype":"locality"
},
  "geometry": {"coordinates":[31.76667,0.95],"type":"Point"}
}