{
  "type": "Feature",
  "properties": {
    "gn:admin1_code":"E",
    "gn:admin2_code":"I4",
    "gn:admin3_code":"11887622.0",
    "gn:admin4_code":"8658455.0",
    "gn:asciiname":"Bomwege",
    "gn:country_code":"UG",
    "gn:dem":1671,
    "gn:feature_class":"P",
    "gn:feature_code":"PPL",
    "gn:name":"Bomwege",
    "gn:population":0,
    "gn:timezone":"Africa/Kampala",
    "iso:country":"UG",
    "name:und_x_variant":[
        "Bomwega",
        "Bomwege"
    ],
    "wof:name":"Bomwege",
    "wof:placetype":"locality"
},
  "geometry": {"coordinates":[34.43333,0.86667],"type":"Point"}
}