{
  "type": "Feature",
  "properties": {
    "gn:country":"UG",
    "gn:fcode":"PPLA2",
    "gn:pop":43200,
    "iso:country":"UG",
    "name:ceb_x_preferred":[
        "Busia"
    ],
    "name:deu_x_preferred":[
        "Busia"
    ],
    "name:eng_x_preferred":[
        "Busia"
    ],
    "name:fra_x_preferred":[
        "Busia"
    ],
    "name:ita_x_preferred":[
        "Busia"
    ],
    "name:lug_x_preferred":[
        "Busia"
    ],
    "name:nds_x_preferred":[
        "Busia"
    ],
    "name:nld_x_preferred":[
        "Busia"
    ],
    "name:ron_x_preferred":[
        "Busia"
    ],
    "name:rus_x_preferred":[
        "\u0411\u0443\u0441\u0438\u0430"
    ],
    "name:spa_x_preferred":[
        "Busia"
    ],
    "name:swe_x_preferred":[
        "Busia"
    ],
    "name:tgl_x_preferred":[
        "Busia"
    ],
    "name:unk_x_variant":[
        "Busla"
    ],
    "name:urd_x_preferred":[
        "\u0628\u0648\u0633\u06cc\u0627\u060c \u06cc\u0648\u06af\u0646\u0688\u0627"
    ],
    "name:zho_x_preferred":[
        "\u5e03\u897f\u4e9e"
    ],
    "ne:ADM0CAP":0.0,
    "ne:ADM0NAME":"Uganda",
    "ne:ADM0_A3":"UGA",
    "ne:ADM1NAME":"Busia",
    "ne:ADMIN1_COD":67,
    "ne:CAPALT":0,
    "ne:CHANGED":4,
    "ne:CHECKME":0,
    "ne:COMPARE":0,
    "ne:DIFFASCII":0,
    "ne:DIFFNOTE":"Added missing admin-1 capital round B. Population from GeoNames.",
    "ne:ELEVATION":0.0,
    "ne:FEATURECLA":"Admin-1 capital",
    "ne:FEATURE_CL":"P",
    "ne:FEATURE_CO":"PPLA",
    "ne:GEONAMEID":234077,
    "ne:GEONAMESNO":"GeoNames match general.",
    "ne:GN_ASCII":"Busia",
    "ne:GN_POP":0,
    "ne:GTOPO30":1198.0,
    "ne:ISO_A2":"UG",
    "ne:LABELRANK":5,
    "ne:LATITUDE":0.454444,
    "ne:LONGITUDE":34.075833,
    "ne:LS_MATCH":0,
    "ne:MAX_AREAKM":0.0,
    "ne:MAX_AREAMI":0.0,
    "ne:MAX_BBXMAX":0.0,
    "ne:MAX_BBXMIN":0.0,
    "ne:MAX_BBYMAX":0.0,
    "ne:MAX_BBYMIN":0.0,
    "ne:MAX_NATSCA":0.0,
    "ne:MAX_PERKM":0.0,
    "ne:MAX_PERMI":0.0,
    "ne:MAX_POP10":0,
    "ne:MAX_POP20":0,
    "ne:MAX_POP300":0,
    "ne:MAX_POP310":0,
    "ne:MAX_POP50":0,
    "ne:MEAN_BBXC":0.0,
    "ne:MEAN_BBYC":0.0,
    "ne:MEGACITY":0,
    "ne:MIN_AREAKM":0.0,
    "ne:MIN_AREAMI":0.0,
    "ne:MIN_BBXMAX":0.0,
    "ne:MIN_BBXMIN":0.0,
    "ne:MIN_BBYMAX":0.0,
    "ne:MIN_BBYMIN":0.0,
    "ne:MIN_PERKM":0.0,
    "ne:MIN_PERMI":0.0,
    "ne:NAME":"Busia",
    "ne:NAMEASCII":"Busia",
    "ne:NAMEDIFF":0,
    "ne:NATSCALE":1,
    "ne:POP1950":0,
    "ne:POP1955":0,
    "ne:POP1960":0,
    "ne:POP1965":0,
    "ne:POP1970":0,
    "ne:POP1975":0,
    "ne:POP1980":0,
    "ne:POP1985":0,
    "ne:POP1990":0,
    "ne:POP1995":0,
    "ne:POP2000":0,
    "ne:POP2005":0,
    "ne:POP2010":0,
    "ne:POP2015":0,
    "ne:POP2020":0,
    "ne:POP2025":0,
    "ne:POP2050":0,
    "ne:POP_MAX":47100,
    "ne:POP_MIN":47100,
    "ne:POP_OTHER":0,
    "ne:RANK_MAX":7,
    "ne:RANK_MIN":7,
    "ne:SCALERANK":10,
    "ne:SOV0NAME":"Uganda",
    "ne:SOV_A3":"UGA",
    "ne:TIMEZONE":"Africa/Kampala",
    "ne:UN_FID":0,
    "ne:UN_LAT":0.0,
    "ne:UN_LONG":0.0,
    "ne:WORLDCITY":0,
    "qs:name":"Busia",
    "qs:photos_9r":0,
    "qs:photos_sr":0,
    "qs:pop_sr":"7",
    "wd:wordcount":54,
    "wof:name":"Busia",
    "wof:placetype":"locality",
    "wof:population":43200
},
  "geometry": {"coordinates":[34.09221,0.46588],"type":"Point"}
}