{
  "type": "Feature",
  "properties": {
    "gn:admin1_code":"N",
    "gn:admin2_code":"G3",
    "gn:admin3_code":"230209.0",
    "gn:admin4_code":"8647182.0",
    "gn:asciiname":"Palabek",
    "gn:country_code":"UG",
    "gn:dem":994,
    "gn:feature_class":"P",
    "gn:feature_code":"PPL",
    "gn:name":"Palabek",
    "gn:population":0,
    "gn:timezone":"Africa/Kampala",
    "iso:country":"UG",
    "wof:name":"Palabek",
    "wof:placetype":"locality"
},
  "geometry": {"coordinates":[32.58291,3.43601],"type":"Point"}
}