{
  "type": "Feature",
  "properties": {
    "gn:admin1_code":"N",
    "gn:admin2_code":"47",
    "gn:admin3_code":"233491.0",
    "gn:admin4_code":"8630011.0",
    "gn:asciiname":"Bar",
    "gn:country_code":"UG",
    "gn:dem":1100,
    "gn:feature_class":"P",
    "gn:feature_code":"PPL",
    "gn:name":"Bar",
    "gn:population":0,
    "gn:timezone":"Africa/Kampala",
    "iso:country":"UG",
    "wof:name":"Bar",
    "wof:placetype":"locality"
},
  "geometry": {"coordinates":[33.06389,2.22278],"type":"Point"}
}