{
  "type": "Feature",
  "properties": {
    "gn:admin1_code":"E",
    "gn:admin2_code":"78",
    "gn:asciiname":"Buzaya",
    "gn:country_code":"UG",
    "gn:dem":1069,
    "gn:feature_class":"P",
    "gn:feature_code":"PPL",
    "gn:name":"Buzaya",
    "gn:population":0,
    "gn:timezone":"Africa/Kampala",
    "iso:country":"UG",
    "wof:name":"Buzaya",
    "wof:placetype":"locality"
},
  "geometry": {"coordinates":[33.41716,0.8948],"type":"Point"}
}