{
  "type": "Feature",
  "properties": {
    "gn:admin1_code":"N",
    "gn:admin2_code":"77",
    "gn:admin3_code":"234911.0",
    "gn:admin4_code":"8657558.0",
    "gn:asciiname":"Ewadri",
    "gn:country_code":"UG",
    "gn:dem":1196,
    "gn:feature_class":"P",
    "gn:feature_code":"PPL",
    "gn:name":"Ewadri",
    "gn:population":0,
    "gn:timezone":"Africa/Kampala",
    "iso:country":"UG",
    "wof:name":"Ewadri",
    "wof:placetype":"locality"
},
  "geometry": {"coordinates":[30.95614,3.08948],"type":"Point"}
}