{
  "type": "Feature",
  "properties": {
    "gn:admin1_code":"N",
    "gn:admin2_code":"88",
    "gn:admin3_code":"229332.0",
    "gn:admin4_code":"8630013.0",
    "gn:asciiname":"Nakiloro",
    "gn:country_code":"UG",
    "gn:dem":1490,
    "gn:feature_class":"P",
    "gn:feature_code":"PPL",
    "gn:name":"Nakiloro",
    "gn:population":0,
    "gn:timezone":"Africa/Kampala",
    "iso:country":"UG",
    "wof:name":"Nakiloro",
    "wof:placetype":"locality"
},
  "geometry": {"coordinates":[34.73341,2.61773],"type":"Point"}
}