{
  "type": "Feature",
  "properties": {
    "gn:admin1_code":"E",
    "gn:admin2_code":"38",
    "gn:asciiname":"Nakabale",
    "gn:country_code":"UG",
    "gn:dem":1093,
    "gn:feature_class":"P",
    "gn:feature_code":"PPL",
    "gn:name":"Nakabale",
    "gn:population":0,
    "gn:timezone":"Africa/Kampala",
    "iso:country":"UG",
    "wof:name":"Nakabale",
    "wof:placetype":"locality"
},
  "geometry": {"coordinates":[33.17572,0.7077],"type":"Point"}
}