{
  "type": "Feature",
  "properties": {
    "gn:admin1_code":"N",
    "gn:admin2_code":"E3",
    "gn:admin3_code":"235459.0",
    "gn:admin4_code":"8657929.0",
    "gn:asciiname":"Lulim",
    "gn:country_code":"UG",
    "gn:dem":1124,
    "gn:feature_class":"P",
    "gn:feature_code":"PPLL",
    "gn:name":"Lulim",
    "gn:population":0,
    "gn:timezone":"Africa/Kampala",
    "iso:country":"UG",
    "wof:name":"Lulim",
    "wof:placetype":"locality"
},
  "geometry": {"coordinates":[33.40105,3.05702],"type":"Point"}
}