{
  "type": "Feature",
  "properties": {
    "gn:admin1_code":"E",
    "gn:admin2_code":"46",
    "gn:admin3_code":"7732907.0",
    "gn:admin4_code":"8658361.0",
    "gn:asciiname":"Ogosoi",
    "gn:country_code":"UG",
    "gn:dem":1057,
    "gn:feature_class":"P",
    "gn:feature_code":"PPL",
    "gn:name":"Ogosoi",
    "gn:population":0,
    "gn:timezone":"Africa/Kampala",
    "iso:country":"UG",
    "name:und_x_variant":[
        "Ogosai",
        "Ogosoi"
    ],
    "wof:name":"Ogosoi",
    "wof:placetype":"locality"
},
  "geometry": {"coordinates":[33.83333,1.33333],"type":"Point"}
}