{
  "type": "Feature",
  "properties": {
    "gn:admin1_code":"W",
    "gn:admin2_code":"28",
    "gn:asciiname":"Bundisana",
    "gn:country_code":"UG",
    "gn:dem":945,
    "gn:feature_class":"P",
    "gn:feature_code":"PPL",
    "gn:name":"Bundisana",
    "gn:population":0,
    "gn:timezone":"Africa/Kampala",
    "iso:country":"UG",
    "name:eng_x_preferred":[
        "Bundisana"
    ],
    "wof:name":"Bundisana",
    "wof:placetype":"locality"
},
  "geometry": {"coordinates":[30.08761,0.75272],"type":"Point"}
}