{
  "type": "Feature",
  "properties": {
    "gn:admin1_code":"W",
    "gn:admin2_code":"C5",
    "gn:admin3_code":"7869947.0",
    "gn:admin4_code":"8657545.0",
    "gn:asciiname":"Bugana",
    "gn:country_code":"UG",
    "gn:dem":661,
    "gn:feature_class":"P",
    "gn:feature_code":"PPL",
    "gn:name":"Bugana",
    "gn:population":0,
    "gn:timezone":"Africa/Kampala",
    "iso:country":"UG",
    "wof:name":"Bugana",
    "wof:placetype":"locality"
},
  "geometry": {"coordinates":[31.50731,2.0642],"type":"Point"}
}