{
  "type": "Feature",
  "properties": {
    "gn:admin1_code":"C",
    "gn:admin2_code":"70",
    "gn:admin3_code":"8644176.0",
    "gn:admin4_code":"7732544.0",
    "gn:asciiname":"Kamala",
    "gn:country_code":"UG",
    "gn:dem":1089,
    "gn:feature_class":"P",
    "gn:feature_code":"PPL",
    "gn:name":"Kamala",
    "gn:population":0,
    "gn:timezone":"Africa/Kampala",
    "iso:country":"UG",
    "wof:name":"Kamala",
    "wof:placetype":"locality"
},
  "geometry": {"coordinates":[32.46917,0.87444],"type":"Point"}
}