{
  "type": "Feature",
  "properties": {
    "gn:admin1_code":"C",
    "gn:admin2_code":"70",
    "gn:admin3_code":"8644176.0",
    "gn:admin4_code":"7732544.0",
    "gn:asciiname":"Kamala",
    "gn:country_code":"UG",
    "gn:dem":1089,
    "gn:feature_class":"P",
    "gn:feature_code":"PPL",
    "gn:name":"Kamala",
    "gn:population":0,
    "gn:timezone":"Africa/Kampala",
    "iso:country":"UG",
    "name:ceb_x_preferred":[
        "Kamala"
    ],
    "name:deu_x_preferred":[
        "Kamala"
    ],
    "name:fra_x_preferred":[
        "Kamala"
    ],
    "name:kor_x_preferred":[
        "\uce74\ub9d0\ub77c"
    ],
    "name:nld_x_preferred":[
        "Kamala"
    ],
    "name:por_x_preferred":[
        "Kamala"
    ],
    "name:swe_x_preferred":[
        "Kamala"
    ],
    "name:tel_x_preferred":[
        "\u0c15\u0c2e\u0c32"
    ],
    "wof:name":"Kamala",
    "wof:placetype":"locality"
},
  "geometry": {"coordinates":[32.46917,0.87444],"type":"Point"}
}