{
  "type": "Feature",
  "properties": {
    "gn:admin1_code":"N",
    "gn:admin2_code":"77",
    "gn:admin3_code":"226158.0",
    "gn:admin4_code":"8657769.0",
    "gn:asciiname":"Otrevu",
    "gn:country_code":"UG",
    "gn:dem":968,
    "gn:feature_class":"P",
    "gn:feature_code":"PPL",
    "gn:name":"Otrevu",
    "gn:population":0,
    "gn:timezone":"Africa/Kampala",
    "iso:country":"UG",
    "wof:name":"Otrevu",
    "wof:placetype":"locality"
},
  "geometry": {"coordinates":[31.08301,3.17781],"type":"Point"}
}