{
  "type": "Feature",
  "properties": {
    "gn:admin1_code":"C",
    "gn:admin2_code":"90",
    "gn:admin3_code":"7732383.0",
    "gn:admin4_code":"8658137.0",
    "gn:asciiname":"Kakinzi",
    "gn:country_code":"UG",
    "gn:dem":1099,
    "gn:feature_class":"P",
    "gn:feature_code":"PPL",
    "gn:name":"Kakinzi",
    "gn:population":0,
    "gn:timezone":"Africa/Kampala",
    "iso:country":"UG",
    "wof:name":"Kakinzi",
    "wof:placetype":"locality"
},
  "geometry": {"coordinates":[32.76667,0.58333],"type":"Point"}
}