{
  "type": "Feature",
  "properties": {
    "gn:admin1_code":"E",
    "gn:admin2_code":"38",
    "gn:admin3_code":"234617.0",
    "gn:admin4_code":"8658093.0",
    "gn:asciiname":"Budatenwa",
    "gn:country_code":"UG",
    "gn:dem":1086,
    "gn:feature_class":"P",
    "gn:feature_code":"PPL",
    "gn:name":"Budatenwa",
    "gn:population":0,
    "gn:timezone":"Africa/Kampala",
    "iso:country":"UG",
    "wof:name":"Budatenwa",
    "wof:placetype":"locality"
},
  "geometry": {"coordinates":[33.16667,0.83333],"type":"Point"}
}