{
  "type": "Feature",
  "properties": {
    "gn:admin1_code":"C",
    "gn:admin2_code":"90",
    "gn:admin3_code":"7732383.0",
    "gn:admin4_code":"8658299.0",
    "gn:asciiname":"Mindi",
    "gn:country_code":"UG",
    "gn:dem":1065,
    "gn:feature_class":"P",
    "gn:feature_code":"PPL",
    "gn:name":"Mindi",
    "gn:population":0,
    "gn:timezone":"Africa/Kampala",
    "iso:country":"UG",
    "wof:name":"Mindi",
    "wof:placetype":"locality"
},
  "geometry": {"coordinates":[32.85,0.68333],"type":"Point"}
}