{
  "type": "Feature",
  "properties": {
    "gn:admin1_code":"E",
    "gn:admin2_code":"80",
    "gn:admin3_code":"233018.0",
    "gn:admin4_code":"8658267.0",
    "gn:asciiname":"Abata",
    "gn:country_code":"UG",
    "gn:dem":1051,
    "gn:feature_class":"P",
    "gn:feature_code":"PPL",
    "gn:name":"Abata",
    "gn:population":0,
    "gn:timezone":"Africa/Kampala",
    "iso:country":"UG",
    "name:und_x_variant":[
        "Abatait",
        "Abata"
    ],
    "wof:name":"Abata",
    "wof:placetype":"locality"
},
  "geometry": {"coordinates":[33.15968,1.70061],"type":"Point"}
}