{
  "type": "Feature",
  "properties": {
    "gn:admin1_code":"N",
    "gn:admin2_code":"H7",
    "gn:admin3_code":"227147.0",
    "gn:admin4_code":"8658461.0",
    "gn:asciiname":"Gamba",
    "gn:country_code":"UG",
    "gn:dem":1535,
    "gn:feature_class":"P",
    "gn:feature_code":"PPL",
    "gn:name":"Gamba",
    "gn:population":0,
    "gn:timezone":"Africa/Kampala",
    "iso:country":"UG",
    "name:cat_x_preferred":[
        "Gamba"
    ],
    "name:ceb_x_preferred":[
        "Gamba"
    ],
    "name:ces_x_preferred":[
        "Gamba"
    ],
    "name:deu_x_preferred":[
        "Gamba"
    ],
    "name:fra_x_preferred":[
        "Gamba"
    ],
    "name:glg_x_preferred":[
        "Gamba"
    ],
    "name:hun_x_preferred":[
        "Gamba"
    ],
    "name:ita_x_preferred":[
        "Gamba"
    ],
    "name:nld_x_preferred":[
        "Gamba"
    ],
    "name:pol_x_preferred":[
        "Gamba"
    ],
    "name:por_x_preferred":[
        "Gamba"
    ],
    "name:rus_x_preferred":[
        "\u0413\u0430\u043c\u0431\u0430"
    ],
    "name:slk_x_preferred":[
        "Gamba"
    ],
    "name:spa_x_preferred":[
        "Gamba"
    ],
    "name:srp_x_preferred":[
        "Gamba"
    ],
    "name:swa_x_preferred":[
        "Gamba"
    ],
    "name:swe_x_preferred":[
        "Gamba"
    ],
    "wof:name":"Gamba",
    "wof:placetype":"locality"
},
  "geometry": {"coordinates":[30.80365,2.58342],"type":"Point"}
}