{
  "type": "Feature",
  "properties": {
    "gn:admin1_code":"N",
    "gn:admin2_code":"92",
    "gn:admin3_code":"8644156.0",
    "gn:admin4_code":"8647784.0",
    "gn:asciiname":"Atanga",
    "gn:country_code":"UG",
    "gn:dem":926,
    "gn:feature_class":"P",
    "gn:feature_code":"PPL",
    "gn:name":"Atanga",
    "gn:population":0,
    "gn:timezone":"Africa/Kampala",
    "iso:country":"UG",
    "wof:name":"Atanga",
    "wof:placetype":"locality"
},
  "geometry": {"coordinates":[32.76154,3.02531],"type":"Point"}
}