{
  "type": "Feature",
  "properties": {
    "gn:admin1_code":"E",
    "gn:admin2_code":"76",
    "gn:asciiname":"Sere",
    "gn:country_code":"UG",
    "gn:dem":1220,
    "gn:feature_class":"P",
    "gn:feature_code":"PPL",
    "gn:name":"Sere",
    "gn:population":0,
    "gn:timezone":"Africa/Kampala",
    "iso:country":"UG",
    "name:eng_x_preferred":[
        "Sere"
    ],
    "wof:name":"Sere",
    "wof:placetype":"locality"
},
  "geometry": {"coordinates":[34.14809,0.75257],"type":"Point"}
}