{
  "type": "Feature",
  "properties": {
    "gn:admin1_code":"E",
    "gn:admin2_code":"78",
    "gn:asciiname":"Mulanga",
    "gn:country_code":"UG",
    "gn:dem":1144,
    "gn:feature_class":"P",
    "gn:feature_code":"PPL",
    "gn:name":"Mulanga",
    "gn:population":0,
    "gn:timezone":"Africa/Kampala",
    "iso:country":"UG",
    "wof:name":"Mulanga",
    "wof:placetype":"locality"
},
  "geometry": {"coordinates":[33.59952,0.57936],"type":"Point"}
}