{
  "type": "Feature",
  "properties": {
    "iso:country":"UG",
    "name:ara_x_preferred":[
        "\u0643\u0627\u0645\u0648\u0644\u064a"
    ],
    "name:dut_x_preferred":[
        "Kamuli"
    ],
    "name:eng_x_preferred":[
        "Kamuli"
    ],
    "name:fre_x_preferred":[
        "Kamuli"
    ],
    "name:ita_x_preferred":[
        "Kamuli"
    ],
    "name:jpn_x_preferred":[
        "\u30ab\u30e0\u30ea"
    ],
    "name:nob_x_preferred":[
        "Kamuli"
    ],
    "name:por_x_preferred":[
        "Kamuli"
    ],
    "name:rum_x_preferred":[
        "Kamuli"
    ],
    "name:rus_x_preferred":[
        "\u041a\u0430\u043c\u0443\u043b\u0438"
    ],
    "name:swa_x_preferred":[
        "Kamuli"
    ],
    "qs:gn_country":"UG",
    "qs:gn_fcode":"ADMD",
    "qs:gn_pop":0,
    "qs:name":"Kamuli",
    "qs:name_adm0":"Uganda",
    "qs:name_adm1":"Kamuli",
    "qs:photos":397,
    "qs:photos_1k":80,
    "qs:photos_9k":2,
    "qs:photos_9r":5,
    "qs:photos_all":397,
    "qs:photos_sr":6,
    "qs:placetype":"Town",
    "qs:pop_sr":"0",
    "qs:woe_adm0":23424974,
    "wof:name":"Kamuli",
    "wof:placetype":"locality"
},
  "geometry": {"coordinates":[33.13333,1.08333],"type":"Point"}
}