{
  "type": "Feature",
  "properties": {
    "gn:admin1_code":"E",
    "gn:admin2_code":"78",
    "gn:asciiname":"Bukwaya",
    "gn:country_code":"UG",
    "gn:dem":1159,
    "gn:feature_class":"P",
    "gn:feature_code":"PPL",
    "gn:name":"Bukwaya",
    "gn:population":0,
    "gn:timezone":"Africa/Kampala",
    "iso:country":"UG",
    "wof:name":"Bukwaya",
    "wof:placetype":"locality"
},
  "geometry": {"coordinates":[33.5041,0.55246],"type":"Point"}
}