{
  "type": "Feature",
  "properties": {
    "gn:admin1_code":"E",
    "gn:admin2_code":"86",
    "gn:admin3_code":"8644164.0",
    "gn:admin4_code":"8658141.0",
    "gn:asciiname":"Bukoba",
    "gn:country_code":"UG",
    "gn:dem":1162,
    "gn:feature_class":"P",
    "gn:feature_code":"PPL",
    "gn:name":"Bukoba",
    "gn:population":0,
    "gn:timezone":"Africa/Kampala",
    "iso:country":"UG",
    "name:ara_x_preferred":[
        "\u0628\u0648\u0643\u0648\u0628\u0627"
    ],
    "name:azb_x_preferred":[
        "\u0628\u0648\u06a9\u0648\u0628\u0627"
    ],
    "name:bel_x_preferred":[
        "\u0411\u0443\u043a\u043e\u0431\u0430"
    ],
    "name:bul_x_preferred":[
        "\u0411\u0443\u043a\u043e\u0431\u0430"
    ],
    "name:ceb_x_preferred":[
        "Bukoba"
    ],
    "name:dan_x_preferred":[
        "Bukoba"
    ],
    "name:deu_x_preferred":[
        "Bukoba"
    ],
    "name:eng_x_preferred":[
        "Bukoba"
    ],
    "name:epo_x_preferred":[
        "Bukobo"
    ],
    "name:est_x_preferred":[
        "Bukoba"
    ],
    "name:eus_x_preferred":[
        "Bukoba"
    ],
    "name:fas_x_preferred":[
        "\u0628\u0648\u06a9\u0648\u0628\u0627"
    ],
    "name:fin_x_preferred":[
        "Bukoba"
    ],
    "name:fra_x_preferred":[
        "Bukoba"
    ],
    "name:hrv_x_preferred":[
        "Bukoba"
    ],
    "name:isl_x_preferred":[
        "Bukoba"
    ],
    "name:ita_x_preferred":[
        "Bukoba"
    ],
    "name:jpn_x_preferred":[
        "\u30d6\u30b3\u30d0"
    ],
    "name:kor_x_preferred":[
        "\ubd80\ucf54\ubc14"
    ],
    "name:lit_x_preferred":[
        "Bukoba"
    ],
    "name:nld_x_preferred":[
        "Bukoba"
    ],
    "name:nor_x_preferred":[
        "Bukoba"
    ],
    "name:pol_x_preferred":[
        "Bukoba"
    ],
    "name:ron_x_preferred":[
        "Bukoba"
    ],
    "name:rus_x_preferred":[
        "\u0411\u0443\u043a\u043e\u0431\u0430"
    ],
    "name:spa_x_preferred":[
        "Bukoba"
    ],
    "name:swa_x_preferred":[
        "Bukoba"
    ],
    "name:swe_x_preferred":[
        "Bukoba"
    ],
    "name:tur_x_preferred":[
        "Bukoba"
    ],
    "name:ukr_x_preferred":[
        "\u0411\u0443\u043a\u043e\u0431\u0430"
    ],
    "name:yor_x_preferred":[
        "Bukoba"
    ],
    "name:zho_x_preferred":[
        "\u5e03\u79d1\u5df4"
    ],
    "wof:name":"Bukoba",
    "wof:placetype":"locality"
},
  "geometry": {"coordinates":[33.50204,0.30745],"type":"Point"}
}