{
  "type": "Feature",
  "properties": {
    "gn:admin1_code":"E",
    "gn:admin2_code":"86",
    "gn:admin3_code":"8644164.0",
    "gn:admin4_code":"8658141.0",
    "gn:asciiname":"Bukoba",
    "gn:country_code":"UG",
    "gn:dem":1162,
    "gn:feature_class":"P",
    "gn:feature_code":"PPL",
    "gn:name":"Bukoba",
    "gn:population":0,
    "gn:timezone":"Africa/Kampala",
    "iso:country":"UG",
    "name:eng_x_preferred":[
        "Bukoba"
    ],
    "wof:name":"Bukoba",
    "wof:placetype":"locality"
},
  "geometry": {"coordinates":[33.50204,0.30745],"type":"Point"}
}