{
  "type": "Feature",
  "properties": {
    "gn:admin1_code":"C",
    "gn:admin2_code":"70",
    "gn:admin3_code":"8644157.0",
    "gn:admin4_code":"8657668.0",
    "gn:asciiname":"Bbuto",
    "gn:country_code":"UG",
    "gn:dem":1143,
    "gn:feature_class":"P",
    "gn:feature_code":"PPL",
    "gn:name":"Bbuto",
    "gn:population":0,
    "gn:timezone":"Africa/Kampala",
    "iso:country":"UG",
    "wof:name":"Bbuto",
    "wof:placetype":"locality"
},
  "geometry": {"coordinates":[32.60805999999999,0.67861],"type":"Point"}
}