{
  "type": "Feature",
  "properties": {
    "gn:admin1_code":"E",
    "gn:admin2_code":"G7",
    "gn:admin3_code":"8644167.0",
    "gn:admin4_code":"8658486.0",
    "gn:asciiname":"Banda",
    "gn:country_code":"UG",
    "gn:dem":1171,
    "gn:feature_class":"P",
    "gn:feature_code":"PPL",
    "gn:name":"Banda",
    "gn:population":0,
    "gn:timezone":"Africa/Kampala",
    "iso:country":"UG",
    "name:eng_x_preferred":[
        "Banda"
    ],
    "wof:name":"Banda",
    "wof:placetype":"locality"
},
  "geometry": {"coordinates":[33.87110999999999,0.24528],"type":"Point"}
}