{
  "type": "Feature",
  "properties": {
    "gn:admin1_code":"E",
    "gn:admin2_code":"38",
    "gn:asciiname":"Nababirye",
    "gn:country_code":"UG",
    "gn:dem":1059,
    "gn:feature_class":"P",
    "gn:feature_code":"PPL",
    "gn:name":"Nababirye",
    "gn:population":0,
    "gn:timezone":"Africa/Kampala",
    "iso:country":"UG",
    "wof:name":"Nababirye",
    "wof:placetype":"locality"
},
  "geometry": {"coordinates":[33.07219,0.83879],"type":"Point"}
}