{
  "type": "Feature",
  "properties": {
    "gn:admin1_code":"C",
    "gn:admin2_code":"D9",
    "gn:admin3_code":"8644153.0",
    "gn:admin4_code":"8657639.0",
    "gn:asciiname":"Lukumbi",
    "gn:country_code":"UG",
    "gn:dem":1101,
    "gn:feature_class":"P",
    "gn:feature_code":"PPL",
    "gn:name":"Lukumbi",
    "gn:population":0,
    "gn:timezone":"Africa/Kampala",
    "iso:country":"UG",
    "wof:name":"Lukumbi",
    "wof:placetype":"locality"
},
  "geometry": {"coordinates":[32.23333,0.85],"type":"Point"}
}