{
  "type": "Feature",
  "properties": {
    "gn:admin1_code":"C",
    "gn:admin2_code":"56",
    "gn:admin3_code":"233891.0",
    "gn:admin4_code":"8658094.0",
    "gn:asciiname":"Lwamvubu",
    "gn:country_code":"UG",
    "gn:dem":1184,
    "gn:feature_class":"P",
    "gn:feature_code":"PPL",
    "gn:name":"Lwamvubu",
    "gn:population":0,
    "gn:timezone":"Africa/Kampala",
    "iso:country":"UG",
    "wof:name":"Lwamvubu",
    "wof:placetype":"locality"
},
  "geometry": {"coordinates":[31.48333,0.31667],"type":"Point"}
}