{
  "type": "Feature",
  "properties": {
    "gn:admin1_code":"C",
    "gn:admin2_code":"96",
    "gn:admin3_code":"234053.0",
    "gn:admin4_code":"8658010.0",
    "gn:asciiname":"Gayaza",
    "gn:country_code":"UG",
    "gn:dem":1180,
    "gn:feature_class":"P",
    "gn:feature_code":"PPL",
    "gn:name":"Gayaza",
    "gn:population":0,
    "gn:timezone":"Africa/Kampala",
    "iso:country":"UG",
    "name:lug_x_preferred":[
        "Gayaza"
    ],
    "wof:name":"Gayaza",
    "wof:placetype":"locality"
},
  "geometry": {"coordinates":[32.50926,0.16139],"type":"Point"}
}