{
  "type": "Feature",
  "properties": {
    "gn:admin1_code":"E",
    "gn:admin2_code":"B8",
    "gn:admin3_code":"235185.0",
    "gn:admin4_code":"8657550.0",
    "gn:asciiname":"Abata",
    "gn:country_code":"UG",
    "gn:dem":1157,
    "gn:feature_class":"P",
    "gn:feature_code":"PPL",
    "gn:name":"Abata",
    "gn:population":0,
    "gn:timezone":"Africa/Kampala",
    "iso:country":"UG",
    "wof:name":"Abata",
    "wof:placetype":"locality"
},
  "geometry": {"coordinates":[33.48333,2.05],"type":"Point"}
}