{
  "type": "Feature",
  "properties": {
    "gn:admin1_code":"N",
    "gn:admin2_code":"I6",
    "gn:admin3_code":"233111.0",
    "gn:admin4_code":"8648147.0",
    "gn:asciiname":"Paroketto",
    "gn:country_code":"UG",
    "gn:dem":661,
    "gn:feature_class":"P",
    "gn:feature_code":"PPL",
    "gn:name":"Paroketto",
    "gn:population":0,
    "gn:timezone":"Africa/Kampala",
    "iso:country":"UG",
    "wof:name":"Paroketto",
    "wof:placetype":"locality"
},
  "geometry": {"coordinates":[31.45349,2.40972],"type":"Point"}
}