{
  "type": "Feature",
  "properties": {
    "gn:admin1_code":"N",
    "gn:admin2_code":"26",
    "gn:admin3_code":"229387.0",
    "gn:admin4_code":"8657675.0",
    "gn:asciiname":"Olwit",
    "gn:country_code":"UG",
    "gn:dem":1058,
    "gn:feature_class":"P",
    "gn:feature_code":"PPL",
    "gn:name":"Olwit",
    "gn:population":0,
    "gn:timezone":"Africa/Kampala",
    "iso:country":"UG",
    "wof:name":"Olwit",
    "wof:placetype":"locality"
},
  "geometry": {"coordinates":[32.38786,1.72607],"type":"Point"}
}