{
  "type": "Feature",
  "properties": {
    "gn:admin1_code":"E",
    "gn:admin2_code":"78",
    "gn:asciiname":"Nakasubi",
    "gn:country_code":"UG",
    "gn:dem":1108,
    "gn:feature_class":"P",
    "gn:feature_code":"PPL",
    "gn:name":"Nakasubi",
    "gn:population":0,
    "gn:timezone":"Africa/Kampala",
    "iso:country":"UG",
    "wof:name":"Nakasubi",
    "wof:placetype":"locality"
},
  "geometry": {"coordinates":[33.66196,0.59416],"type":"Point"}
}