{
  "type": "Feature",
  "properties": {
    "gn:admin1_code":"N",
    "gn:admin2_code":"26",
    "gn:asciiname":"Aboko",
    "gn:country_code":"UG",
    "gn:dem":1056,
    "gn:feature_class":"P",
    "gn:feature_code":"PPLL",
    "gn:name":"Aboko",
    "gn:population":0,
    "gn:timezone":"Africa/Kampala",
    "iso:country":"UG",
    "name:eng_x_preferred":[
        "Aboko"
    ],
    "wof:name":"Aboko",
    "wof:placetype":"locality"
},
  "geometry": {"coordinates":[32.70129,1.97893],"type":"Point"}
}