{
  "type": "Feature",
  "properties": {
    "gn:admin1_code":"C",
    "gn:admin2_code":"F5",
    "gn:admin3_code":"7910220.0",
    "gn:admin4_code":"8657951.0",
    "gn:asciiname":"Butiti",
    "gn:country_code":"UG",
    "gn:dem":1210,
    "gn:feature_class":"P",
    "gn:feature_code":"PPL",
    "gn:name":"Butiti",
    "gn:population":0,
    "gn:timezone":"Africa/Kampala",
    "iso:country":"UG",
    "wof:name":"Butiti",
    "wof:placetype":"locality"
},
  "geometry": {"coordinates":[31.71667,-0.08333],"type":"Point"}
}