{
  "type": "Feature",
  "properties": {
    "gn:admin1_code":"W",
    "gn:admin2_code":"F7",
    "gn:admin3_code":"231597.0",
    "gn:admin4_code":"8658132.0",
    "gn:asciiname":"Buyale",
    "gn:country_code":"UG",
    "gn:dem":1072,
    "gn:feature_class":"P",
    "gn:feature_code":"PPL",
    "gn:name":"Buyale",
    "gn:population":0,
    "gn:timezone":"Africa/Kampala",
    "iso:country":"UG",
    "wof:name":"Buyale",
    "wof:placetype":"locality"
},
  "geometry": {"coordinates":[32.11643,1.93421],"type":"Point"}
}