{
  "type": "Feature",
  "properties": {
    "gn:admin1_code":"W",
    "gn:admin2_code":"79",
    "gn:asciiname":"Kyanangi",
    "gn:country_code":"UG",
    "gn:dem":1556,
    "gn:feature_class":"P",
    "gn:feature_code":"PPL",
    "gn:name":"Kyanangi",
    "gn:population":0,
    "gn:timezone":"Africa/Kampala",
    "iso:country":"UG",
    "name:eng_x_preferred":[
        "Kyanangi"
    ],
    "wof:name":"Kyanangi",
    "wof:placetype":"locality"
},
  "geometry": {"coordinates":[30.19707,0.5729],"type":"Point"}
}