{
  "type": "Feature",
  "properties": {
    "gn:admin1_code":"E",
    "gn:admin2_code":"69",
    "gn:admin3_code":"8644155.0",
    "gn:admin4_code":"8658087.0",
    "gn:asciiname":"Ominya",
    "gn:country_code":"UG",
    "gn:dem":1058,
    "gn:feature_class":"P",
    "gn:feature_code":"PPL",
    "gn:name":"Ominya",
    "gn:population":0,
    "gn:timezone":"Africa/Kampala",
    "iso:country":"UG",
    "wof:name":"Ominya",
    "wof:placetype":"locality"
},
  "geometry": {"coordinates":[33.94934,1.66842],"type":"Point"}
}