{
  "type": "Feature",
  "properties": {
    "gn:admin1_code":"E",
    "gn:admin2_code":"95",
    "gn:admin3_code":"226232.0",
    "gn:admin4_code":"8657815.0",
    "gn:asciiname":"Otatai",
    "gn:country_code":"UG",
    "gn:dem":1094,
    "gn:feature_class":"P",
    "gn:feature_code":"PPL",
    "gn:name":"Otatai",
    "gn:population":0,
    "gn:timezone":"Africa/Kampala",
    "iso:country":"UG",
    "wof:name":"Otatai",
    "wof:placetype":"locality"
},
  "geometry": {"coordinates":[33.61865,1.65046],"type":"Point"}
}