{
  "type": "Feature",
  "properties": {
    "gn:admin1_code":"E",
    "gn:admin2_code":"E1",
    "gn:admin3_code":"8644136.0",
    "gn:admin4_code":"8658053.0",
    "gn:asciiname":"Nakazinga",
    "gn:country_code":"UG",
    "gn:dem":1081,
    "gn:feature_class":"P",
    "gn:feature_code":"PPL",
    "gn:name":"Nakazinga",
    "gn:population":0,
    "gn:timezone":"Africa/Kampala",
    "iso:country":"UG",
    "wof:name":"Nakazinga",
    "wof:placetype":"locality"
},
  "geometry": {"coordinates":[33.79475,0.73957],"type":"Point"}
}