{
  "type": "Feature",
  "properties": {
    "gn:admin1_code":"W",
    "gn:admin2_code":"C9",
    "gn:admin3_code":"8644166.0",
    "gn:admin4_code":"8658270.0",
    "gn:asciiname":"Kasese",
    "gn:country_code":"UG",
    "gn:dem":1572,
    "gn:feature_class":"P",
    "gn:feature_code":"PPL",
    "gn:name":"Kasese",
    "gn:population":0,
    "gn:timezone":"Africa/Kampala",
    "iso:country":"UG",
    "name:azb_x_preferred":[
        "\u06a9\u0627\u0633\u0633\u0647"
    ],
    "name:deu_x_preferred":[
        "Kasese"
    ],
    "name:fas_x_preferred":[
        "\u06a9\u0627\u0633\u0633\u0647"
    ],
    "name:fra_x_preferred":[
        "Kasese"
    ],
    "name:heb_x_preferred":[
        "\u05e7\u05d0\u05e1\u05d4"
    ],
    "name:heb_x_variant":[
        "\u05e7\u05e1\u05e1\u05d4"
    ],
    "name:hrv_x_preferred":[
        "Kasese"
    ],
    "name:hun_x_preferred":[
        "Kasese"
    ],
    "name:ita_x_preferred":[
        "Kasese"
    ],
    "name:jpn_x_preferred":[
        "\u30ab\u30bb\u30bb"
    ],
    "name:lit_x_preferred":[
        "Kases\u0117"
    ],
    "name:lug_x_preferred":[
        "Kasese"
    ],
    "name:nld_x_preferred":[
        "Kasese"
    ],
    "name:pol_x_preferred":[
        "Kasese"
    ],
    "name:por_x_preferred":[
        "Kasese"
    ],
    "name:ron_x_preferred":[
        "Kasese"
    ],
    "name:rus_x_preferred":[
        "\u041a\u0430\u0441\u0435\u0441\u0435"
    ],
    "name:swa_x_preferred":[
        "Kasese"
    ],
    "name:urd_x_preferred":[
        "\u06a9\u0627\u0633\u06cc\u0633\u06d2"
    ],
    "name:zho_x_preferred":[
        "\u5361\u585e\u585e"
    ],
    "wof:name":"Kasese",
    "wof:placetype":"locality"
},
  "geometry": {"coordinates":[30.93333,-0.98333],"type":"Point"}
}