{
  "type": "Feature",
  "properties": {
    "gn:admin1_code":"W",
    "gn:admin2_code":"C9",
    "gn:admin3_code":"8644166.0",
    "gn:admin4_code":"8658270.0",
    "gn:asciiname":"Kasese",
    "gn:country_code":"UG",
    "gn:dem":1572,
    "gn:feature_class":"P",
    "gn:feature_code":"PPL",
    "gn:name":"Kasese",
    "gn:population":0,
    "gn:timezone":"Africa/Kampala",
    "iso:country":"UG",
    "wof:name":"Kasese",
    "wof:placetype":"locality"
},
  "geometry": {"coordinates":[30.93333,-0.98333],"type":"Point"}
}