{
  "type": "Feature",
  "properties": {
    "gn:admin1_code":"N",
    "gn:admin2_code":"58",
    "gn:admin3_code":"8080237.0",
    "gn:admin4_code":"8261564.0",
    "gn:asciiname":"Aryek",
    "gn:country_code":"UG",
    "gn:dem":967,
    "gn:feature_class":"P",
    "gn:feature_code":"PPL",
    "gn:name":"Aryek",
    "gn:population":0,
    "gn:timezone":"Africa/Kampala",
    "iso:country":"UG",
    "wof:name":"Aryek",
    "wof:placetype":"locality"
},
  "geometry": {"coordinates":[31.09125,2.52249],"type":"Point"}
}