{
  "type": "Feature",
  "properties": {
    "gn:admin1_code":"E",
    "gn:admin2_code":"76",
    "gn:asciiname":"Pochowa",
    "gn:country_code":"UG",
    "gn:dem":1129,
    "gn:feature_class":"P",
    "gn:feature_code":"PPL",
    "gn:name":"Pochowa",
    "gn:population":0,
    "gn:timezone":"Africa/Kampala",
    "iso:country":"UG",
    "name:eng_x_preferred":[
        "Pochowa"
    ],
    "wof:name":"Pochowa",
    "wof:placetype":"locality"
},
  "geometry": {"coordinates":[34.02405,0.67816],"type":"Point"}
}