{
  "type": "Feature",
  "properties": {
    "gn:admin1_code":"W",
    "gn:admin2_code":"40",
    "gn:admin3_code":"234040.0",
    "gn:admin4_code":"8657556.0",
    "gn:asciiname":"Kitoko",
    "gn:country_code":"UG",
    "gn:dem":1827,
    "gn:feature_class":"P",
    "gn:feature_code":"PPL",
    "gn:name":"Kitoko",
    "gn:population":0,
    "gn:timezone":"Africa/Kampala",
    "iso:country":"UG",
    "wof:name":"Kitoko",
    "wof:placetype":"locality"
},
  "geometry": {"coordinates":[30.06667,0.36667],"type":"Point"}
}