{
  "type": "Feature",
  "properties": {
    "gn:admin1_code":"E",
    "gn:admin2_code":"38",
    "gn:asciiname":"Agaliawamu",
    "gn:country_code":"UG",
    "gn:dem":1115,
    "gn:feature_class":"P",
    "gn:feature_code":"PPL",
    "gn:name":"Agaliawamu",
    "gn:population":0,
    "gn:timezone":"Africa/Kampala",
    "iso:country":"UG",
    "wof:name":"Agaliawamu",
    "wof:placetype":"locality"
},
  "geometry": {"coordinates":[33.24279,0.94573],"type":"Point"}
}