{
  "type": "Feature",
  "properties": {
    "gn:admin1_code":"N",
    "gn:admin2_code":"B9",
    "gn:admin3_code":"231253.0",
    "gn:admin4_code":"8630017.0",
    "gn:asciiname":"Olwal",
    "gn:country_code":"UG",
    "gn:dem":1075,
    "gn:feature_class":"P",
    "gn:feature_code":"PPL",
    "gn:name":"Olwal",
    "gn:population":0,
    "gn:timezone":"Africa/Kampala",
    "iso:country":"UG",
    "wof:name":"Olwal",
    "wof:placetype":"locality"
},
  "geometry": {"coordinates":[32.08124,2.83646],"type":"Point"}
}