{
  "type": "Feature",
  "properties": {
    "gn:admin1_code":"E",
    "gn:admin2_code":"G4",
    "gn:asciiname":"Nanvunano",
    "gn:country_code":"UG",
    "gn:dem":1140,
    "gn:feature_class":"P",
    "gn:feature_code":"PPL",
    "gn:name":"Nanvunano",
    "gn:population":0,
    "gn:timezone":"Africa/Kampala",
    "iso:country":"UG",
    "wof:name":"Nanvunano",
    "wof:placetype":"locality"
},
  "geometry": {"coordinates":[33.3231,0.67815],"type":"Point"}
}