{
  "type": "Feature",
  "properties": {
    "gn:admin1_code":"W",
    "gn:admin2_code":"D3",
    "gn:admin3_code":"8644177.0",
    "gn:admin4_code":"8658011.0",
    "gn:asciiname":"Kagasa",
    "gn:country_code":"UG",
    "gn:dem":1252,
    "gn:feature_class":"P",
    "gn:feature_code":"PPL",
    "gn:name":"Kagasa",
    "gn:population":0,
    "gn:timezone":"Africa/Kampala",
    "iso:country":"UG",
    "wof:name":"Kagasa",
    "wof:placetype":"locality"
},
  "geometry": {"coordinates":[30.78333,0.15],"type":"Point"}
}