{
  "type": "Feature",
  "properties": {
    "gn:admin1_code":"C",
    "gn:admin2_code":"G5",
    "gn:admin3_code":"7910221.0",
    "gn:admin4_code":"8658034.0",
    "gn:asciiname":"Gulama",
    "gn:country_code":"UG",
    "gn:dem":1303,
    "gn:feature_class":"P",
    "gn:feature_code":"PPL",
    "gn:name":"Gulama",
    "gn:population":0,
    "gn:timezone":"Africa/Kampala",
    "iso:country":"UG",
    "name:ind_x_preferred":[
        "Gulama"
    ],
    "wof:name":"Gulama",
    "wof:placetype":"locality"
},
  "geometry": {"coordinates":[31.71667,-0.41667],"type":"Point"}
}