{
  "type": "Feature",
  "properties": {
    "gn:admin1_code":"E",
    "gn:admin2_code":"E1",
    "gn:admin3_code":"8644136.0",
    "gn:admin4_code":"8658118.0",
    "gn:asciiname":"Budatu",
    "gn:country_code":"UG",
    "gn:dem":1086,
    "gn:feature_class":"P",
    "gn:feature_code":"PPL",
    "gn:name":"Budatu",
    "gn:population":0,
    "gn:timezone":"Africa/Kampala",
    "iso:country":"UG",
    "wof:name":"Budatu",
    "wof:placetype":"locality"
},
  "geometry": {"coordinates":[33.58385,0.885],"type":"Point"}
}