{
  "type": "Feature",
  "properties": {
    "gn:admin1_code":"W",
    "gn:admin2_code":"81",
    "gn:admin3_code":"7732901.0",
    "gn:admin4_code":"8658569.0",
    "gn:asciiname":"Lwemizimu",
    "gn:country_code":"UG",
    "gn:dem":1260,
    "gn:feature_class":"P",
    "gn:feature_code":"PPL",
    "gn:name":"Lwemizimu",
    "gn:population":0,
    "gn:timezone":"Africa/Kampala",
    "iso:country":"UG",
    "wof:name":"Lwemizimu",
    "wof:placetype":"locality"
},
  "geometry": {"coordinates":[30.32944,0.02917],"type":"Point"}
}