{
  "type": "Feature",
  "properties": {
    "gn:admin1_code":"E",
    "gn:admin2_code":"G4",
    "gn:admin3_code":"229762.0",
    "gn:admin4_code":"7732526.0",
    "gn:asciiname":"Bukanga",
    "gn:country_code":"UG",
    "gn:dem":1106,
    "gn:feature_class":"P",
    "gn:feature_code":"PPL",
    "gn:name":"Bukanga",
    "gn:population":0,
    "gn:timezone":"Africa/Kampala",
    "iso:country":"UG",
    "wof:name":"Bukanga",
    "wof:placetype":"locality"
},
  "geometry": {"coordinates":[33.35778,0.70917],"type":"Point"}
}