{
  "type": "Feature",
  "properties": {
    "gn:admin1_code":"C",
    "gn:admin2_code":"89",
    "gn:asciiname":"Kasabo",
    "gn:country_code":"UG",
    "gn:dem":1184,
    "gn:feature_class":"P",
    "gn:feature_code":"PPL",
    "gn:name":"Kasabo",
    "gn:population":0,
    "gn:timezone":"Africa/Kampala",
    "iso:country":"UG",
    "wof:name":"Kasabo",
    "wof:placetype":"locality"
},
  "geometry": {"coordinates":[32.35270999999999,0.37126],"type":"Point"}
}