{
  "type": "Feature",
  "properties": {
    "gn:admin1_code":"E",
    "gn:admin2_code":"G7",
    "gn:admin3_code":"8644167.0",
    "gn:admin4_code":"8657566.0",
    "gn:asciiname":"Buduma",
    "gn:country_code":"UG",
    "gn:dem":1109,
    "gn:feature_class":"P",
    "gn:feature_code":"PPL",
    "gn:name":"Buduma",
    "gn:population":0,
    "gn:timezone":"Africa/Kampala",
    "iso:country":"UG",
    "name:deu_x_preferred":[
        "Buduma"
    ],
    "name:eng_x_preferred":[
        "Buduma"
    ],
    "name:fra_x_preferred":[
        "Buduma"
    ],
    "wof:name":"Buduma",
    "wof:placetype":"locality"
},
  "geometry": {"coordinates":[33.90075,0.49523],"type":"Point"}
}