{
  "type": "Feature",
  "properties": {
    "gn:admin1_code":"W",
    "gn:admin2_code":"52",
    "gn:admin3_code":"232055.0",
    "gn:admin4_code":"8658364.0",
    "gn:asciiname":"Kanama",
    "gn:country_code":"UG",
    "gn:dem":1468,
    "gn:feature_class":"P",
    "gn:feature_code":"PPL",
    "gn:name":"Kanama",
    "gn:population":0,
    "gn:timezone":"Africa/Kampala",
    "iso:country":"UG",
    "wof:name":"Kanama",
    "wof:placetype":"locality"
},
  "geometry": {"coordinates":[30.56667,-0.35],"type":"Point"}
}