{
  "type": "Feature",
  "properties": {
    "gn:admin1_code":"C",
    "gn:admin2_code":"56",
    "gn:admin3_code":"8644175.0",
    "gn:admin4_code":"8658716.0",
    "gn:asciiname":"Kajulirwa",
    "gn:country_code":"UG",
    "gn:dem":1157,
    "gn:feature_class":"P",
    "gn:feature_code":"PPL",
    "gn:name":"Kajulirwa",
    "gn:population":0,
    "gn:timezone":"Africa/Kampala",
    "iso:country":"UG",
    "wof:name":"Kajulirwa",
    "wof:placetype":"locality"
},
  "geometry": {"coordinates":[31.78333,0.71667],"type":"Point"}
}