{
  "type": "Feature",
  "properties": {
    "gn:admin1_code":"N",
    "gn:admin2_code":"26",
    "gn:admin3_code":"229387.0",
    "gn:admin4_code":"8261612.0",
    "gn:asciiname":"Tarogali",
    "gn:country_code":"UG",
    "gn:dem":1051,
    "gn:feature_class":"P",
    "gn:feature_code":"PPL",
    "gn:name":"Tarogali",
    "gn:population":0,
    "gn:timezone":"Africa/Kampala",
    "iso:country":"UG",
    "wof:name":"Tarogali",
    "wof:placetype":"locality"
},
  "geometry": {"coordinates":[32.3381,1.82772],"type":"Point"}
}