{
  "type": "Feature",
  "properties": {
    "gn:admin1_code":"E",
    "gn:admin2_code":"C6",
    "gn:admin3_code":"234147.0",
    "gn:admin4_code":"7732535.0",
    "gn:asciiname":"Mulanga",
    "gn:country_code":"UG",
    "gn:dem":1078,
    "gn:feature_class":"P",
    "gn:feature_code":"PPLL",
    "gn:name":"Mulanga",
    "gn:population":0,
    "gn:timezone":"Africa/Kampala",
    "iso:country":"UG",
    "wof:name":"Mulanga",
    "wof:placetype":"locality"
},
  "geometry": {"coordinates":[33.8261,0.85363],"type":"Point"}
}