{
  "type": "Feature",
  "properties": {
    "gn:admin1_code":"E",
    "gn:admin2_code":"95",
    "gn:admin3_code":"226232.0",
    "gn:admin4_code":"8657623.0",
    "gn:asciiname":"Ojingai",
    "gn:country_code":"UG",
    "gn:dem":1082,
    "gn:feature_class":"P",
    "gn:feature_code":"PPL",
    "gn:name":"Ojingai",
    "gn:population":0,
    "gn:timezone":"Africa/Kampala",
    "iso:country":"UG",
    "name:und_x_variant":[
        "Ogingai",
        "Ojingai"
    ],
    "wof:name":"Ojingai",
    "wof:placetype":"locality"
},
  "geometry": {"coordinates":[33.58153,1.75165],"type":"Point"}
}