{
  "type": "Feature",
  "properties": {
    "gn:admin1_code":"C",
    "gn:admin2_code":"D8",
    "gn:asciiname":"Lugo",
    "gn:country_code":"UG",
    "gn:dem":1249,
    "gn:feature_class":"P",
    "gn:feature_code":"PPL",
    "gn:name":"Lugo",
    "gn:population":0,
    "gn:timezone":"Africa/Kampala",
    "iso:country":"UG",
    "wof:name":"Lugo",
    "wof:placetype":"locality"
},
  "geometry": {"coordinates":[32.15235999999999,0.32001],"type":"Point"}
}