{
  "type": "Feature",
  "properties": {
    "gn:admin1_code":"N",
    "gn:admin2_code":"B7",
    "gn:admin3_code":"231170.0",
    "gn:admin4_code":"8657992.0",
    "gn:asciiname":"Waibalaibi",
    "gn:country_code":"UG",
    "gn:dem":1063,
    "gn:feature_class":"P",
    "gn:feature_code":"PPL",
    "gn:name":"Waibalaibi",
    "gn:population":0,
    "gn:timezone":"Africa/Kampala",
    "iso:country":"UG",
    "name:eng_x_preferred":[
        "Waibalaibi"
    ],
    "wof:name":"Waibalaibi",
    "wof:placetype":"locality"
},
  "geometry": {"coordinates":[32.72897,1.60225],"type":"Point"}
}