{
  "type": "Feature",
  "properties": {
    "gn:admin1_code":"N",
    "gn:admin2_code":"58",
    "gn:admin3_code":"8080237.0",
    "gn:admin4_code":"8080218.0",
    "gn:asciiname":"Rero",
    "gn:country_code":"UG",
    "gn:dem":952,
    "gn:feature_class":"P",
    "gn:feature_code":"PPL",
    "gn:name":"Rero",
    "gn:population":0,
    "gn:timezone":"Africa/Kampala",
    "iso:country":"UG",
    "wof:name":"Rero",
    "wof:placetype":"locality"
},
  "geometry": {"coordinates":[31.24274,2.24968],"type":"Point"}
}