{
  "type": "Feature",
  "properties": {
    "gn:admin1_code":"E",
    "gn:admin2_code":"38",
    "gn:admin3_code":"234617.0",
    "gn:admin4_code":"8657697.0",
    "gn:asciiname":"Malugulya",
    "gn:country_code":"UG",
    "gn:dem":1046,
    "gn:feature_class":"P",
    "gn:feature_code":"PPL",
    "gn:name":"Malugulya",
    "gn:population":0,
    "gn:timezone":"Africa/Kampala",
    "iso:country":"UG",
    "wof:name":"Malugulya",
    "wof:placetype":"locality"
},
  "geometry": {"coordinates":[32.96667,0.95],"type":"Point"}
}