{
  "type": "Feature",
  "properties": {
    "iso:country":"UG",
    "name:ara_x_preferred":[
        "\u0645\u0627\u0633\u064a\u0646\u062f\u0649"
    ],
    "name:ben_x_preferred":[
        "\u09ae\u09be\u09b8\u09bf\u09a8\u09cd\u09a1\u09bf"
    ],
    "name:dan_x_preferred":[
        "Masindi"
    ],
    "name:dut_x_preferred":[
        "Masindi"
    ],
    "name:eng_x_preferred":[
        "Masindi"
    ],
    "name:fin_x_preferred":[
        "Masindi"
    ],
    "name:fre_x_preferred":[
        "Masindi"
    ],
    "name:ger_x_preferred":[
        "Masindi"
    ],
    "name:gre_x_preferred":[
        "\u039c\u03b1\u03c3\u03af\u03bd\u03c4\u03b9"
    ],
    "name:guj_x_preferred":[
        "\u0aae\u0ab8\u0abf\u0a82\u0aa1\u0ac0"
    ],
    "name:hin_x_preferred":[
        "\u092e\u093e\u0938\u093f\u0902\u0926\u0940"
    ],
    "name:ind_x_preferred":[
        "Masindi"
    ],
    "name:ita_x_preferred":[
        "Masindi"
    ],
    "name:jpn_x_preferred":[
        "\u30de\u30b7\u30f3\u30c7\u30a3"
    ],
    "name:kan_x_preferred":[
        "\u0cae\u0cb8\u0cbf\u0c82\u0ca1\u0cbf"
    ],
    "name:kor_x_preferred":[
        "\ub9c8\uc2e0\ub514"
    ],
    "name:lav_x_preferred":[
        "Masindi"
    ],
    "name:lit_x_preferred":[
        "Masindis"
    ],
    "name:mar_x_preferred":[
        "\u092e\u093e\u0938\u093f\u0902\u0926\u0940"
    ],
    "name:may_x_preferred":[
        "Masindi"
    ],
    "name:nob_x_preferred":[
        "Masindi"
    ],
    "name:pol_x_preferred":[
        "Masindi"
    ],
    "name:por_x_preferred":[
        "Masindi"
    ],
    "name:rum_x_preferred":[
        "Masindi"
    ],
    "name:rus_x_preferred":[
        "\u041c\u0430\u0441\u0438\u043d\u0434\u0438"
    ],
    "name:sin_x_preferred":[
        "\u0db8\u0dc3\u0db1\u0dca\u0da9\u0dd2"
    ],
    "name:spa_x_preferred":[
        "Masindi"
    ],
    "name:swa_x_preferred":[
        "Masindi"
    ],
    "name:swe_x_preferred":[
        "Masindi"
    ],
    "name:tam_x_preferred":[
        "\u0bae\u0b9a\u0bbf\u0ba3\u0bcd\u0b9f\u0bbf"
    ],
    "name:tel_x_preferred":[
        "\u0c2e\u0c3e\u0c38\u0c3f\u0c02\u0c26\u0c3f"
    ],
    "name:tha_x_preferred":[
        "\u0e21\u0e32\u0e0b\u0e34\u0e19\u0e14\u0e35"
    ],
    "name:tur_x_preferred":[
        "Masindi"
    ],
    "name:ukr_x_preferred":[
        "\u041c\u0430\u0441\u0456\u043d\u0434\u0456"
    ],
    "name:urd_x_preferred":[
        "\u0645\u0627\u0633\u06cc\u0646\u062f\u06cc"
    ],
    "name:vie_x_preferred":[
        "Masindi"
    ],
    "qs:gn_country":"UG",
    "qs:gn_fcode":"PPL",
    "qs:gn_pop":0,
    "qs:name":"Masindi",
    "qs:name_adm0":"Uganda",
    "qs:name_adm1":"Masindi",
    "qs:photos":113,
    "qs:photos_1k":23,
    "qs:photos_9k":1,
    "qs:photos_9r":3,
    "qs:photos_all":113,
    "qs:photos_sr":3,
    "qs:placetype":"Town",
    "qs:pop_sr":"0",
    "qs:woe_adm0":23424974,
    "wof:name":"Masindi",
    "wof:placetype":"locality"
},
  "geometry": {"coordinates":[31.63737,1.59284],"type":"Point"}
}