{
  "type": "Feature",
  "properties": {
    "gn:admin1_code":"E",
    "gn:admin2_code":"46",
    "gn:admin3_code":"7732907.0",
    "gn:admin4_code":"8658102.0",
    "gn:asciiname":"Akisim",
    "gn:country_code":"UG",
    "gn:dem":1051,
    "gn:feature_class":"P",
    "gn:feature_code":"PPL",
    "gn:name":"Akisim",
    "gn:population":0,
    "gn:timezone":"Africa/Kampala",
    "iso:country":"UG",
    "wof:name":"Akisim",
    "wof:placetype":"locality"
},
  "geometry": {"coordinates":[33.83333,1.38333],"type":"Point"}
}