{
  "type": "Feature",
  "properties": {
    "gn:admin1_code":"E",
    "gn:admin2_code":"33",
    "gn:asciiname":"Busiya",
    "gn:country_code":"UG",
    "gn:dem":1126,
    "gn:feature_class":"P",
    "gn:feature_code":"PPL",
    "gn:name":"Busiya",
    "gn:population":0,
    "gn:timezone":"Africa/Kampala",
    "iso:country":"UG",
    "wof:name":"Busiya",
    "wof:placetype":"locality"
},
  "geometry": {"coordinates":[33.18214,0.64906],"type":"Point"}
}