{
  "type": "Feature",
  "properties": {
    "gn:admin1_code":"W",
    "gn:admin2_code":"I1",
    "gn:admin3_code":"233860.0",
    "gn:admin4_code":"8657660.0",
    "gn:asciiname":"Kasokero",
    "gn:country_code":"UG",
    "gn:dem":1227,
    "gn:feature_class":"P",
    "gn:feature_code":"PPL",
    "gn:name":"Kasokero",
    "gn:population":0,
    "gn:timezone":"Africa/Kampala",
    "iso:country":"UG",
    "wof:name":"Kasokero",
    "wof:placetype":"locality"
},
  "geometry": {"coordinates":[30.86667000000001,0.96667],"type":"Point"}
}