{
  "type": "Feature",
  "properties": {
    "gn:admin1_code":"E",
    "gn:admin2_code":"86",
    "gn:admin3_code":"8644164.0",
    "gn:admin4_code":"8658491.0",
    "gn:asciiname":"Bukasero",
    "gn:country_code":"UG",
    "gn:dem":1162,
    "gn:feature_class":"P",
    "gn:feature_code":"PPL",
    "gn:name":"Bukasero",
    "gn:population":0,
    "gn:timezone":"Africa/Kampala",
    "iso:country":"UG",
    "name:eng_x_preferred":[
        "Bukasero"
    ],
    "wof:name":"Bukasero",
    "wof:placetype":"locality"
},
  "geometry": {"coordinates":[33.46536,0.38335],"type":"Point"}
}