{
  "type": "Feature",
  "properties": {
    "gn:admin1_code":"C",
    "gn:admin2_code":"F2",
    "gn:admin3_code":"233919.0",
    "gn:admin4_code":"8657880.0",
    "gn:asciiname":"Kibo",
    "gn:country_code":"UG",
    "gn:dem":1202,
    "gn:feature_class":"P",
    "gn:feature_code":"PPL",
    "gn:name":"Kibo",
    "gn:population":0,
    "gn:timezone":"Africa/Kampala",
    "iso:country":"UG",
    "name:ceb_x_preferred":[
        "Kibo"
    ],
    "name:dan_x_preferred":[
        "Kibo"
    ],
    "name:deu_x_preferred":[
        "Kibo"
    ],
    "name:eng_x_preferred":[
        "Kibo"
    ],
    "name:epo_x_preferred":[
        "Kibo"
    ],
    "name:fin_x_preferred":[
        "Kibo"
    ],
    "name:fra_x_preferred":[
        "Kib\u014d"
    ],
    "name:hun_x_preferred":[
        "Kibo"
    ],
    "name:lav_x_preferred":[
        "Kibo"
    ],
    "name:pol_x_preferred":[
        "Kibo"
    ],
    "name:rus_x_preferred":[
        "\u041a\u0438\u0431\u043e"
    ],
    "name:swe_x_preferred":[
        "Kibo"
    ],
    "wof:name":"Kibo",
    "wof:placetype":"locality"
},
  "geometry": {"coordinates":[33.26386,0.05353],"type":"Point"}
}