{
  "type": "Feature",
  "properties": {
    "gn:admin1_code":"C",
    "gn:admin2_code":"89",
    "gn:asciiname":"Kafumu",
    "gn:country_code":"UG",
    "gn:dem":1201,
    "gn:feature_class":"P",
    "gn:feature_code":"PPL",
    "gn:name":"Kafumu",
    "gn:population":0,
    "gn:timezone":"Africa/Kampala",
    "iso:country":"UG",
    "wof:name":"Kafumu",
    "wof:placetype":"locality"
},
  "geometry": {"coordinates":[32.26234,0.23306],"type":"Point"}
}