{
  "type": "Feature",
  "properties": {
    "gn:admin1_code":"E",
    "gn:admin2_code":"76",
    "gn:asciiname":"Akouketom",
    "gn:country_code":"UG",
    "gn:dem":1284,
    "gn:feature_class":"P",
    "gn:feature_code":"PPL",
    "gn:name":"Akouketom",
    "gn:population":0,
    "gn:timezone":"Africa/Kampala",
    "iso:country":"UG",
    "name:eng_x_preferred":[
        "Akouketom"
    ],
    "wof:name":"Akouketom",
    "wof:placetype":"locality"
},
  "geometry": {"coordinates":[34.27547,0.72135],"type":"Point"}
}