{
  "type": "Feature",
  "properties": {
    "gn:admin1_code":"C",
    "gn:admin2_code":"I3",
    "gn:admin3_code":"8643028.0",
    "gn:admin4_code":"8657995.0",
    "gn:asciiname":"Nakabanga",
    "gn:country_code":"UG",
    "gn:dem":1336,
    "gn:feature_class":"P",
    "gn:feature_code":"PPL",
    "gn:name":"Nakabanga",
    "gn:population":0,
    "gn:timezone":"Africa/Kampala",
    "iso:country":"UG",
    "wof:name":"Nakabanga",
    "wof:placetype":"locality"
},
  "geometry": {"coordinates":[31.28333,-0.95],"type":"Point"}
}