{
  "type": "Feature",
  "properties": {
    "gn:admin1_code":"W",
    "gn:admin2_code":"79",
    "gn:asciiname":"Busoma",
    "gn:country_code":"UG",
    "gn:dem":1642,
    "gn:feature_class":"P",
    "gn:feature_code":"PPL",
    "gn:name":"Busoma",
    "gn:population":0,
    "gn:timezone":"Africa/Kampala",
    "iso:country":"UG",
    "name:eng_x_preferred":[
        "Busoma"
    ],
    "wof:name":"Busoma",
    "wof:placetype":"locality"
},
  "geometry": {"coordinates":[30.18581,0.68136],"type":"Point"}
}