{
  "type": "Feature",
  "properties": {
    "gn:admin1_code":"E",
    "gn:admin2_code":"60",
    "gn:admin3_code":"226822.0",
    "gn:admin4_code":"8658639.0",
    "gn:asciiname":"Omotoi",
    "gn:country_code":"UG",
    "gn:dem":1041,
    "gn:feature_class":"P",
    "gn:feature_code":"PPL",
    "gn:name":"Omotoi",
    "gn:population":0,
    "gn:timezone":"Africa/Kampala",
    "iso:country":"UG",
    "name:und_x_variant":[
        "Motoi",
        "Omotoi"
    ],
    "wof:name":"Omotoi",
    "wof:placetype":"locality"
},
  "geometry": {"coordinates":[33.78333,1.31667],"type":"Point"}
}