{
  "type": "Feature",
  "properties": {
    "gn:admin1_code":"C",
    "gn:admin2_code":"89",
    "gn:asciiname":"Makumbi",
    "gn:country_code":"UG",
    "gn:dem":1176,
    "gn:feature_class":"P",
    "gn:feature_code":"PPL",
    "gn:name":"Makumbi",
    "gn:population":0,
    "gn:timezone":"Africa/Kampala",
    "iso:country":"UG",
    "wof:name":"Makumbi",
    "wof:placetype":"locality"
},
  "geometry": {"coordinates":[32.20727,0.1112],"type":"Point"}
}