{
  "type": "Feature",
  "properties": {
    "gn:admin1_code":"C",
    "gn:admin2_code":"70",
    "gn:admin3_code":"8644176.0",
    "gn:admin4_code":"8657634.0",
    "gn:asciiname":"Nkampa",
    "gn:country_code":"UG",
    "gn:dem":1149,
    "gn:feature_class":"P",
    "gn:feature_code":"PPL",
    "gn:name":"Nkampa",
    "gn:population":0,
    "gn:timezone":"Africa/Kampala",
    "iso:country":"UG",
    "wof:name":"Nkampa",
    "wof:placetype":"locality"
},
  "geometry": {"coordinates":[32.51167,0.76639],"type":"Point"}
}