{
  "type": "Feature",
  "properties": {
    "gn:admin1_code":"E",
    "gn:admin2_code":"78",
    "gn:asciiname":"Bulyansime",
    "gn:country_code":"UG",
    "gn:dem":1152,
    "gn:feature_class":"P",
    "gn:feature_code":"PPL",
    "gn:name":"Bulyansime",
    "gn:population":0,
    "gn:timezone":"Africa/Kampala",
    "iso:country":"UG",
    "wof:name":"Bulyansime",
    "wof:placetype":"locality"
},
  "geometry": {"coordinates":[33.56069,0.54626],"type":"Point"}
}