{
  "type": "Feature",
  "properties": {
    "gn:admin1_code":"E",
    "gn:admin2_code":"95",
    "gn:admin3_code":"226232.0",
    "gn:admin4_code":"8658303.0",
    "gn:asciiname":"Odina",
    "gn:country_code":"UG",
    "gn:dem":1052,
    "gn:feature_class":"P",
    "gn:feature_code":"PPL",
    "gn:name":"Odina",
    "gn:population":0,
    "gn:timezone":"Africa/Kampala",
    "iso:country":"UG",
    "wof:name":"Odina",
    "wof:placetype":"locality"
},
  "geometry": {"coordinates":[33.45126,1.72063],"type":"Point"}
}