{
  "type": "Feature",
  "properties": {
    "gn:admin1_code":"N",
    "gn:admin2_code":"26",
    "gn:admin3_code":"229387.0",
    "gn:admin4_code":"8261612.0",
    "gn:asciiname":"Abudama",
    "gn:country_code":"UG",
    "gn:dem":1052,
    "gn:feature_class":"P",
    "gn:feature_code":"PPL",
    "gn:name":"Abudama",
    "gn:population":0,
    "gn:timezone":"Africa/Kampala",
    "iso:country":"UG",
    "wof:name":"Abudama",
    "wof:placetype":"locality"
},
  "geometry": {"coordinates":[32.1451,1.72985],"type":"Point"}
}