{
  "type": "Feature",
  "properties": {
    "gn:admin1_code":"E",
    "gn:admin2_code":"38",
    "gn:asciiname":"Bungongo",
    "gn:country_code":"UG",
    "gn:dem":1125,
    "gn:feature_class":"P",
    "gn:feature_code":"PPL",
    "gn:name":"Bungongo",
    "gn:population":0,
    "gn:timezone":"Africa/Kampala",
    "iso:country":"UG",
    "wof:name":"Bungongo",
    "wof:placetype":"locality"
},
  "geometry": {"coordinates":[33.23037,0.89736],"type":"Point"}
}