{
  "type": "Feature",
  "properties": {
    "gn:admin1_code":"C",
    "gn:admin2_code":"F1",
    "gn:asciiname":"Kamugombwa",
    "gn:country_code":"UG",
    "gn:dem":1270,
    "gn:feature_class":"P",
    "gn:feature_code":"PPL",
    "gn:name":"Kamugombwa",
    "gn:population":0,
    "gn:timezone":"Africa/Kampala",
    "iso:country":"UG",
    "wof:name":"Kamugombwa",
    "wof:placetype":"locality"
},
  "geometry": {"coordinates":[32.26369,0.28154],"type":"Point"}
}