{
  "type": "Feature",
  "properties": {
    "gn:admin1_code":"C",
    "gn:admin2_code":"96",
    "gn:admin3_code":"234053.0",
    "gn:admin4_code":"7732546.0",
    "gn:asciiname":"Nakaseta",
    "gn:country_code":"UG",
    "gn:dem":1158,
    "gn:feature_class":"P",
    "gn:feature_code":"PPL",
    "gn:name":"Nakaseta",
    "gn:population":0,
    "gn:timezone":"Africa/Kampala",
    "iso:country":"UG",
    "wof:name":"Nakaseta",
    "wof:placetype":"locality"
},
  "geometry": {"coordinates":[32.22068,0.45387],"type":"Point"}
}