{
  "type": "Feature",
  "properties": {
    "gn:admin1_code":"E",
    "gn:admin2_code":"39",
    "gn:admin3_code":"7870033.0",
    "gn:admin4_code":"8657538.0",
    "gn:asciiname":"Chesebere",
    "gn:country_code":"UG",
    "gn:dem":1493,
    "gn:feature_class":"P",
    "gn:feature_code":"PPL",
    "gn:name":"Chesebere",
    "gn:population":0,
    "gn:timezone":"Africa/Kampala",
    "iso:country":"UG",
    "wof:name":"Chesebere",
    "wof:placetype":"locality"
},
  "geometry": {"coordinates":[34.38333,1.41667],"type":"Point"}
}