{
  "type": "Feature",
  "properties": {
    "gn:admin1_code":"E",
    "gn:admin2_code":"78",
    "gn:admin3_code":"231410.0",
    "gn:admin4_code":"8657982.0",
    "gn:asciiname":"Nakigo",
    "gn:country_code":"UG",
    "gn:dem":1128,
    "gn:feature_class":"P",
    "gn:feature_code":"PPL",
    "gn:name":"Nakigo",
    "gn:population":0,
    "gn:timezone":"Africa/Kampala",
    "iso:country":"UG",
    "wof:name":"Nakigo",
    "wof:placetype":"locality"
},
  "geometry": {"coordinates":[33.51399,0.59471],"type":"Point"}
}