{
  "type": "Feature",
  "properties": {
    "gn:admin1_code":"E",
    "gn:admin2_code":"G4",
    "gn:admin3_code":"229762.0",
    "gn:admin4_code":"7732526.0",
    "gn:asciiname":"Nabubya",
    "gn:country_code":"UG",
    "gn:dem":1130,
    "gn:feature_class":"P",
    "gn:feature_code":"PPL",
    "gn:name":"Nabubya",
    "gn:population":0,
    "gn:timezone":"Africa/Kampala",
    "iso:country":"UG",
    "wof:name":"Nabubya",
    "wof:placetype":"locality"
},
  "geometry": {"coordinates":[33.40472,0.707],"type":"Point"}
}