{
  "type": "Feature",
  "properties": {
    "gn:admin1_code":"E",
    "gn:admin2_code":"H5",
    "gn:admin3_code":"8644174.0",
    "gn:admin4_code":"8658380.0",
    "gn:asciiname":"Okimenga",
    "gn:country_code":"UG",
    "gn:dem":1050,
    "gn:feature_class":"P",
    "gn:feature_code":"PPL",
    "gn:name":"Okimenga",
    "gn:population":0,
    "gn:timezone":"Africa/Kampala",
    "iso:country":"UG",
    "name:und_x_variant":[
        "Kimenga",
        "Okimenga"
    ],
    "wof:name":"Okimenga",
    "wof:placetype":"locality"
},
  "geometry": {"coordinates":[33.36667,1.46667],"type":"Point"}
}