{
  "type": "Feature",
  "properties": {
    "gn:admin1_code":"E",
    "gn:admin2_code":"38",
    "gn:asciiname":"Bukyatifu",
    "gn:country_code":"UG",
    "gn:dem":1077,
    "gn:feature_class":"P",
    "gn:feature_code":"PPL",
    "gn:name":"Bukyatifu",
    "gn:population":0,
    "gn:timezone":"Africa/Kampala",
    "iso:country":"UG",
    "wof:name":"Bukyatifu",
    "wof:placetype":"locality"
},
  "geometry": {"coordinates":[33.07314,0.76084],"type":"Point"}
}