{
  "type": "Feature",
  "properties": {
    "gn:admin1_code":"W",
    "gn:admin2_code":"85",
    "gn:admin3_code":"228643.0",
    "gn:admin4_code":"234622.0",
    "gn:asciiname":"Kitega",
    "gn:country_code":"UG",
    "gn:dem":1417,
    "gn:feature_class":"P",
    "gn:feature_code":"PPL",
    "gn:name":"Kitega",
    "gn:population":0,
    "gn:timezone":"Africa/Kampala",
    "iso:country":"UG",
    "wof:name":"Kitega",
    "wof:placetype":"locality"
},
  "geometry": {"coordinates":[30.85167,0.70722],"type":"Point"}
}