{
  "type": "Feature",
  "properties": {
    "gn:admin1_code":"E",
    "gn:admin2_code":"67",
    "gn:admin3_code":"8644151.0",
    "gn:admin4_code":"8658309.0",
    "gn:asciiname":"Businywa",
    "gn:country_code":"UG",
    "gn:dem":1160,
    "gn:feature_class":"P",
    "gn:feature_code":"PPL",
    "gn:name":"Businywa",
    "gn:population":0,
    "gn:timezone":"Africa/Kampala",
    "iso:country":"UG",
    "name:eng_x_preferred":[
        "Businywa"
    ],
    "wof:name":"Businywa",
    "wof:placetype":"locality"
},
  "geometry": {"coordinates":[33.98492,0.48863],"type":"Point"}
}