{
  "type": "Feature",
  "properties": {
    "gn:admin1_code":"W",
    "gn:admin2_code":"C5",
    "gn:admin3_code":"7869947.0",
    "gn:admin4_code":"8657780.0",
    "gn:asciiname":"Kirama",
    "gn:country_code":"UG",
    "gn:dem":645,
    "gn:feature_class":"P",
    "gn:feature_code":"PPL",
    "gn:name":"Kirama",
    "gn:population":0,
    "gn:timezone":"Africa/Kampala",
    "iso:country":"UG",
    "wof:name":"Kirama",
    "wof:placetype":"locality"
},
  "geometry": {"coordinates":[31.40794,2.18032],"type":"Point"}
}