{
  "type": "Feature",
  "properties": {
    "gn:admin1_code":"E",
    "gn:admin2_code":"78",
    "gn:asciiname":"Naluswa",
    "gn:country_code":"UG",
    "gn:dem":1124,
    "gn:feature_class":"P",
    "gn:feature_code":"PPL",
    "gn:name":"Naluswa",
    "gn:population":0,
    "gn:timezone":"Africa/Kampala",
    "iso:country":"UG",
    "wof:name":"Naluswa",
    "wof:placetype":"locality"
},
  "geometry": {"coordinates":[33.62655,0.65061],"type":"Point"}
}