{
  "type": "Feature",
  "properties": {
    "gn:admin1_code":"W",
    "gn:admin2_code":"79",
    "gn:asciiname":"Bilitakula",
    "gn:country_code":"UG",
    "gn:dem":1323,
    "gn:feature_class":"P",
    "gn:feature_code":"PPL",
    "gn:name":"Bilitakula",
    "gn:population":0,
    "gn:timezone":"Africa/Kampala",
    "iso:country":"UG",
    "name:eng_x_preferred":[
        "Bilitakula"
    ],
    "wof:name":"Bilitakula",
    "wof:placetype":"locality"
},
  "geometry": {"coordinates":[30.19776,0.73911],"type":"Point"}
}