{
  "type": "Feature",
  "properties": {
    "gn:admin1_code":"N",
    "gn:admin2_code":"91",
    "gn:admin3_code":"8644141.0",
    "gn:admin4_code":"8657547.0",
    "gn:asciiname":"Napianyenya",
    "gn:country_code":"UG",
    "gn:dem":1137,
    "gn:feature_class":"P",
    "gn:feature_code":"PPL",
    "gn:name":"Napianyenya",
    "gn:population":0,
    "gn:timezone":"Africa/Kampala",
    "iso:country":"UG",
    "name:und_x_variant":[
        "Napiananya",
        "Napyenenya",
        "Napianyenya"
    ],
    "wof:name":"Napianyenya",
    "wof:placetype":"locality"
},
  "geometry": {"coordinates":[34.58333,1.86667],"type":"Point"}
}