{
  "type": "Feature",
  "properties": {
    "gn:admin1_code":"W",
    "gn:admin2_code":"31",
    "gn:admin3_code":"8644163.0",
    "gn:admin4_code":"8657785.0",
    "gn:asciiname":"Kabwoya",
    "gn:country_code":"UG",
    "gn:dem":1149,
    "gn:feature_class":"P",
    "gn:feature_code":"PPL",
    "gn:name":"Kabwoya",
    "gn:population":0,
    "gn:timezone":"Africa/Kampala",
    "iso:country":"UG",
    "name:ceb_x_preferred":[
        "Kabwoya"
    ],
    "name:lug_x_preferred":[
        "Kabwoya"
    ],
    "wof:name":"Kabwoya",
    "wof:placetype":"locality"
},
  "geometry": {"coordinates":[31.07556,1.25861],"type":"Point"}
}