{
  "type": "Feature",
  "properties": {
    "iso:country":"UG",
    "name:ceb_x_preferred":[
        "Kilembe"
    ],
    "name:lug_x_preferred":[
        "Kilembe"
    ],
    "name:swe_x_preferred":[
        "Kilembe"
    ],
    "qs:gn_country":"UG",
    "qs:gn_fcode":"PPL",
    "qs:gn_pop":7914,
    "qs:name":"Kilembe",
    "qs:name_adm0":"Uganda",
    "qs:name_adm1":"Kasese",
    "qs:photos":338,
    "qs:photos_1k":68,
    "qs:photos_9k":1,
    "qs:photos_9r":5,
    "qs:photos_all":338,
    "qs:photos_sr":5,
    "qs:placetype":"Town",
    "qs:pop_sr":"5",
    "qs:woe_adm0":23424974,
    "wd:wordcount":30,
    "wof:name":"Kilembe",
    "wof:placetype":"locality",
    "wof:population":7914
},
  "geometry": {"coordinates":[30.01302,0.19835],"type":"Point"}
}