{
  "type": "Feature",
  "properties": {
    "gn:admin1_code":"E",
    "gn:admin2_code":"46",
    "gn:admin3_code":"7732907.0",
    "gn:admin4_code":"8658068.0",
    "gn:asciiname":"Akum",
    "gn:cc2":"UG",
    "gn:country_code":"UG",
    "gn:dem":1058,
    "gn:feature_class":"P",
    "gn:feature_code":"PPL",
    "gn:name":"Akum",
    "gn:population":0,
    "gn:timezone":"Africa/Kampala",
    "iso:country":"UG",
    "name:und_x_variant":[
        "Kakum",
        "Akum"
    ],
    "wof:name":"Akum",
    "wof:placetype":"locality"
},
  "geometry": {"coordinates":[34.04889,1.59139],"type":"Point"}
}