{
  "type": "Feature",
  "properties": {
    "gn:admin1_code":"C",
    "gn:admin2_code":"F1",
    "gn:admin3_code":"234000.0",
    "gn:admin4_code":"8658701.0",
    "gn:asciiname":"Kiziiko",
    "gn:country_code":"UG",
    "gn:dem":1249,
    "gn:feature_class":"P",
    "gn:feature_code":"PPL",
    "gn:name":"Kiziiko",
    "gn:population":0,
    "gn:timezone":"Africa/Kampala",
    "iso:country":"UG",
    "name:und_x_variant":[
        "Kiziko"
    ],
    "wof:name":"Kiziiko",
    "wof:placetype":"locality"
},
  "geometry": {"coordinates":[32.17496,0.20024],"type":"Point"}
}