{
  "type": "Feature",
  "properties": {
    "gn:admin1_code":"E",
    "gn:admin2_code":"38",
    "gn:asciiname":"Bukyabanda",
    "gn:country_code":"UG",
    "gn:dem":1117,
    "gn:feature_class":"P",
    "gn:feature_code":"PPL",
    "gn:name":"Bukyabanda",
    "gn:population":0,
    "gn:timezone":"Africa/Kampala",
    "iso:country":"UG",
    "wof:name":"Bukyabanda",
    "wof:placetype":"locality"
},
  "geometry": {"coordinates":[33.23523,0.95726],"type":"Point"}
}