{
  "type": "Feature",
  "properties": {
    "gn:admin1_code":"W",
    "gn:admin2_code":"85",
    "gn:admin3_code":"228643.0",
    "gn:admin4_code":"8657592.0",
    "gn:asciiname":"Kasenyi",
    "gn:country_code":"UG",
    "gn:dem":1520,
    "gn:feature_class":"P",
    "gn:feature_code":"PPL",
    "gn:name":"Kasenyi",
    "gn:population":0,
    "gn:timezone":"Africa/Kampala",
    "iso:country":"UG",
    "name:eng_x_preferred":[
        "Kasenyi"
    ],
    "wof:name":"Kasenyi",
    "wof:placetype":"locality"
},
  "geometry": {"coordinates":[30.45817000000001,0.69238],"type":"Point"}
}