{
  "type": "Feature",
  "properties": {
    "gn:admin1_code":"E",
    "gn:admin2_code":"76",
    "gn:asciiname":"Mukwana-Kijwala",
    "gn:country_code":"UG",
    "gn:dem":1110,
    "gn:feature_class":"P",
    "gn:feature_code":"PPL",
    "gn:name":"Mukwana-Kijwala",
    "gn:population":0,
    "gn:timezone":"Africa/Kampala",
    "iso:country":"UG",
    "wof:name":"Mukwana-Kijwala",
    "wof:placetype":"locality"
},
  "geometry": {"coordinates":[33.97828,0.74823],"type":"Point"}
}