{
  "type": "Feature",
  "properties": {
    "gn:admin1_code":"E",
    "gn:admin2_code":"33",
    "gn:asciiname":"Busegula",
    "gn:country_code":"UG",
    "gn:dem":1102,
    "gn:feature_class":"P",
    "gn:feature_code":"PPL",
    "gn:name":"Busegula",
    "gn:population":0,
    "gn:timezone":"Africa/Kampala",
    "iso:country":"UG",
    "wof:name":"Busegula",
    "wof:placetype":"locality"
},
  "geometry": {"coordinates":[33.21917,0.66182],"type":"Point"}
}