{
  "type": "Feature",
  "properties": {
    "gn:country":"UG",
    "gn:fcode":"PPLA2",
    "gn:pop":21704,
    "iso:country":"UG",
    "name:ara_x_preferred":[
        "\u0645\u062d\u0627\u0641\u0638\u0629 \u0643\u0627\u064a\u0648\u0646\u062c\u0627"
    ],
    "name:deu_x_preferred":[
        "Kayunga"
    ],
    "name:dut_x_preferred":[
        "Kayunga"
    ],
    "name:eng_x_preferred":[
        "Kayunga"
    ],
    "name:fre_x_preferred":[
        "Kayunga"
    ],
    "name:ger_x_preferred":[
        "Kayunga"
    ],
    "name:ita_x_preferred":[
        "Kayunga"
    ],
    "name:nob_x_preferred":[
        "Kayunga"
    ],
    "name:por_x_preferred":[
        "Kayunga"
    ],
    "name:rum_x_preferred":[
        "Kayunga"
    ],
    "name:swa_x_preferred":[
        "Kayunga"
    ],
    "name:urd_x_preferred":[
        "\u06a9\u0627\u0626\u0648\u0646\u06af\u0627"
    ],
    "ne:ADM0CAP":0.0,
    "ne:ADM0NAME":"Uganda",
    "ne:ADM0_A3":"UGA",
    "ne:ADM1NAME":"Kayunga",
    "ne:ADMIN1_COD":83,
    "ne:CAPALT":0,
    "ne:CHANGED":4,
    "ne:CHECKME":0,
    "ne:COMPARE":0,
    "ne:DIFFASCII":0,
    "ne:DIFFNOTE":"Added missing admin-1 capital round B. Population from GeoNames.",
    "ne:ELEVATION":0.0,
    "ne:FEATURECLA":"Admin-1 capital",
    "ne:FEATURE_CL":"P",
    "ne:FEATURE_CO":"PPLA",
    "ne:GEONAMEID":231696,
    "ne:GEONAMESNO":"GeoNames match general.",
    "ne:GN_ASCII":"Kayunga",
    "ne:GN_POP":21704,
    "ne:GTOPO30":1063.0,
    "ne:ISO_A2":"UG",
    "ne:LABELRANK":5,
    "ne:LATITUDE":0.7025,
    "ne:LONGITUDE":32.888611,
    "ne:LS_MATCH":0,
    "ne:MAX_AREAKM":0.0,
    "ne:MAX_AREAMI":0.0,
    "ne:MAX_BBXMAX":0.0,
    "ne:MAX_BBXMIN":0.0,
    "ne:MAX_BBYMAX":0.0,
    "ne:MAX_BBYMIN":0.0,
    "ne:MAX_NATSCA":0.0,
    "ne:MAX_PERKM":0.0,
    "ne:MAX_PERMI":0.0,
    "ne:MAX_POP10":0,
    "ne:MAX_POP20":0,
    "ne:MAX_POP300":0,
    "ne:MAX_POP310":0,
    "ne:MAX_POP50":0,
    "ne:MEAN_BBXC":0.0,
    "ne:MEAN_BBYC":0.0,
    "ne:MEGACITY":0,
    "ne:MIN_AREAKM":0.0,
    "ne:MIN_AREAMI":0.0,
    "ne:MIN_BBXMAX":0.0,
    "ne:MIN_BBXMIN":0.0,
    "ne:MIN_BBYMAX":0.0,
    "ne:MIN_BBYMIN":0.0,
    "ne:MIN_PERKM":0.0,
    "ne:MIN_PERMI":0.0,
    "ne:NAME":"Kayunga",
    "ne:NAMEASCII":"Kayunga",
    "ne:NAMEDIFF":0,
    "ne:NATSCALE":1,
    "ne:POP1950":0,
    "ne:POP1955":0,
    "ne:POP1960":0,
    "ne:POP1965":0,
    "ne:POP1970":0,
    "ne:POP1975":0,
    "ne:POP1980":0,
    "ne:POP1985":0,
    "ne:POP1990":0,
    "ne:POP1995":0,
    "ne:POP2000":0,
    "ne:POP2005":0,
    "ne:POP2010":0,
    "ne:POP2015":0,
    "ne:POP2020":0,
    "ne:POP2025":0,
    "ne:POP2050":0,
    "ne:POP_MAX":21704,
    "ne:POP_MIN":21704,
    "ne:POP_OTHER":0,
    "ne:RANK_MAX":7,
    "ne:RANK_MIN":7,
    "ne:SCALERANK":10,
    "ne:SOV0NAME":"Uganda",
    "ne:SOV_A3":"UGA",
    "ne:TIMEZONE":"Africa/Kampala",
    "ne:UN_FID":0,
    "ne:UN_LAT":0.0,
    "ne:UN_LONG":0.0,
    "ne:WORLDCITY":0,
    "qs:name":"Kayunga",
    "qs:photos_9r":0,
    "qs:photos_sr":0,
    "qs:pop_sr":"7",
    "wd:wordcount":301,
    "wof:name":"Kayunga",
    "wof:placetype":"locality",
    "wof:population":21704
},
  "geometry": {"coordinates":[32.88861,0.7025],"type":"Point"}
}