{
  "type": "Feature",
  "properties": {
    "gn:admin1_code":"C",
    "gn:admin2_code":"89",
    "gn:asciiname":"Bulembo",
    "gn:country_code":"UG",
    "gn:dem":1214,
    "gn:feature_class":"P",
    "gn:feature_code":"PPL",
    "gn:name":"Bulembo",
    "gn:population":0,
    "gn:timezone":"Africa/Kampala",
    "iso:country":"UG",
    "wof:name":"Bulembo",
    "wof:placetype":"locality"
},
  "geometry": {"coordinates":[32.23433,0.13403],"type":"Point"}
}