{
  "type": "Feature",
  "properties": {
    "gn:admin1_code":"N",
    "gn:admin2_code":"G3",
    "gn:admin3_code":"230209.0",
    "gn:admin4_code":"8647182.0",
    "gn:asciiname":"Pauma",
    "gn:country_code":"UG",
    "gn:dem":876,
    "gn:feature_class":"P",
    "gn:feature_code":"PPL",
    "gn:name":"Pauma",
    "gn:population":0,
    "gn:timezone":"Africa/Kampala",
    "iso:country":"UG",
    "wof:name":"Pauma",
    "wof:placetype":"locality"
},
  "geometry": {"coordinates":[32.55938,3.49631],"type":"Point"}
}