{
  "type": "Feature",
  "properties": {
    "gn:admin1_code":"W",
    "gn:admin2_code":"I2",
    "gn:admin3_code":"8644161.0",
    "gn:admin4_code":"8658262.0",
    "gn:asciiname":"Kyabasaja",
    "gn:country_code":"UG",
    "gn:dem":1314,
    "gn:feature_class":"P",
    "gn:feature_code":"PPL",
    "gn:name":"Kyabasaja",
    "gn:population":0,
    "gn:timezone":"Africa/Kampala",
    "iso:country":"UG",
    "name:und_x_variant":[
        "Kyabasajja",
        "Nyabasaja",
        "Kyabasaja"
    ],
    "wof:name":"Kyabasaja",
    "wof:placetype":"locality"
},
  "geometry": {"coordinates":[31.38333,0.76667],"type":"Point"}
}