{
  "type": "Feature",
  "properties": {
    "gn:admin1_code":"E",
    "gn:admin2_code":"D6",
    "gn:asciiname":"Bunatanga",
    "gn:country_code":"UG",
    "gn:dem":1379,
    "gn:feature_class":"P",
    "gn:feature_code":"PPL",
    "gn:name":"Bunatanga",
    "gn:population":0,
    "gn:timezone":"Africa/Kampala",
    "iso:country":"UG",
    "name:eng_x_preferred":[
        "Bunatanga"
    ],
    "wof:name":"Bunatanga",
    "wof:placetype":"locality"
},
  "geometry": {"coordinates":[34.30683,0.87216],"type":"Point"}
}