{
  "type": "Feature",
  "properties": {
    "gn:admin1_code":"C",
    "gn:admin2_code":"89",
    "gn:admin3_code":"7910214.0",
    "gn:admin4_code":"8657607.0",
    "gn:asciiname":"Nseke",
    "gn:country_code":"UG",
    "gn:dem":1192,
    "gn:feature_class":"P",
    "gn:feature_code":"PPL",
    "gn:name":"Nseke",
    "gn:population":0,
    "gn:timezone":"Africa/Kampala",
    "iso:country":"UG",
    "wof:name":"Nseke",
    "wof:placetype":"locality"
},
  "geometry": {"coordinates":[32.30485,0.1687],"type":"Point"}
}