{
  "type": "Feature",
  "properties": {
    "gn:admin1_code":"N",
    "gn:admin2_code":"77",
    "gn:admin3_code":"226029.0",
    "gn:admin4_code":"8657886.0",
    "gn:asciiname":"Asasi",
    "gn:country_code":"UG",
    "gn:dem":1460,
    "gn:feature_class":"P",
    "gn:feature_code":"PPL",
    "gn:name":"Asasi",
    "gn:population":0,
    "gn:timezone":"Africa/Kampala",
    "iso:country":"UG",
    "wof:name":"Asasi",
    "wof:placetype":"locality"
},
  "geometry": {"coordinates":[30.84039000000001,2.71772],"type":"Point"}
}