{
  "type": "Feature",
  "properties": {
    "gn:admin1_code":"E",
    "gn:admin2_code":"D6",
    "gn:asciiname":"Bukikete",
    "gn:country_code":"UG",
    "gn:dem":1415,
    "gn:feature_class":"P",
    "gn:feature_code":"PPL",
    "gn:name":"Bukikete",
    "gn:population":0,
    "gn:timezone":"Africa/Kampala",
    "iso:country":"UG",
    "name:eng_x_preferred":[
        "Bukikete"
    ],
    "wof:name":"Bukikete",
    "wof:placetype":"locality"
},
  "geometry": {"coordinates":[34.34781,0.83925],"type":"Point"}
}