{
  "type": "Feature",
  "properties": {
    "gn:admin1_code":"C",
    "gn:admin2_code":"96",
    "gn:admin3_code":"7732385.0",
    "gn:admin4_code":"8658110.0",
    "gn:asciiname":"Buggu",
    "gn:country_code":"UG",
    "gn:dem":1162,
    "gn:feature_class":"P",
    "gn:feature_code":"PPL",
    "gn:name":"Buggu",
    "gn:population":0,
    "gn:timezone":"Africa/Kampala",
    "iso:country":"UG",
    "wof:name":"Buggu",
    "wof:placetype":"locality"
},
  "geometry": {"coordinates":[32.60909,0.21912],"type":"Point"}
}