{
  "type": "Feature",
  "properties": {
    "gn:admin1_code":"C",
    "gn:admin2_code":"E7",
    "gn:admin3_code":"7732075.0",
    "gn:admin4_code":"8658276.0",
    "gn:asciiname":"Bulamba",
    "gn:country_code":"UG",
    "gn:dem":1163,
    "gn:feature_class":"P",
    "gn:feature_code":"PPL",
    "gn:name":"Bulamba",
    "gn:population":0,
    "gn:timezone":"Africa/Kampala",
    "iso:country":"UG",
    "name:eng_x_preferred":[
        "Bulamba"
    ],
    "wof:name":"Bulamba",
    "wof:placetype":"locality"
},
  "geometry": {"coordinates":[33.19508,0.39444],"type":"Point"}
}