{
  "type": "Feature",
  "properties": {
    "gn:admin1_code":"C",
    "gn:admin2_code":"83",
    "gn:asciiname":"Kasana",
    "gn:country_code":"UG",
    "gn:dem":1079,
    "gn:feature_class":"P",
    "gn:feature_code":"PPL",
    "gn:name":"Kasana",
    "gn:population":0,
    "gn:timezone":"Africa/Kampala",
    "iso:country":"UG",
    "wof:name":"Kasana",
    "wof:placetype":"locality"
},
  "geometry": {"coordinates":[33.02445,0.78259],"type":"Point"}
}