{
  "type": "Feature",
  "properties": {
    "gn:admin1_code":"W",
    "gn:admin2_code":"28",
    "gn:asciiname":"Bundibakileki",
    "gn:country_code":"UG",
    "gn:dem":854,
    "gn:feature_class":"P",
    "gn:feature_code":"PPL",
    "gn:name":"Bundibakileki",
    "gn:population":0,
    "gn:timezone":"Africa/Kampala",
    "iso:country":"UG",
    "name:eng_x_preferred":[
        "Bundibakileki"
    ],
    "wof:name":"Bundibakileki",
    "wof:placetype":"locality"
},
  "geometry": {"coordinates":[30.01946,0.70196],"type":"Point"}
}