{
  "type": "Feature",
  "properties": {
    "gn:admin1_code":"C",
    "gn:admin2_code":"90",
    "gn:admin3_code":"7732384.0",
    "gn:admin4_code":"8658391.0",
    "gn:asciiname":"Kibanga Port",
    "gn:country_code":"UG",
    "gn:dem":1151,
    "gn:feature_class":"P",
    "gn:feature_code":"PPL",
    "gn:name":"Kibanga Port",
    "gn:population":0,
    "gn:timezone":"Africa/Kampala",
    "iso:country":"UG",
    "name:und_x_variant":[
        "Kibanga",
        "Kibanga Port"
    ],
    "wof:name":"Kibanga Port",
    "wof:placetype":"locality"
},
  "geometry": {"coordinates":[32.8678,0.18982],"type":"Point"}
}