{
  "type": "Feature",
  "properties": {
    "gn:admin1_code":"N",
    "gn:admin2_code":"77",
    "gn:admin3_code":"8644146.0",
    "gn:admin4_code":"8658425.0",
    "gn:asciiname":"Katiyi",
    "gn:country_code":"UG",
    "gn:dem":924,
    "gn:feature_class":"P",
    "gn:feature_code":"PPL",
    "gn:name":"Katiyi",
    "gn:population":0,
    "gn:timezone":"Africa/Kampala",
    "iso:country":"UG",
    "wof:name":"Katiyi",
    "wof:placetype":"locality"
},
  "geometry": {"coordinates":[31.07884,2.74212],"type":"Point"}
}