{
  "type": "Feature",
  "properties": {
    "gn:admin1_code":"E",
    "gn:admin2_code":"33",
    "gn:asciiname":"Nakati",
    "gn:country_code":"UG",
    "gn:dem":1183,
    "gn:feature_class":"P",
    "gn:feature_code":"PPL",
    "gn:name":"Nakati",
    "gn:population":0,
    "gn:timezone":"Africa/Kampala",
    "iso:country":"UG",
    "wof:name":"Nakati",
    "wof:placetype":"locality"
},
  "geometry": {"coordinates":[33.32039,0.56985],"type":"Point"}
}