{
  "type": "Feature",
  "properties": {
    "gn:admin1_code":"E",
    "gn:admin2_code":"D6",
    "gn:asciiname":"Buwokona",
    "gn:country_code":"UG",
    "gn:dem":1367,
    "gn:feature_class":"P",
    "gn:feature_code":"PPL",
    "gn:name":"Buwokona",
    "gn:population":0,
    "gn:timezone":"Africa/Kampala",
    "iso:country":"UG",
    "name:eng_x_preferred":[
        "Buwokona"
    ],
    "wof:name":"Buwokona",
    "wof:placetype":"locality"
},
  "geometry": {"coordinates":[34.3351,0.8722],"type":"Point"}
}