{
  "type": "Feature",
  "properties": {
    "gn:admin1_code":"E",
    "gn:admin2_code":"76",
    "gn:asciiname":"Wikusi-Nyakasusa",
    "gn:country_code":"UG",
    "gn:dem":1122,
    "gn:feature_class":"P",
    "gn:feature_code":"PPL",
    "gn:name":"Wikusi-Nyakasusa",
    "gn:population":0,
    "gn:timezone":"Africa/Kampala",
    "iso:country":"UG",
    "wof:name":"Wikusi-Nyakasusa",
    "wof:placetype":"locality"
},
  "geometry": {"coordinates":[33.9571,0.80404],"type":"Point"}
}