{
  "type": "Feature",
  "properties": {
    "gn:admin1_code":"C",
    "gn:admin2_code":"D5",
    "gn:admin3_code":"232958.0",
    "gn:admin4_code":"8657666.0",
    "gn:asciiname":"Mutoke",
    "gn:country_code":"UG",
    "gn:dem":1248,
    "gn:feature_class":"P",
    "gn:feature_code":"PPL",
    "gn:name":"Mutoke",
    "gn:population":0,
    "gn:timezone":"Africa/Kampala",
    "iso:country":"UG",
    "wof:name":"Mutoke",
    "wof:placetype":"locality"
},
  "geometry": {"coordinates":[31.26444,-0.1425],"type":"Point"}
}