{
  "type": "Feature",
  "properties": {
    "gn:admin1_code":"E",
    "gn:admin2_code":"33",
    "gn:admin3_code":"8644138.0",
    "gn:admin4_code":"8657852.0",
    "gn:asciiname":"Gomoja",
    "gn:country_code":"UG",
    "gn:dem":1161,
    "gn:feature_class":"P",
    "gn:feature_code":"PPL",
    "gn:name":"Gomoja",
    "gn:population":0,
    "gn:timezone":"Africa/Kampala",
    "iso:country":"UG",
    "name:eng_x_preferred":[
        "Gomoja"
    ],
    "wof:name":"Gomoja",
    "wof:placetype":"locality"
},
  "geometry": {"coordinates":[33.30505,0.48706],"type":"Point"}
}