{
  "type": "Feature",
  "properties": {
    "gn:admin1_code":"C",
    "gn:admin2_code":"83",
    "gn:asciiname":"Maligita",
    "gn:country_code":"UG",
    "gn:dem":1119,
    "gn:feature_class":"P",
    "gn:feature_code":"PPL",
    "gn:name":"Maligita",
    "gn:population":0,
    "gn:timezone":"Africa/Kampala",
    "iso:country":"UG",
    "wof:name":"Maligita",
    "wof:placetype":"locality"
},
  "geometry": {"coordinates":[33.07399,0.52369],"type":"Point"}
}