{
  "type": "Feature",
  "properties": {
    "gn:admin1_code":"C",
    "gn:admin2_code":"96",
    "gn:asciiname":"Sentigi",
    "gn:country_code":"UG",
    "gn:dem":1165,
    "gn:feature_class":"P",
    "gn:feature_code":"PPL",
    "gn:name":"Sentigi",
    "gn:population":0,
    "gn:timezone":"Africa/Kampala",
    "iso:country":"UG",
    "wof:name":"Sentigi",
    "wof:placetype":"locality"
},
  "geometry": {"coordinates":[32.30386,0.41752],"type":"Point"}
}