{
  "type": "Feature",
  "properties": {
    "gn:admin1_code":"C",
    "gn:admin2_code":"90",
    "gn:admin3_code":"7732384.0",
    "gn:admin4_code":"8658685.0",
    "gn:asciiname":"Buwunga",
    "gn:country_code":"UG",
    "gn:dem":1159,
    "gn:feature_class":"P",
    "gn:feature_code":"PPL",
    "gn:name":"Buwunga",
    "gn:population":0,
    "gn:timezone":"Africa/Kampala",
    "iso:country":"UG",
    "wof:name":"Buwunga",
    "wof:placetype":"locality"
},
  "geometry": {"coordinates":[32.66157,0.16844],"type":"Point"}
}