{
  "type": "Feature",
  "properties": {
    "gn:admin1_code":"C",
    "gn:admin2_code":"E7",
    "gn:admin3_code":"7732075.0",
    "gn:admin4_code":"8658507.0",
    "gn:asciiname":"Kabugoga",
    "gn:country_code":"UG",
    "gn:dem":1148,
    "gn:feature_class":"P",
    "gn:feature_code":"PPL",
    "gn:name":"Kabugoga",
    "gn:population":0,
    "gn:timezone":"Africa/Kampala",
    "iso:country":"UG",
    "name:und_x_variant":[
        "Kabugoge",
        "Kabugoga"
    ],
    "wof:name":"Kabugoga",
    "wof:placetype":"locality"
},
  "geometry": {"coordinates":[33.14364,0.30508],"type":"Point"}
}