{
  "type": "Feature",
  "properties": {
    "gn:admin1_code":"E",
    "gn:admin2_code":"76",
    "gn:asciiname":"Pomede",
    "gn:country_code":"UG",
    "gn:dem":1186,
    "gn:feature_class":"P",
    "gn:feature_code":"PPL",
    "gn:name":"Pomede",
    "gn:population":0,
    "gn:timezone":"Africa/Kampala",
    "iso:country":"UG",
    "name:eng_x_preferred":[
        "Pomede"
    ],
    "wof:name":"Pomede",
    "wof:placetype":"locality"
},
  "geometry": {"coordinates":[34.08192,0.71221],"type":"Point"}
}