{
  "type": "Feature",
  "properties": {
    "gn:admin1_code":"C",
    "gn:admin2_code":"D8",
    "gn:admin3_code":"8644152.0",
    "gn:admin4_code":"8658702.0",
    "gn:asciiname":"Bulera",
    "gn:country_code":"UG",
    "gn:dem":1315,
    "gn:feature_class":"P",
    "gn:feature_code":"PPL",
    "gn:name":"Bulera",
    "gn:population":0,
    "gn:timezone":"Africa/Kampala",
    "iso:country":"UG",
    "wof:name":"Bulera",
    "wof:placetype":"locality"
},
  "geometry": {"coordinates":[32.02028,0.50417],"type":"Point"}
}