{
  "type": "Feature",
  "properties": {
    "gn:admin1_code":"W",
    "gn:admin2_code":"28",
    "gn:asciiname":"Mutunda",
    "gn:country_code":"UG",
    "gn:dem":989,
    "gn:feature_class":"P",
    "gn:feature_code":"PPL",
    "gn:name":"Mutunda",
    "gn:population":0,
    "gn:timezone":"Africa/Kampala",
    "iso:country":"UG",
    "name:eng_x_preferred":[
        "Mutunda"
    ],
    "wof:name":"Mutunda",
    "wof:placetype":"locality"
},
  "geometry": {"coordinates":[29.98216,0.62804],"type":"Point"}
}