{
  "type": "Feature",
  "properties": {
    "gn:admin1_code":"C",
    "gn:admin2_code":"D8",
    "gn:asciiname":"Butalega",
    "gn:country_code":"UG",
    "gn:dem":1266,
    "gn:feature_class":"P",
    "gn:feature_code":"PPL",
    "gn:name":"Butalega",
    "gn:population":0,
    "gn:timezone":"Africa/Kampala",
    "iso:country":"UG",
    "wof:name":"Butalega",
    "wof:placetype":"locality"
},
  "geometry": {"coordinates":[32.03562,0.48804],"type":"Point"}
}