{
  "type": "Feature",
  "properties": {
    "gn:admin1_code":"C",
    "gn:admin2_code":"96",
    "gn:asciiname":"Bumpenje",
    "gn:country_code":"UG",
    "gn:dem":1197,
    "gn:feature_class":"P",
    "gn:feature_code":"PPL",
    "gn:name":"Bumpenje",
    "gn:population":0,
    "gn:timezone":"Africa/Kampala",
    "iso:country":"UG",
    "wof:name":"Bumpenje",
    "wof:placetype":"locality"
},
  "geometry": {"coordinates":[32.4257,0.17955],"type":"Point"}
}