{
  "type": "Feature",
  "properties": {
    "gn:admin1_code":"W",
    "gn:admin2_code":"I1",
    "gn:admin3_code":"233860.0",
    "gn:admin4_code":"8657563.0",
    "gn:asciiname":"Kyambogo",
    "gn:country_code":"UG",
    "gn:dem":1140,
    "gn:feature_class":"P",
    "gn:feature_code":"PPL",
    "gn:name":"Kyambogo",
    "gn:population":0,
    "gn:timezone":"Africa/Kampala",
    "iso:country":"UG",
    "wof:name":"Kyambogo",
    "wof:placetype":"locality"
},
  "geometry": {"coordinates":[30.68333,1.05],"type":"Point"}
}