{
  "type": "Feature",
  "properties": {
    "gn:admin1_code":"N",
    "gn:admin2_code":"B7",
    "gn:admin3_code":"231170.0",
    "gn:admin4_code":"8658492.0",
    "gn:asciiname":"Kibugo",
    "gn:country_code":"UG",
    "gn:dem":1056,
    "gn:feature_class":"P",
    "gn:feature_code":"PPLL",
    "gn:name":"Kibugo",
    "gn:population":0,
    "gn:timezone":"Africa/Kampala",
    "iso:country":"UG",
    "name:eng_x_preferred":[
        "Kibugo"
    ],
    "wof:name":"Kibugo",
    "wof:placetype":"locality"
},
  "geometry": {"coordinates":[32.86727,1.57975],"type":"Point"}
}