{
  "type": "Feature",
  "properties": {
    "gn:admin1_code":"E",
    "gn:admin2_code":"66",
    "gn:asciiname":"Bulanga",
    "gn:country_code":"UG",
    "gn:dem":1082,
    "gn:feature_class":"P",
    "gn:feature_code":"PPL",
    "gn:name":"Bulanga",
    "gn:population":0,
    "gn:timezone":"Africa/Kampala",
    "iso:country":"UG",
    "wof:name":"Bulanga",
    "wof:placetype":"locality"
},
  "geometry": {"coordinates":[33.78762,0.65103],"type":"Point"}
}