{
  "type": "Feature",
  "properties": {
    "gn:admin1_code":"E",
    "gn:admin2_code":"33",
    "gn:asciiname":"Itengeza",
    "gn:country_code":"UG",
    "gn:dem":1166,
    "gn:feature_class":"P",
    "gn:feature_code":"PPL",
    "gn:name":"Itengeza",
    "gn:population":0,
    "gn:timezone":"Africa/Kampala",
    "iso:country":"UG",
    "wof:name":"Itengeza",
    "wof:placetype":"locality"
},
  "geometry": {"coordinates":[33.30121,0.62292],"type":"Point"}
}