{
  "type": "Feature",
  "properties": {
    "gn:admin1_code":"C",
    "gn:admin2_code":"89",
    "gn:admin3_code":"7910214.0",
    "gn:admin4_code":"7732543.0",
    "gn:asciiname":"Kwata",
    "gn:country_code":"UG",
    "gn:dem":1226,
    "gn:feature_class":"P",
    "gn:feature_code":"PPL",
    "gn:name":"Kwata",
    "gn:population":0,
    "gn:timezone":"Africa/Kampala",
    "iso:country":"UG",
    "wof:name":"Kwata",
    "wof:placetype":"locality"
},
  "geometry": {"coordinates":[32.34089,0.36002],"type":"Point"}
}