{
  "type": "Feature",
  "properties": {
    "gn:admin1_code":"E",
    "gn:admin2_code":"38",
    "gn:asciiname":"Bufuuwa",
    "gn:country_code":"UG",
    "gn:dem":1094,
    "gn:feature_class":"P",
    "gn:feature_code":"PPL",
    "gn:name":"Bufuuwa",
    "gn:population":0,
    "gn:timezone":"Africa/Kampala",
    "iso:country":"UG",
    "wof:name":"Bufuuwa",
    "wof:placetype":"locality"
},
  "geometry": {"coordinates":[33.20275,0.96477],"type":"Point"}
}