{
  "type": "Feature",
  "properties": {
    "gn:admin1_code":"E",
    "gn:admin2_code":"38",
    "gn:asciiname":"Buyombo",
    "gn:country_code":"UG",
    "gn:dem":1101,
    "gn:feature_class":"P",
    "gn:feature_code":"PPL",
    "gn:name":"Buyombo",
    "gn:population":0,
    "gn:timezone":"Africa/Kampala",
    "iso:country":"UG",
    "wof:name":"Buyombo",
    "wof:placetype":"locality"
},
  "geometry": {"coordinates":[33.11671,0.9334],"type":"Point"}
}