{
  "type": "Feature",
  "properties": {
    "gn:admin1_code":"C",
    "gn:admin2_code":"96",
    "gn:admin3_code":"7732385.0",
    "gn:admin4_code":"8658059.0",
    "gn:asciiname":"Kazo",
    "gn:country_code":"UG",
    "gn:dem":1212,
    "gn:feature_class":"P",
    "gn:feature_code":"PPL",
    "gn:name":"Kazo",
    "gn:population":0,
    "gn:timezone":"Africa/Kampala",
    "iso:country":"UG",
    "name:ceb_x_preferred":[
        "Kazo"
    ],
    "name:ces_x_preferred":[
        "Kazo"
    ],
    "name:lug_x_preferred":[
        "Kazo"
    ],
    "name:mlg_x_preferred":[
        "Kazo"
    ],
    "name:swe_x_preferred":[
        "Kazo"
    ],
    "wof:name":"Kazo",
    "wof:placetype":"locality"
},
  "geometry": {"coordinates":[32.55584,0.35658],"type":"Point"}
}