{
  "type": "Feature",
  "properties": {
    "gn:admin1_code":"W",
    "gn:admin2_code":"40",
    "gn:admin3_code":"7869968.0",
    "gn:admin4_code":"8658188.0",
    "gn:asciiname":"Bukonyo",
    "gn:country_code":"UG",
    "gn:dem":1522,
    "gn:feature_class":"P",
    "gn:feature_code":"PPL",
    "gn:name":"Bukonyo",
    "gn:population":0,
    "gn:timezone":"Africa/Kampala",
    "iso:country":"UG",
    "wof:name":"Bukonyo",
    "wof:placetype":"locality"
},
  "geometry": {"coordinates":[29.91194,0.12444],"type":"Point"}
}