{
  "type": "Feature",
  "properties": {
    "gn:admin1_code":"E",
    "gn:admin2_code":"38",
    "gn:asciiname":"Nalinyaibi",
    "gn:country_code":"UG",
    "gn:dem":1067,
    "gn:feature_class":"P",
    "gn:feature_code":"PPL",
    "gn:name":"Nalinyaibi",
    "gn:population":0,
    "gn:timezone":"Africa/Kampala",
    "iso:country":"UG",
    "wof:name":"Nalinyaibi",
    "wof:placetype":"locality"
},
  "geometry": {"coordinates":[33.12069,0.77538],"type":"Point"}
}