{
  "type": "Feature",
  "properties": {
    "gn:admin1_code":"E",
    "gn:admin2_code":"66",
    "gn:asciiname":"Bukonde",
    "gn:country_code":"UG",
    "gn:dem":1133,
    "gn:feature_class":"P",
    "gn:feature_code":"PPL",
    "gn:name":"Bukonde",
    "gn:population":0,
    "gn:timezone":"Africa/Kampala",
    "iso:country":"UG",
    "wof:name":"Bukonde",
    "wof:placetype":"locality"
},
  "geometry": {"coordinates":[33.78324,0.54232],"type":"Point"}
}