{
  "type": "Feature",
  "properties": {
    "gn:admin1_code":"W",
    "gn:admin2_code":"40",
    "gn:admin3_code":"7869968.0",
    "gn:admin4_code":"8657869.0",
    "gn:asciiname":"Mpondwe",
    "gn:country_code":"UG",
    "gn:dem":1095,
    "gn:feature_class":"P",
    "gn:feature_code":"PPL",
    "gn:name":"Mpondwe",
    "gn:population":0,
    "gn:timezone":"Africa/Kampala",
    "iso:country":"UG",
    "wof:name":"Mpondwe",
    "wof:placetype":"locality"
},
  "geometry": {"coordinates":[29.7248,0.04008],"type":"Point"}
}