{
  "type": "Feature",
  "properties": {
    "gn:admin1_code":"C",
    "gn:admin2_code":"90",
    "gn:admin3_code":"7732383.0",
    "gn:admin4_code":"8658222.0",
    "gn:asciiname":"Kasana",
    "gn:country_code":"UG",
    "gn:dem":1132,
    "gn:feature_class":"P",
    "gn:feature_code":"PPL",
    "gn:name":"Kasana",
    "gn:population":0,
    "gn:timezone":"Africa/Kampala",
    "iso:country":"UG",
    "name:ceb_x_preferred":[
        "Kasana"
    ],
    "name:swe_x_preferred":[
        "Kasana"
    ],
    "wof:name":"Kasana",
    "wof:placetype":"locality"
},
  "geometry": {"coordinates":[32.83562,0.47148],"type":"Point"}
}