{
  "type": "Feature",
  "properties": {
    "gn:admin1_code":"W",
    "gn:admin2_code":"28",
    "gn:asciiname":"Buhanda",
    "gn:country_code":"UG",
    "gn:dem":792,
    "gn:feature_class":"P",
    "gn:feature_code":"PPL",
    "gn:name":"Buhanda",
    "gn:population":0,
    "gn:timezone":"Africa/Kampala",
    "iso:country":"UG",
    "name:eng_x_preferred":[
        "Buhanda"
    ],
    "wof:name":"Buhanda",
    "wof:placetype":"locality"
},
  "geometry": {"coordinates":[30.02255,0.74279],"type":"Point"}
}