{
  "type": "Feature",
  "properties": {
    "gn:admin1_code":"N",
    "gn:admin2_code":"D1",
    "gn:admin3_code":"233569.0",
    "gn:admin4_code":"8657670.0",
    "gn:asciiname":"Lolelia",
    "gn:country_code":"UG",
    "gn:dem":1246,
    "gn:feature_class":"P",
    "gn:feature_code":"PPL",
    "gn:name":"Lolelia",
    "gn:population":0,
    "gn:timezone":"Africa/Kampala",
    "iso:country":"UG",
    "wof:name":"Lolelia",
    "wof:placetype":"locality"
},
  "geometry": {"coordinates":[33.93037,3.31326],"type":"Point"}
}