{
  "type": "Feature",
  "properties": {
    "gn:admin1_code":"W",
    "gn:admin2_code":"79",
    "gn:admin3_code":"7732254.0",
    "gn:admin4_code":"8657609.0",
    "gn:asciiname":"Kabulisoke",
    "gn:country_code":"UG",
    "gn:dem":1556,
    "gn:feature_class":"P",
    "gn:feature_code":"PPL",
    "gn:name":"Kabulisoke",
    "gn:population":0,
    "gn:timezone":"Africa/Kampala",
    "iso:country":"UG",
    "name:eng_x_preferred":[
        "Kabulisoke"
    ],
    "wof:name":"Kabulisoke",
    "wof:placetype":"locality"
},
  "geometry": {"coordinates":[30.39231,0.70441],"type":"Point"}
}