{
  "type": "Feature",
  "properties": {
    "gn:admin1_code":"E",
    "gn:admin2_code":"B8",
    "gn:asciiname":"Atiriri",
    "gn:country_code":"UG",
    "gn:dem":1103,
    "gn:feature_class":"P",
    "gn:feature_code":"PPLL",
    "gn:name":"Atiriri",
    "gn:population":0,
    "gn:timezone":"Africa/Kampala",
    "iso:country":"UG",
    "wof:name":"Atiriri",
    "wof:placetype":"locality"
},
  "geometry": {"coordinates":[33.68018,1.96469],"type":"Point"}
}