{
  "type": "Feature",
  "properties": {
    "gn:admin1_code":"C",
    "gn:admin2_code":"90",
    "gn:admin3_code":"7732384.0",
    "gn:admin4_code":"8658288.0",
    "gn:asciiname":"Nkooki",
    "gn:country_code":"UG",
    "gn:dem":1174,
    "gn:feature_class":"P",
    "gn:feature_code":"PPL",
    "gn:name":"Nkooki",
    "gn:population":0,
    "gn:timezone":"Africa/Kampala",
    "iso:country":"UG",
    "wof:name":"Nkooki",
    "wof:placetype":"locality"
},
  "geometry": {"coordinates":[32.74316,0.40735],"type":"Point"}
}