{
  "type": "Feature",
  "properties": {
    "gn:admin1_code":"E",
    "gn:admin2_code":"86",
    "gn:admin3_code":"8644164.0",
    "gn:admin4_code":"8658694.0",
    "gn:asciiname":"Buwolya",
    "gn:country_code":"UG",
    "gn:dem":1182,
    "gn:feature_class":"P",
    "gn:feature_code":"PPL",
    "gn:name":"Buwolya",
    "gn:population":0,
    "gn:timezone":"Africa/Kampala",
    "iso:country":"UG",
    "name:eng_x_preferred":[
        "Buwolya"
    ],
    "wof:name":"Buwolya",
    "wof:placetype":"locality"
},
  "geometry": {"coordinates":[33.47432,0.48057],"type":"Point"}
}