{
  "type": "Feature",
  "properties": {
    "gn:admin1_code":"C",
    "gn:admin2_code":"90",
    "gn:admin3_code":"7732384.0",
    "gn:admin4_code":"8658156.0",
    "gn:asciiname":"Kitebe-Namaliga",
    "gn:country_code":"UG",
    "gn:dem":1207,
    "gn:feature_class":"P",
    "gn:feature_code":"PPL",
    "gn:name":"Kitebe-Namaliga",
    "gn:population":0,
    "gn:timezone":"Africa/Kampala",
    "iso:country":"UG",
    "name:und_x_variant":[
        "Kitebe"
    ],
    "wof:name":"Kitebe-Namaliga",
    "wof:placetype":"locality"
},
  "geometry": {"coordinates":[32.84403,0.28187],"type":"Point"}
}