{
  "type": "Feature",
  "properties": {
    "gn:admin1_code":"E",
    "gn:admin2_code":"67",
    "gn:asciiname":"Amagoro",
    "gn:country_code":"UG",
    "gn:dem":1169,
    "gn:feature_class":"P",
    "gn:feature_code":"PPL",
    "gn:name":"Amagoro",
    "gn:population":0,
    "gn:timezone":"Africa/Kampala",
    "iso:country":"UG",
    "name:eng_x_preferred":[
        "Amagoro"
    ],
    "wof:name":"Amagoro",
    "wof:placetype":"locality"
},
  "geometry": {"coordinates":[34.10951,0.49874],"type":"Point"}
}