{
  "type": "Feature",
  "properties": {
    "gn:admin1_code":"C",
    "gn:admin2_code":"90",
    "gn:admin3_code":"8644169.0",
    "gn:admin4_code":"8658070.0",
    "gn:asciiname":"Nabusugwe",
    "gn:country_code":"UG",
    "gn:dem":1180,
    "gn:feature_class":"P",
    "gn:feature_code":"PPL",
    "gn:name":"Nabusugwe",
    "gn:population":0,
    "gn:timezone":"Africa/Kampala",
    "iso:country":"UG",
    "wof:name":"Nabusugwe",
    "wof:placetype":"locality"
},
  "geometry": {"coordinates":[32.67306,0.42186],"type":"Point"}
}