{
  "type": "Feature",
  "properties": {
    "gn:admin1_code":"C",
    "gn:admin2_code":"83",
    "gn:admin3_code":"8644158.0",
    "gn:admin4_code":"8657767.0",
    "gn:asciiname":"Kamusabi",
    "gn:country_code":"UG",
    "gn:dem":1063,
    "gn:feature_class":"P",
    "gn:feature_code":"PPL",
    "gn:name":"Kamusabi",
    "gn:population":0,
    "gn:timezone":"Africa/Kampala",
    "iso:country":"UG",
    "wof:name":"Kamusabi",
    "wof:placetype":"locality"
},
  "geometry": {"coordinates":[32.83333,0.86667],"type":"Point"}
}