{
  "type": "Feature",
  "properties": {
    "gn:admin1_code":"W",
    "gn:admin2_code":"29",
    "gn:admin3_code":"7732267.0",
    "gn:admin4_code":"8657638.0",
    "gn:asciiname":"Kashenyi",
    "gn:country_code":"UG",
    "gn:dem":1616,
    "gn:feature_class":"P",
    "gn:feature_code":"PPL",
    "gn:name":"Kashenyi",
    "gn:population":0,
    "gn:timezone":"Africa/Kampala",
    "iso:country":"UG",
    "wof:name":"Kashenyi",
    "wof:placetype":"locality"
},
  "geometry": {"coordinates":[30.13333,-0.58333],"type":"Point"}
}