{
  "type": "Feature",
  "properties": {
    "gn:admin1_code":"C",
    "gn:admin2_code":"D5",
    "gn:admin3_code":"232958.0",
    "gn:admin4_code":"8658009.0",
    "gn:asciiname":"Kaliro",
    "gn:country_code":"UG",
    "gn:dem":1277,
    "gn:feature_class":"P",
    "gn:feature_code":"PPL",
    "gn:name":"Kaliro",
    "gn:population":0,
    "gn:timezone":"Africa/Kampala",
    "iso:country":"UG",
    "wof:name":"Kaliro",
    "wof:placetype":"locality"
},
  "geometry": {"coordinates":[31.14528,-0.26417],"type":"Point"}
}