{
  "type": "Feature",
  "properties": {
    "gn:admin1_code":"C",
    "gn:admin2_code":"96",
    "gn:admin3_code":"7732385.0",
    "gn:admin4_code":"8658133.0",
    "gn:asciiname":"Tula",
    "gn:country_code":"UG",
    "gn:dem":1205,
    "gn:feature_class":"P",
    "gn:feature_code":"PPL",
    "gn:name":"Tula",
    "gn:population":0,
    "gn:timezone":"Africa/Kampala",
    "iso:country":"UG",
    "name:arg_x_preferred":[
        "Tula"
    ],
    "name:cat_x_preferred":[
        "Tula"
    ],
    "name:ceb_x_preferred":[
        "Tula"
    ],
    "name:ces_x_preferred":[
        "Tula"
    ],
    "name:chv_x_preferred":[
        "\u0422\u0443\u043b\u0103"
    ],
    "name:dan_x_preferred":[
        "Tula"
    ],
    "name:deu_x_preferred":[
        "Tula"
    ],
    "name:epo_x_preferred":[
        "Tula"
    ],
    "name:eus_x_preferred":[
        "Tula"
    ],
    "name:fra_x_preferred":[
        "Tula"
    ],
    "name:heb_x_preferred":[
        "\u05d8\u05d5\u05dc\u05d4"
    ],
    "name:hun_x_preferred":[
        "Tula"
    ],
    "name:hye_x_preferred":[
        "\u054f\u0578\u0582\u056c\u0561"
    ],
    "name:ind_x_preferred":[
        "Tula"
    ],
    "name:ita_x_preferred":[
        "Tula"
    ],
    "name:lat_x_preferred":[
        "Tula"
    ],
    "name:nld_x_preferred":[
        "Tula"
    ],
    "name:nor_x_preferred":[
        "Tula"
    ],
    "name:pol_x_preferred":[
        "Tula"
    ],
    "name:por_x_preferred":[
        "Tula"
    ],
    "name:ron_x_preferred":[
        "Tula"
    ],
    "name:rus_x_preferred":[
        "\u0422\u0443\u043b\u0430"
    ],
    "name:sco_x_preferred":[
        "Tula"
    ],
    "name:slk_x_preferred":[
        "Tula"
    ],
    "name:spa_x_preferred":[
        "Tula"
    ],
    "name:srp_x_preferred":[
        "\u0422\u0443\u043b\u0430"
    ],
    "name:swe_x_preferred":[
        "Tula"
    ],
    "name:tat_x_preferred":[
        "\u0422\u0443\u043b\u0430"
    ],
    "name:ukr_x_preferred":[
        "\u0422\u0443\u043b\u0430"
    ],
    "name:uzb_x_preferred":[
        "Tula"
    ],
    "name:war_x_preferred":[
        "Tula"
    ],
    "wof:name":"Tula",
    "wof:placetype":"locality"
},
  "geometry": {"coordinates":[32.56112,0.39342],"type":"Point"}
}