{
  "type": "Feature",
  "properties": {
    "gn:admin1_code":"E",
    "gn:admin2_code":"76",
    "gn:asciiname":"Sesera",
    "gn:country_code":"UG",
    "gn:dem":1123,
    "gn:feature_class":"P",
    "gn:feature_code":"PPL",
    "gn:name":"Sesera",
    "gn:population":0,
    "gn:timezone":"Africa/Kampala",
    "iso:country":"UG",
    "name:eng_x_preferred":[
        "Sesera"
    ],
    "wof:name":"Sesera",
    "wof:placetype":"locality"
},
  "geometry": {"coordinates":[34.00973,0.78466],"type":"Point"}
}