{
  "type": "Feature",
  "properties": {
    "gn:admin1_code":"E",
    "gn:admin2_code":"95",
    "gn:asciiname":"Arusi",
    "gn:country_code":"UG",
    "gn:dem":1082,
    "gn:feature_class":"P",
    "gn:feature_code":"PPLL",
    "gn:name":"Arusi",
    "gn:population":0,
    "gn:timezone":"Africa/Kampala",
    "iso:country":"UG",
    "wof:name":"Arusi",
    "wof:placetype":"locality"
},
  "geometry": {"coordinates":[33.68115,1.85548],"type":"Point"}
}