{
  "type": "Feature",
  "properties": {
    "iso:country":"UG",
    "name:ceb_x_preferred":[
        "Kanungu"
    ],
    "name:eng_x_preferred":[
        "Kinkiizi"
    ],
    "name:eng_x_variant":[
        "Kanungu"
    ],
    "name:heb_x_preferred":[
        "\u05e7\u05d0\u05e0\u05d5\u05e0\u05d2\u05d5"
    ],
    "name:hun_x_preferred":[
        "Kanungu"
    ],
    "name:hye_x_preferred":[
        "\u053f\u0561\u0576\u0578\u0582\u0576\u0563\u0578\u0582"
    ],
    "name:jpn_x_preferred":[
        "\u30ab\u30cc\u30f3\u30b0"
    ],
    "name:lug_x_preferred":[
        "Kanungu"
    ],
    "name:nds_x_preferred":[
        "Kanungu"
    ],
    "name:nld_x_preferred":[
        "Kanungu"
    ],
    "name:nob_x_preferred":[
        "Kanungu"
    ],
    "name:ron_x_preferred":[
        "Kanungu"
    ],
    "name:swa_x_preferred":[
        "Kanungu"
    ],
    "name:und_x_variant":[
        "Kinkizi"
    ],
    "name:urd_x_preferred":[
        "\u06a9\u0627\u0646\u0648\u0646\u06af\u0648"
    ],
    "qs:gn_country":"UG",
    "qs:gn_fcode":"ADM3",
    "qs:gn_pop":0,
    "qs:name":"Kanungu",
    "qs:name_adm0":"Uganda",
    "qs:name_adm1":"Kanungu",
    "qs:photos":80,
    "qs:photos_1k":16,
    "qs:photos_9k":1,
    "qs:photos_9r":3,
    "qs:photos_all":80,
    "qs:photos_sr":3,
    "qs:placetype":"Town",
    "qs:pop_sr":"0",
    "qs:woe_adm0":23424974,
    "wof:name":"Kanungu",
    "wof:placetype":"locality"
},
  "geometry": {"coordinates":[29.73283,-0.78828],"type":"Point"}
}