{
  "type": "Feature",
  "properties": {
    "iso:country":"UG",
    "name:dut_x_preferred":[
        "Kanungu"
    ],
    "name:eng_x_preferred":[
        "Kinkiizi"
    ],
    "name:nds_x_preferred":[
        "Kanungu"
    ],
    "name:nob_x_preferred":[
        "Kanungu"
    ],
    "name:rum_x_preferred":[
        "Kanungu"
    ],
    "name:swa_x_preferred":[
        "Kanungu"
    ],
    "name:unk_x_variant":[
        "Kinkizi"
    ],
    "name:urd_x_preferred":[
        "\u06a9\u0627\u0646\u0648\u0646\u06af\u0648"
    ],
    "qs:gn_country":"UG",
    "qs:gn_fcode":"ADM3",
    "qs:gn_pop":0,
    "qs:name":"Kanungu",
    "qs:name_adm0":"Uganda",
    "qs:name_adm1":"Kanungu",
    "qs:photos":80,
    "qs:photos_1k":16,
    "qs:photos_9k":1,
    "qs:photos_9r":3,
    "qs:photos_all":80,
    "qs:photos_sr":3,
    "qs:placetype":"Town",
    "qs:pop_sr":"0",
    "qs:woe_adm0":23424974,
    "wof:name":"Kanungu",
    "wof:placetype":"locality"
},
  "geometry": {"coordinates":[29.73283,-0.78828],"type":"Point"}
}