{
  "type": "Feature",
  "properties": {
    "gn:admin1_code":"E",
    "gn:admin2_code":"78",
    "gn:admin3_code":"231410.0",
    "gn:admin4_code":"8657716.0",
    "gn:asciiname":"Nakalama",
    "gn:country_code":"UG",
    "gn:dem":1127,
    "gn:feature_class":"P",
    "gn:feature_code":"PPL",
    "gn:name":"Nakalama",
    "gn:population":0,
    "gn:timezone":"Africa/Kampala",
    "iso:country":"UG",
    "wof:name":"Nakalama",
    "wof:placetype":"locality"
},
  "geometry": {"coordinates":[33.51842,0.62913],"type":"Point"}
}