{
  "type": "Feature",
  "properties": {
    "gn:admin1_code":"E",
    "gn:admin2_code":"G4",
    "gn:asciiname":"Lukunu",
    "gn:country_code":"UG",
    "gn:dem":1147,
    "gn:feature_class":"P",
    "gn:feature_code":"PPL",
    "gn:name":"Lukunu",
    "gn:population":0,
    "gn:timezone":"Africa/Kampala",
    "iso:country":"UG",
    "wof:name":"Lukunu",
    "wof:placetype":"locality"
},
  "geometry": {"coordinates":[33.39731,0.6699],"type":"Point"}
}