{
  "type": "Feature",
  "properties": {
    "gn:admin1_code":"E",
    "gn:admin2_code":"86",
    "gn:admin3_code":"8644164.0",
    "gn:admin4_code":"8658690.0",
    "gn:asciiname":"Kigandolo",
    "gn:country_code":"UG",
    "gn:dem":1180,
    "gn:feature_class":"P",
    "gn:feature_code":"PPL",
    "gn:name":"Kigandolo",
    "gn:population":0,
    "gn:timezone":"Africa/Kampala",
    "iso:country":"UG",
    "name:eng_x_preferred":[
        "Kigandolo"
    ],
    "wof:name":"Kigandolo",
    "wof:placetype":"locality"
},
  "geometry": {"coordinates":[33.62248,0.39109],"type":"Point"}
}