{
  "type": "Feature",
  "properties": {
    "gn:admin1_code":"N",
    "gn:admin2_code":"D7",
    "gn:admin3_code":"229396.0",
    "gn:admin4_code":"8657747.0",
    "gn:asciiname":"Buramali",
    "gn:country_code":"UG",
    "gn:dem":1208,
    "gn:feature_class":"P",
    "gn:feature_code":"PPL",
    "gn:name":"Buramali",
    "gn:population":0,
    "gn:timezone":"Africa/Kampala",
    "iso:country":"UG",
    "wof:name":"Buramali",
    "wof:placetype":"locality"
},
  "geometry": {"coordinates":[30.90492,3.27416],"type":"Point"}
}