{
  "type": "Feature",
  "properties": {
    "gn:admin1_code":"W",
    "gn:admin2_code":"G2",
    "gn:admin3_code":"230499.0",
    "gn:admin4_code":"8658598.0",
    "gn:asciiname":"Wekomire",
    "gn:country_code":"UG",
    "gn:dem":1373,
    "gn:feature_class":"P",
    "gn:feature_code":"PPL",
    "gn:name":"Wekomire",
    "gn:population":0,
    "gn:timezone":"Africa/Kampala",
    "iso:country":"UG",
    "wof:name":"Wekomire",
    "wof:placetype":"locality"
},
  "geometry": {"coordinates":[31.01667,0.45],"type":"Point"}
}