{
  "type": "Feature",
  "properties": {
    "gn:admin1_code":"W",
    "gn:admin2_code":"59",
    "gn:admin3_code":"7732262.0",
    "gn:admin4_code":"8657602.0",
    "gn:asciiname":"Kitondo",
    "gn:country_code":"UG",
    "gn:dem":1504,
    "gn:feature_class":"P",
    "gn:feature_code":"PPL",
    "gn:name":"Kitondo",
    "gn:population":0,
    "gn:timezone":"Africa/Kampala",
    "iso:country":"UG",
    "wof:name":"Kitondo",
    "wof:placetype":"locality"
},
  "geometry": {"coordinates":[30.16523,-0.79456],"type":"Point"}
}