{
  "type": "Feature",
  "properties": {
    "gn:admin1_code":"E",
    "gn:admin2_code":"76",
    "gn:admin3_code":"8644131.0",
    "gn:admin4_code":"8658310.0",
    "gn:asciiname":"Mulanda",
    "gn:country_code":"UG",
    "gn:dem":1170,
    "gn:feature_class":"P",
    "gn:feature_code":"PPL",
    "gn:name":"Mulanda",
    "gn:population":0,
    "gn:timezone":"Africa/Kampala",
    "iso:country":"UG",
    "name:eng_x_preferred":[
        "Mulanda"
    ],
    "wof:name":"Mulanda",
    "wof:placetype":"locality"
},
  "geometry": {"coordinates":[34.01575,0.692],"type":"Point"}
}