{
  "type": "Feature",
  "properties": {
    "gn:admin1_code":"W",
    "gn:admin2_code":"H6",
    "gn:admin3_code":"7732263.0",
    "gn:admin4_code":"8658291.0",
    "gn:asciiname":"Kabura",
    "gn:country_code":"UG",
    "gn:dem":1487,
    "gn:feature_class":"P",
    "gn:feature_code":"PPL",
    "gn:name":"Kabura",
    "gn:population":0,
    "gn:timezone":"Africa/Kampala",
    "iso:country":"UG",
    "wof:name":"Kabura",
    "wof:placetype":"locality"
},
  "geometry": {"coordinates":[30.41667,-0.55],"type":"Point"}
}