{
  "type": "Feature",
  "properties": {
    "gn:admin1_code":"N",
    "gn:admin2_code":"B7",
    "gn:admin3_code":"231170.0",
    "gn:admin4_code":"8658119.0",
    "gn:asciiname":"Akot",
    "gn:country_code":"UG",
    "gn:dem":1047,
    "gn:feature_class":"P",
    "gn:feature_code":"PPLL",
    "gn:name":"Akot",
    "gn:population":0,
    "gn:timezone":"Africa/Kampala",
    "iso:country":"UG",
    "name:eng_x_preferred":[
        "Akot"
    ],
    "wof:name":"Akot",
    "wof:placetype":"locality"
},
  "geometry": {"coordinates":[32.80475999999999,1.74983],"type":"Point"}
}