{
  "type": "Feature",
  "properties": {
    "gn:admin1_code":"E",
    "gn:admin2_code":"G7",
    "gn:admin3_code":"8644167.0",
    "gn:admin4_code":"8657689.0",
    "gn:asciiname":"Bumwangu",
    "gn:country_code":"UG",
    "gn:dem":1175,
    "gn:feature_class":"P",
    "gn:feature_code":"PPL",
    "gn:name":"Bumwangu",
    "gn:population":0,
    "gn:timezone":"Africa/Kampala",
    "iso:country":"UG",
    "name:eng_x_preferred":[
        "Bumwangu"
    ],
    "wof:name":"Bumwangu",
    "wof:placetype":"locality"
},
  "geometry": {"coordinates":[33.80191,0.34569],"type":"Point"}
}