{
  "type": "Feature",
  "properties": {
    "gn:admin1_code":"E",
    "gn:admin2_code":"D6",
    "gn:asciiname":"Bukhoma",
    "gn:country_code":"UG",
    "gn:dem":1380,
    "gn:feature_class":"P",
    "gn:feature_code":"PPL",
    "gn:name":"Bukhoma",
    "gn:population":0,
    "gn:timezone":"Africa/Kampala",
    "iso:country":"UG",
    "name:eng_x_preferred":[
        "Bukhoma"
    ],
    "wof:name":"Bukhoma",
    "wof:placetype":"locality"
},
  "geometry": {"coordinates":[34.37716,0.81012],"type":"Point"}
}