{
  "type": "Feature",
  "properties": {
    "gn:admin1_code":"W",
    "gn:admin2_code":"79",
    "gn:asciiname":"Rwengajo",
    "gn:country_code":"UG",
    "gn:dem":1496,
    "gn:feature_class":"P",
    "gn:feature_code":"PPL",
    "gn:name":"Rwengajo",
    "gn:population":0,
    "gn:timezone":"Africa/Kampala",
    "iso:country":"UG",
    "name:eng_x_preferred":[
        "Rwengajo"
    ],
    "wof:name":"Rwengajo",
    "wof:placetype":"locality"
},
  "geometry": {"coordinates":[30.32009,0.58623],"type":"Point"}
}