{
  "type": "Feature",
  "properties": {
    "gn:admin1_code":"N",
    "gn:admin2_code":"B7",
    "gn:asciiname":"Nabweyo",
    "gn:country_code":"UG",
    "gn:dem":1045,
    "gn:feature_class":"P",
    "gn:feature_code":"PPL",
    "gn:name":"Nabweyo",
    "gn:population":0,
    "gn:timezone":"Africa/Kampala",
    "iso:country":"UG",
    "name:eng_x_preferred":[
        "Nabweyo"
    ],
    "wof:name":"Nabweyo",
    "wof:placetype":"locality"
},
  "geometry": {"coordinates":[32.71821,1.58776],"type":"Point"}
}