{
  "type": "Feature",
  "properties": {
    "gn:admin1_code":"E",
    "gn:admin2_code":"F9",
    "gn:admin3_code":"7732258.0",
    "gn:admin4_code":"8657939.0",
    "gn:asciiname":"Greek River",
    "gn:cc2":"UG",
    "gn:country_code":"UG",
    "gn:dem":1193,
    "gn:feature_class":"P",
    "gn:feature_code":"PPL",
    "gn:name":"Greek River",
    "gn:population":0,
    "gn:timezone":"Africa/Kampala",
    "iso:country":"UG",
    "name:und_x_variant":[
        "Kiriki",
        "Greek River"
    ],
    "wof:name":"Greek River",
    "wof:placetype":"locality"
},
  "geometry": {"coordinates":[34.71667,1.45],"type":"Point"}
}