{
  "type": "Feature",
  "properties": {
    "gn:admin1_code":"W",
    "gn:admin2_code":"50",
    "gn:admin3_code":"234463.0",
    "gn:admin4_code":"8658090.0",
    "gn:asciiname":"Bwijanga",
    "gn:country_code":"UG",
    "gn:dem":1112,
    "gn:feature_class":"P",
    "gn:feature_code":"PPL",
    "gn:name":"Bwijanga",
    "gn:population":0,
    "gn:timezone":"Africa/Kampala",
    "iso:country":"UG",
    "wof:name":"Bwijanga",
    "wof:placetype":"locality"
},
  "geometry": {"coordinates":[31.58477,1.53344],"type":"Point"}
}