{
  "type": "Feature",
  "properties": {
    "gn:admin1_code":"W",
    "gn:admin2_code":"E6",
    "gn:admin3_code":"234484.0",
    "gn:admin4_code":"8657648.0",
    "gn:asciiname":"Butale",
    "gn:country_code":"UG",
    "gn:dem":1851,
    "gn:feature_class":"P",
    "gn:feature_code":"PPL",
    "gn:name":"Butale",
    "gn:population":0,
    "gn:timezone":"Africa/Kampala",
    "iso:country":"UG",
    "name:ceb_x_preferred":[
        "Butale"
    ],
    "name:fra_x_preferred":[
        "Butale"
    ],
    "name:ita_x_preferred":[
        "Butale"
    ],
    "name:mlg_x_preferred":[
        "Butale"
    ],
    "name:nld_x_preferred":[
        "Butale"
    ],
    "name:pol_x_preferred":[
        "Butale"
    ],
    "name:swa_x_preferred":[
        "Butale"
    ],
    "name:swe_x_preferred":[
        "Butale"
    ],
    "name:tsn_x_preferred":[
        "Butale"
    ],
    "name:und_x_variant":[
        "Butare",
        "Butale"
    ],
    "wof:name":"Butale",
    "wof:placetype":"locality"
},
  "geometry": {"coordinates":[30.40111,-0.32639],"type":"Point"}
}