{
  "type": "Feature",
  "properties": {
    "gn:admin1_code":"E",
    "gn:admin2_code":"D2",
    "gn:asciiname":"Kisenyi",
    "gn:country_code":"UG",
    "gn:dem":1073,
    "gn:feature_class":"P",
    "gn:feature_code":"PPL",
    "gn:name":"Kisenyi",
    "gn:population":0,
    "gn:timezone":"Africa/Kampala",
    "iso:country":"UG",
    "wof:name":"Kisenyi",
    "wof:placetype":"locality"
},
  "geometry": {"coordinates":[33.53175,0.97293],"type":"Point"}
}