{
  "type": "Feature",
  "properties": {
    "gn:admin1_code":"E",
    "gn:admin2_code":"76",
    "gn:asciiname":"Pasindi",
    "gn:country_code":"UG",
    "gn:dem":1092,
    "gn:feature_class":"P",
    "gn:feature_code":"PPL",
    "gn:name":"Pasindi",
    "gn:population":0,
    "gn:timezone":"Africa/Kampala",
    "iso:country":"UG",
    "wof:name":"Pasindi",
    "wof:placetype":"locality"
},
  "geometry": {"coordinates":[33.97718,0.64418],"type":"Point"}
}