{
  "type": "Feature",
  "properties": {
    "gn:admin1_code":"W",
    "gn:admin2_code":"59",
    "gn:admin3_code":"7732262.0",
    "gn:admin4_code":"8657699.0",
    "gn:asciiname":"Kyaruhuga",
    "gn:country_code":"UG",
    "gn:dem":1417,
    "gn:feature_class":"P",
    "gn:feature_code":"PPL",
    "gn:name":"Kyaruhuga",
    "gn:population":0,
    "gn:timezone":"Africa/Kampala",
    "iso:country":"UG",
    "name:und_x_variant":[
        "Kyaruhunga",
        "Kyaruhuga"
    ],
    "wof:name":"Kyaruhuga",
    "wof:placetype":"locality"
},
  "geometry": {"coordinates":[30.08333,-0.86667],"type":"Point"}
}