{
  "type": "Feature",
  "properties": {
    "gn:admin1_code":"N",
    "gn:admin2_code":"B7",
    "gn:admin3_code":"231170.0",
    "gn:admin4_code":"8658485.0",
    "gn:asciiname":"Abarikori",
    "gn:country_code":"UG",
    "gn:dem":1054,
    "gn:feature_class":"P",
    "gn:feature_code":"PPLL",
    "gn:name":"Abarikori",
    "gn:population":0,
    "gn:timezone":"Africa/Kampala",
    "iso:country":"UG",
    "name:eng_x_preferred":[
        "Abarikori"
    ],
    "wof:name":"Abarikori",
    "wof:placetype":"locality"
},
  "geometry": {"coordinates":[32.87979,1.65718],"type":"Point"}
}