{
  "type": "Feature",
  "properties": {
    "gn:admin1_code":"E",
    "gn:admin2_code":"H5",
    "gn:admin3_code":"226329.0",
    "gn:admin4_code":"8658732.0",
    "gn:asciiname":"Odungura",
    "gn:country_code":"UG",
    "gn:dem":1107,
    "gn:feature_class":"P",
    "gn:feature_code":"PPL",
    "gn:name":"Odungura",
    "gn:population":0,
    "gn:timezone":"Africa/Kampala",
    "iso:country":"UG",
    "wof:name":"Odungura",
    "wof:placetype":"locality"
},
  "geometry": {"coordinates":[33.51331,1.53489],"type":"Point"}
}