{
  "type": "Feature",
  "properties": {
    "gn:admin1_code":"E",
    "gn:admin2_code":"76",
    "gn:asciiname":"Magoro",
    "gn:country_code":"UG",
    "gn:dem":1174,
    "gn:feature_class":"P",
    "gn:feature_code":"PPL",
    "gn:name":"Magoro",
    "gn:population":0,
    "gn:timezone":"Africa/Kampala",
    "iso:country":"UG",
    "name:eng_x_preferred":[
        "Magoro"
    ],
    "wof:name":"Magoro",
    "wof:placetype":"locality"
},
  "geometry": {"coordinates":[34.12635,0.65178],"type":"Point"}
}