{
  "type": "Feature",
  "properties": {
    "gn:admin1_code":"W",
    "gn:admin2_code":"28",
    "gn:asciiname":"Bundimulinga",
    "gn:country_code":"UG",
    "gn:dem":1514,
    "gn:feature_class":"P",
    "gn:feature_code":"PPL",
    "gn:name":"Bundimulinga",
    "gn:population":0,
    "gn:timezone":"Africa/Kampala",
    "iso:country":"UG",
    "name:eng_x_preferred":[
        "Bundimulinga"
    ],
    "wof:name":"Bundimulinga",
    "wof:placetype":"locality"
},
  "geometry": {"coordinates":[30.14768,0.75775],"type":"Point"}
}