{
  "type": "Feature",
  "properties": {
    "gn:admin1_code":"C",
    "gn:admin2_code":"G5",
    "gn:admin3_code":"7910221.0",
    "gn:admin4_code":"8658697.0",
    "gn:asciiname":"Kanyogoga",
    "gn:country_code":"UG",
    "gn:dem":1325,
    "gn:feature_class":"P",
    "gn:feature_code":"PPL",
    "gn:name":"Kanyogoga",
    "gn:population":0,
    "gn:timezone":"Africa/Kampala",
    "iso:country":"UG",
    "wof:name":"Kanyogoga",
    "wof:placetype":"locality"
},
  "geometry": {"coordinates":[31.33333,-0.38333],"type":"Point"}
}