{
  "type": "Feature",
  "properties": {
    "gn:admin1_code":"E",
    "gn:admin2_code":"D6",
    "gn:asciiname":"Bukhonzo",
    "gn:country_code":"UG",
    "gn:dem":1205,
    "gn:feature_class":"P",
    "gn:feature_code":"PPL",
    "gn:name":"Bukhonzo",
    "gn:population":0,
    "gn:timezone":"Africa/Kampala",
    "iso:country":"UG",
    "name:eng_x_preferred":[
        "Bukhonzo"
    ],
    "wof:name":"Bukhonzo",
    "wof:placetype":"locality"
},
  "geometry": {"coordinates":[34.24255,0.86184],"type":"Point"}
}