{
  "type": "Feature",
  "properties": {
    "gn:admin1_code":"W",
    "gn:admin2_code":"C5",
    "gn:admin3_code":"7869947.0",
    "gn:admin4_code":"8657545.0",
    "gn:asciiname":"Ruangi",
    "gn:country_code":"UG",
    "gn:dem":652,
    "gn:feature_class":"P",
    "gn:feature_code":"PPL",
    "gn:name":"Ruangi",
    "gn:population":0,
    "gn:timezone":"Africa/Kampala",
    "iso:country":"UG",
    "name:und_x_variant":[
        "Kitemura",
        "Ruangi"
    ],
    "wof:name":"Ruangi",
    "wof:placetype":"locality"
},
  "geometry": {"coordinates":[31.45382,2.11039],"type":"Point"}
}