{
  "type": "Feature",
  "properties": {
    "gn:admin1_code":"E",
    "gn:admin2_code":"78",
    "gn:admin3_code":"234502.0",
    "gn:admin4_code":"8643428.0",
    "gn:asciiname":"Busesa",
    "gn:country_code":"UG",
    "gn:dem":1132,
    "gn:feature_class":"P",
    "gn:feature_code":"PPL",
    "gn:name":"Busesa",
    "gn:population":0,
    "gn:timezone":"Africa/Kampala",
    "iso:country":"UG",
    "wof:name":"Busesa",
    "wof:placetype":"locality"
},
  "geometry": {"coordinates":[33.60027,0.62631],"type":"Point"}
}