{
  "type": "Feature",
  "properties": {
    "gn:admin1_code":"E",
    "gn:admin2_code":"38",
    "gn:asciiname":"Buwanga",
    "gn:country_code":"UG",
    "gn:dem":1099,
    "gn:feature_class":"P",
    "gn:feature_code":"PPL",
    "gn:name":"Buwanga",
    "gn:population":0,
    "gn:timezone":"Africa/Kampala",
    "iso:country":"UG",
    "wof:name":"Buwanga",
    "wof:placetype":"locality"
},
  "geometry": {"coordinates":[33.22753,0.9693],"type":"Point"}
}