{
  "type": "Feature",
  "properties": {
    "gn:admin1_code":"C",
    "gn:admin2_code":"56",
    "gn:admin3_code":"8644175.0",
    "gn:admin4_code":"8657557.0",
    "gn:asciiname":"Kasimu",
    "gn:country_code":"UG",
    "gn:dem":1235,
    "gn:feature_class":"P",
    "gn:feature_code":"PPL",
    "gn:name":"Kasimu",
    "gn:population":0,
    "gn:timezone":"Africa/Kampala",
    "iso:country":"UG",
    "wof:name":"Kasimu",
    "wof:placetype":"locality"
},
  "geometry": {"coordinates":[31.76667,0.48333],"type":"Point"}
}