{
  "type": "Feature",
  "properties": {
    "gn:admin1_code":"E",
    "gn:admin2_code":"67",
    "gn:admin3_code":"8644151.0",
    "gn:admin4_code":"8658193.0",
    "gn:asciiname":"Makunda",
    "gn:country_code":"UG",
    "gn:dem":1142,
    "gn:feature_class":"P",
    "gn:feature_code":"PPL",
    "gn:name":"Makunda",
    "gn:population":0,
    "gn:timezone":"Africa/Kampala",
    "iso:country":"UG",
    "name:eng_x_preferred":[
        "Makunda"
    ],
    "name:fra_x_preferred":[
        "Makunda"
    ],
    "name:ita_x_preferred":[
        "Makunda"
    ],
    "name:mlg_x_preferred":[
        "Makunda"
    ],
    "name:nld_x_preferred":[
        "Makunda"
    ],
    "name:pol_x_preferred":[
        "Makunda"
    ],
    "name:swa_x_preferred":[
        "Makunda"
    ],
    "name:swe_x_preferred":[
        "Makunda"
    ],
    "wof:name":"Makunda",
    "wof:placetype":"locality"
},
  "geometry": {"coordinates":[33.95444000000001,0.39152],"type":"Point"}
}