{
  "type": "Feature",
  "properties": {
    "gn:admin1_code":"N",
    "gn:admin2_code":"26",
    "gn:admin3_code":"229387.0",
    "gn:admin4_code":"8261613.0",
    "gn:asciiname":"Awir",
    "gn:country_code":"UG",
    "gn:dem":1051,
    "gn:feature_class":"P",
    "gn:feature_code":"PPL",
    "gn:name":"Awir",
    "gn:population":0,
    "gn:timezone":"Africa/Kampala",
    "iso:country":"UG",
    "name:eng_x_preferred":[
        "Awir"
    ],
    "wof:name":"Awir",
    "wof:placetype":"locality"
},
  "geometry": {"coordinates":[32.66212,1.96524],"type":"Point"}
}