{
  "type": "Feature",
  "properties": {
    "gn:admin1_code":"W",
    "gn:admin2_code":"81",
    "gn:admin3_code":"231608.0",
    "gn:admin4_code":"8658588.0",
    "gn:asciiname":"Rwebikwato",
    "gn:country_code":"UG",
    "gn:dem":1252,
    "gn:feature_class":"P",
    "gn:feature_code":"PPL",
    "gn:name":"Rwebikwato",
    "gn:population":0,
    "gn:timezone":"Africa/Kampala",
    "iso:country":"UG",
    "wof:name":"Rwebikwato",
    "wof:placetype":"locality"
},
  "geometry": {"coordinates":[30.48333,0.33333],"type":"Point"}
}