{
  "type": "Feature",
  "properties": {
    "gn:admin1_code":"W",
    "gn:admin2_code":"79",
    "gn:admin3_code":"7732254.0",
    "gn:admin4_code":"8657930.0",
    "gn:asciiname":"Kyakabaseke",
    "gn:country_code":"UG",
    "gn:dem":1525,
    "gn:feature_class":"P",
    "gn:feature_code":"PPL",
    "gn:name":"Kyakabaseke",
    "gn:population":0,
    "gn:timezone":"Africa/Kampala",
    "iso:country":"UG",
    "name:eng_x_preferred":[
        "Kyakabaseke"
    ],
    "wof:name":"Kyakabaseke",
    "wof:placetype":"locality"
},
  "geometry": {"coordinates":[30.42647,0.84588],"type":"Point"}
}