{
  "type": "Feature",
  "properties": {
    "gn:admin1_code":"E",
    "gn:admin2_code":"76",
    "gn:asciiname":"Chalumba",
    "gn:country_code":"UG",
    "gn:dem":1148,
    "gn:feature_class":"P",
    "gn:feature_code":"PPL",
    "gn:name":"Chalumba",
    "gn:population":0,
    "gn:timezone":"Africa/Kampala",
    "iso:country":"UG",
    "name:eng_x_preferred":[
        "Chalumba"
    ],
    "wof:name":"Chalumba",
    "wof:placetype":"locality"
},
  "geometry": {"coordinates":[34.00756,0.77352],"type":"Point"}
}