{
  "type": "Feature",
  "properties": {
    "gn:admin1_code":"W",
    "gn:admin2_code":"H4",
    "gn:admin3_code":"234151.0",
    "gn:admin4_code":"8658002.0",
    "gn:asciiname":"Katunguru",
    "gn:country_code":"UG",
    "gn:dem":953,
    "gn:feature_class":"P",
    "gn:feature_code":"PPL",
    "gn:name":"Katunguru",
    "gn:population":0,
    "gn:timezone":"Africa/Kampala",
    "iso:country":"UG",
    "wof:name":"Katunguru",
    "wof:placetype":"locality"
},
  "geometry": {"coordinates":[30.06529,-0.14797],"type":"Point"}
}