{
  "type": "Feature",
  "properties": {
    "gn:admin1_code":"C",
    "gn:admin2_code":"96",
    "gn:asciiname":"Bukondo",
    "gn:country_code":"UG",
    "gn:dem":1216,
    "gn:feature_class":"P",
    "gn:feature_code":"PPL",
    "gn:name":"Bukondo",
    "gn:population":0,
    "gn:timezone":"Africa/Kampala",
    "iso:country":"UG",
    "wof:name":"Bukondo",
    "wof:placetype":"locality"
},
  "geometry": {"coordinates":[32.28985,0.46389],"type":"Point"}
}