{
  "type": "Feature",
  "properties": {
    "gn:admin1_code":"E",
    "gn:admin2_code":"C1",
    "gn:admin3_code":"8644159.0",
    "gn:admin4_code":"8657941.0",
    "gn:asciiname":"Kabuna",
    "gn:country_code":"UG",
    "gn:dem":1135,
    "gn:feature_class":"P",
    "gn:feature_code":"PPL",
    "gn:name":"Kabuna",
    "gn:population":0,
    "gn:timezone":"Africa/Kampala",
    "iso:country":"UG",
    "wof:name":"Kabuna",
    "wof:placetype":"locality"
},
  "geometry": {"coordinates":[33.98333,1.08333],"type":"Point"}
}