{
  "type": "Feature",
  "properties": {
    "gn:admin1_code":"W",
    "gn:admin2_code":"I2",
    "gn:admin3_code":"8644161.0",
    "gn:admin4_code":"8658063.0",
    "gn:asciiname":"Muchubwa",
    "gn:country_code":"UG",
    "gn:dem":1175,
    "gn:feature_class":"P",
    "gn:feature_code":"PPL",
    "gn:name":"Muchubwa",
    "gn:population":0,
    "gn:timezone":"Africa/Kampala",
    "iso:country":"UG",
    "wof:name":"Muchubwa",
    "wof:placetype":"locality"
},
  "geometry": {"coordinates":[31.41667,1.01667],"type":"Point"}
}