{
  "type": "Feature",
  "properties": {
    "gn:admin1_code":"C",
    "gn:admin2_code":"I3",
    "gn:admin3_code":"8644144.0",
    "gn:admin4_code":"8657681.0",
    "gn:asciiname":"Kabira",
    "gn:country_code":"UG",
    "gn:dem":1220,
    "gn:feature_class":"P",
    "gn:feature_code":"PPL",
    "gn:name":"Kabira",
    "gn:population":0,
    "gn:timezone":"Africa/Kampala",
    "iso:country":"UG",
    "name:ceb_x_preferred":[
        "Kabira"
    ],
    "name:swe_x_preferred":[
        "Kabira"
    ],
    "wof:name":"Kabira",
    "wof:placetype":"locality"
},
  "geometry": {"coordinates":[31.64528,-0.65333],"type":"Point"}
}