{
  "type": "Feature",
  "properties": {
    "gn:admin1_code":"C",
    "gn:admin2_code":"E7",
    "gn:admin3_code":"7732075.0",
    "gn:admin4_code":"8657733.0",
    "gn:asciiname":"Malongwe",
    "gn:country_code":"UG",
    "gn:dem":1255,
    "gn:feature_class":"P",
    "gn:feature_code":"PPL",
    "gn:name":"Malongwe",
    "gn:population":0,
    "gn:timezone":"Africa/Kampala",
    "iso:country":"UG",
    "name:eng_x_preferred":[
        "Malongwe"
    ],
    "wof:name":"Malongwe",
    "wof:placetype":"locality"
},
  "geometry": {"coordinates":[33.02527,0.30659],"type":"Point"}
}