{
  "type": "Feature",
  "properties": {
    "gn:admin1_code":"W",
    "gn:admin2_code":"79",
    "gn:asciiname":"Maguru",
    "gn:country_code":"UG",
    "gn:dem":1538,
    "gn:feature_class":"P",
    "gn:feature_code":"PPL",
    "gn:name":"Maguru",
    "gn:population":0,
    "gn:timezone":"Africa/Kampala",
    "iso:country":"UG",
    "name:eng_x_preferred":[
        "Maguru"
    ],
    "wof:name":"Maguru",
    "wof:placetype":"locality"
},
  "geometry": {"coordinates":[30.27048,0.64121],"type":"Point"}
}