{
  "type": "Feature",
  "properties": {
    "gn:admin1_code":"C",
    "gn:admin2_code":"D8",
    "gn:admin3_code":"8644137.0",
    "gn:admin4_code":"8658316.0",
    "gn:asciiname":"Nakaseta",
    "gn:country_code":"UG",
    "gn:dem":1211,
    "gn:feature_class":"P",
    "gn:feature_code":"PPL",
    "gn:name":"Nakaseta",
    "gn:population":0,
    "gn:timezone":"Africa/Kampala",
    "iso:country":"UG",
    "wof:name":"Nakaseta",
    "wof:placetype":"locality"
},
  "geometry": {"coordinates":[32.16628,0.37951],"type":"Point"}
}