{
  "type": "Feature",
  "properties": {
    "gn:admin1_code":"E",
    "gn:admin2_code":"78",
    "gn:asciiname":"Bufutula",
    "gn:country_code":"UG",
    "gn:dem":1126,
    "gn:feature_class":"P",
    "gn:feature_code":"PPL",
    "gn:name":"Bufutula",
    "gn:population":0,
    "gn:timezone":"Africa/Kampala",
    "iso:country":"UG",
    "wof:name":"Bufutula",
    "wof:placetype":"locality"
},
  "geometry": {"coordinates":[33.50758,0.67818],"type":"Point"}
}