{
  "type": "Feature",
  "properties": {
    "gn:admin1_code":"C",
    "gn:admin2_code":"96",
    "gn:asciiname":"Ggambirana",
    "gn:country_code":"UG",
    "gn:dem":1192,
    "gn:feature_class":"P",
    "gn:feature_code":"PPL",
    "gn:name":"Ggambirana",
    "gn:population":0,
    "gn:timezone":"Africa/Kampala",
    "iso:country":"UG",
    "wof:name":"Ggambirana",
    "wof:placetype":"locality"
},
  "geometry": {"coordinates":[32.46377,0.19882],"type":"Point"}
}