{
  "type": "Feature",
  "properties": {
    "gn:admin1_code":"N",
    "gn:admin2_code":"B7",
    "gn:admin3_code":"231170.0",
    "gn:admin4_code":"8658492.0",
    "gn:asciiname":"Amolatar",
    "gn:country_code":"UG",
    "gn:dem":1041,
    "gn:feature_class":"P",
    "gn:feature_code":"PPLA2",
    "gn:name":"Amolatar",
    "gn:population":0,
    "gn:timezone":"Africa/Kampala",
    "iso:country":"UG",
    "name:und_x_variant":[
        "Molitar",
        "Amolota",
        "Amolitar",
        "Amolotar",
        "Amolatar"
    ],
    "wof:name":"Amolatar",
    "wof:placetype":"locality"
},
  "geometry": {"coordinates":[32.83972,1.61556],"type":"Point"}
}