{
  "type": "Feature",
  "properties": {
    "gn:admin1_code":"N",
    "gn:admin2_code":"B7",
    "gn:admin3_code":"231170.0",
    "gn:admin4_code":"8658492.0",
    "gn:asciiname":"Amolatar",
    "gn:country_code":"UG",
    "gn:dem":1041,
    "gn:feature_class":"P",
    "gn:feature_code":"PPLA2",
    "gn:name":"Amolatar",
    "gn:population":0,
    "gn:timezone":"Africa/Kampala",
    "iso:country":"UG",
    "name:azb_x_preferred":[
        "\u0627\u0645\u0648\u0644\u0627\u062a\u0627\u0631"
    ],
    "name:ceb_x_preferred":[
        "Amolatar"
    ],
    "name:fas_x_preferred":[
        "\u0627\u0645\u0648\u0644\u0627\u062a\u0627\u0631"
    ],
    "name:heb_x_preferred":[
        "\u05d0\u05de\u05d5\u05dc\u05d8\u05d0\u05e8"
    ],
    "name:hun_x_preferred":[
        "Amolatar"
    ],
    "name:lug_x_preferred":[
        "Amolatar"
    ],
    "name:mal_x_preferred":[
        "\u0d05\u0d2e\u0d4a\u0d32\u0d1f\u0d7c"
    ],
    "name:ron_x_preferred":[
        "Amolatar"
    ],
    "name:swa_x_preferred":[
        "Amolatar"
    ],
    "name:und_x_variant":[
        "Molitar",
        "Amolota",
        "Amolitar",
        "Amolotar"
    ],
    "name:urd_x_preferred":[
        "\u0627\u0645\u0648\u0644\u0627\u062a\u0627\u0631"
    ],
    "wof:name":"Amolatar",
    "wof:placetype":"locality"
},
  "geometry": {"coordinates":[32.83972,1.61556],"type":"Point"}
}