{
  "type": "Feature",
  "properties": {
    "gn:admin1_code":"W",
    "gn:admin2_code":"79",
    "gn:asciiname":"Makobi",
    "gn:country_code":"UG",
    "gn:dem":1508,
    "gn:feature_class":"P",
    "gn:feature_code":"PPL",
    "gn:name":"Makobi",
    "gn:population":0,
    "gn:timezone":"Africa/Kampala",
    "iso:country":"UG",
    "name:eng_x_preferred":[
        "Makobi"
    ],
    "wof:name":"Makobi",
    "wof:placetype":"locality"
},
  "geometry": {"coordinates":[30.3345,0.57086],"type":"Point"}
}