{
  "type": "Feature",
  "properties": {
    "gn:admin1_code":"E",
    "gn:admin2_code":"38",
    "gn:admin3_code":"234617.0",
    "gn:admin4_code":"8657697.0",
    "gn:asciiname":"Budali",
    "gn:country_code":"UG",
    "gn:dem":1037,
    "gn:feature_class":"P",
    "gn:feature_code":"PPL",
    "gn:name":"Budali",
    "gn:population":0,
    "gn:timezone":"Africa/Kampala",
    "iso:country":"UG",
    "name:und_x_variant":[
        "Budale",
        "Budali"
    ],
    "wof:name":"Budali",
    "wof:placetype":"locality"
},
  "geometry": {"coordinates":[32.95,1.08333],"type":"Point"}
}