{
  "type": "Feature",
  "properties": {
    "gn:admin1_code":"E",
    "gn:admin2_code":"E1",
    "gn:asciiname":"Bupaluka",
    "gn:country_code":"UG",
    "gn:dem":1084,
    "gn:feature_class":"P",
    "gn:feature_code":"PPL",
    "gn:name":"Bupaluka",
    "gn:population":0,
    "gn:timezone":"Africa/Kampala",
    "iso:country":"UG",
    "wof:name":"Bupaluka",
    "wof:placetype":"locality"
},
  "geometry": {"coordinates":[33.65997,0.97774],"type":"Point"}
}