{
  "type": "Feature",
  "properties": {
    "gn:admin1_code":"C",
    "gn:admin2_code":"73",
    "gn:admin3_code":"234123.0",
    "gn:admin4_code":"8657970.0",
    "gn:asciiname":"Katuba",
    "gn:country_code":"UG",
    "gn:dem":1042,
    "gn:feature_class":"P",
    "gn:feature_code":"PPL",
    "gn:name":"Katuba",
    "gn:population":0,
    "gn:timezone":"Africa/Kampala",
    "iso:country":"UG",
    "name:ceb_x_preferred":[
        "Katuba"
    ],
    "name:fra_x_preferred":[
        "Katuba"
    ],
    "wof:name":"Katuba",
    "wof:placetype":"locality"
},
  "geometry": {"coordinates":[32.27844,1.60272],"type":"Point"}
}