{
  "type": "Feature",
  "properties": {
    "gn:admin1_code":"C",
    "gn:admin2_code":"96",
    "gn:admin3_code":"7732385.0",
    "gn:admin4_code":"8658110.0",
    "gn:asciiname":"Seguku",
    "gn:country_code":"UG",
    "gn:dem":1185,
    "gn:feature_class":"P",
    "gn:feature_code":"PPL",
    "gn:name":"Seguku",
    "gn:population":0,
    "gn:timezone":"Africa/Kampala",
    "iso:country":"UG",
    "wof:name":"Seguku",
    "wof:placetype":"locality"
},
  "geometry": {"coordinates":[32.55011,0.23108],"type":"Point"}
}