{
  "type": "Feature",
  "properties": {
    "gn:admin1_code":"E",
    "gn:admin2_code":"G4",
    "gn:asciiname":"Namakakale",
    "gn:country_code":"UG",
    "gn:dem":1141,
    "gn:feature_class":"P",
    "gn:feature_code":"PPL",
    "gn:name":"Namakakale",
    "gn:population":0,
    "gn:timezone":"Africa/Kampala",
    "iso:country":"UG",
    "wof:name":"Namakakale",
    "wof:placetype":"locality"
},
  "geometry": {"coordinates":[33.38785,0.64386],"type":"Point"}
}