{
  "type": "Feature",
  "properties": {
    "gn:admin1_code":"E",
    "gn:admin2_code":"78",
    "gn:asciiname":"Ikumbya",
    "gn:country_code":"UG",
    "gn:dem":1118,
    "gn:feature_class":"P",
    "gn:feature_code":"PPL",
    "gn:name":"Ikumbya",
    "gn:population":0,
    "gn:timezone":"Africa/Kampala",
    "iso:country":"UG",
    "wof:name":"Ikumbya",
    "wof:placetype":"locality"
},
  "geometry": {"coordinates":[33.44505,0.87532],"type":"Point"}
}