{
  "type": "Feature",
  "properties": {
    "gn:admin1_code":"C",
    "gn:admin2_code":"37",
    "gn:admin3_code":"8644170.0",
    "gn:admin4_code":"7732390.0",
    "gn:asciiname":"Kitebi",
    "gn:country_code":"UG",
    "gn:dem":1171,
    "gn:feature_class":"P",
    "gn:feature_code":"PPL",
    "gn:name":"Kitebi",
    "gn:population":0,
    "gn:timezone":"Africa/Kampala",
    "iso:country":"UG",
    "wof:name":"Kitebi",
    "wof:placetype":"locality"
},
  "geometry": {"coordinates":[32.54764,0.2853],"type":"Point"}
}