{
  "type": "Feature",
  "properties": {
    "gn:admin1_code":"C",
    "gn:admin2_code":"96",
    "gn:admin3_code":"234053.0",
    "gn:admin4_code":"8658307.0",
    "gn:asciiname":"Memere",
    "gn:country_code":"UG",
    "gn:dem":1135,
    "gn:feature_class":"P",
    "gn:feature_code":"PPL",
    "gn:name":"Memere",
    "gn:population":0,
    "gn:timezone":"Africa/Kampala",
    "iso:country":"UG",
    "wof:name":"Memere",
    "wof:placetype":"locality"
},
  "geometry": {"coordinates":[32.33333,0.05],"type":"Point"}
}