{
  "type": "Feature",
  "properties": {
    "gn:admin1_code":"E",
    "gn:admin2_code":"76",
    "gn:asciiname":"Odoponyi",
    "gn:country_code":"UG",
    "gn:dem":1131,
    "gn:feature_class":"P",
    "gn:feature_code":"PPL",
    "gn:name":"Odoponyi",
    "gn:population":0,
    "gn:timezone":"Africa/Kampala",
    "iso:country":"UG",
    "name:eng_x_preferred":[
        "Odoponyi"
    ],
    "wof:name":"Odoponyi",
    "wof:placetype":"locality"
},
  "geometry": {"coordinates":[34.05573,0.75467],"type":"Point"}
}