{
  "type": "Feature",
  "properties": {
    "gn:admin1_code":"E",
    "gn:admin2_code":"86",
    "gn:admin3_code":"8644164.0",
    "gn:admin4_code":"8658690.0",
    "gn:asciiname":"Kiriwe",
    "gn:country_code":"UG",
    "gn:dem":1203,
    "gn:feature_class":"P",
    "gn:feature_code":"PPL",
    "gn:name":"Kiriwe",
    "gn:population":0,
    "gn:timezone":"Africa/Kampala",
    "iso:country":"UG",
    "name:eng_x_preferred":[
        "Kiriwe"
    ],
    "name:eng_x_variant":[
        "Kirewe"
    ],
    "wof:name":"Kiriwe",
    "wof:placetype":"locality"
},
  "geometry": {"coordinates":[33.64254,0.42338],"type":"Point"}
}