{
  "type": "Feature",
  "properties": {
    "gn:admin1_code":"E",
    "gn:admin2_code":"33",
    "gn:admin3_code":"7732228.0",
    "gn:admin4_code":"8657586.0",
    "gn:asciiname":"Masese",
    "gn:country_code":"UG",
    "gn:dem":1181,
    "gn:feature_class":"P",
    "gn:feature_code":"PPL",
    "gn:name":"Masese",
    "gn:population":0,
    "gn:timezone":"Africa/Kampala",
    "iso:country":"UG",
    "name:eng_x_preferred":[
        "Masese"
    ],
    "wof:name":"Masese",
    "wof:placetype":"locality"
},
  "geometry": {"coordinates":[33.22952,0.44871],"type":"Point"}
}