{
  "type": "Feature",
  "properties": {
    "gn:admin1_code":"W",
    "gn:admin2_code":"G2",
    "gn:admin3_code":"230499.0",
    "gn:admin4_code":"8658598.0",
    "gn:asciiname":"Butokebulamu",
    "gn:country_code":"UG",
    "gn:dem":1362,
    "gn:feature_class":"P",
    "gn:feature_code":"PPL",
    "gn:name":"Butokebulamu",
    "gn:population":0,
    "gn:timezone":"Africa/Kampala",
    "iso:country":"UG",
    "name:und_x_variant":[
        "Butoke Butano",
        "Butokebulamu"
    ],
    "wof:name":"Butokebulamu",
    "wof:placetype":"locality"
},
  "geometry": {"coordinates":[31.13333,0.46667],"type":"Point"}
}