{
  "type": "Feature",
  "properties": {
    "gn:admin1_code":"E",
    "gn:admin2_code":"78",
    "gn:asciiname":"Namalemba-Bunio",
    "gn:country_code":"UG",
    "gn:dem":1077,
    "gn:feature_class":"P",
    "gn:feature_code":"PPL",
    "gn:name":"Namalemba-Bunio",
    "gn:population":0,
    "gn:timezone":"Africa/Kampala",
    "iso:country":"UG",
    "wof:name":"Namalemba-Bunio",
    "wof:placetype":"locality"
},
  "geometry": {"coordinates":[33.61055,0.7368],"type":"Point"}
}