{
  "type": "Feature",
  "properties": {
    "gn:admin1_code":"E",
    "gn:admin2_code":"87",
    "gn:asciiname":"Mahanga",
    "gn:country_code":"UG",
    "gn:dem":1229,
    "gn:feature_class":"P",
    "gn:feature_code":"PPL",
    "gn:name":"Mahanga",
    "gn:population":0,
    "gn:timezone":"Africa/Kampala",
    "iso:country":"UG",
    "name:eng_x_preferred":[
        "Mahanga"
    ],
    "wof:name":"Mahanga",
    "wof:placetype":"locality"
},
  "geometry": {"coordinates":[34.20224,0.98958],"type":"Point"}
}