{
  "type": "Feature",
  "properties": {
    "gn:admin1_code":"W",
    "gn:admin2_code":"81",
    "gn:admin3_code":"7732901.0",
    "gn:admin4_code":"8658629.0",
    "gn:asciiname":"Rwenjaza",
    "gn:country_code":"UG",
    "gn:dem":1258,
    "gn:feature_class":"P",
    "gn:feature_code":"PPL",
    "gn:name":"Rwenjaza",
    "gn:population":0,
    "gn:timezone":"Africa/Kampala",
    "iso:country":"UG",
    "wof:name":"Rwenjaza",
    "wof:placetype":"locality"
},
  "geometry": {"coordinates":[30.45,0.13333],"type":"Point"}
}