{
  "type": "Feature",
  "properties": {
    "gn:admin1_code":"W",
    "gn:admin2_code":"79",
    "gn:asciiname":"Burungu",
    "gn:country_code":"UG",
    "gn:dem":1583,
    "gn:feature_class":"P",
    "gn:feature_code":"PPL",
    "gn:name":"Burungu",
    "gn:population":0,
    "gn:timezone":"Africa/Kampala",
    "iso:country":"UG",
    "name:eng_x_preferred":[
        "Burungu"
    ],
    "wof:name":"Burungu",
    "wof:placetype":"locality"
},
  "geometry": {"coordinates":[30.23151,0.62545],"type":"Point"}
}