{
  "type": "Feature",
  "properties": {
    "gn:admin1_code":"W",
    "gn:admin2_code":"28",
    "gn:admin3_code":"7732250.0",
    "gn:admin4_code":"8658204.0",
    "gn:asciiname":"Bundibundu",
    "gn:country_code":"UG",
    "gn:dem":672,
    "gn:feature_class":"P",
    "gn:feature_code":"PPL",
    "gn:name":"Bundibundu",
    "gn:population":0,
    "gn:timezone":"Africa/Kampala",
    "iso:country":"UG",
    "name:eng_x_preferred":[
        "Bundibundu"
    ],
    "wof:name":"Bundibundu",
    "wof:placetype":"locality"
},
  "geometry": {"coordinates":[29.98887,0.83561],"type":"Point"}
}