{
  "type": "Feature",
  "properties": {
    "gn:admin1_code":"C",
    "gn:admin2_code":"89",
    "gn:asciiname":"Tiribogo",
    "gn:country_code":"UG",
    "gn:dem":1229,
    "gn:feature_class":"P",
    "gn:feature_code":"PPL",
    "gn:name":"Tiribogo",
    "gn:population":0,
    "gn:timezone":"Africa/Kampala",
    "iso:country":"UG",
    "wof:name":"Tiribogo",
    "wof:placetype":"locality"
},
  "geometry": {"coordinates":[32.30729,0.36929],"type":"Point"}
}