{
  "type": "Feature",
  "properties": {
    "gn:admin1_code":"W",
    "gn:admin2_code":"59",
    "gn:admin3_code":"7732260.0",
    "gn:admin4_code":"8657779.0",
    "gn:asciiname":"Chondo",
    "gn:country_code":"UG",
    "gn:dem":1378,
    "gn:feature_class":"P",
    "gn:feature_code":"PPL",
    "gn:name":"Chondo",
    "gn:population":0,
    "gn:timezone":"Africa/Kampala",
    "iso:country":"UG",
    "wof:name":"Chondo",
    "wof:placetype":"locality"
},
  "geometry": {"coordinates":[30.26667,-0.98333],"type":"Point"}
}