{
  "type": "Feature",
  "properties": {
    "gn:admin1_code":"C",
    "gn:admin2_code":"89",
    "gn:admin3_code":"7910214.0",
    "gn:admin4_code":"8657607.0",
    "gn:asciiname":"Senene",
    "gn:country_code":"UG",
    "gn:dem":1194,
    "gn:feature_class":"P",
    "gn:feature_code":"PPL",
    "gn:name":"Senene",
    "gn:population":0,
    "gn:timezone":"Africa/Kampala",
    "iso:country":"UG",
    "wof:name":"Senene",
    "wof:placetype":"locality"
},
  "geometry": {"coordinates":[32.35103,0.20623],"type":"Point"}
}