{
  "type": "Feature",
  "properties": {
    "gn:admin1_code":"E",
    "gn:admin2_code":"76",
    "gn:asciiname":"Gule",
    "gn:country_code":"UG",
    "gn:dem":1094,
    "gn:feature_class":"P",
    "gn:feature_code":"PPL",
    "gn:name":"Gule",
    "gn:population":0,
    "gn:timezone":"Africa/Kampala",
    "iso:country":"UG",
    "name:ceb_x_preferred":[
        "Gule"
    ],
    "name:deu_x_preferred":[
        "Gule"
    ],
    "name:eng_x_preferred":[
        "Gule"
    ],
    "name:swe_x_preferred":[
        "Gule"
    ],
    "name:vie_x_preferred":[
        "Gule"
    ],
    "wof:name":"Gule",
    "wof:placetype":"locality"
},
  "geometry": {"coordinates":[34.00601,0.62787],"type":"Point"}
}