{
  "type": "Feature",
  "properties": {
    "gn:admin1_code":"E",
    "gn:admin2_code":"G7",
    "gn:admin3_code":"8644167.0",
    "gn:admin4_code":"8658448.0",
    "gn:asciiname":"Maluba",
    "gn:country_code":"UG",
    "gn:dem":1148,
    "gn:feature_class":"P",
    "gn:feature_code":"PPL",
    "gn:name":"Maluba",
    "gn:population":0,
    "gn:timezone":"Africa/Kampala",
    "iso:country":"UG",
    "name:eng_x_preferred":[
        "Maluba"
    ],
    "wof:name":"Maluba",
    "wof:placetype":"locality"
},
  "geometry": {"coordinates":[33.70074,0.26723],"type":"Point"}
}