{
  "type": "Feature",
  "properties": {
    "gn:admin1_code":"C",
    "gn:admin2_code":"F2",
    "gn:admin3_code":"233919.0",
    "gn:admin4_code":"8658641.0",
    "gn:asciiname":"Kitamilo",
    "gn:country_code":"UG",
    "gn:dem":1134,
    "gn:feature_class":"P",
    "gn:feature_code":"PPLA2",
    "gn:name":"Kitamilo",
    "gn:population":0,
    "gn:timezone":"Africa/Kampala",
    "iso:country":"UG",
    "name:lug_x_preferred":[
        "Kitamilo"
    ],
    "name:urd_x_preferred":[
        "\u06a9\u06cc\u062a\u0627\u0645\u06cc\u0644\u0648"
    ],
    "wof:name":"Kitamilo",
    "wof:placetype":"locality"
},
  "geometry": {"coordinates":[33.20608,0.22215],"type":"Point"}
}