{
  "type": "Feature",
  "properties": {
    "gn:admin1_code":"E",
    "gn:admin2_code":"67",
    "gn:admin3_code":"8644151.0",
    "gn:admin4_code":"8658236.0",
    "gn:asciiname":"Busikho",
    "gn:country_code":"UG",
    "gn:dem":1215,
    "gn:feature_class":"P",
    "gn:feature_code":"PPL",
    "gn:name":"Busikho",
    "gn:population":0,
    "gn:timezone":"Africa/Kampala",
    "iso:country":"UG",
    "name:und_x_variant":[
        "Busiko",
        "Busikho"
    ],
    "wof:name":"Busikho",
    "wof:placetype":"locality"
},
  "geometry": {"coordinates":[34.03389,0.38917],"type":"Point"}
}