{
  "type": "Feature",
  "properties": {
    "gn:admin1_code":"C",
    "gn:admin2_code":"F4",
    "gn:admin3_code":"233383.0",
    "gn:admin4_code":"8657737.0",
    "gn:asciiname":"Ggolola",
    "gn:country_code":"UG",
    "gn:dem":1224,
    "gn:feature_class":"P",
    "gn:feature_code":"PPL",
    "gn:name":"Ggolola",
    "gn:population":0,
    "gn:timezone":"Africa/Kampala",
    "iso:country":"UG",
    "name:und_x_variant":[
        "Golola"
    ],
    "wof:name":"Ggolola",
    "wof:placetype":"locality"
},
  "geometry": {"coordinates":[32.06302,0.16383],"type":"Point"}
}