{
  "type": "Feature",
  "properties": {
    "gn:admin1_code":"C",
    "gn:admin2_code":"96",
    "gn:admin3_code":"7732385.0",
    "gn:admin4_code":"8658110.0",
    "gn:asciiname":"Lubowa",
    "gn:country_code":"UG",
    "gn:dem":1204,
    "gn:feature_class":"P",
    "gn:feature_code":"PPL",
    "gn:name":"Lubowa",
    "gn:population":0,
    "gn:timezone":"Africa/Kampala",
    "iso:country":"UG",
    "wof:name":"Lubowa",
    "wof:placetype":"locality"
},
  "geometry": {"coordinates":[32.55218,0.24033],"type":"Point"}
}