{
  "type": "Feature",
  "properties": {
    "gn:admin1_code":"E",
    "gn:admin2_code":"33",
    "gn:admin3_code":"8644143.0",
    "gn:admin4_code":"8658475.0",
    "gn:asciiname":"Butangala",
    "gn:country_code":"UG",
    "gn:dem":1130,
    "gn:feature_class":"P",
    "gn:feature_code":"PPL",
    "gn:name":"Butangala",
    "gn:population":0,
    "gn:timezone":"Africa/Kampala",
    "iso:country":"UG",
    "wof:name":"Butangala",
    "wof:placetype":"locality"
},
  "geometry": {"coordinates":[33.16823,0.61282],"type":"Point"}
}