{
  "type": "Feature",
  "properties": {
    "gn:admin1_code":"E",
    "gn:admin2_code":"78",
    "gn:admin3_code":"231410.0",
    "gn:admin4_code":"8657795.0",
    "gn:asciiname":"Bulumwaki",
    "gn:country_code":"UG",
    "gn:dem":1109,
    "gn:feature_class":"P",
    "gn:feature_code":"PPL",
    "gn:name":"Bulumwaki",
    "gn:population":0,
    "gn:timezone":"Africa/Kampala",
    "iso:country":"UG",
    "wof:name":"Bulumwaki",
    "wof:placetype":"locality"
},
  "geometry": {"coordinates":[33.45179,0.7242],"type":"Point"}
}