{
  "type": "Feature",
  "properties": {
    "gn:admin1_code":"C",
    "gn:admin2_code":"89",
    "gn:asciiname":"Bumoozi",
    "gn:country_code":"UG",
    "gn:dem":1223,
    "gn:feature_class":"P",
    "gn:feature_code":"PPL",
    "gn:name":"Bumoozi",
    "gn:population":0,
    "gn:timezone":"Africa/Kampala",
    "iso:country":"UG",
    "wof:name":"Bumoozi",
    "wof:placetype":"locality"
},
  "geometry": {"coordinates":[32.30322,0.26894],"type":"Point"}
}