{
  "type": "Feature",
  "properties": {
    "gn:admin1_code":"E",
    "gn:admin2_code":"D2",
    "gn:asciiname":"Kigodo",
    "gn:country_code":"UG",
    "gn:dem":1077,
    "gn:feature_class":"P",
    "gn:feature_code":"PPL",
    "gn:name":"Kigodo",
    "gn:population":0,
    "gn:timezone":"Africa/Kampala",
    "iso:country":"UG",
    "wof:name":"Kigodo",
    "wof:placetype":"locality"
},
  "geometry": {"coordinates":[33.46042,0.94892],"type":"Point"}
}