{
  "type": "Feature",
  "properties": {
    "gn:admin1_code":"E",
    "gn:admin2_code":"F3",
    "gn:admin3_code":"8644160.0",
    "gn:admin4_code":"8657814.0",
    "gn:asciiname":"Nabitula",
    "gn:country_code":"UG",
    "gn:dem":1064,
    "gn:feature_class":"P",
    "gn:feature_code":"PPL",
    "gn:name":"Nabitula",
    "gn:population":0,
    "gn:timezone":"Africa/Kampala",
    "iso:country":"UG",
    "wof:name":"Nabitula",
    "wof:placetype":"locality"
},
  "geometry": {"coordinates":[33.26667,1.08333],"type":"Point"}
}