{
  "type": "Feature",
  "properties": {
    "gn:admin1_code":"E",
    "gn:admin2_code":"D6",
    "gn:asciiname":"Bukisebe",
    "gn:country_code":"UG",
    "gn:dem":1443,
    "gn:feature_class":"P",
    "gn:feature_code":"PPL",
    "gn:name":"Bukisebe",
    "gn:population":0,
    "gn:timezone":"Africa/Kampala",
    "iso:country":"UG",
    "name:eng_x_preferred":[
        "Bukisebe"
    ],
    "wof:name":"Bukisebe",
    "wof:placetype":"locality"
},
  "geometry": {"coordinates":[34.41299,0.84053],"type":"Point"}
}