{
  "type": "Feature",
  "properties": {
    "gn:admin1_code":"C",
    "gn:admin2_code":"96",
    "gn:admin3_code":"7732385.0",
    "gn:admin4_code":"8658439.0",
    "gn:asciiname":"Gombe",
    "gn:country_code":"UG",
    "gn:dem":1172,
    "gn:feature_class":"P",
    "gn:feature_code":"PPLA4",
    "gn:name":"Gombe",
    "gn:population":0,
    "gn:timezone":"Africa/Kampala",
    "iso:country":"UG",
    "name:cat_x_preferred":[
        "Gombe"
    ],
    "name:ceb_x_preferred":[
        "Gombe"
    ],
    "name:dan_x_preferred":[
        "Gombe"
    ],
    "name:deu_x_preferred":[
        "Gombe"
    ],
    "name:fra_x_preferred":[
        "Gombe"
    ],
    "name:glg_x_preferred":[
        "Gombe"
    ],
    "name:hau_x_preferred":[
        "Gombe"
    ],
    "name:ita_x_preferred":[
        "Gombe"
    ],
    "name:lug_x_preferred":[
        "Gombe"
    ],
    "name:mlg_x_preferred":[
        "Gombe"
    ],
    "name:nld_x_preferred":[
        "Gombe"
    ],
    "name:pol_x_preferred":[
        "Gombe"
    ],
    "name:por_x_preferred":[
        "Gombe"
    ],
    "name:spa_x_preferred":[
        "Gombe"
    ],
    "name:swe_x_preferred":[
        "Gombe"
    ],
    "wof:name":"Gombe",
    "wof:placetype":"locality"
},
  "geometry": {"coordinates":[32.47938,0.48695],"type":"Point"}
}