{
  "type": "Feature",
  "properties": {
    "gn:admin1_code":"E",
    "gn:admin2_code":"66",
    "gn:asciiname":"Nakivamba",
    "gn:country_code":"UG",
    "gn:dem":1091,
    "gn:feature_class":"P",
    "gn:feature_code":"PPL",
    "gn:name":"Nakivamba",
    "gn:population":0,
    "gn:timezone":"Africa/Kampala",
    "iso:country":"UG",
    "wof:name":"Nakivamba",
    "wof:placetype":"locality"
},
  "geometry": {"coordinates":[33.71019,0.67362],"type":"Point"}
}