{
  "type": "Feature",
  "properties": {
    "gn:admin1_code":"C",
    "gn:admin2_code":"I3",
    "gn:admin3_code":"8644144.0",
    "gn:admin4_code":"8658249.0",
    "gn:asciiname":"Kabuwoko",
    "gn:country_code":"UG",
    "gn:dem":1290,
    "gn:feature_class":"P",
    "gn:feature_code":"PPL",
    "gn:name":"Kabuwoko",
    "gn:population":0,
    "gn:timezone":"Africa/Kampala",
    "iso:country":"UG",
    "wof:name":"Kabuwoko",
    "wof:placetype":"locality"
},
  "geometry": {"coordinates":[31.66361,-0.46806],"type":"Point"}
}