{
  "type": "Feature",
  "properties": {
    "gn:admin1_code":"E",
    "gn:admin2_code":"38",
    "gn:asciiname":"Butekanga",
    "gn:country_code":"UG",
    "gn:dem":1100,
    "gn:feature_class":"P",
    "gn:feature_code":"PPL",
    "gn:name":"Butekanga",
    "gn:population":0,
    "gn:timezone":"Africa/Kampala",
    "iso:country":"UG",
    "wof:name":"Butekanga",
    "wof:placetype":"locality"
},
  "geometry": {"coordinates":[33.24395,0.82911],"type":"Point"}
}