{
  "type": "Feature",
  "properties": {
    "gn:admin1_code":"C",
    "gn:admin2_code":"83",
    "gn:admin3_code":"8644158.0",
    "gn:admin4_code":"8657767.0",
    "gn:asciiname":"Kitwe",
    "gn:country_code":"UG",
    "gn:dem":1092,
    "gn:feature_class":"P",
    "gn:feature_code":"PPL",
    "gn:name":"Kitwe",
    "gn:population":0,
    "gn:timezone":"Africa/Kampala",
    "iso:country":"UG",
    "name:afr_x_preferred":[
        "Kitwe"
    ],
    "name:ara_x_preferred":[
        "\u0643\u064a\u062a\u0648\u064a"
    ],
    "name:azb_x_preferred":[
        "\u06a9\u06cc\u062a\u0648"
    ],
    "name:bel_x_preferred":[
        "\u041a\u0456\u0442\u0432\u044d"
    ],
    "name:bul_x_preferred":[
        "\u041a\u0438\u0442\u0443\u0435"
    ],
    "name:cat_x_preferred":[
        "Kitwe"
    ],
    "name:ceb_x_preferred":[
        "Kitwe"
    ],
    "name:ces_x_preferred":[
        "Kitwe"
    ],
    "name:dan_x_preferred":[
        "Kitwe"
    ],
    "name:deu_x_preferred":[
        "Kitwe"
    ],
    "name:ell_x_preferred":[
        "\u039a\u03af\u03c4\u03bf\u03c5\u03b5"
    ],
    "name:epo_x_preferred":[
        "Kitwe"
    ],
    "name:est_x_preferred":[
        "Kitwe"
    ],
    "name:fas_x_preferred":[
        "\u06a9\u06cc\u062a\u0648"
    ],
    "name:fin_x_preferred":[
        "Kitwe"
    ],
    "name:fra_x_preferred":[
        "Kitwe"
    ],
    "name:hrv_x_preferred":[
        "Kitwe"
    ],
    "name:hye_x_preferred":[
        "\u053f\u056b\u057f\u057e\u0565-\u0546\u056f\u0561\u0576\u0561"
    ],
    "name:ind_x_preferred":[
        "Kitwe"
    ],
    "name:ita_x_preferred":[
        "Kitwe"
    ],
    "name:jpn_x_preferred":[
        "\u30ad\u30c8\u30a6\u30a7"
    ],
    "name:kat_x_preferred":[
        "\u10d9\u10d8\u10e2\u10d5\u10d4"
    ],
    "name:kor_x_preferred":[
        "\ud0a4\ud2b8\uc6e8"
    ],
    "name:lit_x_preferred":[
        "Kitv\u0117"
    ],
    "name:mkd_x_preferred":[
        "\u041a\u0438\u0442\u0432\u0435"
    ],
    "name:mrj_x_preferred":[
        "\u041a\u0438\u0442\u0432\u0435"
    ],
    "name:nld_x_preferred":[
        "Kitwe"
    ],
    "name:nor_x_preferred":[
        "Kitwe"
    ],
    "name:pol_x_preferred":[
        "Kitwe"
    ],
    "name:por_x_preferred":[
        "Kitwe"
    ],
    "name:ron_x_preferred":[
        "Kitwe"
    ],
    "name:rus_x_preferred":[
        "\u041a\u0438\u0442\u0432\u0435-\u041d\u043a\u0430\u043d\u0430"
    ],
    "name:sco_x_preferred":[
        "Kitwe"
    ],
    "name:spa_x_preferred":[
        "Kitwe"
    ],
    "name:swe_x_preferred":[
        "Kitwe"
    ],
    "name:tgl_x_preferred":[
        "Kitwe"
    ],
    "name:tur_x_preferred":[
        "Kitwe"
    ],
    "name:ukr_x_preferred":[
        "\u041a\u0456\u0442\u0432\u0435-\u041d\u043a\u0430\u043d\u0430"
    ],
    "name:urd_x_preferred":[
        "\u06a9\u062a\u0648\u06d2"
    ],
    "name:war_x_preferred":[
        "Kitwe"
    ],
    "name:zho_x_preferred":[
        "\u57fa\u7279\u97e6"
    ],
    "wof:name":"Kitwe",
    "wof:placetype":"locality"
},
  "geometry": {"coordinates":[32.88333,0.95],"type":"Point"}
}