{
  "type": "Feature",
  "properties": {
    "gn:admin1_code":"N",
    "gn:admin2_code":"97",
    "gn:admin3_code":"235054.0",
    "gn:admin4_code":"8658538.0",
    "gn:asciiname":"Akpokoa",
    "gn:country_code":"UG",
    "gn:dem":691,
    "gn:feature_class":"P",
    "gn:feature_code":"PPL",
    "gn:name":"Akpokoa",
    "gn:population":0,
    "gn:timezone":"Africa/Kampala",
    "iso:country":"UG",
    "wof:name":"Akpokoa",
    "wof:placetype":"locality"
},
  "geometry": {"coordinates":[31.3677,3.25044],"type":"Point"}
}