{
  "type": "Feature",
  "properties": {
    "gn:admin1_code":"C",
    "gn:admin2_code":"89",
    "gn:admin3_code":"7910214.0",
    "gn:admin4_code":"7732543.0",
    "gn:asciiname":"Kolokolo",
    "gn:country_code":"UG",
    "gn:dem":1218,
    "gn:feature_class":"P",
    "gn:feature_code":"PPL",
    "gn:name":"Kolokolo",
    "gn:population":0,
    "gn:timezone":"Africa/Kampala",
    "iso:country":"UG",
    "name:und_x_variant":[
        "Kololo"
    ],
    "wof:name":"Kolokolo",
    "wof:placetype":"locality"
},
  "geometry": {"coordinates":[32.3737,0.35582],"type":"Point"}
}