{
  "type": "Feature",
  "properties": {
    "gn:admin1_code":"E",
    "gn:admin2_code":"G9",
    "gn:asciiname":"Atira",
    "gn:country_code":"UG",
    "gn:dem":1050,
    "gn:feature_class":"P",
    "gn:feature_code":"PPLL",
    "gn:name":"Atira",
    "gn:population":0,
    "gn:timezone":"Africa/Kampala",
    "iso:country":"UG",
    "wof:name":"Atira",
    "wof:placetype":"locality"
},
  "geometry": {"coordinates":[33.77459,1.64788],"type":"Point"}
}