{
  "type": "Feature",
  "properties": {
    "gn:admin1_code":"W",
    "gn:admin2_code":"41",
    "gn:admin3_code":"8644139.0",
    "gn:admin4_code":"8658596.0",
    "gn:asciiname":"Banda",
    "gn:country_code":"UG",
    "gn:dem":1282,
    "gn:feature_class":"P",
    "gn:feature_code":"PPL",
    "gn:name":"Banda",
    "gn:population":0,
    "gn:timezone":"Africa/Kampala",
    "iso:country":"UG",
    "wof:name":"Banda",
    "wof:placetype":"locality"
},
  "geometry": {"coordinates":[31.05,0.68333],"type":"Point"}
}