{
  "type": "Feature",
  "properties": {
    "gn:admin1_code":"C",
    "gn:admin2_code":"74",
    "gn:admin3_code":"229304.0",
    "gn:admin4_code":"8657816.0",
    "gn:asciiname":"Nsangala",
    "gn:country_code":"UG",
    "gn:dem":1255,
    "gn:feature_class":"P",
    "gn:feature_code":"PPL",
    "gn:name":"Nsangala",
    "gn:population":0,
    "gn:timezone":"Africa/Kampala",
    "iso:country":"UG",
    "wof:name":"Nsangala",
    "wof:placetype":"locality"
},
  "geometry": {"coordinates":[31.48639,-0.295],"type":"Point"}
}