{
  "type": "Feature",
  "properties": {
    "gn:admin1_code":"E",
    "gn:admin2_code":"67",
    "gn:admin3_code":"8644151.0",
    "gn:admin4_code":"8657977.0",
    "gn:asciiname":"Buhatuba",
    "gn:country_code":"UG",
    "gn:dem":1149,
    "gn:feature_class":"P",
    "gn:feature_code":"PPLL",
    "gn:name":"Buhatuba",
    "gn:population":0,
    "gn:timezone":"Africa/Kampala",
    "iso:country":"UG",
    "wof:name":"Buhatuba",
    "wof:placetype":"locality"
},
  "geometry": {"coordinates":[33.98599,0.41853],"type":"Point"}
}