{
  "type": "Feature",
  "properties": {
    "gn:admin1_code":"E",
    "gn:admin2_code":"C6",
    "gn:asciiname":"Namatoke",
    "gn:country_code":"UG",
    "gn:dem":1089,
    "gn:feature_class":"P",
    "gn:feature_code":"PPL",
    "gn:name":"Namatoke",
    "gn:population":0,
    "gn:timezone":"Africa/Kampala",
    "iso:country":"UG",
    "name:eng_x_preferred":[
        "Namatoke"
    ],
    "wof:name":"Namatoke",
    "wof:placetype":"locality"
},
  "geometry": {"coordinates":[34.05086,0.92668],"type":"Point"}
}