{
  "type": "Feature",
  "properties": {
    "gn:admin1_code":"C",
    "gn:admin2_code":"E7",
    "gn:admin3_code":"7732075.0",
    "gn:admin4_code":"8658159.0",
    "gn:asciiname":"Tega",
    "gn:country_code":"UG",
    "gn:dem":1262,
    "gn:feature_class":"P",
    "gn:feature_code":"PPL",
    "gn:name":"Tega",
    "gn:population":0,
    "gn:timezone":"Africa/Kampala",
    "iso:country":"UG",
    "name:eng_x_preferred":[
        "Tega"
    ],
    "wof:name":"Tega",
    "wof:placetype":"locality"
},
  "geometry": {"coordinates":[33.00658,0.34848],"type":"Point"}
}