{
  "type": "Feature",
  "properties": {
    "gn:admin1_code":"E",
    "gn:admin2_code":"76",
    "gn:asciiname":"Nyalakot",
    "gn:country_code":"UG",
    "gn:dem":1269,
    "gn:feature_class":"P",
    "gn:feature_code":"PPL",
    "gn:name":"Nyalakot",
    "gn:population":0,
    "gn:timezone":"Africa/Kampala",
    "iso:country":"UG",
    "name:eng_x_preferred":[
        "Nyalakot"
    ],
    "wof:name":"Nyalakot",
    "wof:placetype":"locality"
},
  "geometry": {"coordinates":[34.24212,0.70824],"type":"Point"}
}