{
  "type": "Feature",
  "properties": {
    "gn:admin1_code":"W",
    "gn:admin2_code":"28",
    "gn:asciiname":"Bundikayanja",
    "gn:country_code":"UG",
    "gn:dem":875,
    "gn:feature_class":"P",
    "gn:feature_code":"PPL",
    "gn:name":"Bundikayanja",
    "gn:population":0,
    "gn:timezone":"Africa/Kampala",
    "iso:country":"UG",
    "name:eng_x_preferred":[
        "Bundikayanja"
    ],
    "wof:name":"Bundikayanja",
    "wof:placetype":"locality"
},
  "geometry": {"coordinates":[30.05368,0.73096],"type":"Point"}
}