{
  "type": "Feature",
  "properties": {
    "gn:admin1_code":"C",
    "gn:admin2_code":"73",
    "gn:admin3_code":"234123.0",
    "gn:admin4_code":"8658322.0",
    "gn:asciiname":"Erima",
    "gn:country_code":"UG",
    "gn:dem":1041,
    "gn:feature_class":"P",
    "gn:feature_code":"PPL",
    "gn:name":"Erima",
    "gn:population":0,
    "gn:timezone":"Africa/Kampala",
    "iso:country":"UG",
    "wof:name":"Erima",
    "wof:placetype":"locality"
},
  "geometry": {"coordinates":[32.73333,1.35],"type":"Point"}
}