{
  "type": "Feature",
  "properties": {
    "gn:admin1_code":"C",
    "gn:admin2_code":"I3",
    "gn:admin3_code":"8644144.0",
    "gn:admin4_code":"8657681.0",
    "gn:asciiname":"Katulu",
    "gn:country_code":"UG",
    "gn:dem":1170,
    "gn:feature_class":"P",
    "gn:feature_code":"PPL",
    "gn:name":"Katulu",
    "gn:population":0,
    "gn:timezone":"Africa/Kampala",
    "iso:country":"UG",
    "wof:name":"Katulu",
    "wof:placetype":"locality"
},
  "geometry": {"coordinates":[31.61667000000001,-0.68333],"type":"Point"}
}