{
  "type": "Feature",
  "properties": {
    "gn:admin1_code":"N",
    "gn:admin2_code":"77",
    "gn:admin3_code":"226029.0",
    "gn:admin4_code":"8657975.0",
    "gn:asciiname":"Vurra",
    "gn:country_code":"UG",
    "gn:dem":1333,
    "gn:feature_class":"P",
    "gn:feature_code":"PPL",
    "gn:name":"Vurra",
    "gn:population":0,
    "gn:timezone":"Africa/Kampala",
    "iso:country":"UG",
    "name:lug_x_preferred":[
        "Vurra"
    ],
    "name:und_x_variant":[
        "Vura"
    ],
    "wof:name":"Vurra",
    "wof:placetype":"locality"
},
  "geometry": {"coordinates":[30.88248,2.90906],"type":"Point"}
}