{
  "type": "Feature",
  "properties": {
    "gn:admin1_code":"E",
    "gn:admin2_code":"76",
    "gn:admin3_code":"8644131.0",
    "gn:admin4_code":"8657740.0",
    "gn:asciiname":"Osia",
    "gn:country_code":"UG",
    "gn:dem":1141,
    "gn:feature_class":"P",
    "gn:feature_code":"PPL",
    "gn:name":"Osia",
    "gn:population":0,
    "gn:timezone":"Africa/Kampala",
    "iso:country":"UG",
    "name:eng_x_preferred":[
        "Osia"
    ],
    "wof:name":"Osia",
    "wof:placetype":"locality"
},
  "geometry": {"coordinates":[34.10019,0.62276],"type":"Point"}
}