{
  "type": "Feature",
  "properties": {
    "gn:admin1_code":"E",
    "gn:admin2_code":"78",
    "gn:admin3_code":"234502.0",
    "gn:admin4_code":"8658167.0",
    "gn:asciiname":"Namalemba",
    "gn:country_code":"UG",
    "gn:dem":1114,
    "gn:feature_class":"P",
    "gn:feature_code":"PPL",
    "gn:name":"Namalemba",
    "gn:population":0,
    "gn:timezone":"Africa/Kampala",
    "iso:country":"UG",
    "wof:name":"Namalemba",
    "wof:placetype":"locality"
},
  "geometry": {"coordinates":[33.60781,0.75676],"type":"Point"}
}