{
  "type": "Feature",
  "properties": {
    "gn:admin1_code":"W",
    "gn:admin2_code":"52",
    "gn:admin3_code":"232055.0",
    "gn:admin4_code":"8657567.0",
    "gn:asciiname":"Nyakakoni",
    "gn:country_code":"UG",
    "gn:dem":1388,
    "gn:feature_class":"P",
    "gn:feature_code":"PPL",
    "gn:name":"Nyakakoni",
    "gn:population":0,
    "gn:timezone":"Africa/Kampala",
    "iso:country":"UG",
    "name:und_x_variant":[
        "Nyakinoni",
        "Nyakakoni"
    ],
    "wof:name":"Nyakakoni",
    "wof:placetype":"locality"
},
  "geometry": {"coordinates":[30.71667,-0.45],"type":"Point"}
}