{
  "type": "Feature",
  "properties": {
    "gn:admin1_code":"E",
    "gn:admin2_code":"D6",
    "gn:asciiname":"Buwasebya",
    "gn:country_code":"UG",
    "gn:dem":1261,
    "gn:feature_class":"P",
    "gn:feature_code":"PPL",
    "gn:name":"Buwasebya",
    "gn:population":0,
    "gn:timezone":"Africa/Kampala",
    "iso:country":"UG",
    "name:eng_x_preferred":[
        "Buwasebya"
    ],
    "wof:name":"Buwasebya",
    "wof:placetype":"locality"
},
  "geometry": {"coordinates":[34.23544,0.91225],"type":"Point"}
}