{
  "type": "Feature",
  "properties": {
    "gn:admin1_code":"E",
    "gn:admin2_code":"H5",
    "gn:asciiname":"Opiio",
    "gn:country_code":"UG",
    "gn:dem":1062,
    "gn:feature_class":"P",
    "gn:feature_code":"PPLL",
    "gn:name":"Opiio",
    "gn:population":0,
    "gn:timezone":"Africa/Kampala",
    "iso:country":"UG",
    "wof:name":"Opiio",
    "wof:placetype":"locality"
},
  "geometry": {"coordinates":[33.51948,1.58931],"type":"Point"}
}