{
  "type": "Feature",
  "properties": {
    "gn:admin1_code":"C",
    "gn:admin2_code":"56",
    "gn:admin3_code":"233891.0",
    "gn:admin4_code":"7732534.0",
    "gn:asciiname":"Mugamba",
    "gn:country_code":"UG",
    "gn:dem":1438,
    "gn:feature_class":"P",
    "gn:feature_code":"PPL",
    "gn:name":"Mugamba",
    "gn:population":0,
    "gn:timezone":"Africa/Kampala",
    "iso:country":"UG",
    "name:run_x_preferred":[
        "Mugamba"
    ],
    "wof:name":"Mugamba",
    "wof:placetype":"locality"
},
  "geometry": {"coordinates":[31.56667,0.83333],"type":"Point"}
}