{
  "type": "Feature",
  "properties": {
    "gn:admin1_code":"E",
    "gn:admin2_code":"67",
    "gn:admin3_code":"8644151.0",
    "gn:admin4_code":"8657978.0",
    "gn:asciiname":"South East",
    "gn:country_code":"UG",
    "gn:dem":1218,
    "gn:feature_class":"P",
    "gn:feature_code":"PPL",
    "gn:name":"South East",
    "gn:population":0,
    "gn:timezone":"Africa/Kampala",
    "iso:country":"UG",
    "name:ara_x_preferred":[
        "\u0627\u0644\u062c\u0646\u0648\u0628 \u0627\u0644\u0634\u0631\u0642\u064a"
    ],
    "name:ben_x_preferred":[
        "\u09a6\u0995\u09cd\u09b7\u09bf\u09a3 -\u09aa\u09c2\u09b0\u09cd\u09ac"
    ],
    "name:ell_x_preferred":[
        "\u03a3\u03ac\u03bf\u03c5\u03b8 \u0399\u03c3\u03c4"
    ],
    "name:fas_x_preferred":[
        "\u062c\u0646\u0648\u0628 \u0634\u0631\u0642"
    ],
    "name:heb_x_preferred":[
        "\u05d3\u05e8\u05d5\u05dd \u05de\u05d6\u05e8\u05d7"
    ],
    "name:hin_x_preferred":[
        "\u0926\u0915\u094d\u0937\u093f\u0923 \u092a\u0942\u0930\u094d\u0935"
    ],
    "name:hun_x_preferred":[
        "D\u00e9lkelet"
    ],
    "name:ita_x_preferred":[
        "Sud-Est"
    ],
    "name:nld_x_preferred":[
        "South East"
    ],
    "name:pol_x_preferred":[
        "Po\u0142udniowy-wsch\u00f3d"
    ],
    "name:por_x_preferred":[
        "Sudeste"
    ],
    "name:rus_x_preferred":[
        "\u042e\u0433\u043e-\u0412\u043e\u0441\u0442\u043e\u0447\u043d\u044b\u0439 \u0440\u0435\u0433\u0438\u043e\u043d"
    ],
    "name:swe_x_preferred":[
        "Syd\u00f6stra Singapore"
    ],
    "name:tur_x_preferred":[
        "G\u00fcneydo\u011fu"
    ],
    "name:ukr_x_preferred":[
        "\u0421\u0430\u0443\u0441-\u0406\u0441\u0442"
    ],
    "name:vie_x_preferred":[
        "V\u00f9ng \u0110\u00f4ng Nam"
    ],
    "wof:name":"South East",
    "wof:placetype":"locality"
},
  "geometry": {"coordinates":[34.0947,0.46353],"type":"Point"}
}