{
  "type": "Feature",
  "properties": {
    "gn:admin1_code":"E",
    "gn:admin2_code":"69",
    "gn:admin3_code":"8644130.0",
    "gn:admin4_code":"8657832.0",
    "gn:asciiname":"Adachal",
    "gn:cc2":"UG",
    "gn:country_code":"UG",
    "gn:dem":1087,
    "gn:feature_class":"P",
    "gn:feature_code":"PPL",
    "gn:name":"Adachal",
    "gn:population":0,
    "gn:timezone":"Africa/Kampala",
    "iso:country":"UG",
    "name:und_x_variant":[
        "Kadachal",
        "Adachal"
    ],
    "wof:name":"Adachal",
    "wof:placetype":"locality"
},
  "geometry": {"coordinates":[34.05222,2.04861],"type":"Point"}
}