{
  "type": "Feature",
  "properties": {
    "gn:admin1_code":"E",
    "gn:admin2_code":"33",
    "gn:asciiname":"Ibungu",
    "gn:country_code":"UG",
    "gn:dem":1187,
    "gn:feature_class":"P",
    "gn:feature_code":"PPL",
    "gn:name":"Ibungu",
    "gn:population":0,
    "gn:timezone":"Africa/Kampala",
    "iso:country":"UG",
    "wof:name":"Ibungu",
    "wof:placetype":"locality"
},
  "geometry": {"coordinates":[33.15313,0.52424],"type":"Point"}
}