{
  "type": "Feature",
  "properties": {
    "gn:admin1_code":"E",
    "gn:admin2_code":"B8",
    "gn:admin3_code":"8644171.0",
    "gn:admin4_code":"8658643.0",
    "gn:asciiname":"Amero",
    "gn:country_code":"UG",
    "gn:dem":1106,
    "gn:feature_class":"P",
    "gn:feature_code":"PPL",
    "gn:name":"Amero",
    "gn:population":0,
    "gn:timezone":"Africa/Kampala",
    "iso:country":"UG",
    "wof:name":"Amero",
    "wof:placetype":"locality"
},
  "geometry": {"coordinates":[33.76667,2.11667],"type":"Point"}
}