{
  "type": "Feature",
  "properties": {
    "gn:admin1_code":"C",
    "gn:admin2_code":"89",
    "gn:asciiname":"Masiko-Mbule",
    "gn:country_code":"UG",
    "gn:dem":1203,
    "gn:feature_class":"P",
    "gn:feature_code":"PPL",
    "gn:name":"Masiko-Mbule",
    "gn:population":0,
    "gn:timezone":"Africa/Kampala",
    "iso:country":"UG",
    "wof:name":"Masiko-Mbule",
    "wof:placetype":"locality"
},
  "geometry": {"coordinates":[32.01032,0.05524],"type":"Point"}
}