{
  "type": "Feature",
  "properties": {
    "gn:admin1_code":"N",
    "gn:admin2_code":"26",
    "gn:admin3_code":"230563.0",
    "gn:admin4_code":"8657727.0",
    "gn:asciiname":"Acenluoro",
    "gn:country_code":"UG",
    "gn:dem":1044,
    "gn:feature_class":"P",
    "gn:feature_code":"PPLL",
    "gn:name":"Acenluoro",
    "gn:population":0,
    "gn:timezone":"Africa/Kampala",
    "iso:country":"UG",
    "name:eng_x_preferred":[
        "Acenluoro"
    ],
    "wof:name":"Acenluoro",
    "wof:placetype":"locality"
},
  "geometry": {"coordinates":[32.70746,1.82911],"type":"Point"}
}