{
  "type": "Feature",
  "properties": {
    "gn:admin1_code":"E",
    "gn:admin2_code":"38",
    "gn:asciiname":"Buyoga",
    "gn:country_code":"UG",
    "gn:dem":1087,
    "gn:feature_class":"P",
    "gn:feature_code":"PPL",
    "gn:name":"Buyoga",
    "gn:population":0,
    "gn:timezone":"Africa/Kampala",
    "iso:country":"UG",
    "name:ita_x_preferred":[
        "Buyoga"
    ],
    "wof:name":"Buyoga",
    "wof:placetype":"locality"
},
  "geometry": {"coordinates":[33.05005999999999,0.88781],"type":"Point"}
}