{
  "type": "Feature",
  "properties": {
    "gn:admin1_code":"C",
    "gn:admin2_code":"89",
    "gn:asciiname":"Malube",
    "gn:country_code":"UG",
    "gn:dem":1208,
    "gn:feature_class":"P",
    "gn:feature_code":"PPL",
    "gn:name":"Malube",
    "gn:population":0,
    "gn:timezone":"Africa/Kampala",
    "iso:country":"UG",
    "wof:name":"Malube",
    "wof:placetype":"locality"
},
  "geometry": {"coordinates":[32.39291,0.3214],"type":"Point"}
}