{
  "type": "Feature",
  "properties": {
    "gn:admin1_code":"W",
    "gn:admin2_code":"H6",
    "gn:admin3_code":"7732263.0",
    "gn:admin4_code":"8657830.0",
    "gn:asciiname":"Bwangamba",
    "gn:country_code":"UG",
    "gn:dem":1484,
    "gn:feature_class":"P",
    "gn:feature_code":"PPL",
    "gn:name":"Bwangamba",
    "gn:population":0,
    "gn:timezone":"Africa/Kampala",
    "iso:country":"UG",
    "name:und_x_variant":[
        "Bwengamba",
        "Bwangamba"
    ],
    "wof:name":"Bwangamba",
    "wof:placetype":"locality"
},
  "geometry": {"coordinates":[30.41667,-0.51667],"type":"Point"}
}