{
  "type": "Feature",
  "properties": {
    "gn:admin1_code":"E",
    "gn:admin2_code":"C1",
    "gn:admin3_code":"8644159.0",
    "gn:admin4_code":"8657941.0",
    "gn:asciiname":"Iki Iki",
    "gn:country_code":"UG",
    "gn:dem":1112,
    "gn:feature_class":"P",
    "gn:feature_code":"PPL",
    "gn:name":"Iki Iki",
    "gn:population":0,
    "gn:timezone":"Africa/Kampala",
    "iso:country":"UG",
    "name:und_x_variant":[
        "Ikilki",
        "Iki Iki"
    ],
    "wof:name":"Iki Iki",
    "wof:placetype":"locality"
},
  "geometry": {"coordinates":[34.0125,1.08417],"type":"Point"}
}