{
  "type": "Feature",
  "properties": {
    "gn:admin1_code":"E",
    "gn:admin2_code":"G4",
    "gn:admin3_code":"229762.0",
    "gn:admin4_code":"8658139.0",
    "gn:asciiname":"Kirimwa",
    "gn:country_code":"UG",
    "gn:dem":1107,
    "gn:feature_class":"P",
    "gn:feature_code":"PPL",
    "gn:name":"Kirimwa",
    "gn:population":0,
    "gn:timezone":"Africa/Kampala",
    "iso:country":"UG",
    "wof:name":"Kirimwa",
    "wof:placetype":"locality"
},
  "geometry": {"coordinates":[33.30463,0.88264],"type":"Point"}
}