{
  "type": "Feature",
  "properties": {
    "gn:admin1_code":"C",
    "gn:admin2_code":"D8",
    "gn:asciiname":"Lulumbu",
    "gn:country_code":"UG",
    "gn:dem":1250,
    "gn:feature_class":"P",
    "gn:feature_code":"PPL",
    "gn:name":"Lulumbu",
    "gn:population":0,
    "gn:timezone":"Africa/Kampala",
    "iso:country":"UG",
    "wof:name":"Lulumbu",
    "wof:placetype":"locality"
},
  "geometry": {"coordinates":[32.21062,0.33307],"type":"Point"}
}