{
  "type": "Feature",
  "properties": {
    "gn:admin1_code":"N",
    "gn:admin2_code":"58",
    "gn:admin3_code":"8080237.0",
    "gn:admin4_code":"8261561.0",
    "gn:asciiname":"Pulum",
    "gn:country_code":"UG",
    "gn:dem":1020,
    "gn:feature_class":"P",
    "gn:feature_code":"PPL",
    "gn:name":"Pulum",
    "gn:population":0,
    "gn:timezone":"Africa/Kampala",
    "iso:country":"UG",
    "wof:name":"Pulum",
    "wof:placetype":"locality"
},
  "geometry": {"coordinates":[31.18536,2.30959],"type":"Point"}
}