{
  "type": "Feature",
  "properties": {
    "gn:admin1_code":"N",
    "gn:admin2_code":"77",
    "gn:admin3_code":"226158.0",
    "gn:admin4_code":"8658459.0",
    "gn:asciiname":"Tangala",
    "gn:country_code":"UG",
    "gn:dem":841,
    "gn:feature_class":"P",
    "gn:feature_code":"PPL",
    "gn:name":"Tangala",
    "gn:population":0,
    "gn:timezone":"Africa/Kampala",
    "iso:country":"UG",
    "wof:name":"Tangala",
    "wof:placetype":"locality"
},
  "geometry": {"coordinates":[31.1359,3.04687],"type":"Point"}
}