{
  "type": "Feature",
  "properties": {
    "gn:admin1_code":"N",
    "gn:admin2_code":"91",
    "gn:admin3_code":"8644141.0",
    "gn:admin4_code":"8657805.0",
    "gn:asciiname":"Nakapiripirit",
    "gn:country_code":"UG",
    "gn:dem":1352,
    "gn:feature_class":"P",
    "gn:feature_code":"PPLA2",
    "gn:name":"Nakapiripirit",
    "gn:population":0,
    "gn:timezone":"Africa/Kampala",
    "iso:country":"UG",
    "wof:name":"Nakapiripirit",
    "wof:placetype":"locality"
},
  "geometry": {"coordinates":[34.78333,1.91667],"type":"Point"}
}