{
  "type": "Feature",
  "properties": {
    "gn:admin1_code":"N",
    "gn:admin2_code":"91",
    "gn:admin3_code":"8644141.0",
    "gn:admin4_code":"8657805.0",
    "gn:asciiname":"Nakapiripirit",
    "gn:country_code":"UG",
    "gn:dem":1352,
    "gn:feature_class":"P",
    "gn:feature_code":"PPLA2",
    "gn:name":"Nakapiripirit",
    "gn:population":0,
    "gn:timezone":"Africa/Kampala",
    "iso:country":"UG",
    "name:ceb_x_preferred":[
        "Nakapiripirit"
    ],
    "name:hun_x_preferred":[
        "Nakapiripirit"
    ],
    "name:ita_x_preferred":[
        "Nakapiripirit"
    ],
    "name:nld_x_preferred":[
        "Nakapiripirit"
    ],
    "name:ron_x_preferred":[
        "Nakapiripirit"
    ],
    "name:swa_x_preferred":[
        "Nakapiripirit"
    ],
    "name:urd_x_preferred":[
        "\u0646\u0627\u06a9\u0627\u067e\u06cc\u0631\u06cc\u067e\u06cc\u0631\u06cc\u062a"
    ],
    "wof:name":"Nakapiripirit",
    "wof:placetype":"locality"
},
  "geometry": {"coordinates":[34.78333,1.91667],"type":"Point"}
}