{
  "type": "Feature",
  "properties": {
    "gn:admin1_code":"E",
    "gn:admin2_code":"D6",
    "gn:asciiname":"Buwahinga",
    "gn:country_code":"UG",
    "gn:dem":1173,
    "gn:feature_class":"P",
    "gn:feature_code":"PPL",
    "gn:name":"Buwahinga",
    "gn:population":0,
    "gn:timezone":"Africa/Kampala",
    "iso:country":"UG",
    "name:eng_x_preferred":[
        "Buwahinga"
    ],
    "wof:name":"Buwahinga",
    "wof:placetype":"locality"
},
  "geometry": {"coordinates":[34.19827,0.83222],"type":"Point"}
}