{
  "type": "Feature",
  "properties": {
    "gn:admin1_code":"C",
    "gn:admin2_code":"G5",
    "gn:admin3_code":"7910221.0",
    "gn:admin4_code":"8658034.0",
    "gn:asciiname":"Tekala",
    "gn:country_code":"UG",
    "gn:dem":1181,
    "gn:feature_class":"P",
    "gn:feature_code":"PPL",
    "gn:name":"Tekala",
    "gn:population":0,
    "gn:timezone":"Africa/Kampala",
    "iso:country":"UG",
    "name:und_x_variant":[
        "Tekela",
        "Tekala"
    ],
    "wof:name":"Tekala",
    "wof:placetype":"locality"
},
  "geometry": {"coordinates":[31.81667,-0.43333],"type":"Point"}
}