{
  "type": "Feature",
  "properties": {
    "gn:admin1_code":"N",
    "gn:admin2_code":"B7",
    "gn:admin3_code":"231170.0",
    "gn:admin4_code":"8658377.0",
    "gn:asciiname":"Abalodyang",
    "gn:country_code":"UG",
    "gn:dem":1059,
    "gn:feature_class":"P",
    "gn:feature_code":"PPLL",
    "gn:name":"Abalodyang",
    "gn:population":0,
    "gn:timezone":"Africa/Kampala",
    "iso:country":"UG",
    "name:eng_x_preferred":[
        "Abalodyang"
    ],
    "wof:name":"Abalodyang",
    "wof:placetype":"locality"
},
  "geometry": {"coordinates":[32.87493,1.72541],"type":"Point"}
}