{
  "type": "Feature",
  "properties": {
    "gn:admin1_code":"E",
    "gn:admin2_code":"G7",
    "gn:admin3_code":"8644167.0",
    "gn:admin4_code":"8658689.0",
    "gn:asciiname":"Budiba",
    "gn:country_code":"UG",
    "gn:dem":1129,
    "gn:feature_class":"P",
    "gn:feature_code":"PPL",
    "gn:name":"Budiba",
    "gn:population":0,
    "gn:timezone":"Africa/Kampala",
    "iso:country":"UG",
    "name:eng_x_preferred":[
        "Budiba"
    ],
    "wof:name":"Budiba",
    "wof:placetype":"locality"
},
  "geometry": {"coordinates":[33.89935,0.41938],"type":"Point"}
}