{
  "type": "Feature",
  "properties": {
    "gn:admin1_code":"C",
    "gn:admin2_code":"89",
    "gn:asciiname":"Lungala",
    "gn:country_code":"UG",
    "gn:dem":1186,
    "gn:feature_class":"P",
    "gn:feature_code":"PPL",
    "gn:name":"Lungala",
    "gn:population":0,
    "gn:timezone":"Africa/Kampala",
    "iso:country":"UG",
    "wof:name":"Lungala",
    "wof:placetype":"locality"
},
  "geometry": {"coordinates":[32.34845,0.23708],"type":"Point"}
}