{
  "type": "Feature",
  "properties": {
    "gn:admin1_code":"E",
    "gn:admin2_code":"G7",
    "gn:admin3_code":"8644167.0",
    "gn:admin4_code":"8657679.0",
    "gn:asciiname":"Kitumba",
    "gn:country_code":"UG",
    "gn:dem":1211,
    "gn:feature_class":"P",
    "gn:feature_code":"PPL",
    "gn:name":"Kitumba",
    "gn:population":0,
    "gn:timezone":"Africa/Kampala",
    "iso:country":"UG",
    "name:eng_x_preferred":[
        "Kitumba"
    ],
    "wof:name":"Kitumba",
    "wof:placetype":"locality"
},
  "geometry": {"coordinates":[33.73951,0.42179],"type":"Point"}
}