{
  "type": "Feature",
  "properties": {
    "gn:admin1_code":"C",
    "gn:admin2_code":"D5",
    "gn:admin3_code":"232958.0",
    "gn:admin4_code":"8658337.0",
    "gn:asciiname":"Kalagala",
    "gn:country_code":"UG",
    "gn:dem":1278,
    "gn:feature_class":"P",
    "gn:feature_code":"PPL",
    "gn:name":"Kalagala",
    "gn:population":0,
    "gn:timezone":"Africa/Kampala",
    "iso:country":"UG",
    "name:lug_x_preferred":[
        "Kalagala"
    ],
    "wof:name":"Kalagala",
    "wof:placetype":"locality"
},
  "geometry": {"coordinates":[31.16667,-0.05],"type":"Point"}
}