{
  "type": "Feature",
  "properties": {
    "gn:admin1_code":"N",
    "gn:admin2_code":"D4",
    "gn:admin3_code":"230723.0",
    "gn:admin4_code":"8658037.0",
    "gn:asciiname":"Ibanga",
    "gn:country_code":"UG",
    "gn:dem":1037,
    "gn:feature_class":"P",
    "gn:feature_code":"PPL",
    "gn:name":"Ibanga",
    "gn:population":0,
    "gn:timezone":"Africa/Kampala",
    "iso:country":"UG",
    "wof:name":"Ibanga",
    "wof:placetype":"locality"
},
  "geometry": {"coordinates":[31.06201,3.43556],"type":"Point"}
}