{
  "type": "Feature",
  "properties": {
    "gn:admin1_code":"E",
    "gn:admin2_code":"D6",
    "gn:asciiname":"Nabitere",
    "gn:country_code":"UG",
    "gn:dem":1968,
    "gn:feature_class":"P",
    "gn:feature_code":"PPL",
    "gn:name":"Nabitere",
    "gn:population":0,
    "gn:timezone":"Africa/Kampala",
    "iso:country":"UG",
    "name:eng_x_preferred":[
        "Nabitere"
    ],
    "wof:name":"Nabitere",
    "wof:placetype":"locality"
},
  "geometry": {"coordinates":[34.37706,0.96792],"type":"Point"}
}