{
  "type": "Feature",
  "properties": {
    "gn:admin1_code":"C",
    "gn:admin2_code":"E7",
    "gn:admin3_code":"7732075.0",
    "gn:admin4_code":"8657733.0",
    "gn:asciiname":"Matale",
    "gn:country_code":"UG",
    "gn:dem":1247,
    "gn:feature_class":"P",
    "gn:feature_code":"PPL",
    "gn:name":"Matale",
    "gn:population":0,
    "gn:timezone":"Africa/Kampala",
    "iso:country":"UG",
    "wof:name":"Matale",
    "wof:placetype":"locality"
},
  "geometry": {"coordinates":[32.96952,0.28139],"type":"Point"}
}