{
  "type": "Feature",
  "properties": {
    "gn:admin1_code":"E",
    "gn:admin2_code":"86",
    "gn:asciiname":"Mbaale",
    "gn:country_code":"UG",
    "gn:dem":1157,
    "gn:feature_class":"P",
    "gn:feature_code":"PPL",
    "gn:name":"Mbaale",
    "gn:population":0,
    "gn:timezone":"Africa/Kampala",
    "iso:country":"UG",
    "wof:name":"Mbaale",
    "wof:placetype":"locality"
},
  "geometry": {"coordinates":[33.46783,0.51035],"type":"Point"}
}