{
  "type": "Feature",
  "properties": {
    "gn:admin1_code":"E",
    "gn:admin2_code":"D6",
    "gn:asciiname":"Buteteya",
    "gn:country_code":"UG",
    "gn:dem":1642,
    "gn:feature_class":"P",
    "gn:feature_code":"PPL",
    "gn:name":"Buteteya",
    "gn:population":0,
    "gn:timezone":"Africa/Kampala",
    "iso:country":"UG",
    "name:eng_x_preferred":[
        "Buteteya"
    ],
    "wof:name":"Buteteya",
    "wof:placetype":"locality"
},
  "geometry": {"coordinates":[34.37653,0.8802],"type":"Point"}
}