{
  "type": "Feature",
  "properties": {
    "gn:admin1_code":"E",
    "gn:admin2_code":"C2",
    "gn:admin3_code":"7869957.0",
    "gn:admin4_code":"8658233.0",
    "gn:asciiname":"Bunakhayoti",
    "gn:country_code":"UG",
    "gn:dem":1528,
    "gn:feature_class":"P",
    "gn:feature_code":"PPL",
    "gn:name":"Bunakhayoti",
    "gn:population":0,
    "gn:timezone":"Africa/Kampala",
    "iso:country":"UG",
    "wof:name":"Bunakhayoti",
    "wof:placetype":"locality"
},
  "geometry": {"coordinates":[34.3593,1.03896],"type":"Point"}
}