{
  "type": "Feature",
  "properties": {
    "gn:admin1_code":"W",
    "gn:admin2_code":"43",
    "gn:admin3_code":"7874701.0",
    "gn:admin4_code":"8658603.0",
    "gn:asciiname":"Bwanjebe",
    "gn:country_code":"UG",
    "gn:dem":2137,
    "gn:feature_class":"P",
    "gn:feature_code":"PPL",
    "gn:name":"Bwanjebe",
    "gn:population":0,
    "gn:timezone":"Africa/Kampala",
    "iso:country":"UG",
    "wof:name":"Bwanjebe",
    "wof:placetype":"locality"
},
  "geometry": {"coordinates":[29.61667000000001,-1.33333],"type":"Point"}
}