{
  "type": "Feature",
  "properties": {
    "gn:admin1_code":"E",
    "gn:admin2_code":"78",
    "gn:admin3_code":"234502.0",
    "gn:admin4_code":"8643426.0",
    "gn:asciiname":"Nondwe",
    "gn:country_code":"UG",
    "gn:dem":1218,
    "gn:feature_class":"P",
    "gn:feature_code":"PPL",
    "gn:name":"Nondwe",
    "gn:population":0,
    "gn:timezone":"Africa/Kampala",
    "iso:country":"UG",
    "name:eng_x_preferred":[
        "Nondwe"
    ],
    "wof:name":"Nondwe",
    "wof:placetype":"locality"
},
  "geometry": {"coordinates":[33.59611,0.45602],"type":"Point"}
}