{
  "type": "Feature",
  "properties": {
    "gn:admin1_code":"C",
    "gn:admin2_code":"D8",
    "gn:asciiname":"Kito",
    "gn:country_code":"UG",
    "gn:dem":1264,
    "gn:feature_class":"P",
    "gn:feature_code":"PPL",
    "gn:name":"Kito",
    "gn:population":0,
    "gn:timezone":"Africa/Kampala",
    "iso:country":"UG",
    "name:ceb_x_preferred":[
        "Kito"
    ],
    "name:deu_x_preferred":[
        "Kito"
    ],
    "name:eus_x_preferred":[
        "Kito"
    ],
    "name:ita_x_preferred":[
        "Kito"
    ],
    "name:swa_x_preferred":[
        "Kito"
    ],
    "name:swe_x_preferred":[
        "Kito"
    ],
    "wof:name":"Kito",
    "wof:placetype":"locality"
},
  "geometry": {"coordinates":[32.1241,0.42057],"type":"Point"}
}