{
  "type": "Feature",
  "properties": {
    "gn:admin1_code":"W",
    "gn:admin2_code":"I2",
    "gn:admin3_code":"8644161.0",
    "gn:admin4_code":"8657806.0",
    "gn:asciiname":"Kibojana",
    "gn:country_code":"UG",
    "gn:dem":1264,
    "gn:feature_class":"P",
    "gn:feature_code":"PPL",
    "gn:name":"Kibojana",
    "gn:population":0,
    "gn:timezone":"Africa/Kampala",
    "iso:country":"UG",
    "wof:name":"Kibojana",
    "wof:placetype":"locality"
},
  "geometry": {"coordinates":[31.21667,0.91667],"type":"Point"}
}