{
  "type": "Feature",
  "properties": {
    "gn:admin1_code":"C",
    "gn:admin2_code":"D9",
    "gn:admin3_code":"8644153.0",
    "gn:admin4_code":"8658426.0",
    "gn:asciiname":"Kigege",
    "gn:country_code":"UG",
    "gn:dem":1116,
    "gn:feature_class":"P",
    "gn:feature_code":"PPL",
    "gn:name":"Kigege",
    "gn:population":0,
    "gn:timezone":"Africa/Kampala",
    "iso:country":"UG",
    "wof:name":"Kigege",
    "wof:placetype":"locality"
},
  "geometry": {"coordinates":[32.38333,0.76667],"type":"Point"}
}