{
  "type": "Feature",
  "properties": {
    "gn:admin1_code":"E",
    "gn:admin2_code":"33",
    "gn:admin3_code":"8644143.0",
    "gn:admin4_code":"8657862.0",
    "gn:asciiname":"Buyala",
    "gn:country_code":"UG",
    "gn:dem":1148,
    "gn:feature_class":"P",
    "gn:feature_code":"PPL",
    "gn:name":"Buyala",
    "gn:population":0,
    "gn:timezone":"Africa/Kampala",
    "iso:country":"UG",
    "wof:name":"Buyala",
    "wof:placetype":"locality"
},
  "geometry": {"coordinates":[33.13514,0.51679],"type":"Point"}
}