{
  "type": "Feature",
  "properties": {
    "gn:admin1_code":"W",
    "gn:admin2_code":"41",
    "gn:admin3_code":"8644139.0",
    "gn:admin4_code":"8658062.0",
    "gn:asciiname":"Kiwumulo",
    "gn:cc2":"UG",
    "gn:country_code":"UG",
    "gn:dem":1277,
    "gn:feature_class":"P",
    "gn:feature_code":"PPL",
    "gn:name":"Kiwumulo",
    "gn:population":0,
    "gn:timezone":"Africa/Kampala",
    "iso:country":"UG",
    "name:und_x_variant":[
        "Kiwumala",
        "Kiwumula",
        "Kiwumulo"
    ],
    "wof:name":"Kiwumulo",
    "wof:placetype":"locality"
},
  "geometry": {"coordinates":[31.15361,0.81139],"type":"Point"}
}