{
  "type": "Feature",
  "properties": {
    "gn:admin1_code":"E",
    "gn:admin2_code":"69",
    "gn:admin3_code":"8644130.0",
    "gn:admin4_code":"8657776.0",
    "gn:asciiname":"Lale",
    "gn:country_code":"UG",
    "gn:dem":1093,
    "gn:feature_class":"P",
    "gn:feature_code":"PPL",
    "gn:name":"Lale",
    "gn:population":0,
    "gn:timezone":"Africa/Kampala",
    "iso:country":"UG",
    "wof:name":"Lale",
    "wof:placetype":"locality"
},
  "geometry": {"coordinates":[33.98658,1.89429],"type":"Point"}
}