{
  "type": "Feature",
  "properties": {
    "gn:admin1_code":"E",
    "gn:admin2_code":"D2",
    "gn:admin3_code":"234305.0",
    "gn:admin4_code":"8658085.0",
    "gn:asciiname":"Saaka",
    "gn:country_code":"UG",
    "gn:dem":1042,
    "gn:feature_class":"P",
    "gn:feature_code":"PPLL",
    "gn:name":"Saaka",
    "gn:population":0,
    "gn:timezone":"Africa/Kampala",
    "iso:country":"UG",
    "wof:name":"Saaka",
    "wof:placetype":"locality"
},
  "geometry": {"coordinates":[33.58462,1.12171],"type":"Point"}
}