{
  "type": "Feature",
  "properties": {
    "gn:admin1_code":"W",
    "gn:admin2_code":"I2",
    "gn:admin3_code":"8644161.0",
    "gn:admin4_code":"8657988.0",
    "gn:asciiname":"Bucumbi",
    "gn:country_code":"UG",
    "gn:dem":1291,
    "gn:feature_class":"P",
    "gn:feature_code":"PPL",
    "gn:name":"Bucumbi",
    "gn:population":0,
    "gn:timezone":"Africa/Kampala",
    "iso:country":"UG",
    "wof:name":"Bucumbi",
    "wof:placetype":"locality"
},
  "geometry": {"coordinates":[31.38333,0.81667],"type":"Point"}
}