{
  "type": "Feature",
  "properties": {
    "gn:admin1_code":"E",
    "gn:admin2_code":"76",
    "gn:asciiname":"Pimori",
    "gn:country_code":"UG",
    "gn:dem":1104,
    "gn:feature_class":"P",
    "gn:feature_code":"PPL",
    "gn:name":"Pimori",
    "gn:population":0,
    "gn:timezone":"Africa/Kampala",
    "iso:country":"UG",
    "name:eng_x_preferred":[
        "Pimori"
    ],
    "wof:name":"Pimori",
    "wof:placetype":"locality"
},
  "geometry": {"coordinates":[34.0508,0.64005],"type":"Point"}
}