{
  "type": "Feature",
  "properties": {
    "gn:admin1_code":"C",
    "gn:admin2_code":"83",
    "gn:admin3_code":"227613.0",
    "gn:admin4_code":"8657831.0",
    "gn:asciiname":"Wampologoma",
    "gn:country_code":"UG",
    "gn:dem":1065,
    "gn:feature_class":"P",
    "gn:feature_code":"PPL",
    "gn:name":"Wampologoma",
    "gn:population":0,
    "gn:timezone":"Africa/Kampala",
    "iso:country":"UG",
    "wof:name":"Wampologoma",
    "wof:placetype":"locality"
},
  "geometry": {"coordinates":[33.01133,0.79666],"type":"Point"}
}