{
  "type": "Feature",
  "properties": {
    "gn:admin1_code":"C",
    "gn:admin2_code":"96",
    "gn:admin3_code":"234053.0",
    "gn:admin4_code":"8658010.0",
    "gn:asciiname":"Kaga",
    "gn:country_code":"UG",
    "gn:dem":1200,
    "gn:feature_class":"P",
    "gn:feature_code":"PPL",
    "gn:name":"Kaga",
    "gn:population":0,
    "gn:timezone":"Africa/Kampala",
    "iso:country":"UG",
    "name:ceb_x_preferred":[
        "Kaga"
    ],
    "name:ces_x_preferred":[
        "Kaga"
    ],
    "name:deu_x_preferred":[
        "Kaga"
    ],
    "name:fin_x_preferred":[
        "Kaga"
    ],
    "name:fra_x_preferred":[
        "Kaga"
    ],
    "name:lit_x_preferred":[
        "Kaga"
    ],
    "name:nld_x_preferred":[
        "Kaga"
    ],
    "name:por_x_preferred":[
        "Kaga"
    ],
    "name:rus_x_preferred":[
        "\u041a\u0430\u0433\u0430"
    ],
    "name:slk_x_preferred":[
        "Kaga"
    ],
    "name:spa_x_preferred":[
        "Kaga"
    ],
    "name:srp_x_preferred":[
        "\u041a\u0430\u0433\u0430"
    ],
    "name:swe_x_preferred":[
        "Kaga"
    ],
    "name:ukr_x_preferred":[
        "\u041a\u0430\u0433\u0430"
    ],
    "name:vie_x_preferred":[
        "Kaga"
    ],
    "wof:name":"Kaga",
    "wof:placetype":"locality"
},
  "geometry": {"coordinates":[32.48443,0.20136],"type":"Point"}
}