{
  "type": "Feature",
  "properties": {
    "gn:admin1_code":"W",
    "gn:admin2_code":"79",
    "gn:asciiname":"Kitengya",
    "gn:country_code":"UG",
    "gn:dem":1547,
    "gn:feature_class":"P",
    "gn:feature_code":"PPL",
    "gn:name":"Kitengya",
    "gn:population":0,
    "gn:timezone":"Africa/Kampala",
    "iso:country":"UG",
    "name:eng_x_preferred":[
        "Kitengya"
    ],
    "wof:name":"Kitengya",
    "wof:placetype":"locality"
},
  "geometry": {"coordinates":[30.19277,0.57627],"type":"Point"}
}