{
  "type": "Feature",
  "properties": {
    "gn:admin1_code":"W",
    "gn:admin2_code":"31",
    "gn:admin3_code":"7732256.0",
    "gn:admin4_code":"8658194.0",
    "gn:asciiname":"Kyarwakahorogo",
    "gn:country_code":"UG",
    "gn:dem":1083,
    "gn:feature_class":"P",
    "gn:feature_code":"PPL",
    "gn:name":"Kyarwakahorogo",
    "gn:population":0,
    "gn:timezone":"Africa/Kampala",
    "iso:country":"UG",
    "wof:name":"Kyarwakahorogo",
    "wof:placetype":"locality"
},
  "geometry": {"coordinates":[31.36502,1.62616],"type":"Point"}
}