{
  "type": "Feature",
  "properties": {
    "gn:admin1_code":"E",
    "gn:admin2_code":"G7",
    "gn:admin3_code":"8644167.0",
    "gn:admin4_code":"8657525.0",
    "gn:asciiname":"Namukonge",
    "gn:country_code":"UG",
    "gn:dem":1087,
    "gn:feature_class":"P",
    "gn:feature_code":"PPL",
    "gn:name":"Namukonge",
    "gn:population":0,
    "gn:timezone":"Africa/Kampala",
    "iso:country":"UG",
    "wof:name":"Namukonge",
    "wof:placetype":"locality"
},
  "geometry": {"coordinates":[33.83333,0.56667],"type":"Point"}
}