{
  "type": "Feature",
  "properties": {
    "gn:admin1_code":"W",
    "gn:admin2_code":"50",
    "gn:admin3_code":"8644149.0",
    "gn:admin4_code":"8657654.0",
    "gn:asciiname":"Karujubu",
    "gn:country_code":"UG",
    "gn:dem":1116,
    "gn:feature_class":"P",
    "gn:feature_code":"PPL",
    "gn:name":"Karujubu",
    "gn:population":0,
    "gn:timezone":"Africa/Kampala",
    "iso:country":"UG",
    "wof:name":"Karujubu",
    "wof:placetype":"locality"
},
  "geometry": {"coordinates":[31.66113,1.67479],"type":"Point"}
}