{
  "type": "Feature",
  "properties": {
    "gn:admin1_code":"E",
    "gn:admin2_code":"E9",
    "gn:admin3_code":"7869956.0",
    "gn:admin4_code":"8657847.0",
    "gn:asciiname":"Bulago",
    "gn:country_code":"UG",
    "gn:dem":1672,
    "gn:feature_class":"P",
    "gn:feature_code":"PPL",
    "gn:name":"Bulago",
    "gn:population":0,
    "gn:timezone":"Africa/Kampala",
    "iso:country":"UG",
    "wof:name":"Bulago",
    "wof:placetype":"locality"
},
  "geometry": {"coordinates":[34.35,1.25],"type":"Point"}
}