{
  "type": "Feature",
  "properties": {
    "gn:admin1_code":"E",
    "gn:admin2_code":"E9",
    "gn:admin3_code":"7869956.0",
    "gn:admin4_code":"8657825.0",
    "gn:asciiname":"Kaptokwoi",
    "gn:cc2":"UG",
    "gn:country_code":"UG",
    "gn:dem":1121,
    "gn:feature_class":"P",
    "gn:feature_code":"PPL",
    "gn:name":"Kaptokwoi",
    "gn:population":0,
    "gn:timezone":"Africa/Kampala",
    "iso:country":"UG",
    "name:und_x_variant":[
        "Kaptokoi",
        "Kaptokwoi"
    ],
    "wof:name":"Kaptokwoi",
    "wof:placetype":"locality"
},
  "geometry": {"coordinates":[34.43333,1.46667],"type":"Point"}
}