{
  "type": "Feature",
  "properties": {
    "gn:admin1_code":"E",
    "gn:admin2_code":"78",
    "gn:asciiname":"Kasolo",
    "gn:country_code":"UG",
    "gn:dem":1149,
    "gn:feature_class":"P",
    "gn:feature_code":"PPL",
    "gn:name":"Kasolo",
    "gn:population":0,
    "gn:timezone":"Africa/Kampala",
    "iso:country":"UG",
    "wof:name":"Kasolo",
    "wof:placetype":"locality"
},
  "geometry": {"coordinates":[33.44909000000001,0.6105],"type":"Point"}
}