{
  "type": "Feature",
  "properties": {
    "gn:admin1_code":"E",
    "gn:admin2_code":"33",
    "gn:asciiname":"Kigaya",
    "gn:country_code":"UG",
    "gn:dem":1121,
    "gn:feature_class":"P",
    "gn:feature_code":"PPL",
    "gn:name":"Kigaya",
    "gn:population":0,
    "gn:timezone":"Africa/Kampala",
    "iso:country":"UG",
    "wof:name":"Kigaya",
    "wof:placetype":"locality"
},
  "geometry": {"coordinates":[33.12021,0.66462],"type":"Point"}
}