{
  "type": "Feature",
  "properties": {
    "gn:admin1_code":"E",
    "gn:admin2_code":"D6",
    "gn:asciiname":"Bubotsatsa",
    "gn:country_code":"UG",
    "gn:dem":1368,
    "gn:feature_class":"P",
    "gn:feature_code":"PPL",
    "gn:name":"Bubotsatsa",
    "gn:population":0,
    "gn:timezone":"Africa/Kampala",
    "iso:country":"UG",
    "name:eng_x_preferred":[
        "Bubotsatsa"
    ],
    "wof:name":"Bubotsatsa",
    "wof:placetype":"locality"
},
  "geometry": {"coordinates":[34.30357,0.88981],"type":"Point"}
}