{
  "type": "Feature",
  "properties": {
    "gn:admin1_code":"C",
    "gn:admin2_code":"90",
    "gn:admin3_code":"7732383.0",
    "gn:admin4_code":"8658222.0",
    "gn:asciiname":"Lunya",
    "gn:country_code":"UG",
    "gn:dem":1160,
    "gn:feature_class":"P",
    "gn:feature_code":"PPL",
    "gn:name":"Lunya",
    "gn:population":0,
    "gn:timezone":"Africa/Kampala",
    "iso:country":"UG",
    "wof:name":"Lunya",
    "wof:placetype":"locality"
},
  "geometry": {"coordinates":[32.91772,0.44132],"type":"Point"}
}