{
  "type": "Feature",
  "properties": {
    "gn:admin1_code":"E",
    "gn:admin2_code":"76",
    "gn:asciiname":"Aturukuku",
    "gn:country_code":"UG",
    "gn:dem":1175,
    "gn:feature_class":"P",
    "gn:feature_code":"PPL",
    "gn:name":"Aturukuku",
    "gn:population":0,
    "gn:timezone":"Africa/Kampala",
    "iso:country":"UG",
    "name:eng_x_preferred":[
        "Aturukuku"
    ],
    "wof:name":"Aturukuku",
    "wof:placetype":"locality"
},
  "geometry": {"coordinates":[34.14657,0.69334],"type":"Point"}
}