{
  "type": "Feature",
  "properties": {
    "gn:admin1_code":"W",
    "gn:admin2_code":"28",
    "gn:asciiname":"Bunguha",
    "gn:country_code":"UG",
    "gn:dem":1859,
    "gn:feature_class":"P",
    "gn:feature_code":"PPL",
    "gn:name":"Bunguha",
    "gn:population":0,
    "gn:timezone":"Africa/Kampala",
    "iso:country":"UG",
    "name:eng_x_preferred":[
        "Bunguha"
    ],
    "wof:name":"Bunguha",
    "wof:placetype":"locality"
},
  "geometry": {"coordinates":[30.12768,0.70365],"type":"Point"}
}